Workbook

Sheet 2026-01
A1: ENERO 2026
B3: Total | D3: AS Güemes | F3: AS San Telmo | H3: El Solar | J3: Florida | L3: French | N3: Güemes 1 | P3: Güemes 2 | R3: Recoleta | T3: San Telmo 1 | V3: San Telmo 2
A4: Ventas Brutas (Odoo) | B4: Monto | C4: Cantidad | D4: Monto | E4: Cantidad | F4: Monto | G4: Cantidad | H4: Monto | I4: Cantidad | J4: Monto | K4: Cantidad | L4: Monto | M4: Cantidad | N4: Monto | O4: Cantidad | P4: Monto | Q4: Cantidad | R4: Monto | S4: Cantidad | T4: Monto | U4: Cantidad | V4: Monto | W4: Cantidad
B5: 1.8546067e+08 | C5: 2981 | D5: 623750.33 | E5: 68 | F5: 16125917 | G5: 1390 | H5: 4959712.8 | I5: 46 | J5: 50274662 | K5: 436 | L5: 21769882 | M5: 218 | N5: 3651320 | O5: 44 | P5: 5092799.9 | Q5: 35 | R5: 25475593 | S5: 255 | T5: 39663000 | U5: 339 | V5: 17824030 | W5: 150
A6: Distribución de ventas por Método de Pago | B6: % sobre facturación | C6: Cantidad | D6: % sobre facturación | E6: Cantidad | F6: % sobre facturación | G6: Cantidad | H6: % sobre facturación | I6: Cantidad | J6: % sobre facturación | K6: Cantidad | L6: % sobre facturación | M6: Cantidad | N6: % sobre facturación | O6: Cantidad | P6: % sobre facturación | Q6: Cantidad | R6: % sobre facturación | S6: Cantidad | T6: % sobre facturación | U6: Cantidad | V6: % sobre facturación | W6: Cantidad
A7: Efectivo | B7: =1-B8-B9-B10 -> 0.17666079 | C7: sin datos | D7: =1-D8-D9-D10 -> 0.49606439 | E7: =E5-E8-E9-E10 -> 39 | F7: =1-F8-F9-F10 -> 0.32933984 | G7: sin datos | H7: =1-H8-H9-H10 -> 0.059824599 | I7: =I5-I8-I9-I10 -> 8 | J7: =1-J8-J9-J10 -> 0.22205464 | K7: =K5-K8-K9-K10 -> 104 | L7: =1-L8-L9-L10 -> 0.11903748 | M7: sin datos | N7: =1-N8-N9-N10 -> 0.15744442 | O7: =O5-O8-O9-O10 -> 10 | P7: =1-P8-P9-P10 -> 0.095468292 | Q7: =Q5-Q8-Q9-Q10 -> 5 | R7: =1-R8-R9-R10 -> 0.1495099 | S7: =S5-S8-S9-S10 -> 50 | T7: =1-T8-T9-T10 -> 0.13031836 | U7: sin datos | V7: =1-V8-V9-V10 -> 0.17126779 | W7: sin datos
A8: Mercado pago (MP) | B8: =Hoja2!C6/'2026-01'!B5 -> 0.025824128 | C8: sin datos | D8: =Hoja2!D6/'2026-01'!D5 -> 0 | E8: 0 | F8: =Hoja2!E6/'2026-01'!F5 -> 0.25948726 | G8: sin datos | H8: 0 | I8: 0 | J8: 0 | K8: 0 | L8: =Hoja2!H6/'2026-01'!L5 -> 0.013777291 | M8: sin datos | N8: 0 | O8: 0 | P8: 0 | Q8: 0 | R8: 0 | S8: 0 | T8: =Hoja2!L6/'2026-01'!T5 -> 0.0055459748 | U8: sin datos | V8: =Hoja2!M6/'2026-01'!V5 -> 0.0047682819 | W8: sin datos
A9: Crédito (TC) | B9: 0.63236277 | C9: 1171 | D9: 0.3199357 | E9: 15 | F9: 0.24567595 | G9: 223 | H9: 0.78913843 | I9: 28 | J9: 0.64869218 | K9: 261 | L9: 0.73375501 | M9: 141 | N9: 0.58599083 | O9: 20 | P9: 0.83001474 | Q9: 23 | R9: 0.67097161 | S9: 157 | T9: 0.68006011 | U9: 216 | V9: 0.57132466 | W9: 87
A10: Débito (TD) | B10: 0.16515232 | C10: 545 | D10: 0.1839999 | E10: 14 | F10: 0.16549695 | G10: 238 | H10: 0.15103697 | I10: 10 | J10: 0.12925318 | K10: 71 | L10: 0.13343021 | M10: 39 | N10: 0.25656475 | O10: 14 | P10: 0.074516966 | Q10: 7 | R10: 0.17951849 | S10: 48 | T10: 0.18407556 | U10: 68 | V10: 0.25263927 | W10: 36
A11: Distribución de ventas según cuotas con TC | B11: % sobre facturación | C11: Cantidad | D11: % sobre facturación | E11: Cantidad | F11: % sobre facturación | G11: Cantidad | H11: % sobre facturación | I11: Cantidad | J11: % sobre facturación | K11: Cantidad | L11: % sobre facturación | M11: Cantidad | N11: % sobre facturación | O11: Cantidad | P11: % sobre facturación | Q11: Cantidad | R11: % sobre facturación | S11: Cantidad | T11: % sobre facturación | U11: Cantidad | V11: % sobre facturación | W11: Cantidad
A12: 1 cuotas | B12: 0.73036533 | C12: 1652 | D12: 0.3199357 | E12: 15 | F12: 0.21226948 | G12: 217 | H12: 0.16712661 | I12: 17 | J12: 0.62880502 | K12: 254 | L12: 0.72916197 | M12: 140 | N12: 0.27379962 | O12: 15 | P12: 0.18135407 | Q12: 9 | R12: 0.58854841 | S12: 144 | T12: 0.65593309 | U12: 211 | V12: 0.55842186 | W12: 85
A13: 3 cuotas | B13: 0.042687003 | C13: 53 | F13: 0.033406473 | G13: 6 | H13: 0.43147659 | I13: 9 | J13: 0.019887155 | K13: 7 | L13: 0.0045930428 | M13: 1 | N13: 0.18074012 | O13: 4 | P13: 0.23827757 | Q13: 9 | R13: 0.056048155 | S13: 11 | T13: 0.015302927 | U13: 4 | V13: 0.012902806 | W13: 2
A14: 6 cuotas | B14: 0.024462756 | C14: 11 | H14: 0.19053523 | I14: 2 | N14: 0.13145109 | O14: 1 | P14: 0.4103831 | Q14: 5 | R14: 0.026375048 | S14: 2 | T14: 0.008824093 | U14: 1
A15: Costo Financiero + Tasa (TC) | B15: Monto | C15: % sobre facturación en esa cant de cuotas | D15: Monto | E15: % sobre facturación | F15: Monto | G15: % sobre facturación | H15: Monto | I15: % sobre facturación | J15: Monto | K15: % sobre facturación | L15: Monto | M15: % sobre facturación | N15: Monto | O15: % sobre facturación | P15: Monto | Q15: % sobre facturación | R15: Monto | S15: % sobre facturación | T15: Monto | U15: % sobre facturación | V15: Monto | W15: % sobre facturación
A16: 1 cuota | B16: 5997497 | C16: 0.057214495 | D16: 13256.3 | E16: 0.066427641 | F16: 196350.5 | G16: 0.057361439 | H16: 30628.33 | I16: 0.036950573 | J16: 1936986.1 | K16: 0.0612719 | L16: 904513.33 | M16: 0.056981633 | N16: 52295.11 | O16: 0.052309233 | P16: 18946.46 | Q16: 0.020513707 | R16: 814822.25 | S16: 0.054344598 | T16: 1482531.2 | U16: 0.056984763 | V16: 547167.41 | W16: 0.054973312
A17: 3 cuotas | B17: 888070.2 | C17: 0.11217597 | F17: 57984.7 | G17: 0.10763621 | H17: 251749.98 | I17: 0.11764018 | J17: 107441.9 | K17: 0.10746124 | L17: 12046.89 | M17: 0.12048095 | N17: 74466.55 | O17: 0.11283836 | P17: 140771.6 | Q17: 0.11600461 | R17: 153689.5 | S17: 0.10763625 | T17: 65164.88 | U17: 0.10736273 | V17: 24754.2 | W17: 0.10763632
A18: 6 cuotas | B18: 881805.52 | C18: 0.19436391 | H18: 191055.82 | I18: 0.20217547 | N18: 86556.38 | O18: 0.18033706 | P18: 409539.45 | Q18: 0.19595198 | R18: 127987.64 | S18: 0.19048047 | T18: 66666.23 | U18: 0.19048039
A19: Total | B19: 7767372.7 | C19: 0.066230195 | D19: 13256.3 | E19: 0.066427641 | F19: 254335.2 | G19: 0.06419769 | H19: 473434.13 | I19: 0.12096224 | J19: 2044428 | K19: 0.06268794 | L19: 916560.22 | M19: 0.057379115 | N19: 213318.04 | O19: 0.099698099 | P19: 569257.51 | Q19: 0.1346686 | R19: 1096499.4 | S19: 0.06414753 | T19: 1614362.3 | U19: 0.059850551 | V19: 571921.61 | W19: 0.056162655
A20: Comisión | B20: Monto | C20: % sobre facturación | D20: Monto | E20: % sobre facturación | F20: Monto | G20: % sobre facturación | H20: Monto | I20: % sobre facturación | J20: Monto | K20: % sobre facturación | L20: Monto | M20: % sobre facturación | N20: Monto | O20: % sobre facturación | P20: Monto | Q20: % sobre facturación | R20: Monto | S20: % sobre facturación | T20: Monto | U20: % sobre facturación | V20: Monto | W20: % sobre facturación
A21: Crédito | B21: 2308653 | C21: 0.019685232 | D21: 3592.08 | E21: 0.018 | F21: 76530.12 | G21: 0.019317251 | H21: 75110.8 | I21: 0.019190782 | J21: 632241.95 | K21: 0.019386325 | L21: 312728.17 | M21: 0.019577618 | N21: 39717.1 | O21: 0.018562515 | P21: 81110.98 | Q21: 0.019188332 | R21: 349808.99 | S21: 0.020464565 | T21: 534546.58 | U21: 0.019817675 | V21: 203266.19 | W21: 0.019960723
A22: Débito | B22: 306292.59 | C22: 0.01 | D22: 1147.7 | E22: 0.01 | F22: 26687.9 | G22: 0.01 | H22: 7491 | I22: 0.01 | J22: 64981.6 | K22: 0.01 | L22: 29047.6 | M22: 0.01 | N22: 9368 | O22: 0.01 | P22: 3795 | Q22: 0.01 | R22: 45733.4 | S22: 0.01 | T22: 73009.89 | U22: 0.01 | V22: 45030.5 | W22: 0.01
A23: Costo Mercado pago | B23: Monto | C23: % sobre facturación con MP | D23: Monto | E23: % sobre facturación | F23: Monto | G23: % sobre facturación | H23: Monto | I23: % sobre facturación | J23: Monto | K23: % sobre facturación | L23: Monto | M23: % sobre facturación | N23: Monto | O23: % sobre facturación | P23: Monto | Q23: % sobre facturación | R23: Monto | S23: % sobre facturación | T23: Monto | U23: % sobre facturación | V23: Monto | W23: % sobre facturación
B24: 28641 | C24: 0.005999998 | F24: =4184470*C24 -> 25106.812 | G24: 0.005999998 | L24: =C24*299930 -> 1799.5794 | M24: 0.005999998 | T24: =219970*U24 -> 1319.8196 | U24: 0.005999998 | V24: =84990*W24 -> 509.93983 | W24: 0.005999998
A25: Costo total | B25: Monto | C25: % sobre facturación | D25: Monto | E25: % sobre facturación | F25: Monto | G25: % sobre facturación | H25: Monto | I25: % sobre facturación | J25: Monto | K25: % sobre facturación | L25: Monto | M25: % sobre facturación | N25: Monto | O25: % sobre facturación | P25: Monto | Q25: % sobre facturación | R25: Monto | S25: % sobre facturación | T25: Monto | U25: % sobre facturación | V25: Monto | W25: % sobre facturación
B26: =B19+B21+B22+B24 -> 10410959 | C26: =B26/B5 -> 0.056135672 | D26: =D19+D21+D22+D24 -> 17996.08 | E26: =D26/D5 -> 0.028851416 | F26: =F19+F21+F22+F24 -> 382660.03 | G26: =F26/F5 -> 0.023729505 | H26: =H19+H21+H22+H24 -> 556035.93 | I26: =H26/H5 -> 0.11211051 | J26: =J19+J21+J22+J24 -> 2741651.6 | K26: =J26/J5 -> 0.054533466 | L26: =L19+L21+L22+L24 -> 1260135.6 | M26: =L26/L5 -> 0.057884355 | N26: =N19+N21+N22+N24 -> 262403.14 | O26: =N26/N5 -> 0.071865282 | P26: =P19+P21+P22+P24 -> 654163.49 | Q26: =P26/P5 -> 0.12844869 | R26: =R19+R21+R22+R24 -> 1492041.8 | S26: =R26/R5 -> 0.058567499 | T26: =T19+T21+T22+T24 -> 2223238.6 | U26: =T26/T5 -> 0.056053213 | V26: =V19+V21+V22+V24 -> 820728.24 | W26: =V26/V5 -> 0.046046165
A27: Ventas Netas | B27: Monto | D27: Monto | F27: Monto | H27: Monto | J27: Monto | L27: Monto | N27: Monto | P27: Monto | R27: Monto | T27: Monto | V27: Monto
B28: =B5-B26 -> 1.7504971e+08 | D28: =D5-D26 -> 605754.25 | F28: =F5-F26 -> 15743257 | H28: =H5-H26 -> 4403676.9 | J28: =J5-J26 -> 47533011 | L28: =L5-L26 -> 20509746 | N28: =N5-N26 -> 3388916.8 | P28: =P5-P26 -> 4438636.4 | R28: =R5-R26 -> 23983552 | T28: =T5-T26 -> 37439761 | V28: =V5-V26 -> 17003302

Sheet 2026-02
A1: FEBRERO 2026
B3: Total | D3: AS Güemes | F3: AS San Telmo | H3: El Solar | J3: Florida | L3: French | N3: Güemes 1 | P3: Güemes 2 | R3: Recoleta | T3: San Telmo 1 | V3: San Telmo 2
A4: Ventas Brutas (Odoo) | B4: Monto | C4: Cantidad | D4: Monto | E4: Cantidad | F4: Monto | G4: Cantidad | H4: Monto | I4: Cantidad | J4: Monto | K4: Cantidad | L4: Monto | M4: Cantidad | N4: Monto | O4: Cantidad | P4: Monto | Q4: Cantidad | R4: Monto | S4: Cantidad | T4: Monto | U4: Cantidad | V4: Monto | W4: Cantidad
B5: 1.718163e+08 | C5: 2859 | D5: 174650.05 | E5: 28 | F5: 13803286 | G5: 1343 | H5: 8175537.8 | I5: 77 | J5: 56315546 | K5: 460 | L5: 16320662 | M5: 175 | N5: 3017386.8 | O5: 50 | P5: 9635799.9 | Q5: 72 | R5: 20983345 | S5: 217 | T5: 30438640 | U5: 317 | V5: 12951444 | W5: 120
A6: Distribución de ventas por Método de Pago | B6: % sobre facturación | C6: Cantidad | D6: % sobre facturación | E6: Cantidad | F6: % sobre facturación | G6: Cantidad | H6: % sobre facturación | I6: Cantidad | J6: % sobre facturación | K6: Cantidad | L6: % sobre facturación | M6: Cantidad | N6: % sobre facturación | O6: Cantidad | P6: % sobre facturación | Q6: Cantidad | R6: % sobre facturación | S6: Cantidad | T6: % sobre facturación | U6: Cantidad | V6: % sobre facturación | W6: Cantidad
A7: Efectivo | B7: =1-B8-B9-B10 -> 0.20312752 | C7: sin datos | D7: =1-D8-D9-D10 -> 0.48571443 | E7: =E5-E8-E9-E10 -> 13 | F7: =1-F8-F9-F10 -> 0.34701855 | G7: sin datos | H7: =1-H8-H9-H10 -> 0.30727126 | I7: =I5-I8-I9-I10 -> 30 | J7: =1-J8-J9-J10 -> 0.26963129 | K7: =K5-K8-K9-K10 -> 130 | L7: =1-L8-L9-L10 -> 0.14709096 | M7: sin datos | N7: =1-N8-N9-N10 -> 0.17526882 | O7: =O5-O8-O9-O10 -> 14 | P7: =1-P8-P9-P10 -> 0.16579836 | Q7: sin datos | R7: =1-R8-R9-R10 -> 0.14809055 | S7: =S5-S8-S9-S10 -> 37 | T7: =1-T8-T9-T10 -> 0.10167803 | U7: sin datos | V7: =1-V8-V9-V10 -> 0.12352291 | W7: sin datos
A8: Mercado pago (MP) | B8: 0.027850152 | C8: sin datos | D8: 0 | E8: 0 | F8: 0.30951325 | G8: sin datos | H8: 0 | I8: 0 | J8: 0 | K8: 0 | L8: 0.019174467 | M8: sin datos | N8: 0 | O8: 0 | P8: 0.0046597066 | Q8: sin datos | R8: 0 | S8: 0 | T8: 0.0027918461 | U8: sin datos | V8: 0.0054040306 | W8: sin datos
A9: Crédito (TC) | B9: 0.60951086 | C9: 1036 | D9: 0.34285704 | E9: 9 | F9: 0.18429814 | G9: 152 | H9: 0.61384708 | I9: 35 | J9: 0.60434987 | K9: 262 | L9: 0.63560841 | M9: 104 | N9: 0.65707618 | O9: 24 | P9: 0.76036241 | Q9: 45 | R9: 0.69400612 | S9: 133 | T9: 0.66437919 | U9: 195 | V9: 0.66394172 | W9: 77
A10: Débito (TD) | B10: 0.15951147 | C10: 477 | D10: 0.17142852 | E10: 6 | F10: 0.15917007 | G10: 198 | H10: 0.078881661 | I10: 12 | J10: 0.12601884 | K10: 68 | L10: 0.19812616 | M10: 35 | N10: 0.167655 | O10: 12 | P10: 0.069179519 | Q10: 9 | R10: 0.15790333 | S10: 47 | T10: 0.23115093 | U10: 65 | V10: 0.20713134 | W10: 25
A11: Distribución de ventas según cuotas con TC | B11: % sobre facturación | C11: Cantidad | D11: % sobre facturación | E11: Cantidad | F11: % sobre facturación | G11: Cantidad | H11: % sobre facturación | I11: Cantidad | J11: % sobre facturación | K11: Cantidad | L11: % sobre facturación | M11: Cantidad | N11: % sobre facturación | O11: Cantidad | P11: % sobre facturación | Q11: Cantidad | R11: % sobre facturación | S11: Cantidad | T11: % sobre facturación | U11: Cantidad | V11: % sobre facturación | W11: Cantidad
A12: 1 cuotas | B12: 0.66751348 | C12: 1415 | D12: 0.34285704 | E12: 9 | F12: 0.14513138 | G12: 144 | H12: 0.1918198 | I12: 20 | J12: 0.57611996 | K12: 252 | L12: 0.59474487 | M12: 100 | N12: 0.26804087 | O12: 16 | P12: 0.094543267 | Q12: 14 | R12: 0.57134837 | S12: 119 | T12: 0.63711352 | U12: 189 | V12: 0.64850174 | W12: 75
A13: 2 cuotas | B13: 0.00080318341 | C13: 1 | P13: 0.014321593 | Q13: 1
A14: 3 cuotas | B14: 0.08713302 | C14: 93 | F14: 0.03916676 | G14: 8 | H14: 0.3075394 | I14: 13 | J14: 0.028229914 | K14: 10 | L14: 0.040863539 | M14: 4 | N14: 0.3890353 | O14: 8 | P14: 0.50662115 | Q14: 28 | R14: 0.12265775 | S14: 14 | T14: 0.027265673 | U14: 6 | V14: 0.015439977 | W14: 2
A15: 6 cuotas | B15: 0.013572636 | C15: 4 | H15: 0.11448788 | I15: 2 | P15: 0.1448764 | Q15: 2
A16: Costo Financiero + Tasa (TC) | B16: Monto | C16: % sobre facturación en esa cant de cuotas | D16: Monto | E16: % sobre facturación | F16: Monto | G16: % sobre facturación | H16: Monto | I16: % sobre facturación | J16: Monto | K16: % sobre facturación | L16: Monto | M16: % sobre facturación | N16: Monto | O16: % sobre facturación | P16: Monto | Q16: % sobre facturación | R16: Monto | S16: % sobre facturación | T16: Monto | U16: % sobre facturación | V16: Monto | W16: % sobre facturación
A17: 1 cuota | B17: 5753097 | C17: 0.065913124 | D17: 2392.51 | E17: 0.039955077 | F17: 100334.08 | G17: 0.050084651 | H17: 55107.88 | I17: 0.035140177 | J17: 2103413.1 | K17: 0.064831096 | L17: 660109.67 | M17: 0.068006061 | N17: 41597.86 | O17: 0.051432659 | P17: 26377.19 | Q17: 0.028954105 | R17: 762122.35 | S17: 0.063569527 | T17: 1403639.6 | U17: 0.072379161 | V17: 598002.68 | W17: 0.071198983
A18: 2 cuotas | B18: 12198.87 | C18: 0.088397609 | P18: 12198.87 | Q18: 0.088397609
A19: 3 cuotas | B19: 1712184 | C19: 0.11436768 | F19: 58131.38 | G19: 0.10752526 | H19: 298881.45 | I19: 0.11887263 | J19: 170620.28 | K19: 0.107323 | L19: 77803.83 | M19: 0.11666141 | N19: 139072.21 | O19: 0.11847326 | P19: 573235.96 | Q19: 0.11742548 | R19: 283584.34 | S19: 0.11018247 | T19: 89330.52 | U19: 0.10763621 | V19: 21524.01 | W19: 0.1076362
A20: 6 cuotas | B20: 453546.26 | C20: 0.1944881 | H20: 182040.87 | I20: 0.19448811 | P20: 271505.39 | Q20: 0.1944881
A21: Total | B21: 7931026.1 | C21: 0.075732723 | D21: 2392.51 | E21: 0.039955077 | F21: 158465.46 | G21: 0.062291841 | H21: 536030.2 | I21: 0.1068102 | J21: 2274033.4 | K21: 0.066815944 | L21: 737913.5 | M21: 0.071134134 | N21: 180670.07 | O21: 0.091125411 | P21: 883317.41 | Q21: 0.12056143 | R21: 1045706.7 | S21: 0.07180784 | T21: 1492970.1 | U21: 0.073826087 | V21: 619526.69 | W21: 0.072046331
A22: Comisión | B22: Monto | C22: % sobre facturación | D22: Monto | E22: % sobre facturación | F22: Monto | G22: % sobre facturación | H22: Monto | I22: % sobre facturación | J22: Monto | K22: % sobre facturación | L22: Monto | M22: % sobre facturación | N22: Monto | O22: % sobre facturación | P22: Monto | Q22: % sobre facturación | R22: Monto | S22: % sobre facturación | T22: Monto | U22: % sobre facturación | V22: Monto | W22: % sobre facturación
A23: Crédito | B23: 2012197.7 | C23: 0.019214312 | D23: 1112.77 | E23: 0.018583333 | F23: 51414.19 | G23: 0.020210616 | H23: 93425.44 | I23: 0.018616097 | J23: 660030.08 | K23: 0.019393089 | L23: 195066.71 | M23: 0.018804239 | N23: 35687.75 | O23: 0.017999998 | P23: 137431.6 | Q23: 0.01875764 | R23: 294054.36 | S23: 0.020192477 | T23: 382213.48 | U23: 0.018900128 | V23: 161761.32 | W23: 0.018811634
A24: Débito | B24: 274066.7 | C24: 0.01 | D24: 299.4 | E24: 0.01 | F24: 21970.7 | G24: 0.01 | H24: 6449 | I24: 0.01 | J24: 70968.2 | K24: 0.01 | L24: 32335.5 | M24: 0.01 | N24: 5058.8 | O24: 0.01 | P24: 6666 | Q24: 0.01 | R24: 33133.4 | S24: 0.01 | T24: 70359.2 | U24: 0.01 | V24: 26826.5 | W24: 0.01
A25: Costo Mercado pago | B25: Monto | C25: % sobre facturación con MP | D25: Monto | E25: % sobre facturación | F25: Monto | G25: % sobre facturación | H25: Monto | I25: % sobre facturación | J25: Monto | K25: % sobre facturación | L25: Monto | M25: % sobre facturación | N25: Monto | O25: % sobre facturación | P25: Monto | Q25: % sobre facturación | R25: Monto | S25: % sobre facturación | T25: Monto | U25: % sobre facturación | V25: Monto | W25: % sobre facturación
B26: 30405.43 | C26: 0.0063250705 | F26: =4272300*G26 -> 27022.599 | G26: 0.0063250705 | L26: =312941*M26 -> 1979.3739 | M26: 0.0063250705 | P26: =44900*Q26 -> 283.99567 | Q26: 0.0063250705 | T26: =84980*U26 -> 537.50449 | U26: 0.0063250705 | V26: =69990*W26 -> 442.69168 | W26: 0.0063250705
A27: Costo total | B27: Monto | C27: % sobre facturación | D27: Monto | E27: % sobre facturación | F27: Monto | G27: % sobre facturación | H27: Monto | I27: % sobre facturación | J27: Monto | K27: % sobre facturación | L27: Monto | M27: % sobre facturación | N27: Monto | O27: % sobre facturación | P27: Monto | Q27: % sobre facturación | R27: Monto | S27: % sobre facturación | T27: Monto | U27: % sobre facturación | V27: Monto | W27: % sobre facturación
B28: =B21+B23+B24+B26 -> 10247696 | C28: =B28/B5 -> 0.059643328 | D28: =D21+D23+D24+D26 -> 3804.68 | E28: =D28/D5 -> 0.021784592 | F28: =F21+F23+F24+F26 -> 258872.95 | G28: =F28/F5 -> 0.018754443 | H28: =H21+H23+H24+H26 -> 635904.64 | I28: =H28/H5 -> 0.077781383 | J28: =J21+J23+J24+J26 -> 3005031.7 | K28: =J28/J5 -> 0.053360606 | L28: =L21+L23+L24+L26 -> 967295.08 | M28: =L28/L5 -> 0.059268128 | N28: =N21+N23+N24+N26 -> 221416.62 | O28: =N28/N5 -> 0.073380257 | P28: =P21+P23+P24+P26 -> 1027699 | Q28: =P28/P5 -> 0.10665425 | R28: =R21+R23+R24+R26 -> 1372894.4 | S28: =R28/R5 -> 0.065427816 | T28: =T21+T23+T24+T26 -> 1946080.3 | U28: =T28/T5 -> 0.063934535 | V28: =V21+V23+V24+V26 -> 808557.2 | W28: =V28/V5 -> 0.062429888
A29: Ventas Netas | B29: Monto | D29: Monto | F29: Monto | H29: Monto | J29: Monto | L29: Monto | N29: Monto | P29: Monto | R29: Monto | T29: Monto | V29: Monto
B30: =B5-B28 -> 1.615686e+08 | D30: =D5-D28 -> 170845.37 | F30: =F5-F28 -> 13544413 | H30: =H5-H28 -> 7539633.2 | J30: =J5-J28 -> 53310515 | L30: =L5-L28 -> 15353367 | N30: =N5-N28 -> 2795970.2 | P30: =P5-P28 -> 8608100.9 | R30: =R5-R28 -> 19610451 | T30: =T5-T28 -> 28492560 | V30: =V5-V28 -> 12142887

Sheet 2026-03
A1: MARZO 2026
B3: Total | D3: AS Güemes | F3: AS San Telmo | H3: El Solar | J3: Florida | L3: French | N3: Güemes 1 | P3: Güemes 2 | R3: Recoleta | T3: San Telmo 1 | V3: San Telmo 2
A4: Ventas Brutas (Odoo) | B4: Monto | C4: Cantidad | D4: Monto | E4: Cantidad | F4: Monto | G4: Cantidad | H4: Monto | I4: Cantidad | J4: Monto | K4: Cantidad | L4: Monto | M4: Cantidad | N4: Monto | O4: Cantidad | P4: Monto | Q4: Cantidad | R4: Monto | S4: Cantidad | T4: Monto | U4: Cantidad | V4: Monto | W4: Cantidad
A6: Distribución de ventas por Método de Pago | B6: % sobre facturación | C6: Cantidad | D6: % sobre facturación | E6: Cantidad | F6: % sobre facturación | G6: Cantidad | H6: % sobre facturación | I6: Cantidad | J6: % sobre facturación | K6: Cantidad | L6: % sobre facturación | M6: Cantidad | N6: % sobre facturación | O6: Cantidad | P6: % sobre facturación | Q6: Cantidad | R6: % sobre facturación | S6: Cantidad | T6: % sobre facturación | U6: Cantidad | V6: % sobre facturación | W6: Cantidad
A7: Efectivo
A8: Mercado pago (MP)
A9: Crédito (TC)
A10: Débito (TD)
A11: Distribución de ventas según cuotas con TC | B11: % sobre facturación | C11: Cantidad | D11: % sobre facturación | E11: Cantidad | F11: % sobre facturación | G11: Cantidad | H11: % sobre facturación | I11: Cantidad | J11: % sobre facturación | K11: Cantidad | L11: % sobre facturación | M11: Cantidad | N11: % sobre facturación | O11: Cantidad | P11: % sobre facturación | Q11: Cantidad | R11: % sobre facturación | S11: Cantidad | T11: % sobre facturación | U11: Cantidad | V11: % sobre facturación | W11: Cantidad
A12: 1 cuotas
A13: 3 cuotas
A14: 6 cuotas
A15: Costo Financiero + Tasa (TC) | B15: Monto | C15: % sobre facturación en esa cant de cuotas | D15: Monto | E15: % sobre facturación | F15: Monto | G15: % sobre facturación | H15: Monto | I15: % sobre facturación | J15: Monto | K15: % sobre facturación | L15: Monto | M15: % sobre facturación | N15: Monto | O15: % sobre facturación | P15: Monto | Q15: % sobre facturación | R15: Monto | S15: % sobre facturación | T15: Monto | U15: % sobre facturación | V15: Monto | W15: % sobre facturación
A16: 1 cuota
A17: 3 cuotas
A18: 6 cuotas
A19: Total
A20: Comisión | B20: Monto | C20: % sobre facturación | D20: Monto | E20: % sobre facturación | F20: Monto | G20: % sobre facturación | H20: Monto | I20: % sobre facturación | J20: Monto | K20: % sobre facturación | L20: Monto | M20: % sobre facturación | N20: Monto | O20: % sobre facturación | P20: Monto | Q20: % sobre facturación | R20: Monto | S20: % sobre facturación | T20: Monto | U20: % sobre facturación | V20: Monto | W20: % sobre facturación
A21: Crédito
A22: Débito
A23: Costo Mercado pago | B23: Monto | C23: % sobre facturación con MP | D23: Monto | E23: % sobre facturación | F23: Monto | G23: % sobre facturación | H23: Monto | I23: % sobre facturación | J23: Monto | K23: % sobre facturación | L23: Monto | M23: % sobre facturación | N23: Monto | O23: % sobre facturación | P23: Monto | Q23: % sobre facturación | R23: Monto | S23: % sobre facturación | T23: Monto | U23: % sobre facturación | V23: Monto | W23: % sobre facturación
A25: Costo total | B25: Monto | C25: % sobre facturación | D25: Monto | E25: % sobre facturación | F25: Monto | G25: % sobre facturación | H25: Monto | I25: % sobre facturación | J25: Monto | K25: % sobre facturación | L25: Monto | M25: % sobre facturación | N25: Monto | O25: % sobre facturación | P25: Monto | Q25: % sobre facturación | R25: Monto | S25: % sobre facturación | T25: Monto | U25: % sobre facturación | V25: Monto | W25: % sobre facturación
B26: =B19+B21+B22+B24 -> 0 | C26: =B26/B5 -> #DIV/0! | D26: =D19+D21+D22+D24 -> 0 | E26: =D26/D5 -> #DIV/0! | F26: =F19+F21+F22+F24 -> 0 | G26: =F26/F5 -> #DIV/0! | H26: =H19+H21+H22+H24 -> 0 | I26: =H26/H5 -> #DIV/0! | J26: =J19+J21+J22+J24 -> 0 | K26: =J26/J5 -> #DIV/0! | L26: =L19+L21+L22+L24 -> 0 | M26: =L26/L5 -> #DIV/0! | N26: =N19+N21+N22+N24 -> 0 | O26: =N26/N5 -> #DIV/0! | P26: =P19+P21+P22+P24 -> 0 | Q26: =P26/P5 -> #DIV/0! | R26: =R19+R21+R22+R24 -> 0 | S26: =R26/R5 -> #DIV/0! | T26: =T19+T21+T22+T24 -> 0 | U26: =T26/T5 -> #DIV/0! | V26: =V19+V21+V22+V24 -> 0 | W26: =V26/V5 -> #DIV/0!
A27: Ventas Netas | B27: Monto | D27: Monto | F27: Monto | H27: Monto | J27: Monto | L27: Monto | N27: Monto | P27: Monto | R27: Monto | T27: Monto | V27: Monto
B28: =B5-B26 -> 0 | D28: =D5-D26 -> 0 | F28: =F5-F26 -> 0 | H28: =H5-H26 -> 0 | J28: =J5-J26 -> 0 | L28: =L5-L26 -> 0 | N28: =N5-N26 -> 0 | P28: =P5-P26 -> 0 | R28: =R5-R26 -> 0 | T28: =T5-T26 -> 0 | V28: =V5-V26 -> 0

Sheet Hoja2
A3: VENTAS
A4: AÑO-MES | B4: TARJETA | C4: Total | D4: AS Güemes | E4: AS San Telmo | F4: El Solar | G4: Florida | H4: French | I4: Güemes | J4: Güemes 2 | K4: Recoleta | L4: San Telmo | M4: San Telmo 2
A5: 2026-01 | B5: EFECTIVO | C5: =C9-C8-C7-C6 -> 32763628 | D5: =D9-D8-D7-D6 -> 309420.33 | E5: =E9-E8-E7-E6 -> 5310906.8 | F5: =F9-F8-F7-F6 -> 296712.83 | G5: =G9-G8-G7-G6 -> 11163722 | H5: =H9-H8-H7-H6 -> 2591431.9 | I5: =I9-I8-I7-I6 -> 574879.96 | J5: =J9-J8-J7-J6 -> 486200.91 | ... M5: =M9-M8-M7-M6 -> 3052682.2
A6: 2026-01 | B6: MP | C6: 4789360 | D6: 0 | E6: 4184470 | F6: 0 | G6: 0 | H6: 299930 | I6: 0 | J6: 0 | K6: 0 | L6: 219970 | M6: 84990
A7: 2026-01 | B7: CRÉDITO | C7: 117278421 | D7: 199560 | E7: 3961750 | F7: 3913900 | G7: 32612780 | H7: 15973760 | I7: 2139640 | J7: 4227099 | K7: 17093400 | L7: 26973224 | M7: 10183308
A8: 2026-01 | B8: DÉBITO | C8: 30629259 | D8: 114770 | E8: 2668790 | F8: 749100 | G8: 6498160 | H8: 2904760 | I8: 936800 | J8: 379500 | K8: 4573340 | L8: 7300989 | M8: 4503050
A9: 2026-01 | B9: TOTAL | C9: 1.8546067e+08 | D9: 623750.33 | E9: 16125917 | F9: 4959712.8 | G9: 50274662 | H9: 21769882 | I9: 3651320 | J9: 5092799.9 | K9: 25475593 | L9: 39663000 | M9: 17824030
A10: 2026-02 | B10: EFECTIVO | C10: =C14-C13-C12-C11 -> 34900619 | D10: =D14-D13-D12-D11 -> 84830.05 | E10: =E14-E13-E12-E11 -> 4789996.4 | F10: =F14-F13-F12-F11 -> 2512107.8 | G10: =G14-G13-G12-G11 -> 15184433 | H10: =H14-H13-H12-H11 -> 2400621.9 | I10: =I14-I13-I12-I11 -> 528853.82 | J10: =J14-J13-J12-J11 -> 1597599.9 | ... M10: =M14-M13-M12-M11 -> 1599800
A11: 2026-02 | B11: MP | C11: =SUM(D11:M11) -> 4785110 | D11: 0 | E11: 4272300 | F11: 0 | G11: 0 | H11: 312940 | I11: 0 | J11: 44900 | K11: 0 | L11: 84980 | M11: 69990
A12: 2026-02 | B12: CRÉDITO | C12: 104723899 | D12: 59880 | E12: 2543920 | F12: 5018530 | G12: 34034293 | H12: 10373550 | I12: 1982653 | J12: 7326700 | K12: 14562570 | L12: 20222799 | M12: 8599004
A13: 2026-02 | B13: DÉBITO | C13: 27406670 | D13: 29940 | E13: 2197070 | F13: 644900 | G13: 7096820 | H13: 3233550 | I13: 505880 | J13: 666600 | K13: 3313340 | L13: 7035920 | M13: 2682650
A14: 2026-02 | B14: TOTAL | C14: 1.718163e+08 | D14: 174650.05 | E14: 13803286 | F14: 8175537.8 | G14: 56315546 | H14: 16320662 | I14: 3017386.8 | J14: 9635799.9 | K14: 20983345 | L14: 30438640 | M14: 12951444
