Workbook

Sheet RESERVA
AP1: Cotizaciones | AU1: De | AV1: Hasta
A2: Empresa: EL LUCERO CUERO S.A. | AU2: ='LUCERO RECOLETA'!AX2 | AV2: ='LUCERO RECOLETA'!AY2 | AW2: ='LUCERO RECOLETA'!AZ2 | AX2: ='LUCERO RECOLETA'!BA2 | AY2: ='LUCERO RECOLETA'!BB2 | AZ2: ='LUCERO RECOLETA'!BC2 | BA2: ='LUCERO RECOLETA'!BD2 | BB2: ='LUCERO RECOLETA'!BE2 | ... BG2: ='LUCERO RECOLETA'!BJ2
A3: Sucursal: LUCERO FLORIDA - Florida 823 CABA - Caja 1 - CP C1005AAQ | AP3: ='LUCERO RECOLETA'!AS3 | AU3: ='LUCERO RECOLETA'!AX3 | AV3: ='LUCERO RECOLETA'!AY3 | AW3: ='LUCERO RECOLETA'!AZ3 | AX3: ='LUCERO RECOLETA'!BA3 | AY3: ='LUCERO RECOLETA'!BB3 | AZ3: ='LUCERO RECOLETA'!BC3 | BA3: ='LUCERO RECOLETA'!BD3 | BB3: ='LUCERO RECOLETA'!BE3 | ... BG3: ='LUCERO RECOLETA'!BJ3
AP4: ='LUCERO RECOLETA'!AS4 | AU4: ='LUCERO RECOLETA'!AX4 | AV4: ='LUCERO RECOLETA'!AY4 | AW4: ='LUCERO RECOLETA'!AZ4 | AX4: ='LUCERO RECOLETA'!BA4 | AY4: ='LUCERO RECOLETA'!BB4 | AZ4: ='LUCERO RECOLETA'!BC4 | BA4: ='LUCERO RECOLETA'!BD4 | BB4: ='LUCERO RECOLETA'!BE4 | ... BG4: ='LUCERO RECOLETA'!BJ4
A5: INFORME DE VENTAS MENSUAL | E5: pv 26 | AP5: ='LUCERO RECOLETA'!AS5 | AU5: ='LUCERO RECOLETA'!AX5 | AV5: ='LUCERO RECOLETA'!AY5 | AW5: ='LUCERO RECOLETA'!AZ5 | AX5: ='LUCERO RECOLETA'!BA5 | AY5: ='LUCERO RECOLETA'!BB5 | AZ5: ='LUCERO RECOLETA'!BC5 | BA5: ='LUCERO RECOLETA'!BD5 | BB5: ='LUCERO RECOLETA'!BE5 | ... BF5: ='LUCERO RECOLETA'!BI5
AU6: ='LUCERO RECOLETA'!AX6 | AY6: 1450
A7: ='LUCERO RECOLETA'!A7 -> ABRIL | B7: Detalle de TICKETS | L7: Detalle de FACTURAS B | Q7: Detalle de FACTURAS A | V7: Detalle de NOTAS DE CREDITO | AA7: VENTA FINAL | AB7: INFORME SEGÚN MAIL | AM7: DIFERENCIA | AN7: CONTROL DE CIERRE DE CAJA
A8: Fecha | B8: Informe de cierre | C8: N° Tickets | D8: Desde | E8: Hasta | F8: Anulados y/o cancelados | G8: Cant. de art. | H8: Imp. de VTA gravado | I8: IVA 21% | J8: Otros imp. | K8: Imp. de VTA total | L8: Desde | M8: Hasta | N8: Imp.de VTA gravado | O8: IVA 21% | P8: Imp.de vta total | Q8: Desde | R8: Hasta | S8: Imp.de VTA gravado | T8: IVA 21% | U8: Imp.de vta total | V8: Desde | W8: Hasta | X8: Imp.de VTA gravado | Y8: IVA 21% | Z8: Imp.de vta total | AB8: VENTA TOTAL | AC8: EFECTIVO $ | AD8: TARJETAS | AE8: MERCADO PAGO | AF8: Real | AH8: Dolar | AJ8: EURO | AL8: TOTAL DE INGRESO | AN8: $ Efectivo | AO8: $ Deposito / PIX | AP8: TARJ SEGUN PLANILLA | AQ8: TOTAL TARJETAS OK | AR8: TARJETA DEBITO | AS8: TARJETA CREDITO | AT8: Mercado Pago / TF | AU8: Gastos | AV8: Real | AX8: Dólar 100 | AZ8: Dólar 50 | BB8: Dólar 10. 20 | BD8: Dólar 1. 5 | BF8: EURO | BH8: Total | BI8: CIERRE | BJ8: DIFERENCIA | BL8: =AN8 -> $ Efectivo | BM8: =AR8 -> TARJETA DEBITO | BN8: =AS8 -> TARJETA CREDITO | BO8: =AT8 -> Mercado Pago / TF | BP8: =AV8 -> Real | BQ8: Dólar | BR8: Euro | BS8: Total | BT8: Venta x día
A9: ='LUCERO RECOLETA'!A9 -> 46143 | B9: 940 | D9: 9715 | E9: =IF(C9="","",C9+D9-1) | I9: =H9*21% -> 0 | K9: =H9+I9+J9 -> 0 | O9: =N9*21% -> 0 | P9: =+N9+O9 -> 0 | T9: =S9*21% -> 0 | U9: =SUM(S9:T9) -> 0 | Y9: =X9*21% -> 0 | Z9: =SUM(X9:Y9) -> 0 | AA9: =+K9+P9+U9-Z9 -> 0 | AG9: =AF9*220 -> 0 | AI9: =AH9*1200 -> 0 | AK9: =AJ9*1200 -> 0 | AL9: =AC9+AD9+AE9+AG9+AI9+AK9 -> 0 | AM9: =SUM(AL9-BH9) -> 0 | AP9: =AD9 | AQ9: =SUM(AR9:AS9) -> 0 | AW9: =AV9*AW$2 -> 0 | AY9: =AX9*AY$2 -> 0 | BA9: =AZ9*BA$2 -> 0 | BC9: =BB9*BC$2 -> 0 | BE9: =BD9*BE$2 -> 0 | BG9: =BF9*BG$2 -> 0 | BH9: =+AN9+AO9+AQ9+AT9+AU9+AW9+AY9+BA9+BC9+BE8+BG9 -> 0 | BI9: =AA9 -> 0 | BJ9: =SUM(BH9-BI9) -> 0 | BL9: =IF(AN9+AO9=0,0,(AN9+AO9)/AA9) -> 0 | BM9: =IF(AR9=0,0,AR9/AA9) -> 0 | BN9: =IF(AS9=0,0,AS9/AA9) -> 0 | BO9: =IF(AT9=0,0,AT9/AA9) -> 0 | BP9: =IF(AW9=0,0,AW9/AA9) -> 0 | BQ9: =IF(AY9+BA9+BC9=0,0,(AY9+BA9+BC9)/AA9) -> 0 | BR9: =IF(BG9=0,0,BG9/AA9) -> 0 | BS9: =SUM(BL9:BR9) -> 0 | BT9: =AA9/$AA$41 -> #DIV/0!
A10: ='LUCERO RECOLETA'!A10 -> 46144 | B10: =B9+1 -> 941 | D10: =E9+1 -> 1 | E10: =IF(C10="","",C10+D10-1) | I10: =H10*21% -> 0 | K10: =H10+I10+J10 -> 0 | O10: =N10*21% -> 0 | P10: =+N10+O10 -> 0 | T10: =S10*21% -> 0 | U10: =SUM(S10:T10) -> 0 | Y10: =X10*21% -> 0 | Z10: =SUM(X10:Y10) -> 0 | AA10: =+K10+P10+U10-Z10 -> 0 | AG10: =AF10*220 -> 0 | AI10: =AH10*1200 -> 0 | AK10: =AJ10*1200 -> 0 | AL10: =AC10+AD10+AE10+AG10+AI10+AK10 -> 0 | AM10: =SUM(AL10-BH10) -> 0 | AP10: =AD10 | AQ10: =SUM(AR10:AS10) -> 0 | AW10: =AV10*AW$2 -> 0 | AY10: =AX10*AY$2 -> 0 | BA10: =AZ10*BA$2 -> 0 | BC10: =BB10*BC$2 -> 0 | BE10: =BD10*BE$2 -> 0 | BG10: =BF10*BG$2 -> 0 | BH10: =+AN10+AO10+AQ10+AT10+AU10+AW10+AY10+BA10+BC10+BE9+BG10 -> 0 | BI10: =AA10 -> 0 | BJ10: =SUM(BH10-BI10) -> 0 | BL10: =IF(AN10+AO10=0,0,(AN10+AO10)/AA10) -> 0 | BM10: =IF(AR10=0,0,AR10/AA10) -> 0 | BN10: =IF(AS10=0,0,AS10/AA10) -> 0 | BO10: =IF(AT10=0,0,AT10/AA10) -> 0 | BP10: =IF(AW10=0,0,AW10/AA10) -> 0 | BQ10: =IF(AY10+BA10+BC10=0,0,(AY10+BA10+BC10)/AA10) -> 0 | BR10: =IF(BG10=0,0,BG10/AA10) -> 0 | BS10: =SUM(BL10:BR10) -> 0 | BT10: =AA10/$AA$41 -> #DIV/0!
A11: ='LUCERO RECOLETA'!A11 -> 46145 | B11: =B10+1 -> 942 | D11: =E10+1 -> 1 | E11: =IF(C11="","",C11+D11-1) | I11: =H11*21% -> 0 | K11: =H11+I11+J11 -> 0 | O11: =N11*21% -> 0 | P11: =+N11+O11 -> 0 | T11: =S11*21% -> 0 | U11: =SUM(S11:T11) -> 0 | Y11: =X11*21% -> 0 | Z11: =SUM(X11:Y11) -> 0 | AA11: =+K11+P11+U11-Z11 -> 0 | AG11: =AF11*220 -> 0 | AI11: =AH11*1200 -> 0 | AK11: =AJ11*1200 -> 0 | AL11: =AC11+AD11+AE11+AG11+AI11+AK11 -> 0 | AM11: =SUM(AL11-BH11) -> 0 | AP11: =AD11 | AQ11: =AR11+AS11 -> 0 | AW11: =AV11*AW$3 -> 0 | AY11: =AX11*AY$2 -> 0 | BA11: =AZ11*BA$2 -> 0 | BC11: =BB11*BC$2 -> 0 | BE11: =BD11*BE$2 -> 0 | BG11: =BF11*BG$2 -> 0 | BH11: =+AN11+AO11+AQ11+AT11+AU11+AW11+AY11+BA11+BC11+BE11+BG11 -> 0 | BI11: =AA11 -> 0 | BJ11: =SUM(BH11-BI11) -> 0 | BL11: =IF(AN11+AO11=0,0,(AN11+AO11)/AA11) -> 0 | BM11: =IF(AR11=0,0,AR11/AA11) -> 0 | BN11: =IF(AS11=0,0,AS11/AA11) -> 0 | BO11: =IF(AT11=0,0,AT11/AA11) -> 0 | BP11: =IF(AW11=0,0,AW11/AA11) -> 0 | BQ11: =IF(AY11+BA11+BC11=0,0,(AY11+BA11+BC11)/AA11) -> 0 | BR11: =IF(BG11=0,0,BG11/AA11) -> 0 | BS11: =SUM(BL11:BR11) -> 0 | BT11: =AA11/$AA$41 -> #DIV/0!
A12: ='LUCERO RECOLETA'!A12 -> 46146 | B12: =B11+1 -> 943 | D12: =E11+1 -> 1 | E12: =IF(C12="","",C12+D12-1) | I12: =H12*21% -> 0 | K12: =H12+I12+J12 -> 0 | O12: =N12*21% -> 0 | P12: =+N12+O12 -> 0 | T12: =S12*21% -> 0 | U12: =SUM(S12:T12) -> 0 | Y12: =X12*21% -> 0 | Z12: =SUM(X12:Y12) -> 0 | AA12: =+K12+P12+U12-Z12 -> 0 | AG12: =AF12*220 -> 0 | AI12: =AH12*1200 -> 0 | AK12: =AJ12*1200 -> 0 | AL12: =AC12+AD12+AE12+AG12+AI12+AK12 -> 0 | AM12: =SUM(AL12-BH12) -> 0 | AP12: =AD12 | AQ12: =SUM(AR12:AS12) -> 0 | AW12: =AV12*AW$3 -> 0 | AY12: =AX12*AY$2 -> 0 | BA12: =AZ12*BA$2 -> 0 | BC12: =BB12*BC$2 -> 0 | BE12: =BD12*BE$2 -> 0 | BG12: =BF12*BG$2 -> 0 | BH12: =+AN12+AO12+AQ12+AT12+AU12+AW12+AY12+BA12+BC12+BE12+BG12 -> 0 | BI12: =AA12 -> 0 | BJ12: =SUM(BH12-BI12) -> 0 | BL12: =IF(AN12+AO12=0,0,(AN12+AO12)/AA12) -> 0 | BM12: =IF(AR12=0,0,AR12/AA12) -> 0 | BN12: =IF(AS12=0,0,AS12/AA12) -> 0 | BO12: =IF(AT12=0,0,AT12/AA12) -> 0 | BP12: =IF(AW12=0,0,AW12/AA12) -> 0 | BQ12: =IF(AY12+BA12+BC12=0,0,(AY12+BA12+BC12)/AA12) -> 0 | BR12: =IF(BG12=0,0,BG12/AA12) -> 0 | BS12: =SUM(BL12:BR12) -> 0 | BT12: =AA12/$AA$41 -> #DIV/0!
A13: ='LUCERO RECOLETA'!A13 -> 46147 | B13: =B12+1 -> 944 | D13: =E12+1 -> 1 | E13: =IF(C13="","",C13+D13-1) | I13: =H13*21% -> 0 | K13: =H13+I13+J13 -> 0 | O13: =N13*21% -> 0 | P13: =+N13+O13 -> 0 | T13: =S13*21% -> 0 | U13: =SUM(S13:T13) -> 0 | Y13: =X13*21% -> 0 | Z13: =SUM(X13:Y13) -> 0 | AA13: =+K13+P13+U13-Z13 -> 0 | AG13: =AF13*220 -> 0 | AI13: =AH13*1200 -> 0 | AK13: =AJ13*1200 -> 0 | AL13: =AC13+AD13+AE13+AG13+AI13+AK13 -> 0 | AM13: =SUM(AL13-BH13) -> 0 | AP13: =AD13 | AQ13: =SUM(AR13:AS13) -> 0 | AW13: =AV13*AW$3 -> 0 | AY13: =AX13*AY$2 -> 0 | BA13: =AZ13*BA$2 -> 0 | BC13: =BB13*BC$2 -> 0 | BE13: =BD13*BE$2 -> 0 | BG13: =BF13*BG$2 -> 0 | BH13: =+AN13+AO13+AQ13+AT13+AU13+AW13+AY13+BA13+BC13+BE13+BG13 -> 0 | BI13: =AA13 -> 0 | BJ13: =SUM(BH13-BI13) -> 0 | BL13: =IF(AN13+AO13=0,0,(AN13+AO13)/AA13) -> 0 | BM13: =IF(AR13=0,0,AR13/AA13) -> 0 | BN13: =IF(AS13=0,0,AS13/AA13) -> 0 | BO13: =IF(AT13=0,0,AT13/AA13) -> 0 | BP13: =IF(AW13=0,0,AW13/AA13) -> 0 | BQ13: =IF(AY13+BA13+BC13=0,0,(AY13+BA13+BC13)/AA13) -> 0 | BR13: =IF(BG13=0,0,BG13/AA13) -> 0 | BS13: =SUM(BL13:BR13) -> 0 | BT13: =AA13/$AA$41 -> #DIV/0!
A14: ='LUCERO RECOLETA'!A14 -> 46148 | B14: =B13+1 -> 945 | D14: =E13+1 -> 1 | E14: =IF(C14="","",C14+D14-1) | I14: =H14*21% -> 0 | K14: =H14+I14+J14 -> 0 | O14: =N14*21% -> 0 | P14: =+N14+O14 -> 0 | T14: =S14*21% -> 0 | U14: =SUM(S14:T14) -> 0 | Y14: =X14*21% -> 0 | Z14: =SUM(X14:Y14) -> 0 | AA14: =+K14+P14+U14-Z14 -> 0 | AG14: =AF14*220 -> 0 | AI14: =AH14*1200 -> 0 | AK14: =AJ14*1200 -> 0 | AL14: =AC14+AD14+AE14+AG14+AI14+AK14 -> 0 | AM14: =SUM(AL14-BH14) -> 0 | AP14: =AD14 | AQ14: =SUM(AR14:AS14) -> 0 | AW14: =AV14*AW$3 -> 0 | AY14: =AX14*AY$2 -> 0 | BA14: =AZ14*BA$2 -> 0 | BC14: =BB14*BC$2 -> 0 | BE14: =BD14*BE$2 -> 0 | BG14: =BF14*BG$2 -> 0 | BH14: =+AN14+AO14+AQ14+AT14+AU14+AW14+AY14+BA14+BC14+BE14+BG14 -> 0 | BI14: =AA14 -> 0 | BJ14: =SUM(BH14-BI14) -> 0 | BL14: =IF(AN14+AO14=0,0,(AN14+AO14)/AA14) -> 0 | BM14: =IF(AR14=0,0,AR14/AA14) -> 0 | BN14: =IF(AS14=0,0,AS14/AA14) -> 0 | BO14: =IF(AT14=0,0,AT14/AA14) -> 0 | BP14: =IF(AW14=0,0,AW14/AA14) -> 0 | BQ14: =IF(AY14+BA14+BC14=0,0,(AY14+BA14+BC14)/AA14) -> 0 | BR14: =IF(BG14=0,0,BG14/AA14) -> 0 | BS14: =SUM(BL14:BR14) -> 0 | BT14: =AA14/$AA$41 -> #DIV/0!
A15: ='LUCERO RECOLETA'!A15 -> 46149 | B15: =B14+1 -> 946 | D15: =E14+1 -> 1 | E15: =IF(C15="","",C15+D15-1) | I15: =H15*21% -> 0 | K15: =H15+I15+J15 -> 0 | O15: =N15*21% -> 0 | P15: =+N15+O15 -> 0 | T15: =S15*21% -> 0 | U15: =SUM(S15:T15) -> 0 | Y15: =X15*21% -> 0 | Z15: =SUM(X15:Y15) -> 0 | AA15: =+K15+P15+U15-Z15 -> 0 | AG15: =AF15*220 -> 0 | AI15: =AH15*1200 -> 0 | AK15: =AJ15*1200 -> 0 | AL15: =AC15+AD15+AE15+AG15+AI15+AK15 -> 0 | AM15: =SUM(AL15-BH15) -> 0 | AP15: =AD15 | AQ15: =SUM(AR15:AS15) -> 0 | AW15: =AV15*AW$3 -> 0 | AY15: =AX15*AY$2 -> 0 | BA15: =AZ15*BA$2 -> 0 | BC15: =BB15*BC$2 -> 0 | BE15: =BD15*BE$2 -> 0 | BG15: =BF15*BG$4 -> 0 | BH15: =+AN15+AO15+AQ15+AT15+AU15+AW15+AY15+BA15+BC15+BE15+BG15 -> 0 | BI15: =AA15 -> 0 | BJ15: =SUM(BH15-BI15) -> 0 | BL15: =IF(AN15+AO15=0,0,(AN15+AO15)/AA15) -> 0 | BM15: =IF(AR15=0,0,AR15/AA15) -> 0 | BN15: =IF(AS15=0,0,AS15/AA15) -> 0 | BO15: =IF(AT15=0,0,AT15/AA15) -> 0 | BP15: =IF(AW15=0,0,AW15/AA15) -> 0 | BQ15: =IF(AY15+BA15+BC15=0,0,(AY15+BA15+BC15)/AA15) -> 0 | BR15: =IF(BG15=0,0,BG15/AA15) -> 0 | BS15: =SUM(BL15:BR15) -> 0 | BT15: =AA15/$AA$41 -> #DIV/0!
A16: ='LUCERO RECOLETA'!A16 -> 46150 | B16: =B15+1 -> 947 | D16: =E15+1 -> 1 | E16: =IF(C16="","",C16+D16-1) | I16: =H16*21% -> 0 | K16: =H16+I16+J16 -> 0 | O16: =N16*21% -> 0 | P16: =+N16+O16 -> 0 | T16: =S16*21% -> 0 | U16: =SUM(S16:T16) -> 0 | Y16: =X16*21% -> 0 | Z16: =SUM(X16:Y16) -> 0 | AA16: =+K16+P16+U16-Z16 -> 0 | AG16: =AF16*220 -> 0 | AI16: =AH16*1200 -> 0 | AK16: =AJ16*1200 -> 0 | AL16: =AC16+AD16+AE16+AG16+AI16+AK16 -> 0 | AM16: =SUM(AL16-BH16) -> 0 | AP16: =AD16 | AQ16: =SUM(AR16:AS16) -> 0 | AW16: =AV16*AW$3 -> 0 | AY16: =AX16*AY$2 -> 0 | BA16: =AZ16*BA$2 -> 0 | BC16: =BB16*BC$2 -> 0 | BE16: =BD16*BE$2 -> 0 | BG16: =BF16*BG$4 -> 0 | BH16: =+AN16+AO16+AQ16+AT16+AU16+AW16+AY16+BA16+BC16+BE16+BG16 -> 0 | BI16: =AA16 -> 0 | BJ16: =SUM(BH16-BI16) -> 0 | BL16: =IF(AN16+AO16=0,0,(AN16+AO16)/AA16) -> 0 | BM16: =IF(AR16=0,0,AR16/AA16) -> 0 | BN16: =IF(AS16=0,0,AS16/AA16) -> 0 | BO16: =IF(AT16=0,0,AT16/AA16) -> 0 | BP16: =IF(AW16=0,0,AW16/AA16) -> 0 | BQ16: =IF(AY16+BA16+BC16=0,0,(AY16+BA16+BC16)/AA16) -> 0 | BR16: =IF(BG16=0,0,BG16/AA16) -> 0 | BS16: =SUM(BL16:BR16) -> 0 | BT16: =AA16/$AA$41 -> #DIV/0!
A17: ='LUCERO RECOLETA'!A17 -> 46151 | B17: =B16+1 -> 948 | D17: =E16+1 -> 1 | E17: =IF(C17="","",C17+D17-1) | I17: =H17*21% -> 0 | K17: =H17+I17+J17 -> 0 | O17: =N17*21% -> 0 | P17: =+N17+O17 -> 0 | T17: =S17*21% -> 0 | U17: =SUM(S17:T17) -> 0 | Y17: =X17*21% -> 0 | Z17: =SUM(X17:Y17) -> 0 | AA17: =+K17+P17+U17-Z17 -> 0 | AG17: =AF17*220 -> 0 | AI17: =AH17*1200 -> 0 | AK17: =AJ17*1200 -> 0 | AL17: =AC17+AD17+AE17+AG17+AI17+AK17 -> 0 | AM17: =SUM(AL17-BH17) -> 0 | AP17: =AD17 | AQ17: =SUM(AR17:AS17) -> 0 | AW17: =AV17*AW$3 -> 0 | AY17: =AX17*AY$2 -> 0 | BA17: =AZ17*BA$2 -> 0 | BC17: =BB17*BC$2 -> 0 | BE17: =BD17*BE$2 -> 0 | BG17: =BF17*BG$4 -> 0 | BH17: =+AN17+AO17+AQ17+AT17+AU17+AW17+AY17+BA17+BC17+BE17+BG17 -> 0 | BI17: =AA17 -> 0 | BJ17: =SUM(BH17-BI17) -> 0 | BL17: =IF(AN17+AO17=0,0,(AN17+AO17)/AA17) -> 0 | BM17: =IF(AR17=0,0,AR17/AA17) -> 0 | BN17: =IF(AS17=0,0,AS17/AA17) -> 0 | BO17: =IF(AT17=0,0,AT17/AA17) -> 0 | BP17: =IF(AW17=0,0,AW17/AA17) -> 0 | BQ17: =IF(AY17+BA17+BC17=0,0,(AY17+BA17+BC17)/AA17) -> 0 | BR17: =IF(BG17=0,0,BG17/AA17) -> 0 | BS17: =SUM(BL17:BR17) -> 0 | BT17: =AA17/$AA$41 -> #DIV/0!
A18: ='LUCERO RECOLETA'!A18 -> 46152 | B18: =B17+1 -> 949 | D18: =E17+1 -> 1 | E18: =IF(C18="","",C18+D18-1) | I18: =H18*21% -> 0 | K18: =H18+I18+J18 -> 0 | O18: =N18*21% -> 0 | P18: =+N18+O18 -> 0 | T18: =S18*21% -> 0 | U18: =SUM(S18:T18) -> 0 | Y18: =X18*21% -> 0 | Z18: =SUM(X18:Y18) -> 0 | AA18: =+K18+P18+U18-Z18 -> 0 | AG18: =AF18*220 -> 0 | AI18: =AH18*1200 -> 0 | AK18: =AJ18*1200 -> 0 | AL18: =AC18+AD18+AE18+AG18+AI18+AK18 -> 0 | AM18: =SUM(AL18-BH18) -> 0 | AP18: =AD18 | AQ18: =SUM(AR18:AS18) -> 0 | AW18: =AV18*AW$3 -> 0 | AY18: =AX18*AY$2 -> 0 | BA18: =AZ18*BA$2 -> 0 | BC18: =BB18*BC$2 -> 0 | BE18: =BD18*BE$2 -> 0 | BG18: =BF18*BG$4 -> 0 | BH18: =+AN18+AO18+AQ18+AT18+AU18+AW18+AY18+BA18+BC18+BE18+BG18 -> 0 | BI18: =AA18 -> 0 | BJ18: =SUM(BH18-BI18) -> 0 | BL18: =IF(AN18+AO18=0,0,(AN18+AO18)/AA18) -> 0 | BM18: =IF(AR18=0,0,AR18/AA18) -> 0 | BN18: =IF(AS18=0,0,AS18/AA18) -> 0 | BO18: =IF(AT18=0,0,AT18/AA18) -> 0 | BP18: =IF(AW18=0,0,AW18/AA18) -> 0 | BQ18: =IF(AY18+BA18+BC18=0,0,(AY18+BA18+BC18)/AA18) -> 0 | BR18: =IF(BG18=0,0,BG18/AA18) -> 0 | BS18: =SUM(BL18:BR18) -> 0 | BT18: =AA18/$AA$41 -> #DIV/0!
A19: ='LUCERO RECOLETA'!A19 -> 46153 | B19: =B18+1 -> 950 | D19: =E18+1 -> 1 | E19: =IF(C19="","",C19+D19-1) | I19: =H19*21% -> 0 | K19: =H19+I19+J19 -> 0 | O19: =N19*21% -> 0 | P19: =+N19+O19 -> 0 | T19: =S19*21% -> 0 | U19: =SUM(S19:T19) -> 0 | Y19: =X19*21% -> 0 | Z19: =+X19+Y19 -> 0 | AA19: =+K19+P19+U19-Z19 -> 0 | AG19: =AF19*220 -> 0 | AI19: =AH19*1200 -> 0 | AK19: =AJ19*1200 -> 0 | AL19: =AC19+AD19+AE19+AG19+AI19+AK19 -> 0 | AM19: =SUM(AL19-BH19) -> 0 | AP19: =AD19 | AQ19: =SUM(AR19:AS19) -> 0 | AW19: =AV19*AW$3 -> 0 | AY19: =AX19*AY$2 -> 0 | BA19: =AZ19*BA$2 -> 0 | BC19: =BB19*BC$2 -> 0 | BE19: =BD19*BE$2 -> 0 | BG19: =BF19*BG$4 -> 0 | BH19: =+AN19+AO19+AQ19+AT19+AU19+AW19+AY19+BA19+BC19+BE19+BG19 -> 0 | BI19: =AA19 -> 0 | BJ19: =SUM(BH19-BI19) -> 0 | BL19: =IF(AN19+AO19=0,0,(AN19+AO19)/AA19) -> 0 | BM19: =IF(AR19=0,0,AR19/AA19) -> 0 | BN19: =IF(AS19=0,0,AS19/AA19) -> 0 | BO19: =IF(AT19=0,0,AT19/AA19) -> 0 | BP19: =IF(AW19=0,0,AW19/AA19) -> 0 | BQ19: =IF(AY19+BA19+BC19=0,0,(AY19+BA19+BC19)/AA19) -> 0 | BR19: =IF(BG19=0,0,BG19/AA19) -> 0 | BS19: =SUM(BL19:BR19) -> 0 | BT19: =AA19/$AA$41 -> #DIV/0!
A20: ='LUCERO RECOLETA'!A20 -> 46154 | B20: =B19+1 -> 951 | D20: =E19+1 -> 1 | E20: =IF(C20="","",C20+D20-1) | I20: =H20*21% -> 0 | K20: =H20+I20+J20 -> 0 | O20: =N20*21% -> 0 | P20: =+N20+O20 -> 0 | T20: =S20*21% -> 0 | U20: =SUM(S20:T20) -> 0 | Y20: =X20*21% -> 0 | Z20: =SUM(X20:Y20) -> 0 | AA20: =+K20+P20+U20-Z20 -> 0 | AG20: =AF20*220 -> 0 | AI20: =AH20*1200 -> 0 | AK20: =AJ20*1200 -> 0 | AL20: =AC20+AD20+AE20+AG20+AI20+AK20 -> 0 | AM20: =SUM(AL20-BH20) -> 0 | AP20: =AD20 | AQ20: =SUM(AR20:AS20) -> 0 | AW20: =AV20*AW$3 -> 0 | AY20: =AX20*AY$2 -> 0 | BA20: =AZ20*BA$2 -> 0 | BC20: =BB20*BC$2 -> 0 | BE20: =BD20*BE$2 -> 0 | BG20: =BF20*BG$4 -> 0 | BH20: =+AN20+AO20+AQ20+AT20+AU20+AW20+AY20+BA20+BC20+BE20+BG20 -> 0 | BI20: =AA20 -> 0 | BJ20: =SUM(BH20-BI20) -> 0 | BL20: =IF(AN20+AO20=0,0,(AN20+AO20)/AA20) -> 0 | BM20: =IF(AR20=0,0,AR20/AA20) -> 0 | BN20: =IF(AS20=0,0,AS20/AA20) -> 0 | BO20: =IF(AT20=0,0,AT20/AA20) -> 0 | BP20: =IF(AW20=0,0,AW20/AA20) -> 0 | BQ20: =IF(AY20+BA20+BC20=0,0,(AY20+BA20+BC20)/AA20) -> 0 | BR20: =IF(BG20=0,0,BG20/AA20) -> 0 | BS20: =SUM(BL20:BR20) -> 0 | BT20: =AA20/$AA$41 -> #DIV/0!
A21: ='LUCERO RECOLETA'!A21 -> 46155 | B21: =B20+1 -> 952 | D21: =E20+1 -> 1 | E21: =IF(C21="","",C21+D21-1) | I21: =H21*21% -> 0 | K21: =H21+I21+J21 -> 0 | O21: =N21*21% -> 0 | P21: =+N21+O21 -> 0 | T21: =S21*21% -> 0 | U21: =SUM(S21:T21) -> 0 | Y21: =X21*21% -> 0 | Z21: =SUM(X21:Y21) -> 0 | AA21: =+K21+P21+U21-Z21 -> 0 | AG21: =AF21*220 -> 0 | AI21: =AH21*1200 -> 0 | AK21: =AJ21*1200 -> 0 | AL21: =AC21+AD21+AE21+AG21+AI21+AK21 -> 0 | AM21: =SUM(AL21-BH21) -> 0 | AP21: =AD21 | AQ21: =SUM(AR21:AS21) -> 0 | AW21: =AV21*AW$3 -> 0 | AY21: =AX21*AY$2 -> 0 | BA21: =AZ21*BA$2 -> 0 | BC21: =BB21*BC$2 -> 0 | BE21: =BD21*BE$2 -> 0 | BG21: =BF21*BG$4 -> 0 | BH21: =+AN21+AO21+AQ21+AT21+AU21+AW21+AY21+BA21+BC21+BE21+BG21 -> 0 | BI21: =AA21 -> 0 | BJ21: =SUM(BH21-BI21) -> 0 | BL21: =IF(AN21+AO21=0,0,(AN21+AO21)/AA21) -> 0 | BM21: =IF(AR21=0,0,AR21/AA21) -> 0 | BN21: =IF(AS21=0,0,AS21/AA21) -> 0 | BO21: =IF(AT21=0,0,AT21/AA21) -> 0 | BP21: =IF(AW21=0,0,AW21/AA21) -> 0 | BQ21: =IF(AY21+BA21+BC21=0,0,(AY21+BA21+BC21)/AA21) -> 0 | BR21: =IF(BG21=0,0,BG21/AA21) -> 0 | BS21: =SUM(BL21:BR21) -> 0 | BT21: =AA21/$AA$41 -> #DIV/0!
A22: ='LUCERO RECOLETA'!A22 -> 46156 | B22: =B21+1 -> 953 | D22: =E21+1 -> 1 | E22: =IF(C22="","",C22+D22-1) | I22: =H22*21% -> 0 | K22: =H22+I22+J22 -> 0 | O22: =N22*21% -> 0 | P22: =+N22+O22 -> 0 | T22: =S22*21% -> 0 | U22: =SUM(S22:T22) -> 0 | Y22: =X22*21% -> 0 | Z22: =SUM(X22:Y22) -> 0 | AA22: =+K22+P22+U22-Z22 -> 0 | AG22: =AF22*220 -> 0 | AI22: =AH22*1200 -> 0 | AK22: =AJ22*1200 -> 0 | AL22: =AC22+AD22+AE22+AG22+AI22+AK22 -> 0 | AM22: =SUM(AL22-BH22) -> 0 | AP22: =AD22 | AQ22: =SUM(AR22:AS22) -> 0 | AW22: =AV22*AW$3 -> 0 | AY22: =AX22*AY$2 -> 0 | BA22: =AZ22*BA$2 -> 0 | BC22: =BB22*BC$2 -> 0 | BE22: =BD22*BE$2 -> 0 | BG22: =BF22*BG$4 -> 0 | BH22: =+AN22+AO22+AQ22+AT22+AU22+AW22+AY22+BA22+BC22+BE22+BG22 -> 0 | BI22: =AA22 -> 0 | BJ22: =SUM(BH22-BI22) -> 0 | BL22: =IF(AN22+AO22=0,0,(AN22+AO22)/AA22) -> 0 | BM22: =IF(AR22=0,0,AR22/AA22) -> 0 | BN22: =IF(AS22=0,0,AS22/AA22) -> 0 | BO22: =IF(AT22=0,0,AT22/AA22) -> 0 | BP22: =IF(AW22=0,0,AW22/AA22) -> 0 | BQ22: =IF(AY22+BA22+BC22=0,0,(AY22+BA22+BC22)/AA22) -> 0 | BR22: =IF(BG22=0,0,BG22/AA22) -> 0 | BS22: =SUM(BL22:BR22) -> 0 | BT22: =AA22/$AA$41 -> #DIV/0!
A23: ='LUCERO RECOLETA'!A23 -> 46157 | B23: =B22+1 -> 954 | D23: =E22+1 -> 1 | E23: =IF(C23="","",C23+D23-1) | I23: =H23*21% -> 0 | K23: =H23+I23+J23 -> 0 | O23: =N23*21% -> 0 | P23: =+N23+O23 -> 0 | T23: =S23*21% -> 0 | U23: =SUM(S23:T23) -> 0 | Y23: =X23*21% -> 0 | Z23: =SUM(X23:Y23) -> 0 | AA23: =+K23+P23+U23-Z23 -> 0 | AG23: =AF23*220 -> 0 | AI23: =AH23*1200 -> 0 | AK23: =AJ23*1200 -> 0 | AL23: =AC23+AD23+AE23+AG23+AI23+AK23 -> 0 | AM23: =SUM(AL23-BH23) -> 0 | AP23: =AD23 | AQ23: =SUM(AR23:AS23) -> 0 | AW23: =AV23*AW$3 -> 0 | AY23: =AX23*AY$2 -> 0 | BA23: =AZ23*BA$2 -> 0 | BC23: =BB23*BC$2 -> 0 | BE23: =BD23*BE$2 -> 0 | BG23: =BF23*BG$4 -> 0 | BH23: =+AN23+AO23+AQ23+AT23+AU23+AW23+AY23+BA23+BC23+BE23+BG23 -> 0 | BI23: =AA23 -> 0 | BJ23: =SUM(BH23-BI23) -> 0 | BL23: =IF(AN23+AO23=0,0,(AN23+AO23)/AA23) -> 0 | BM23: =IF(AR23=0,0,AR23/AA23) -> 0 | BN23: =IF(AS23=0,0,AS23/AA23) -> 0 | BO23: =IF(AT23=0,0,AT23/AA23) -> 0 | BP23: =IF(AW23=0,0,AW23/AA23) -> 0 | BQ23: =IF(AY23+BA23+BC23=0,0,(AY23+BA23+BC23)/AA23) -> 0 | BR23: =IF(BG23=0,0,BG23/AA23) -> 0 | BS23: =SUM(BL23:BR23) -> 0 | BT23: =AA23/$AA$41 -> #DIV/0!
A24: ='LUCERO RECOLETA'!A24 -> 46158 | B24: =B23+1 -> 955 | D24: =E23+1 -> 1 | E24: =IF(C24="","",C24+D24-1) | I24: =H24*21% -> 0 | K24: =H24+I24+J24 -> 0 | O24: =N24*21% -> 0 | P24: =+N24+O24 -> 0 | T24: =S24*21% -> 0 | U24: =SUM(S24:T24) -> 0 | Y24: =X24*21% -> 0 | Z24: =SUM(X24:Y24) -> 0 | AA24: =+K24+P24+U24-Z24 -> 0 | AG24: =AF24*220 -> 0 | AI24: =AH24*1200 -> 0 | AK24: =AJ24*1200 -> 0 | AL24: =AC24+AD24+AE24+AG24+AI24+AK24 -> 0 | AM24: =SUM(AL24-BH24) -> 0 | AP24: =AD24 | AQ24: =SUM(AR24:AS24) -> 0 | AW24: =AV24*AW$3 -> 0 | AY24: =AX24*AY$2 -> 0 | BA24: =AZ24*BA$2 -> 0 | BC24: =BB24*BC$2 -> 0 | BE24: =BD24*BE$2 -> 0 | BG24: =BF24*BG$4 -> 0 | BH24: =+AN24+AO24+AQ24+AT24+AU24+AW24+AY24+BA24+BC24+BE24+BG24 -> 0 | BI24: =AA24 -> 0 | BJ24: =SUM(BH24-BI24) -> 0 | BL24: =IF(AN24+AO24=0,0,(AN24+AO24)/AA24) -> 0 | BM24: =IF(AR24=0,0,AR24/AA24) -> 0 | BN24: =IF(AS24=0,0,AS24/AA24) -> 0 | BO24: =IF(AT24=0,0,AT24/AA24) -> 0 | BP24: =IF(AW24=0,0,AW24/AA24) -> 0 | BQ24: =IF(AY24+BA24+BC24=0,0,(AY24+BA24+BC24)/AA24) -> 0 | BR24: =IF(BG24=0,0,BG24/AA24) -> 0 | BS24: =SUM(BL24:BR24) -> 0 | BT24: =AA24/$AA$41 -> #DIV/0!
A25: ='LUCERO RECOLETA'!A25 -> 46159 | B25: =B24+1 -> 956 | D25: =E24+1 -> 1 | E25: =IF(C25="","",C25+D25-1) | I25: =H25*21% -> 0 | K25: =H25+I25+J25 -> 0 | O25: =N25*21% -> 0 | P25: =+N25+O25 -> 0 | T25: =S25*21% -> 0 | U25: =SUM(S25:T25) -> 0 | Y25: =X25*21% -> 0 | Z25: =SUM(X25:Y25) -> 0 | AA25: =+K25+P25+U25-Z25 -> 0 | AG25: =AF25*220 -> 0 | AI25: =AH25*1200 -> 0 | AK25: =AJ25*1200 -> 0 | AL25: =AC25+AD25+AE25+AG25+AI25+AK25 -> 0 | AM25: =SUM(AL25-BH25) -> 0 | AP25: =AD25 | AQ25: =SUM(AR25:AS25) -> 0 | AW25: =AV25*AW$3 -> 0 | AY25: =AX25*AY$2 -> 0 | BA25: =AZ25*BA$2 -> 0 | BC25: =BB25*BC$2 -> 0 | BE25: =BD25*BE$2 -> 0 | BG25: =BF25*BG$4 -> 0 | BH25: =+AN25+AO25+AQ25+AT25+AU25+AW25+AY25+BA25+BC25+BE25+BG25 -> 0 | BI25: =AA25 -> 0 | BJ25: =SUM(BH25-BI25) -> 0 | BL25: =IF(AN25+AO25=0,0,(AN25+AO25)/AA25) -> 0 | BM25: =IF(AR25=0,0,AR25/AA25) -> 0 | BN25: =IF(AS25=0,0,AS25/AA25) -> 0 | BO25: =IF(AT25=0,0,AT25/AA25) -> 0 | BP25: =IF(AW25=0,0,AW25/AA25) -> 0 | BQ25: =IF(AY25+BA25+BC25=0,0,(AY25+BA25+BC25)/AA25) -> 0 | BR25: =IF(BG25=0,0,BG25/AA25) -> 0 | BS25: =SUM(BL25:BR25) -> 0 | BT25: =AA25/$AA$41 -> #DIV/0!
A26: ='LUCERO RECOLETA'!A26 -> 46160 | B26: =B25+1 -> 957 | D26: =E25+1 -> 1 | E26: =IF(C26="","",C26+D26-1) | I26: =H26*21% -> 0 | K26: =H26+I26+J26 -> 0 | O26: =N26*21% -> 0 | P26: =+N26+O26 -> 0 | T26: =S26*21% -> 0 | U26: =SUM(S26:T26) -> 0 | Y26: =X26*21% -> 0 | Z26: =SUM(X26:Y26) -> 0 | AA26: =+K26+P26+U26-Z26 -> 0 | AG26: =AF26*220 -> 0 | AI26: =AH26*1200 -> 0 | AK26: =AJ26*1200 -> 0 | AL26: =AC26+AD26+AE26+AG26+AI26+AK26 -> 0 | AM26: =SUM(AL26-BH26) -> 0 | AP26: =AD26 | AQ26: =SUM(AR26:AS26) -> 0 | AW26: =AV26*AW$3 -> 0 | AY26: =AX26*AY$2 -> 0 | BA26: =AZ26*BA$2 -> 0 | BC26: =BB26*BC$2 -> 0 | BE26: =BD26*BE$2 -> 0 | BG26: =BF26*BG$4 -> 0 | BH26: =+AN26+AO26+AQ26+AT26+AU26+AW26+AY26+BA26+BC26+BE26+BG26 -> 0 | BI26: =AA26 -> 0 | BJ26: =SUM(BH26-BI26) -> 0 | BL26: =IF(AN26+AO26=0,0,(AN26+AO26)/AA26) -> 0 | BM26: =IF(AR26=0,0,AR26/AA26) -> 0 | BN26: =IF(AS26=0,0,AS26/AA26) -> 0 | BO26: =IF(AT26=0,0,AT26/AA26) -> 0 | BP26: =IF(AW26=0,0,AW26/AA26) -> 0 | BQ26: =IF(AY26+BA26+BC26=0,0,(AY26+BA26+BC26)/AA26) -> 0 | BR26: =IF(BG26=0,0,BG26/AA26) -> 0 | BS26: =SUM(BL26:BR26) -> 0 | BT26: =AA26/$AA$41 -> #DIV/0!
A27: ='LUCERO RECOLETA'!A27 -> 46161 | B27: =B26+1 -> 958 | D27: =E26+1 -> 1 | E27: =IF(C27="","",C27+D27-1) | I27: =H27*21% -> 0 | K27: =H27+I27+J27 -> 0 | O27: =N27*21% -> 0 | P27: =+N27+O27 -> 0 | T27: =S27*21% -> 0 | U27: =SUM(S27:T27) -> 0 | Y27: =X27*21% -> 0 | Z27: =SUM(X27:Y27) -> 0 | AA27: =+K27+P27+U27-Z27 -> 0 | AG27: =AF27*220 -> 0 | AI27: =AH27*1200 -> 0 | AK27: =AJ27*1200 -> 0 | AL27: =AC27+AD27+AE27+AG27+AI27+AK27 -> 0 | AM27: =SUM(AL27-BH27) -> 0 | AP27: =AD27 | AQ27: =SUM(AR27:AS27) -> 0 | AW27: =AV27*AW$3 -> 0 | AY27: =AX27*AY$2 -> 0 | BA27: =AZ27*BA$2 -> 0 | BC27: =BB27*BC$2 -> 0 | BE27: =BD27*BE$2 -> 0 | BG27: =BF27*BG$4 -> 0 | BH27: =+AN27+AO27+AQ27+AT27+AU27+AW27+AY27+BA27+BC27+BE27+BG27 -> 0 | BI27: =AA27 -> 0 | BJ27: =SUM(BH27-BI27) -> 0 | BL27: =IF(AN27+AO27=0,0,(AN27+AO27)/AA27) -> 0 | BM27: =IF(AR27=0,0,AR27/AA27) -> 0 | BN27: =IF(AS27=0,0,AS27/AA27) -> 0 | BO27: =IF(AT27=0,0,AT27/AA27) -> 0 | BP27: =IF(AW27=0,0,AW27/AA27) -> 0 | BQ27: =IF(AY27+BA27+BC27=0,0,(AY27+BA27+BC27)/AA27) -> 0 | BR27: =IF(BG27=0,0,BG27/AA27) -> 0 | BS27: =SUM(BL27:BR27) -> 0 | BT27: =AA27/$AA$41 -> #DIV/0!
A28: ='LUCERO RECOLETA'!A28 -> 46162 | B28: =B27+1 -> 959 | D28: =E27+1 -> 1 | E28: =IF(C28="","",C28+D28-1) | I28: =H28*21% -> 0 | K28: =H28+I28+J28 -> 0 | O28: =N28*21% -> 0 | P28: =+N28+O28 -> 0 | T28: =S28*21% -> 0 | U28: =SUM(S28:T28) -> 0 | Y28: =X28*21% -> 0 | Z28: =SUM(X28:Y28) -> 0 | AA28: =+K28+P28+U28-Z28 -> 0 | AG28: =AF28*220 -> 0 | AI28: =AH28*1200 -> 0 | AK28: =AJ28*1200 -> 0 | AL28: =AC28+AD28+AE28+AG28+AI28+AK28 -> 0 | AM28: =SUM(AL28-BH28) -> 0 | AP28: =AD28 | AQ28: =SUM(AR28:AS28) -> 0 | AW28: =AV28*AW$3 -> 0 | AY28: =AX28*AY$2 -> 0 | BA28: =AZ28*BA$2 -> 0 | BC28: =BB28*BC$2 -> 0 | BE28: =BD28*BE$2 -> 0 | BG28: =BF28*BG$4 -> 0 | BH28: =+AN28+AO28+AQ28+AT28+AU28+AW28+AY28+BA28+BC28+BE28+BG28 -> 0 | BI28: =AA28 -> 0 | BJ28: =SUM(BH28-BI28) -> 0 | BL28: =IF(AN28+AO28=0,0,(AN28+AO28)/AA28) -> 0 | BM28: =IF(AR28=0,0,AR28/AA28) -> 0 | BN28: =IF(AS28=0,0,AS28/AA28) -> 0 | BO28: =IF(AT28=0,0,AT28/AA28) -> 0 | BP28: =IF(AW28=0,0,AW28/AA28) -> 0 | BQ28: =IF(AY28+BA28+BC28=0,0,(AY28+BA28+BC28)/AA28) -> 0 | BR28: =IF(BG28=0,0,BG28/AA28) -> 0 | BS28: =SUM(BL28:BR28) -> 0 | BT28: =AA28/$AA$41 -> #DIV/0!
A29: ='LUCERO RECOLETA'!A29 -> 46163 | B29: =B28+1 -> 960 | D29: =E28+1 -> 1 | E29: =IF(C29="","",C29+D29-1) | I29: =H29*21% -> 0 | K29: =H29+I29+J29 -> 0 | O29: =N29*21% -> 0 | P29: =+N29+O29 -> 0 | T29: =S29*21% -> 0 | U29: =SUM(S29:T29) -> 0 | Y29: =X29*21% -> 0 | Z29: =SUM(X29:Y29) -> 0 | AA29: =+K29+P29+U29-Z29 -> 0 | AG29: =AF29*220 -> 0 | AI29: =AH29*1200 -> 0 | AK29: =AJ29*1200 -> 0 | AL29: =AC29+AD29+AE29+AG29+AI29+AK29 -> 0 | AM29: =SUM(AL29-BH29) -> 0 | AP29: =AD29 | AQ29: =SUM(AR29:AS29) -> 0 | AW29: =AV29*AW$3 -> 0 | AY29: =AX29*AY$2 -> 0 | BA29: =AZ29*BA$2 -> 0 | BC29: =BB29*BC$2 -> 0 | BE29: =BD29*BE$2 -> 0 | BG29: =BF29*BG$4 -> 0 | BH29: =+AN29+AO29+AQ29+AT29+AU29+AW29+AY29+BA29+BC29+BE29+BG29 -> 0 | BI29: =AA29 -> 0 | BJ29: =SUM(BH29-BI29) -> 0 | BL29: =IF(AN29+AO29=0,0,(AN29+AO29)/AA29) -> 0 | BM29: =IF(AR29=0,0,AR29/AA29) -> 0 | BN29: =IF(AS29=0,0,AS29/AA29) -> 0 | BO29: =IF(AT29=0,0,AT29/AA29) -> 0 | BP29: =IF(AW29=0,0,AW29/AA29) -> 0 | BQ29: =IF(AY29+BA29+BC29=0,0,(AY29+BA29+BC29)/AA29) -> 0 | BR29: =IF(BG29=0,0,BG29/AA29) -> 0 | BS29: =SUM(BL29:BR29) -> 0 | BT29: =AA29/$AA$41 -> #DIV/0!
A30: ='LUCERO RECOLETA'!A30 -> 46164 | B30: =B29+1 -> 961 | D30: =E29+1 -> 1 | E30: =IF(C30="","",C30+D30-1) | I30: =H30*21% -> 0 | K30: =H30+I30+J30 -> 0 | O30: =N30*21% -> 0 | P30: =+N30+O30 -> 0 | T30: =S30*21% -> 0 | U30: =SUM(S30:T30) -> 0 | Y30: =X30*21% -> 0 | Z30: =SUM(X30:Y30) -> 0 | AA30: =+K30+P30+U30-Z30 -> 0 | AG30: =AF30*220 -> 0 | AI30: =AH30*1200 -> 0 | AK30: =AJ30*1200 -> 0 | AL30: =AC30+AD30+AE30+AG30+AI30+AK30 -> 0 | AM30: =SUM(AL30-BH30) -> 0 | AP30: =AD30 | AQ30: =SUM(AR30:AS30) -> 0 | AW30: =AV30*AW$3 -> 0 | AY30: =AX30*AY$2 -> 0 | BA30: =AZ30*BA$2 -> 0 | BC30: =BB30*BC$2 -> 0 | BE30: =BD30*BE$2 -> 0 | BG30: =BF30*BG$4 -> 0 | BH30: =+AN30+AO30+AQ30+AT30+AU30+AW30+AY30+BA30+BC30+BE30+BG30 -> 0 | BI30: =AA30 -> 0 | BJ30: =SUM(BH30-BI30) -> 0 | BL30: =IF(AN30+AO30=0,0,(AN30+AO30)/AA30) -> 0 | BM30: =IF(AR30=0,0,AR30/AA30) -> 0 | BN30: =IF(AS30=0,0,AS30/AA30) -> 0 | BO30: =IF(AT30=0,0,AT30/AA30) -> 0 | BP30: =IF(AW30=0,0,AW30/AA30) -> 0 | BQ30: =IF(AY30+BA30+BC30=0,0,(AY30+BA30+BC30)/AA30) -> 0 | BR30: =IF(BG30=0,0,BG30/AA30) -> 0 | BS30: =SUM(BL30:BR30) -> 0 | BT30: =AA30/$AA$41 -> #DIV/0!
A31: ='LUCERO RECOLETA'!A31 -> 46165 | B31: =B30+1 -> 962 | D31: =E30+1 -> 1 | E31: =IF(C31="","",C31+D31-1) | I31: =H31*21% -> 0 | K31: =H31+I31+J31 -> 0 | O31: =N31*21% -> 0 | P31: =+N31+O31 -> 0 | T31: =S31*21% -> 0 | U31: =SUM(S31:T31) -> 0 | Y31: =X31*21% -> 0 | Z31: =SUM(X31:Y31) -> 0 | AA31: =+K31+P31+U31-Z31 -> 0 | AG31: =AF31*220 -> 0 | AI31: =AH31*1200 -> 0 | AK31: =AJ31*1200 -> 0 | AL31: =AC31+AD31+AE31+AG31+AI31+AK31 -> 0 | AM31: =SUM(AL31-BH31) -> 0 | AP31: =AD31 | AQ31: =SUM(AR31:AS31) -> 0 | AW31: =AV31*AW$3 -> 0 | AY31: =AX31*AY$2 -> 0 | BA31: =AZ31*BA$2 -> 0 | BC31: =BB31*BC$2 -> 0 | BE31: =BD31*BE$2 -> 0 | BG31: =BF31*BG$4 -> 0 | BH31: =+AN31+AO31+AQ31+AT31+AU31+AW31+AY31+BA31+BC31+BE31+BG31 -> 0 | BI31: =AA31 -> 0 | BJ31: =SUM(BH31-BI31) -> 0 | BL31: =IF(AN31+AO31=0,0,(AN31+AO31)/AA31) -> 0 | BM31: =IF(AR31=0,0,AR31/AA31) -> 0 | BN31: =IF(AS31=0,0,AS31/AA31) -> 0 | BO31: =IF(AT31=0,0,AT31/AA31) -> 0 | BP31: =IF(AW31=0,0,AW31/AA31) -> 0 | BQ31: =IF(AY31+BA31+BC31=0,0,(AY31+BA31+BC31)/AA31) -> 0 | BR31: =IF(BG31=0,0,BG31/AA31) -> 0 | BS31: =SUM(BL31:BR31) -> 0 | BT31: =AA31/$AA$41 -> #DIV/0!
... A38: ='LUCERO RECOLETA'!A38 -> 46172 | B38: =B37+1 -> 969 | D38: =E37+1 -> 1 | E38: =IF(C38="","",C38+D38-1) | I38: =H38*21% -> 0 | K38: =H38+I38+J38 -> 0 | O38: =N38*21% -> 0 | P38: =+N38+O38 -> 0 | T38: =S38*21% -> 0 | U38: =SUM(S38:T38) -> 0 | Y38: =X38*21% -> 0 | Z38: =SUM(X38:Y38) -> 0 | AA38: =+K38+P38+U38-Z38 -> 0 | AG38: =AF38*220 -> 0 | AI38: =AH38*1200 -> 0 | AK38: =AJ38*1200 -> 0 | AL38: =AC38+AD38+AE38+AG38+AI38+AK38 -> 0 | AM38: =SUM(AL38-BH38) -> 0 | AP38: =AD38 | AQ38: =SUM(AR38:AS38) -> 0 | AW38: =AV38*AW$3 -> 0 | AY38: =AX38*AY$2 -> 0 | BA38: =AZ38*BA$2 -> 0 | BC38: =BB38*BC$2 -> 0 | BE38: =BD38*BE$2 -> 0 | BG38: =BF38*BG$4 -> 0 | BH38: =+AN38+AO38+AQ38+AT38+AU38+AW38+AY38+BA38+BC38+BE38+BG38 -> 0 | BI38: =AA38 -> 0 | BJ38: =SUM(BH38-BI38) -> 0 | BL38: =IF(AN38+AO38=0,0,(AN38+AO38)/AA38) -> 0 | BM38: =IF(AR38=0,0,AR38/AA38) -> 0 | BN38: =IF(AS38=0,0,AS38/AA38) -> 0 | BO38: =IF(AT38=0,0,AT38/AA38) -> 0 | BP38: =IF(AW38=0,0,AW38/AA38) -> 0 | BQ38: =IF(AY38+BA38+BC38=0,0,(AY38+BA38+BC38)/AA38) -> 0 | BR38: =IF(BG38=0,0,BG38/AA38) -> 0 | BS38: =SUM(BL38:BR38) -> 0 | BT38: =AA38/$AA$41 -> #DIV/0!
A39: ='LUCERO RECOLETA'!A39 -> 46173 | B39: =B38+1 -> 970 | I39: =H39*21% -> 0 | K39: =H39+I39+J39 -> 0 | O39: =N39*21% -> 0 | P39: =+N39+O39 -> 0 | T39: =S39*21% -> 0 | U39: =SUM(S39:T39) -> 0 | Y39: =X39*21% -> 0 | Z39: =SUM(X39:Y39) -> 0 | AA39: =+K39+P39+U39-Z39 -> 0 | AG39: =AF39*220 -> 0 | AI39: =AH39*1200 -> 0 | AK39: =AJ39*1200 -> 0 | AQ39: =SUM(AR39:AS39) -> 0 | AW39: =AV39*AW$3 -> 0 | AY39: =AX39*AY$2 -> 0 | BA39: =AZ39*BA$2 -> 0 | BC39: =BB39*BC$2 -> 0 | BE39: =BD39*BE$2 -> 0 | BG39: =BF39*BG$4 -> 0 | BH39: =+AN39+AO39+AQ39+AT39+AU39+AW39+AY39+BA39+BC39+BE39+BG39 -> 0 | BI39: =AA39 -> 0 | BJ39: =SUM(BH39-BI39) -> 0 | BL39: =IF(AN39+AO39=0,0,(AN39+AO39)/AA39) -> 0 | BM39: =IF(AR39=0,0,AR39/AA39) -> 0 | BN39: =IF(AS39=0,0,AS39/AA39) -> 0 | BO39: =IF(AT39=0,0,AT39/AA39) -> 0 | BP39: =IF(AW39=0,0,AW39/AA39) -> 0 | BQ39: =IF(AY39+BA39+BC39=0,0,(AY39+BA39+BC39)/AA39) -> 0 | BR39: =IF(BG39=0,0,BG39/AA39) -> 0 | BS39: =SUM(BL39:BR39) -> 0 | BT39: =AA39/$AA$41 -> #DIV/0!
O40: =N40*21% -> 0 | T40: =S40*21% -> 0 | Y40: =X40*21% -> 0 | AW40: =AV40*AW$3 -> 0 | AY40: =AX40*AY$2 -> 0 | BA40: =AZ40*BA$2 -> 0 | BC40: =BB40*BC$2 -> 0 | BE40: =BD40*BE$2 -> 0 | BG40: =BF40*BG$4 -> 0 | BH40: =+AN40+AO40+AQ40+AT40+AU40+AW40+AY40+BA40+BC40+BE40+BG40 -> 0 | BJ40: =SUM(BH40-BI40) -> 0
A41: TOTALES | B41: =MAX(B9:B40) -> 970 | C41: =SUM(C9:C40) -> 0 | D41: =MIN(D9:D40) -> 1 | E41: =MAX(E9:E40) -> 0 | F41: =SUM(F9:F40) -> 0 | G41: =SUM(G9:G40) -> 0 | H41: =SUM(H9:H40) -> 0 | I41: =SUM(I9:I40) -> 0 | K41: =SUM(K9:K40) -> 0 | L41: =MIN(L9:L40) -> 0 | M41: =MAX(M9:M40) -> 0 | N41: =SUM(N9:N40) -> 0 | O41: =SUM(O9:O40) -> 0 | P41: =SUM(P9:P40) -> 0 | Q41: =MIN(Q9:Q40) -> 0 | R41: =MAX(R9:R40) -> 0 | S41: =SUM(S9:S40) -> 0 | T41: =SUM(T9:T40) -> 0 | U41: =SUM(U9:U40) -> 0 | V41: =MIN(V9:V40) -> 0 | W41: =MAX(W9:W40) -> 0 | X41: =SUM(X9:X40) -> 0 | Y41: =SUM(Y9:Y40) -> 0 | Z41: =SUM(Z9:Z40) -> 0 | AA41: =SUM(AA9:AA40) -> 0 | AB41: =SUM(AB9:AB38) -> 0 | AC41: =SUM(AC9:AC38) -> 0 | AD41: =SUM(AD9:AD38) -> 0 | AE41: =SUM(AE9:AE38) -> 0 | AF41: =SUM(AF9:AF38) -> 0 | AG41: =SUM(AG9:AG38) -> 0 | AH41: =SUM(AH9:AH38) -> 0 | AI41: =SUM(AI9:AI38) -> 0 | ... AM41: =SUM(AM9:AM38) -> 0 | AN41: =SUM(AN9:AN40) -> 0 | AO41: =SUM(AO9:AO40) -> 0 | AP41: =SUM(AP9:AP40) -> 0 | AQ41: =SUM(AQ9:AQ40) -> 0 | AR41: =SUM(AR9:AR40) -> 0 | AS41: =SUM(AS9:AS40) -> 0 | AT41: =SUM(AT9:AT40) -> 0 | AU41: =SUM(AU9:AU40) -> 0 | ... BJ41: =SUM(BJ9:BJ40) -> 0 | BL41: =IF(AA41=0,0,(AN41+AO41)/AA41) -> 0 | BM41: =IF(AA41=0,0,(AR41)/AA41) -> 0 | BN41: =IF(AA41=0,0,(AS41)/AA41) -> 0 | BO41: =IF($AA$41=0,0,(AT41)/$AA$41) -> 0 | BP41: =IF($AA$41=0,0,(AU41)/$AA$41) -> 0 | BQ41: =IF($AA$41=0,0,(AY41+BA41+BC41)/AA41) -> 0 | BR41: =IF($AA$41=0,0,BG41/AA41) -> 0 | BS41: =SUM(BL41:BR41) -> 0
B42: 939 | D42: 9714 | L42: 13 | Q42: 32 | V42: 84
A43: CONTROL | B43: =B9-B42 -> 1 | D43: =D41-D42 -> -9713 | L43: =L41-L42 -> -13 | Q43: =Q41-Q42 -> -32 | V43: =V41-V42 -> -84 | AB43: 0 | AC43: 0 | AD43: 0 | AE43: 0 | AF43: 0 | AG43: 0 | AH43: 0 | AI43: 0 | AJ43: 0 | AK43: 0 | AL43: 0
Z46: TOTAL | AA46: =AA41+AA45 -> 0 | AN46: $ Efectivo | AO46: $ Deposito / PIX | AP46: TARJETA DEBITO | AQ46: TARJETA CREDITO | AR46: Mercado Pago / TF | AS46: Real | AT46: Dólares | AU46: Euros
AM47: RESUMEN COBRANZA | AN47: =AN41 -> 0 | AO47: =AO41 -> 0 | AP47: =AR41 -> 0 | AQ47: =AS41 -> 0 | AR47: =AT41 -> 0 | AS47: =AW41 -> 0 | AT47: =BA41+BC41+BE41+AY41 -> 0 | AU47: =BG41 -> 0
AN48: =AN47/$AA$41 -> #DIV/0! | AO48: =AO47/$AA$41 -> #DIV/0! | AP48: =AP47/$AA$41 -> #DIV/0! | AQ48: =AQ47/$AA$41 -> #DIV/0! | AR48: =AR47/$AA$41 -> #DIV/0! | AS48: =AS47/$AA$41 -> #DIV/0! | AT48: =AT47/$AA$41 -> #DIV/0! | AU48: =AU47/$AA$41 -> #DIV/0!

Sheet SD 2468
AP1: Cotizaciones | AU1: De | AV1: Hasta
A2: Empresa: SUCCESSFUL BOXES SRL | AU2: ='LUCERO RECOLETA'!AX2 | AV2: ='LUCERO RECOLETA'!AY2 | AW2: ='LUCERO RECOLETA'!AZ2 | AX2: ='LUCERO RECOLETA'!BA2 | AY2: ='LUCERO RECOLETA'!BB2 | AZ2: ='LUCERO RECOLETA'!BC2 | BA2: ='LUCERO RECOLETA'!BD2 | BB2: ='LUCERO RECOLETA'!BE2 | ... BG2: ='LUCERO RECOLETA'!BJ2
A3: Sucursal: LUCERO CENTRAL - Santo Domingo 2468 - CP 1290 | AU3: ='LUCERO RECOLETA'!AX3 | AV3: ='LUCERO RECOLETA'!AY3 | AW3: ='LUCERO RECOLETA'!AZ3 | AX3: ='LUCERO RECOLETA'!BA3 | AY3: ='LUCERO RECOLETA'!BB3 | AZ3: ='LUCERO RECOLETA'!BC3 | BA3: ='LUCERO RECOLETA'!BD3 | BB3: ='LUCERO RECOLETA'!BE3 | ... BG3: ='LUCERO RECOLETA'!BJ3
A5: INFORME DE VENTAS MENSUAL | F5: pv 20 | BA5: =19960+141980+26990+15990+55990+99990+81980+22000+108980+826900+39980+9990+9990 -> 1460720
A7: JUNIO | B7: Detalle de TICKETS | L7: Detalle de FACTURAS B | Q7: Detalle de FACTURAS A | V7: Detalle de NOTAS DE CREDITO | AA7: VENTA FINAL | AB7: INFORME SEGÚN MAIL | AM7: DIFERENCIA | AN7: CONTROL DE CIERRE DE CAJA
A8: Fecha | B8: Informe de cierre | C8: N° Tickets | D8: Desde | E8: Hasta | F8: Anulados y/o cancelados | G8: Cant. de art. | H8: Imp. de VTA gravado | I8: IVA 21% | J8: Otros imp. | K8: Imp. de VTA total | L8: Desde | M8: Hasta | N8: Imp.de VTA gravado | O8: IVA 21% | P8: Imp.de vta total | Q8: Desde | R8: Hasta | S8: Imp.de VTA gravado | T8: IVA 21% | U8: Imp.de vta total | V8: Desde | W8: Hasta | X8: Imp.de VTA gravado | Y8: IVA 21% | Z8: Imp.de vta total | AB8: VENTA TOTAL | AC8: EFECTIVO $ | AD8: TARJETAS | AE8: MERCADO PAGO | AF8: Real | AH8: Dolar | AJ8: EURO | AL8: TOTAL DE INGRESO | AN8: $ Efectivo | AO8: $ Deposito / PIX | AP8: TARJ SEGUN PLANILLA | AQ8: TOTAL TARJETAS OK | AR8: TARJETA DEBITO | AS8: TARJETA CREDITO | AT8: Mercado Pago / TF | AU8: Gastos | AV8: Real | AX8: Dólar 100 | AZ8: Dólar 50 | BB8: Dólar 10. 20 | BD8: Dólar 1. 5 | BF8: EURO | BH8: Total | BI8: CIERRE | BJ8: DIFERENCIA | BL8: =AN8 -> $ Efectivo | BM8: =AR8 -> TARJETA DEBITO | BN8: =AS8 -> TARJETA CREDITO | BO8: =AT8 -> Mercado Pago / TF | BP8: =AV8 -> Real | BQ8: Dólar | BR8: Euro | BS8: Total | BT8: Venta x día
A9: ='LUCERO RECOLETA'!A9 -> 46143 | I9: =H9*21% -> 0 | K9: =H9+I9+J9 -> 0 | O9: =N9*21% -> 0 | P9: =+N9+O9 -> 0 | T9: =S9*21% -> 0 | U9: =SUM(S9:T9) -> 0 | Y9: =X9*21% -> 0 | Z9: =SUM(X9:Y9) -> 0 | AA9: =+K9+P9+U9-Z9 -> 0 | AG9: =AF9*220 -> 0 | AI9: =AH9*1200 -> 0 | AK9: =AJ9*1200 -> 0 | AL9: =AC9+AD9+AE9+AG9+AI9+AK9 -> 0 | AM9: =SUM(AL9-BH9) -> 0 | AP9: =AD9 | AQ9: =SUM(AR9:AS9) -> 0 | AW9: =AV9*AW$2 -> 0 | AY9: =AX9*AY$2 -> 0 | BA9: =AZ9*BA$2 -> 0 | BC9: =BB9*BC$2 -> 0 | BE9: =BD9*BE$2 -> 0 | BG9: =BF9*BG$2 -> 0 | BH9: =+AN9+AO9+AQ9+AT9+AU9+AW9+AY9+BA9+BC9+BE8+BG9 -> 0 | BI9: =AA9 -> 0 | BJ9: =SUM(BH9-BI9) -> 0 | BL9: =IF(AN9+AO9=0,0,(AN9+AO9)/AA9) -> 0 | BM9: =IF(AR9=0,0,AR9/AA9) -> 0 | BN9: =IF(AS9=0,0,AS9/AA9) -> 0 | BO9: =IF(AT9=0,0,AT9/AA9) -> 0 | BP9: =IF(AW9=0,0,AW9/AA9) -> 0 | BQ9: =IF(AY9+BA9+BC9=0,0,(AY9+BA9+BC9)/AA9) -> 0 | BR9: =IF(BG9=0,0,BG9/AA9) -> 0 | BS9: =SUM(BL9:BR9) -> 0 | BT9: =AA9/$AA$41 -> #DIV/0!
A10: =A9+1 -> 46144 | I10: =H10*21% -> 0 | K10: =H10+I10+J10 -> 0 | O10: =N10*21% -> 0 | P10: =+N10+O10 -> 0 | T10: =S10*21% -> 0 | U10: =SUM(S10:T10) -> 0 | Y10: =X10*21% -> 0 | Z10: =SUM(X10:Y10) -> 0 | AA10: =+K10+P10+U10-Z10 -> 0 | AG10: =AF10*220 -> 0 | AI10: =AH10*1200 -> 0 | AK10: =AJ10*1200 -> 0 | AL10: =AC10+AD10+AE10+AG10+AI10+AK10 -> 0 | AM10: =SUM(AL10-BH10) -> 0 | AP10: =AD10 | AQ10: =SUM(AR10:AS10) -> 0 | AW10: =AV10*AW$2 -> 0 | AY10: =AX10*AY$2 -> 0 | BA10: =AZ10*BA$2 -> 0 | BC10: =BB10*BC$2 -> 0 | BE10: =BD10*BE$2 -> 0 | BG10: =BF10*BG$2 -> 0 | BH10: =+AN10+AO10+AQ10+AT10+AU10+AW10+AY10+BA10+BC10+BE9+BG10 -> 0 | BI10: =AA10 -> 0 | BJ10: =SUM(BH10-BI10) -> 0 | BL10: =IF(AN10+AO10=0,0,(AN10+AO10)/AA10) -> 0 | BM10: =IF(AR10=0,0,AR10/AA10) -> 0 | BN10: =IF(AS10=0,0,AS10/AA10) -> 0 | BO10: =IF(AT10=0,0,AT10/AA10) -> 0 | BP10: =IF(AW10=0,0,AW10/AA10) -> 0 | BQ10: =IF(AY10+BA10+BC10=0,0,(AY10+BA10+BC10)/AA10) -> 0 | BR10: =IF(BG10=0,0,BG10/AA10) -> 0 | BS10: =SUM(BL10:BR10) -> 0 | BT10: =AA10/$AA$41 -> #DIV/0!
A11: =A10+1 -> 46145 | I11: =H11*21% -> 0 | K11: =H11+I11+J11 -> 0 | O11: =N11*21% -> 0 | P11: =+N11+O11 -> 0 | T11: =S11*21% -> 0 | U11: =SUM(S11:T11) -> 0 | Y11: =X11*21% -> 0 | Z11: =SUM(X11:Y11) -> 0 | AA11: =+K11+P11+U11-Z11 -> 0 | AG11: =AF11*220 -> 0 | AI11: =AH11*1200 -> 0 | AK11: =AJ11*1200 -> 0 | AL11: =AC11+AD11+AE11+AG11+AI11+AK11 -> 0 | AM11: =SUM(AL11-BH11) -> 0 | AP11: =AD11 | AQ11: =AR11+AS11 -> 0 | AW11: =AV11*AW$3 -> 0 | AY11: =AX11*AY$2 -> 0 | BA11: =AZ11*BA$2 -> 0 | BC11: =BB11*BC$2 -> 0 | BE11: =BD11*BE$2 -> 0 | BG11: =BF11*BG$2 -> 0 | BH11: =+AN11+AO11+AQ11+AT11+AU11+AW11+AY11+BA11+BC11+BE11+BG11 -> 0 | BI11: =AA11 -> 0 | BJ11: =SUM(BH11-BI11) -> 0 | BL11: =IF(AN11+AO11=0,0,(AN11+AO11)/AA11) -> 0 | BM11: =IF(AR11=0,0,AR11/AA11) -> 0 | BN11: =IF(AS11=0,0,AS11/AA11) -> 0 | BO11: =IF(AT11=0,0,AT11/AA11) -> 0 | BP11: =IF(AW11=0,0,AW11/AA11) -> 0 | BQ11: =IF(AY11+BA11+BC11=0,0,(AY11+BA11+BC11)/AA11) -> 0 | BR11: =IF(BG11=0,0,BG11/AA11) -> 0 | BS11: =SUM(BL11:BR11) -> 0 | BT11: =AA11/$AA$41 -> #DIV/0!
A12: =A11+1 -> 46146 | I12: =H12*21% -> 0 | K12: =H12+I12+J12 -> 0 | O12: =N12*21% -> 0 | P12: =+N12+O12 -> 0 | T12: =S12*21% -> 0 | U12: =SUM(S12:T12) -> 0 | Y12: =X12*21% -> 0 | Z12: =SUM(X12:Y12) -> 0 | AA12: =+K12+P12+U12-Z12 -> 0 | AG12: =AF12*220 -> 0 | AI12: =AH12*1200 -> 0 | AK12: =AJ12*1200 -> 0 | AL12: =AC12+AD12+AE12+AG12+AI12+AK12 -> 0 | AM12: =SUM(AL12-BH12) -> 0 | AP12: =AD12 | AQ12: =SUM(AR12:AS12) -> 0 | AW12: =AV12*AW$3 -> 0 | AY12: =AX12*AY$2 -> 0 | BA12: =AZ12*BA$2 -> 0 | BC12: =BB12*BC$2 -> 0 | BE12: =BD12*BE$2 -> 0 | BG12: =BF12*BG$2 -> 0 | BH12: =+AN12+AO12+AQ12+AT12+AU12+AW12+AY12+BA12+BC12+BE12+BG12 -> 0 | BI12: =AA12 -> 0 | BJ12: =SUM(BH12-BI12) -> 0 | BL12: =IF(AN12+AO12=0,0,(AN12+AO12)/AA12) -> 0 | BM12: =IF(AR12=0,0,AR12/AA12) -> 0 | BN12: =IF(AS12=0,0,AS12/AA12) -> 0 | BO12: =IF(AT12=0,0,AT12/AA12) -> 0 | BP12: =IF(AW12=0,0,AW12/AA12) -> 0 | BQ12: =IF(AY12+BA12+BC12=0,0,(AY12+BA12+BC12)/AA12) -> 0 | BR12: =IF(BG12=0,0,BG12/AA12) -> 0 | BS12: =SUM(BL12:BR12) -> 0 | BT12: =AA12/$AA$41 -> #DIV/0!
A13: =A12+1 -> 46147 | I13: =H13*21% -> 0 | K13: =H13+I13+J13 -> 0 | O13: =N13*21% -> 0 | P13: =+N13+O13 -> 0 | T13: =S13*21% -> 0 | U13: =SUM(S13:T13) -> 0 | Y13: =X13*21% -> 0 | Z13: =SUM(X13:Y13) -> 0 | AA13: =+K13+P13+U13-Z13 -> 0 | AG13: =AF13*220 -> 0 | AI13: =AH13*1200 -> 0 | AK13: =AJ13*1200 -> 0 | AL13: =AC13+AD13+AE13+AG13+AI13+AK13 -> 0 | AM13: =SUM(AL13-BH13) -> 0 | AP13: =AD13 | AQ13: =SUM(AR13:AS13) -> 0 | AW13: =AV13*AW$3 -> 0 | AY13: =AX13*AY$2 -> 0 | BA13: =AZ13*BA$2 -> 0 | BC13: =BB13*BC$2 -> 0 | BE13: =BD13*BE$2 -> 0 | BG13: =BF13*BG$2 -> 0 | BH13: =+AN13+AO13+AQ13+AT13+AU13+AW13+AY13+BA13+BC13+BE13+BG13 -> 0 | BI13: =AA13 -> 0 | BJ13: =SUM(BH13-BI13) -> 0 | BL13: =IF(AN13+AO13=0,0,(AN13+AO13)/AA13) -> 0 | BM13: =IF(AR13=0,0,AR13/AA13) -> 0 | BN13: =IF(AS13=0,0,AS13/AA13) -> 0 | BO13: =IF(AT13=0,0,AT13/AA13) -> 0 | BP13: =IF(AW13=0,0,AW13/AA13) -> 0 | BQ13: =IF(AY13+BA13+BC13=0,0,(AY13+BA13+BC13)/AA13) -> 0 | BR13: =IF(BG13=0,0,BG13/AA13) -> 0 | BS13: =SUM(BL13:BR13) -> 0 | BT13: =AA13/$AA$41 -> #DIV/0!
A14: =A13+1 -> 46148 | I14: =H14*21% -> 0 | K14: =H14+I14+J14 -> 0 | O14: =N14*21% -> 0 | P14: =+N14+O14 -> 0 | T14: =S14*21% -> 0 | U14: =SUM(S14:T14) -> 0 | Y14: =X14*21% -> 0 | Z14: =SUM(X14:Y14) -> 0 | AA14: =+K14+P14+U14-Z14 -> 0 | AG14: =AF14*220 -> 0 | AI14: =AH14*1200 -> 0 | AK14: =AJ14*1200 -> 0 | AL14: =AC14+AD14+AE14+AG14+AI14+AK14 -> 0 | AM14: =SUM(AL14-BH14) -> 0 | AP14: =AD14 | AQ14: =SUM(AR14:AS14) -> 0 | AW14: =AV14*AW$3 -> 0 | AY14: =AX14*AY$2 -> 0 | BA14: =AZ14*BA$2 -> 0 | BC14: =BB14*BC$2 -> 0 | BE14: =BD14*BE$2 -> 0 | BG14: =BF14*BG$2 -> 0 | BH14: =+AN14+AO14+AQ14+AT14+AU14+AW14+AY14+BA14+BC14+BE14+BG14 -> 0 | BI14: =AA14 -> 0 | BJ14: =SUM(BH14-BI14) -> 0 | BL14: =IF(AN14+AO14=0,0,(AN14+AO14)/AA14) -> 0 | BM14: =IF(AR14=0,0,AR14/AA14) -> 0 | BN14: =IF(AS14=0,0,AS14/AA14) -> 0 | BO14: =IF(AT14=0,0,AT14/AA14) -> 0 | BP14: =IF(AW14=0,0,AW14/AA14) -> 0 | BQ14: =IF(AY14+BA14+BC14=0,0,(AY14+BA14+BC14)/AA14) -> 0 | BR14: =IF(BG14=0,0,BG14/AA14) -> 0 | BS14: =SUM(BL14:BR14) -> 0 | BT14: =AA14/$AA$41 -> #DIV/0!
A15: =A14+1 -> 46149 | I15: =H15*21% -> 0 | K15: =H15+I15+J15 -> 0 | O15: =N15*21% -> 0 | P15: =+N15+O15 -> 0 | T15: =S15*21% -> 0 | U15: =SUM(S15:T15) -> 0 | Y15: =X15*21% -> 0 | Z15: =SUM(X15:Y15) -> 0 | AA15: =+K15+P15+U15-Z15 -> 0 | AG15: =AF15*220 -> 0 | AI15: =AH15*1200 -> 0 | AK15: =AJ15*1200 -> 0 | AL15: =AC15+AD15+AE15+AG15+AI15+AK15 -> 0 | AM15: =SUM(AL15-BH15) -> 0 | AP15: =AD15 | AQ15: =SUM(AR15:AS15) -> 0 | AW15: =AV15*AW$3 -> 0 | AY15: =AX15*AY$2 -> 0 | BA15: =AZ15*BA$2 -> 0 | BC15: =BB15*BC$2 -> 0 | BE15: =BD15*BE$2 -> 0 | BG15: =BF15*BG$4 -> 0 | BH15: =+AN15+AO15+AQ15+AT15+AU15+AW15+AY15+BA15+BC15+BE15+BG15 -> 0 | BI15: =AA15 -> 0 | BJ15: =SUM(BH15-BI15) -> 0 | BL15: =IF(AN15+AO15=0,0,(AN15+AO15)/AA15) -> 0 | BM15: =IF(AR15=0,0,AR15/AA15) -> 0 | BN15: =IF(AS15=0,0,AS15/AA15) -> 0 | BO15: =IF(AT15=0,0,AT15/AA15) -> 0 | BP15: =IF(AW15=0,0,AW15/AA15) -> 0 | BQ15: =IF(AY15+BA15+BC15=0,0,(AY15+BA15+BC15)/AA15) -> 0 | BR15: =IF(BG15=0,0,BG15/AA15) -> 0 | BS15: =SUM(BL15:BR15) -> 0 | BT15: =AA15/$AA$41 -> #DIV/0!
A16: =A15+1 -> 46150 | I16: =H16*21% -> 0 | K16: =H16+I16+J16 -> 0 | O16: =N16*21% -> 0 | P16: =+N16+O16 -> 0 | T16: =S16*21% -> 0 | U16: =SUM(S16:T16) -> 0 | Y16: =X16*21% -> 0 | Z16: =SUM(X16:Y16) -> 0 | AA16: =+K16+P16+U16-Z16 -> 0 | AG16: =AF16*220 -> 0 | AI16: =AH16*1200 -> 0 | AK16: =AJ16*1200 -> 0 | AL16: =AC16+AD16+AE16+AG16+AI16+AK16 -> 0 | AM16: =SUM(AL16-BH16) -> 0 | AP16: =AD16 | AQ16: =SUM(AR16:AS16) -> 0 | AW16: =AV16*AW$3 -> 0 | AY16: =AX16*AY$2 -> 0 | BA16: =AZ16*BA$2 -> 0 | BC16: =BB16*BC$2 -> 0 | BE16: =BD16*BE$2 -> 0 | BG16: =BF16*BG$4 -> 0 | BH16: =+AN16+AO16+AQ16+AT16+AU16+AW16+AY16+BA16+BC16+BE16+BG16 -> 0 | BI16: =AA16 -> 0 | BJ16: =SUM(BH16-BI16) -> 0 | BL16: =IF(AN16+AO16=0,0,(AN16+AO16)/AA16) -> 0 | BM16: =IF(AR16=0,0,AR16/AA16) -> 0 | BN16: =IF(AS16=0,0,AS16/AA16) -> 0 | BO16: =IF(AT16=0,0,AT16/AA16) -> 0 | BP16: =IF(AW16=0,0,AW16/AA16) -> 0 | BQ16: =IF(AY16+BA16+BC16=0,0,(AY16+BA16+BC16)/AA16) -> 0 | BR16: =IF(BG16=0,0,BG16/AA16) -> 0 | BS16: =SUM(BL16:BR16) -> 0 | BT16: =AA16/$AA$41 -> #DIV/0!
A17: =A16+1 -> 46151 | I17: =H17*21% -> 0 | K17: =H17+I17+J17 -> 0 | O17: =N17*21% -> 0 | P17: =+N17+O17 -> 0 | T17: =S17*21% -> 0 | U17: =SUM(S17:T17) -> 0 | Y17: =X17*21% -> 0 | Z17: =SUM(X17:Y17) -> 0 | AA17: =+K17+P17+U17-Z17 -> 0 | AG17: =AF17*220 -> 0 | AI17: =AH17*1200 -> 0 | AK17: =AJ17*1200 -> 0 | AL17: =AC17+AD17+AE17+AG17+AI17+AK17 -> 0 | AM17: =SUM(AL17-BH17) -> 0 | AP17: =AD17 | AQ17: =SUM(AR17:AS17) -> 0 | AW17: =AV17*AW$3 -> 0 | AY17: =AX17*AY$2 -> 0 | BA17: =AZ17*BA$2 -> 0 | BC17: =BB17*BC$2 -> 0 | BE17: =BD17*BE$2 -> 0 | BG17: =BF17*BG$4 -> 0 | BH17: =+AN17+AO17+AQ17+AT17+AU17+AW17+AY17+BA17+BC17+BE17+BG17 -> 0 | BI17: =AA17 -> 0 | BJ17: =SUM(BH17-BI17) -> 0 | BL17: =IF(AN17+AO17=0,0,(AN17+AO17)/AA17) -> 0 | BM17: =IF(AR17=0,0,AR17/AA17) -> 0 | BN17: =IF(AS17=0,0,AS17/AA17) -> 0 | BO17: =IF(AT17=0,0,AT17/AA17) -> 0 | BP17: =IF(AW17=0,0,AW17/AA17) -> 0 | BQ17: =IF(AY17+BA17+BC17=0,0,(AY17+BA17+BC17)/AA17) -> 0 | BR17: =IF(BG17=0,0,BG17/AA17) -> 0 | BS17: =SUM(BL17:BR17) -> 0 | BT17: =AA17/$AA$41 -> #DIV/0!
A18: =A17+1 -> 46152 | I18: =H18*21% -> 0 | K18: =H18+I18+J18 -> 0 | O18: =N18*21% -> 0 | P18: =+N18+O18 -> 0 | T18: =S18*21% -> 0 | U18: =SUM(S18:T18) -> 0 | Y18: =X18*21% -> 0 | Z18: =SUM(X18:Y18) -> 0 | AA18: =+K18+P18+U18-Z18 -> 0 | AG18: =AF18*220 -> 0 | AI18: =AH18*1200 -> 0 | AK18: =AJ18*1200 -> 0 | AL18: =AC18+AD18+AE18+AG18+AI18+AK18 -> 0 | AM18: =SUM(AL18-BH18) -> 0 | AP18: =AD18 | AQ18: =SUM(AR18:AS18) -> 0 | AW18: =AV18*AW$3 -> 0 | AY18: =AX18*AY$2 -> 0 | BA18: =AZ18*BA$2 -> 0 | BC18: =BB18*BC$2 -> 0 | BE18: =BD18*BE$2 -> 0 | BG18: =BF18*BG$4 -> 0 | BH18: =+AN18+AO18+AQ18+AT18+AU18+AW18+AY18+BA18+BC18+BE18+BG18 -> 0 | BI18: =AA18 -> 0 | BJ18: =SUM(BH18-BI18) -> 0 | BL18: =IF(AN18+AO18=0,0,(AN18+AO18)/AA18) -> 0 | BM18: =IF(AR18=0,0,AR18/AA18) -> 0 | BN18: =IF(AS18=0,0,AS18/AA18) -> 0 | BO18: =IF(AT18=0,0,AT18/AA18) -> 0 | BP18: =IF(AW18=0,0,AW18/AA18) -> 0 | BQ18: =IF(AY18+BA18+BC18=0,0,(AY18+BA18+BC18)/AA18) -> 0 | BR18: =IF(BG18=0,0,BG18/AA18) -> 0 | BS18: =SUM(BL18:BR18) -> 0 | BT18: =AA18/$AA$41 -> #DIV/0!
A19: =A18+1 -> 46153 | I19: =H19*21% -> 0 | K19: =H19+I19+J19 -> 0 | O19: =N19*21% -> 0 | P19: =+N19+O19 -> 0 | T19: =S19*21% -> 0 | U19: =SUM(S19:T19) -> 0 | Y19: =X19*21% -> 0 | Z19: =+X19+Y19 -> 0 | AA19: =+K19+P19+U19-Z19 -> 0 | AG19: =AF19*220 -> 0 | AI19: =AH19*1200 -> 0 | AK19: =AJ19*1200 -> 0 | AL19: =AC19+AD19+AE19+AG19+AI19+AK19 -> 0 | AM19: =SUM(AL19-BH19) -> 0 | AP19: =AD19 | AQ19: =SUM(AR19:AS19) -> 0 | AW19: =AV19*AW$3 -> 0 | AY19: =AX19*AY$2 -> 0 | BA19: =AZ19*BA$2 -> 0 | BC19: =BB19*BC$2 -> 0 | BE19: =BD19*BE$2 -> 0 | BG19: =BF19*BG$4 -> 0 | BH19: =+AN19+AO19+AQ19+AT19+AU19+AW19+AY19+BA19+BC19+BE19+BG19 -> 0 | BI19: =AA19 -> 0 | BJ19: =SUM(BH19-BI19) -> 0 | BL19: =IF(AN19+AO19=0,0,(AN19+AO19)/AA19) -> 0 | BM19: =IF(AR19=0,0,AR19/AA19) -> 0 | BN19: =IF(AS19=0,0,AS19/AA19) -> 0 | BO19: =IF(AT19=0,0,AT19/AA19) -> 0 | BP19: =IF(AW19=0,0,AW19/AA19) -> 0 | BQ19: =IF(AY19+BA19+BC19=0,0,(AY19+BA19+BC19)/AA19) -> 0 | BR19: =IF(BG19=0,0,BG19/AA19) -> 0 | BS19: =SUM(BL19:BR19) -> 0 | BT19: =AA19/$AA$41 -> #DIV/0!
A20: =A19+1 -> 46154 | I20: =H20*21% -> 0 | K20: =H20+I20+J20 -> 0 | O20: =N20*21% -> 0 | P20: =+N20+O20 -> 0 | T20: =S20*21% -> 0 | U20: =SUM(S20:T20) -> 0 | Y20: =X20*21% -> 0 | Z20: =SUM(X20:Y20) -> 0 | AA20: =+K20+P20+U20-Z20 -> 0 | AG20: =AF20*220 -> 0 | AI20: =AH20*1200 -> 0 | AK20: =AJ20*1200 -> 0 | AL20: =AC20+AD20+AE20+AG20+AI20+AK20 -> 0 | AM20: =SUM(AL20-BH20) -> 0 | AP20: =AD20 | AQ20: =SUM(AR20:AS20) -> 0 | AW20: =AV20*AW$3 -> 0 | AY20: =AX20*AY$2 -> 0 | BA20: =AZ20*BA$2 -> 0 | BC20: =BB20*BC$2 -> 0 | BE20: =BD20*BE$2 -> 0 | BG20: =BF20*BG$4 -> 0 | BH20: =+AN20+AO20+AQ20+AT20+AU20+AW20+AY20+BA20+BC20+BE20+BG20 -> 0 | BI20: =AA20 -> 0 | BJ20: =SUM(BH20-BI20) -> 0 | BL20: =IF(AN20+AO20=0,0,(AN20+AO20)/AA20) -> 0 | BM20: =IF(AR20=0,0,AR20/AA20) -> 0 | BN20: =IF(AS20=0,0,AS20/AA20) -> 0 | BO20: =IF(AT20=0,0,AT20/AA20) -> 0 | BP20: =IF(AW20=0,0,AW20/AA20) -> 0 | BQ20: =IF(AY20+BA20+BC20=0,0,(AY20+BA20+BC20)/AA20) -> 0 | BR20: =IF(BG20=0,0,BG20/AA20) -> 0 | BS20: =SUM(BL20:BR20) -> 0 | BT20: =AA20/$AA$41 -> #DIV/0!
A21: =A20+1 -> 46155 | I21: =H21*21% -> 0 | K21: =H21+I21+J21 -> 0 | O21: =N21*21% -> 0 | P21: =+N21+O21 -> 0 | T21: =S21*21% -> 0 | U21: =SUM(S21:T21) -> 0 | Y21: =X21*21% -> 0 | Z21: =SUM(X21:Y21) -> 0 | AA21: =+K21+P21+U21-Z21 -> 0 | AG21: =AF21*220 -> 0 | AI21: =AH21*1200 -> 0 | AK21: =AJ21*1200 -> 0 | AL21: =AC21+AD21+AE21+AG21+AI21+AK21 -> 0 | AM21: =SUM(AL21-BH21) -> 0 | AP21: =AD21 | AQ21: =SUM(AR21:AS21) -> 0 | AW21: =AV21*AW$3 -> 0 | AY21: =AX21*AY$2 -> 0 | BA21: =AZ21*BA$2 -> 0 | BC21: =BB21*BC$2 -> 0 | BE21: =BD21*BE$2 -> 0 | BG21: =BF21*BG$4 -> 0 | BH21: =+AN21+AO21+AQ21+AT21+AU21+AW21+AY21+BA21+BC21+BE21+BG21 -> 0 | BI21: =AA21 -> 0 | BJ21: =SUM(BH21-BI21) -> 0 | BL21: =IF(AN21+AO21=0,0,(AN21+AO21)/AA21) -> 0 | BM21: =IF(AR21=0,0,AR21/AA21) -> 0 | BN21: =IF(AS21=0,0,AS21/AA21) -> 0 | BO21: =IF(AT21=0,0,AT21/AA21) -> 0 | BP21: =IF(AW21=0,0,AW21/AA21) -> 0 | BQ21: =IF(AY21+BA21+BC21=0,0,(AY21+BA21+BC21)/AA21) -> 0 | BR21: =IF(BG21=0,0,BG21/AA21) -> 0 | BS21: =SUM(BL21:BR21) -> 0 | BT21: =AA21/$AA$41 -> #DIV/0!
A22: =A21+1 -> 46156 | I22: =H22*21% -> 0 | K22: =H22+I22+J22 -> 0 | O22: =N22*21% -> 0 | P22: =+N22+O22 -> 0 | T22: =S22*21% -> 0 | U22: =SUM(S22:T22) -> 0 | Y22: =X22*21% -> 0 | Z22: =SUM(X22:Y22) -> 0 | AA22: =+K22+P22+U22-Z22 -> 0 | AG22: =AF22*220 -> 0 | AI22: =AH22*1200 -> 0 | AK22: =AJ22*1200 -> 0 | AL22: =AC22+AD22+AE22+AG22+AI22+AK22 -> 0 | AM22: =SUM(AL22-BH22) -> 0 | AP22: =AD22 | AQ22: =SUM(AR22:AS22) -> 0 | AW22: =AV22*AW$3 -> 0 | AY22: =AX22*AY$2 -> 0 | BA22: =AZ22*BA$2 -> 0 | BC22: =BB22*BC$2 -> 0 | BE22: =BD22*BE$2 -> 0 | BG22: =BF22*BG$4 -> 0 | BH22: =+AN22+AO22+AQ22+AT22+AU22+AW22+AY22+BA22+BC22+BE22+BG22 -> 0 | BI22: =AA22 -> 0 | BJ22: =SUM(BH22-BI22) -> 0 | BL22: =IF(AN22+AO22=0,0,(AN22+AO22)/AA22) -> 0 | BM22: =IF(AR22=0,0,AR22/AA22) -> 0 | BN22: =IF(AS22=0,0,AS22/AA22) -> 0 | BO22: =IF(AT22=0,0,AT22/AA22) -> 0 | BP22: =IF(AW22=0,0,AW22/AA22) -> 0 | BQ22: =IF(AY22+BA22+BC22=0,0,(AY22+BA22+BC22)/AA22) -> 0 | BR22: =IF(BG22=0,0,BG22/AA22) -> 0 | BS22: =SUM(BL22:BR22) -> 0 | BT22: =AA22/$AA$41 -> #DIV/0!
A23: =A22+1 -> 46157 | I23: =H23*21% -> 0 | K23: =H23+I23+J23 -> 0 | O23: =N23*21% -> 0 | P23: =+N23+O23 -> 0 | T23: =S23*21% -> 0 | U23: =SUM(S23:T23) -> 0 | Y23: =X23*21% -> 0 | Z23: =SUM(X23:Y23) -> 0 | AA23: =+K23+P23+U23-Z23 -> 0 | AG23: =AF23*220 -> 0 | AI23: =AH23*1200 -> 0 | AK23: =AJ23*1200 -> 0 | AL23: =AC23+AD23+AE23+AG23+AI23+AK23 -> 0 | AM23: =SUM(AL23-BH23) -> 0 | AP23: =AD23 | AQ23: =SUM(AR23:AS23) -> 0 | AW23: =AV23*AW$3 -> 0 | AY23: =AX23*AY$2 -> 0 | BA23: =AZ23*BA$2 -> 0 | BC23: =BB23*BC$2 -> 0 | BE23: =BD23*BE$2 -> 0 | BG23: =BF23*BG$4 -> 0 | BH23: =+AN23+AO23+AQ23+AT23+AU23+AW23+AY23+BA23+BC23+BE23+BG23 -> 0 | BI23: =AA23 -> 0 | BJ23: =SUM(BH23-BI23) -> 0 | BL23: =IF(AN23+AO23=0,0,(AN23+AO23)/AA23) -> 0 | BM23: =IF(AR23=0,0,AR23/AA23) -> 0 | BN23: =IF(AS23=0,0,AS23/AA23) -> 0 | BO23: =IF(AT23=0,0,AT23/AA23) -> 0 | BP23: =IF(AW23=0,0,AW23/AA23) -> 0 | BQ23: =IF(AY23+BA23+BC23=0,0,(AY23+BA23+BC23)/AA23) -> 0 | BR23: =IF(BG23=0,0,BG23/AA23) -> 0 | BS23: =SUM(BL23:BR23) -> 0 | BT23: =AA23/$AA$41 -> #DIV/0!
A24: =A23+1 -> 46158 | I24: =H24*21% -> 0 | K24: =H24+I24+J24 -> 0 | O24: =N24*21% -> 0 | P24: =+N24+O24 -> 0 | T24: =S24*21% -> 0 | U24: =SUM(S24:T24) -> 0 | Y24: =X24*21% -> 0 | Z24: =SUM(X24:Y24) -> 0 | AA24: =+K24+P24+U24-Z24 -> 0 | AG24: =AF24*220 -> 0 | AI24: =AH24*1200 -> 0 | AK24: =AJ24*1200 -> 0 | AL24: =AC24+AD24+AE24+AG24+AI24+AK24 -> 0 | AM24: =SUM(AL24-BH24) -> 0 | AP24: =AD24 | AQ24: =SUM(AR24:AS24) -> 0 | AW24: =AV24*AW$3 -> 0 | AY24: =AX24*AY$2 -> 0 | BA24: =AZ24*BA$2 -> 0 | BC24: =BB24*BC$2 -> 0 | BE24: =BD24*BE$2 -> 0 | BG24: =BF24*BG$4 -> 0 | BH24: =+AN24+AO24+AQ24+AT24+AU24+AW24+AY24+BA24+BC24+BE24+BG24 -> 0 | BI24: =AA24 -> 0 | BJ24: =SUM(BH24-BI24) -> 0 | BL24: =IF(AN24+AO24=0,0,(AN24+AO24)/AA24) -> 0 | BM24: =IF(AR24=0,0,AR24/AA24) -> 0 | BN24: =IF(AS24=0,0,AS24/AA24) -> 0 | BO24: =IF(AT24=0,0,AT24/AA24) -> 0 | BP24: =IF(AW24=0,0,AW24/AA24) -> 0 | BQ24: =IF(AY24+BA24+BC24=0,0,(AY24+BA24+BC24)/AA24) -> 0 | BR24: =IF(BG24=0,0,BG24/AA24) -> 0 | BS24: =SUM(BL24:BR24) -> 0 | BT24: =AA24/$AA$41 -> #DIV/0!
A25: =A24+1 -> 46159 | I25: =H25*21% -> 0 | K25: =H25+I25+J25 -> 0 | O25: =N25*21% -> 0 | P25: =+N25+O25 -> 0 | T25: =S25*21% -> 0 | U25: =SUM(S25:T25) -> 0 | Y25: =X25*21% -> 0 | Z25: =SUM(X25:Y25) -> 0 | AA25: =+K25+P25+U25-Z25 -> 0 | AG25: =AF25*220 -> 0 | AI25: =AH25*1200 -> 0 | AK25: =AJ25*1200 -> 0 | AL25: =AC25+AD25+AE25+AG25+AI25+AK25 -> 0 | AM25: =SUM(AL25-BH25) -> 0 | AP25: =AD25 | AQ25: =SUM(AR25:AS25) -> 0 | AW25: =AV25*AW$3 -> 0 | AY25: =AX25*AY$2 -> 0 | BA25: =AZ25*BA$2 -> 0 | BC25: =BB25*BC$2 -> 0 | BE25: =BD25*BE$2 -> 0 | BG25: =BF25*BG$4 -> 0 | BH25: =+AN25+AO25+AQ25+AT25+AU25+AW25+AY25+BA25+BC25+BE25+BG25 -> 0 | BI25: =AA25 -> 0 | BJ25: =SUM(BH25-BI25) -> 0 | BL25: =IF(AN25+AO25=0,0,(AN25+AO25)/AA25) -> 0 | BM25: =IF(AR25=0,0,AR25/AA25) -> 0 | BN25: =IF(AS25=0,0,AS25/AA25) -> 0 | BO25: =IF(AT25=0,0,AT25/AA25) -> 0 | BP25: =IF(AW25=0,0,AW25/AA25) -> 0 | BQ25: =IF(AY25+BA25+BC25=0,0,(AY25+BA25+BC25)/AA25) -> 0 | BR25: =IF(BG25=0,0,BG25/AA25) -> 0 | BS25: =SUM(BL25:BR25) -> 0 | BT25: =AA25/$AA$41 -> #DIV/0!
A26: =A25+1 -> 46160 | I26: =H26*21% -> 0 | K26: =H26+I26+J26 -> 0 | O26: =N26*21% -> 0 | P26: =+N26+O26 -> 0 | T26: =S26*21% -> 0 | U26: =SUM(S26:T26) -> 0 | Y26: =X26*21% -> 0 | Z26: =SUM(X26:Y26) -> 0 | AA26: =+K26+P26+U26-Z26 -> 0 | AG26: =AF26*220 -> 0 | AI26: =AH26*1200 -> 0 | AK26: =AJ26*1200 -> 0 | AL26: =AC26+AD26+AE26+AG26+AI26+AK26 -> 0 | AM26: =SUM(AL26-BH26) -> 0 | AP26: =AD26 | AQ26: =SUM(AR26:AS26) -> 0 | AW26: =AV26*AW$3 -> 0 | AY26: =AX26*AY$2 -> 0 | BA26: =AZ26*BA$2 -> 0 | BC26: =BB26*BC$2 -> 0 | BE26: =BD26*BE$2 -> 0 | BG26: =BF26*BG$4 -> 0 | BH26: =+AN26+AO26+AQ26+AT26+AU26+AW26+AY26+BA26+BC26+BE26+BG26 -> 0 | BI26: =AA26 -> 0 | BJ26: =SUM(BH26-BI26) -> 0 | BL26: =IF(AN26+AO26=0,0,(AN26+AO26)/AA26) -> 0 | BM26: =IF(AR26=0,0,AR26/AA26) -> 0 | BN26: =IF(AS26=0,0,AS26/AA26) -> 0 | BO26: =IF(AT26=0,0,AT26/AA26) -> 0 | BP26: =IF(AW26=0,0,AW26/AA26) -> 0 | BQ26: =IF(AY26+BA26+BC26=0,0,(AY26+BA26+BC26)/AA26) -> 0 | BR26: =IF(BG26=0,0,BG26/AA26) -> 0 | BS26: =SUM(BL26:BR26) -> 0 | BT26: =AA26/$AA$41 -> #DIV/0!
A27: =A26+1 -> 46161 | I27: =H27*21% -> 0 | K27: =H27+I27+J27 -> 0 | O27: =N27*21% -> 0 | P27: =+N27+O27 -> 0 | T27: =S27*21% -> 0 | U27: =SUM(S27:T27) -> 0 | Y27: =X27*21% -> 0 | Z27: =SUM(X27:Y27) -> 0 | AA27: =+K27+P27+U27-Z27 -> 0 | AG27: =AF27*220 -> 0 | AI27: =AH27*1200 -> 0 | AK27: =AJ27*1200 -> 0 | AL27: =AC27+AD27+AE27+AG27+AI27+AK27 -> 0 | AM27: =SUM(AL27-BH27) -> 0 | AP27: =AD27 | AQ27: =SUM(AR27:AS27) -> 0 | AW27: =AV27*AW$3 -> 0 | AY27: =AX27*AY$2 -> 0 | BA27: =AZ27*BA$2 -> 0 | BC27: =BB27*BC$2 -> 0 | BE27: =BD27*BE$2 -> 0 | BG27: =BF27*BG$4 -> 0 | BH27: =+AN27+AO27+AQ27+AT27+AU27+AW27+AY27+BA27+BC27+BE27+BG27 -> 0 | BI27: =AA27 -> 0 | BJ27: =SUM(BH27-BI27) -> 0 | BL27: =IF(AN27+AO27=0,0,(AN27+AO27)/AA27) -> 0 | BM27: =IF(AR27=0,0,AR27/AA27) -> 0 | BN27: =IF(AS27=0,0,AS27/AA27) -> 0 | BO27: =IF(AT27=0,0,AT27/AA27) -> 0 | BP27: =IF(AW27=0,0,AW27/AA27) -> 0 | BQ27: =IF(AY27+BA27+BC27=0,0,(AY27+BA27+BC27)/AA27) -> 0 | BR27: =IF(BG27=0,0,BG27/AA27) -> 0 | BS27: =SUM(BL27:BR27) -> 0 | BT27: =AA27/$AA$41 -> #DIV/0!
A28: =A27+1 -> 46162 | I28: =H28*21% -> 0 | K28: =H28+I28+J28 -> 0 | O28: =N28*21% -> 0 | P28: =+N28+O28 -> 0 | T28: =S28*21% -> 0 | U28: =SUM(S28:T28) -> 0 | Y28: =X28*21% -> 0 | Z28: =SUM(X28:Y28) -> 0 | AA28: =+K28+P28+U28-Z28 -> 0 | AG28: =AF28*220 -> 0 | AI28: =AH28*1200 -> 0 | AK28: =AJ28*1200 -> 0 | AL28: =AC28+AD28+AE28+AG28+AI28+AK28 -> 0 | AM28: =SUM(AL28-BH28) -> 0 | AP28: =AD28 | AQ28: =SUM(AR28:AS28) -> 0 | AW28: =AV28*AW$3 -> 0 | AY28: =AX28*AY$2 -> 0 | BA28: =AZ28*BA$2 -> 0 | BC28: =BB28*BC$2 -> 0 | BE28: =BD28*BE$2 -> 0 | BG28: =BF28*BG$4 -> 0 | BH28: =+AN28+AO28+AQ28+AT28+AU28+AW28+AY28+BA28+BC28+BE28+BG28 -> 0 | BI28: =AA28 -> 0 | BJ28: =SUM(BH28-BI28) -> 0 | BL28: =IF(AN28+AO28=0,0,(AN28+AO28)/AA28) -> 0 | BM28: =IF(AR28=0,0,AR28/AA28) -> 0 | BN28: =IF(AS28=0,0,AS28/AA28) -> 0 | BO28: =IF(AT28=0,0,AT28/AA28) -> 0 | BP28: =IF(AW28=0,0,AW28/AA28) -> 0 | BQ28: =IF(AY28+BA28+BC28=0,0,(AY28+BA28+BC28)/AA28) -> 0 | BR28: =IF(BG28=0,0,BG28/AA28) -> 0 | BS28: =SUM(BL28:BR28) -> 0 | BT28: =AA28/$AA$41 -> #DIV/0!
A29: =A28+1 -> 46163 | I29: =H29*21% -> 0 | K29: =H29+I29+J29 -> 0 | O29: =N29*21% -> 0 | P29: =+N29+O29 -> 0 | T29: =S29*21% -> 0 | U29: =SUM(S29:T29) -> 0 | Y29: =X29*21% -> 0 | Z29: =SUM(X29:Y29) -> 0 | AA29: =+K29+P29+U29-Z29 -> 0 | AG29: =AF29*220 -> 0 | AI29: =AH29*1200 -> 0 | AK29: =AJ29*1200 -> 0 | AL29: =AC29+AD29+AE29+AG29+AI29+AK29 -> 0 | AM29: =SUM(AL29-BH29) -> 0 | AP29: =AD29 | AQ29: =SUM(AR29:AS29) -> 0 | AW29: =AV29*AW$3 -> 0 | AY29: =AX29*AY$2 -> 0 | BA29: =AZ29*BA$2 -> 0 | BC29: =BB29*BC$2 -> 0 | BE29: =BD29*BE$2 -> 0 | BG29: =BF29*BG$4 -> 0 | BH29: =+AN29+AO29+AQ29+AT29+AU29+AW29+AY29+BA29+BC29+BE29+BG29 -> 0 | BI29: =AA29 -> 0 | BJ29: =SUM(BH29-BI29) -> 0 | BK29: =SUM(BJ9:BJ29) -> 0 | BL29: =IF(AN29+AO29=0,0,(AN29+AO29)/AA29) -> 0 | BM29: =IF(AR29=0,0,AR29/AA29) -> 0 | BN29: =IF(AS29=0,0,AS29/AA29) -> 0 | BO29: =IF(AT29=0,0,AT29/AA29) -> 0 | BP29: =IF(AW29=0,0,AW29/AA29) -> 0 | BQ29: =IF(AY29+BA29+BC29=0,0,(AY29+BA29+BC29)/AA29) -> 0 | BR29: =IF(BG29=0,0,BG29/AA29) -> 0 | BS29: =SUM(BL29:BR29) -> 0 | BT29: =AA29/$AA$41 -> #DIV/0!
A30: =A29+1 -> 46164 | I30: =H30*21% -> 0 | K30: =H30+I30+J30 -> 0 | O30: =N30*21% -> 0 | P30: =+N30+O30 -> 0 | T30: =S30*21% -> 0 | U30: =SUM(S30:T30) -> 0 | Y30: =X30*21% -> 0 | Z30: =SUM(X30:Y30) -> 0 | AA30: =+K30+P30+U30-Z30 -> 0 | AG30: =AF30*220 -> 0 | AI30: =AH30*1200 -> 0 | AK30: =AJ30*1200 -> 0 | AL30: =AC30+AD30+AE30+AG30+AI30+AK30 -> 0 | AM30: =SUM(AL30-BH30) -> 0 | AP30: =AD30 | AQ30: =SUM(AR30:AS30) -> 0 | AW30: =AV30*AW$3 -> 0 | AY30: =AX30*AY$2 -> 0 | BA30: =AZ30*BA$2 -> 0 | BC30: =BB30*BC$2 -> 0 | BE30: =BD30*BE$2 -> 0 | BG30: =BF30*BG$4 -> 0 | BH30: =+AN30+AO30+AQ30+AT30+AU30+AW30+AY30+BA30+BC30+BE30+BG30 -> 0 | BI30: =AA30 -> 0 | BJ30: =SUM(BH30-BI30) -> 0 | BL30: =IF(AN30+AO30=0,0,(AN30+AO30)/AA30) -> 0 | BM30: =IF(AR30=0,0,AR30/AA30) -> 0 | BN30: =IF(AS30=0,0,AS30/AA30) -> 0 | BO30: =IF(AT30=0,0,AT30/AA30) -> 0 | BP30: =IF(AW30=0,0,AW30/AA30) -> 0 | BQ30: =IF(AY30+BA30+BC30=0,0,(AY30+BA30+BC30)/AA30) -> 0 | BR30: =IF(BG30=0,0,BG30/AA30) -> 0 | BS30: =SUM(BL30:BR30) -> 0 | BT30: =AA30/$AA$41 -> #DIV/0!
A31: =A30+1 -> 46165 | I31: =H31*21% -> 0 | K31: =H31+I31+J31 -> 0 | O31: =N31*21% -> 0 | P31: =+N31+O31 -> 0 | T31: =S31*21% -> 0 | U31: =SUM(S31:T31) -> 0 | Y31: =X31*21% -> 0 | Z31: =SUM(X31:Y31) -> 0 | AA31: =+K31+P31+U31-Z31 -> 0 | AG31: =AF31*220 -> 0 | AI31: =AH31*1200 -> 0 | AK31: =AJ31*1200 -> 0 | AL31: =AC31+AD31+AE31+AG31+AI31+AK31 -> 0 | AM31: =SUM(AL31-BH31) -> 0 | AP31: =AD31 | AQ31: =SUM(AR31:AS31) -> 0 | AW31: =AV31*AW$3 -> 0 | AY31: =AX31*AY$2 -> 0 | BA31: =AZ31*BA$2 -> 0 | BC31: =BB31*BC$2 -> 0 | BE31: =BD31*BE$2 -> 0 | BG31: =BF31*BG$4 -> 0 | BH31: =+AN31+AO31+AQ31+AT31+AU31+AW31+AY31+BA31+BC31+BE31+BG31 -> 0 | BI31: =AA31 -> 0 | BJ31: =SUM(BH31-BI31) -> 0 | BL31: =IF(AN31+AO31=0,0,(AN31+AO31)/AA31) -> 0 | BM31: =IF(AR31=0,0,AR31/AA31) -> 0 | BN31: =IF(AS31=0,0,AS31/AA31) -> 0 | BO31: =IF(AT31=0,0,AT31/AA31) -> 0 | BP31: =IF(AW31=0,0,AW31/AA31) -> 0 | BQ31: =IF(AY31+BA31+BC31=0,0,(AY31+BA31+BC31)/AA31) -> 0 | BR31: =IF(BG31=0,0,BG31/AA31) -> 0 | BS31: =SUM(BL31:BR31) -> 0 | BT31: =AA31/$AA$41 -> #DIV/0!
A32: =A31+1 -> 46166 | I32: =H32*21% -> 0 | K32: =H32+I32+J32 -> 0 | O32: =N32*21% -> 0 | P32: =+N32+O32 -> 0 | T32: =S32*21% -> 0 | U32: =SUM(S32:T32) -> 0 | Y32: =X32*21% -> 0 | Z32: =SUM(X32:Y32) -> 0 | AA32: =+K32+P32+U32-Z32 -> 0 | AG32: =AF32*220 -> 0 | AI32: =AH32*1200 -> 0 | AK32: =AJ32*1200 -> 0 | AL32: =AC32+AD32+AE32+AG32+AI32+AK32 -> 0 | AM32: =SUM(AL32-BH32) -> 0 | AP32: =AD32 | AQ32: =SUM(AR32:AS32) -> 0 | AW32: =AV32*AW$3 -> 0 | AY32: =AX32*AY$2 -> 0 | BA32: =AZ32*BA$2 -> 0 | BC32: =BB32*BC$2 -> 0 | BE32: =BD32*BE$2 -> 0 | BG32: =BF32*BG$4 -> 0 | BH32: =+AN32+AO32+AQ32+AT32+AU32+AW32+AY32+BA32+BC32+BE32+BG32 -> 0 | BI32: =AA32 -> 0 | BJ32: =SUM(BH32-BI32) -> 0 | BL32: =IF(AN32+AO32=0,0,(AN32+AO32)/AA32) -> 0 | BM32: =IF(AR32=0,0,AR32/AA32) -> 0 | BN32: =IF(AS32=0,0,AS32/AA32) -> 0 | BO32: =IF(AT32=0,0,AT32/AA32) -> 0 | BP32: =IF(AW32=0,0,AW32/AA32) -> 0 | BQ32: =IF(AY32+BA32+BC32=0,0,(AY32+BA32+BC32)/AA32) -> 0 | BR32: =IF(BG32=0,0,BG32/AA32) -> 0 | BS32: =SUM(BL32:BR32) -> 0 | BT32: =AA32/$AA$41 -> #DIV/0!
A33: =A32+1 -> 46167 | I33: =H33*21% -> 0 | K33: =H33+I33+J33 -> 0 | O33: =N33*21% -> 0 | P33: =+N33+O33 -> 0 | T33: =S33*21% -> 0 | U33: =SUM(S33:T33) -> 0 | Y33: =X33*21% -> 0 | Z33: =SUM(X33:Y33) -> 0 | AA33: =+K33+P33+U33-Z33 -> 0 | AG33: =AF33*220 -> 0 | AI33: =AH33*1200 -> 0 | AK33: =AJ33*1200 -> 0 | AL33: =AC33+AD33+AE33+AG33+AI33+AK33 -> 0 | AM33: =SUM(AL33-BH33) -> 0 | AP33: =AD33 | AQ33: =SUM(AR33:AS33) -> 0 | AW33: =AV33*AW$3 -> 0 | AY33: =AX33*AY$2 -> 0 | BA33: =AZ33*BA$2 -> 0 | BC33: =BB33*BC$2 -> 0 | BE33: =BD33*BE$2 -> 0 | BG33: =BF33*BG$4 -> 0 | BH33: =+AN33+AO33+AQ33+AT33+AU33+AW33+AY33+BA33+BC33+BE33+BG33 -> 0 | BI33: =AA33 -> 0 | BJ33: =SUM(BH33-BI33) -> 0 | BL33: =IF(AN33+AO33=0,0,(AN33+AO33)/AA33) -> 0 | BM33: =IF(AR33=0,0,AR33/AA33) -> 0 | BN33: =IF(AS33=0,0,AS33/AA33) -> 0 | BO33: =IF(AT33=0,0,AT33/AA33) -> 0 | BP33: =IF(AW33=0,0,AW33/AA33) -> 0 | BQ33: =IF(AY33+BA33+BC33=0,0,(AY33+BA33+BC33)/AA33) -> 0 | BR33: =IF(BG33=0,0,BG33/AA33) -> 0 | BS33: =SUM(BL33:BR33) -> 0 | BT33: =AA33/$AA$41 -> #DIV/0!
A34: =A33+1 -> 46168 | I34: =H34*21% -> 0 | K34: =H34+I34+J34 -> 0 | O34: =N34*21% -> 0 | P34: =+N34+O34 -> 0 | T34: =S34*21% -> 0 | U34: =SUM(S34:T34) -> 0 | Y34: =X34*21% -> 0 | Z34: =SUM(X34:Y34) -> 0 | AA34: =+K34+P34+U34-Z34 -> 0 | AG34: =AF34*220 -> 0 | AI34: =AH34*1200 -> 0 | AK34: =AJ34*1200 -> 0 | AL34: =AC34+AD34+AE34+AG34+AI34+AK34 -> 0 | AM34: =SUM(AL34-BH34) -> 0 | AP34: =AD34 | AQ34: =SUM(AR34:AS34) -> 0 | AW34: =AV34*AW$3 -> 0 | AY34: =AX34*AY$2 -> 0 | BA34: =AZ34*BA$2 -> 0 | BC34: =BB34*BC$2 -> 0 | BE34: =BD34*BE$2 -> 0 | BG34: =BF34*BG$4 -> 0 | BH34: =+AN34+AO34+AQ34+AT34+AU34+AW34+AY34+BA34+BC34+BE34+BG34 -> 0 | BI34: =AA34 -> 0 | BJ34: =SUM(BH34-BI34) -> 0 | BL34: =IF(AN34+AO34=0,0,(AN34+AO34)/AA34) -> 0 | BM34: =IF(AR34=0,0,AR34/AA34) -> 0 | BN34: =IF(AS34=0,0,AS34/AA34) -> 0 | BO34: =IF(AT34=0,0,AT34/AA34) -> 0 | BP34: =IF(AW34=0,0,AW34/AA34) -> 0 | BQ34: =IF(AY34+BA34+BC34=0,0,(AY34+BA34+BC34)/AA34) -> 0 | BR34: =IF(BG34=0,0,BG34/AA34) -> 0 | BS34: =SUM(BL34:BR34) -> 0 | BT34: =AA34/$AA$41 -> #DIV/0!
A35: =A34+1 -> 46169 | I35: =H35*21% -> 0 | K35: =H35+I35+J35 -> 0 | O35: =N35*21% -> 0 | P35: =+N35+O35 -> 0 | T35: =S35*21% -> 0 | U35: =SUM(S35:T35) -> 0 | Y35: =X35*21% -> 0 | Z35: =SUM(X35:Y35) -> 0 | AA35: =+K35+P35+U35-Z35 -> 0 | AG35: =AF35*220 -> 0 | AI35: =AH35*1200 -> 0 | AK35: =AJ35*1200 -> 0 | AL35: =AC35+AD35+AE35+AG35+AI35+AK35 -> 0 | AM35: =SUM(AL35-BH35) -> 0 | AP35: =AD35 | AQ35: =SUM(AR35:AS35) -> 0 | AW35: =AV35*AW$3 -> 0 | AY35: =AX35*AY$2 -> 0 | BA35: =AZ35*BA$2 -> 0 | BC35: =BB35*BC$2 -> 0 | BE35: =BD35*BE$2 -> 0 | BG35: =BF35*BG$4 -> 0 | BH35: =+AN35+AO35+AQ35+AT35+AU35+AW35+AY35+BA35+BC35+BE35+BG35 -> 0 | BI35: =AA35 -> 0 | BJ35: =SUM(BH35-BI35) -> 0 | BL35: =IF(AN35+AO35=0,0,(AN35+AO35)/AA35) -> 0 | BM35: =IF(AR35=0,0,AR35/AA35) -> 0 | BN35: =IF(AS35=0,0,AS35/AA35) -> 0 | BO35: =IF(AT35=0,0,AT35/AA35) -> 0 | BP35: =IF(AW35=0,0,AW35/AA35) -> 0 | BQ35: =IF(AY35+BA35+BC35=0,0,(AY35+BA35+BC35)/AA35) -> 0 | BR35: =IF(BG35=0,0,BG35/AA35) -> 0 | BS35: =SUM(BL35:BR35) -> 0 | BT35: =AA35/$AA$41 -> #DIV/0!
A36: =A35+1 -> 46170 | I36: =H36*21% -> 0 | K36: =H36+I36+J36 -> 0 | O36: =N36*21% -> 0 | P36: =+N36+O36 -> 0 | T36: =S36*21% -> 0 | U36: =SUM(S36:T36) -> 0 | Y36: =X36*21% -> 0 | Z36: =SUM(X36:Y36) -> 0 | AA36: =+K36+P36+U36-Z36 -> 0 | AG36: =AF36*220 -> 0 | AI36: =AH36*1200 -> 0 | AK36: =AJ36*1200 -> 0 | AL36: =AC36+AD36+AE36+AG36+AI36+AK36 -> 0 | AM36: =SUM(AL36-BH36) -> 0 | AP36: =AD36 | AQ36: =SUM(AR36:AS36) -> 0 | AW36: =AV36*AW$3 -> 0 | AY36: =AX36*AY$2 -> 0 | BA36: =AZ36*BA$2 -> 0 | BC36: =BB36*BC$2 -> 0 | BE36: =BD36*BE$2 -> 0 | BG36: =BF36*BG$4 -> 0 | BH36: =+AN36+AO36+AQ36+AT36+AU36+AW36+AY36+BA36+BC36+BE36+BG36 -> 0 | BI36: =AA36 -> 0 | BJ36: =SUM(BH36-BI36) -> 0 | BL36: =IF(AN36+AO36=0,0,(AN36+AO36)/AA36) -> 0 | BM36: =IF(AR36=0,0,AR36/AA36) -> 0 | BN36: =IF(AS36=0,0,AS36/AA36) -> 0 | BO36: =IF(AT36=0,0,AT36/AA36) -> 0 | BP36: =IF(AW36=0,0,AW36/AA36) -> 0 | BQ36: =IF(AY36+BA36+BC36=0,0,(AY36+BA36+BC36)/AA36) -> 0 | BR36: =IF(BG36=0,0,BG36/AA36) -> 0 | BS36: =SUM(BL36:BR36) -> 0 | BT36: =AA36/$AA$41 -> #DIV/0!
A37: =A36+1 -> 46171 | I37: =H37*21% -> 0 | K37: =H37+I37+J37 -> 0 | O37: =N37*21% -> 0 | P37: =+N37+O37 -> 0 | T37: =S37*21% -> 0 | U37: =SUM(S37:T37) -> 0 | Y37: =X37*21% -> 0 | Z37: =SUM(X37:Y37) -> 0 | AA37: =+K37+P37+U37-Z37 -> 0 | AG37: =AF37*220 -> 0 | AI37: =AH37*1200 -> 0 | AK37: =AJ37*1200 -> 0 | AL37: =AC37+AD37+AE37+AG37+AI37+AK37 -> 0 | AM37: =SUM(AL37-BH37) -> 0 | AP37: =AD37 | AQ37: =SUM(AR37:AS37) -> 0 | AW37: =AV37*AW$3 -> 0 | AY37: =AX37*AY$2 -> 0 | BA37: =AZ37*BA$2 -> 0 | BC37: =BB37*BC$2 -> 0 | BE37: =BD37*BE$2 -> 0 | BG37: =BF37*BG$4 -> 0 | BH37: =+AN37+AO37+AQ37+AT37+AU37+AW37+AY37+BA37+BC37+BE37+BG37 -> 0 | BI37: =AA37 -> 0 | BJ37: =SUM(BH37-BI37) -> 0 | BL37: =IF(AN37+AO37=0,0,(AN37+AO37)/AA37) -> 0 | BM37: =IF(AR37=0,0,AR37/AA37) -> 0 | BN37: =IF(AS37=0,0,AS37/AA37) -> 0 | BO37: =IF(AT37=0,0,AT37/AA37) -> 0 | BP37: =IF(AW37=0,0,AW37/AA37) -> 0 | BQ37: =IF(AY37+BA37+BC37=0,0,(AY37+BA37+BC37)/AA37) -> 0 | BR37: =IF(BG37=0,0,BG37/AA37) -> 0 | BS37: =SUM(BL37:BR37) -> 0 | BT37: =AA37/$AA$41 -> #DIV/0!
A38: =A37+1 -> 46172 | I38: =H38*21% -> 0 | K38: =H38+I38+J38 -> 0 | O38: =N38*21% -> 0 | P38: =+N38+O38 -> 0 | T38: =S38*21% -> 0 | U38: =SUM(S38:T38) -> 0 | Y38: =X38*21% -> 0 | Z38: =SUM(X38:Y38) -> 0 | AA38: =+K38+P38+U38-Z38 -> 0 | AG38: =AF38*220 -> 0 | AI38: =AH38*1200 -> 0 | AK38: =AJ38*1200 -> 0 | AL38: =AC38+AD38+AE38+AG38+AI38+AK38 -> 0 | AM38: =SUM(AL38-BH38) -> 0 | AP38: =AD38 | AQ38: =SUM(AR38:AS38) -> 0 | AW38: =AV38*AW$3 -> 0 | AY38: =AX38*AY$2 -> 0 | BA38: =AZ38*BA$2 -> 0 | BC38: =BB38*BC$2 -> 0 | BE38: =BD38*BE$2 -> 0 | BG38: =BF38*BG$4 -> 0 | BH38: =+AN38+AO38+AQ38+AT38+AU38+AW38+AY38+BA38+BC38+BE38+BG38 -> 0 | BI38: =AA38 -> 0 | BJ38: =SUM(BH38-BI38) -> 0 | BL38: =IF(AN38+AO38=0,0,(AN38+AO38)/AA38) -> 0 | BM38: =IF(AR38=0,0,AR38/AA38) -> 0 | BN38: =IF(AS38=0,0,AS38/AA38) -> 0 | BO38: =IF(AT38=0,0,AT38/AA38) -> 0 | BP38: =IF(AW38=0,0,AW38/AA38) -> 0 | BQ38: =IF(AY38+BA38+BC38=0,0,(AY38+BA38+BC38)/AA38) -> 0 | BR38: =IF(BG38=0,0,BG38/AA38) -> 0 | BS38: =SUM(BL38:BR38) -> 0 | BT38: =AA38/$AA$41 -> #DIV/0!
I39: =H39*21% -> 0 | K39: =H39+I39+J39 -> 0 | O39: =N39*21% -> 0 | P39: =+N39+O39 -> 0 | T39: =S39*21% -> 0 | U39: =SUM(S39:T39) -> 0 | Y39: =X39*21% -> 0 | Z39: =SUM(X39:Y39) -> 0 | AA39: =+K39+P39+U39-Z39 -> 0 | AG39: =AF39*220 -> 0 | AI39: =AH39*1200 -> 0 | AK39: =AJ39*1200 -> 0 | AQ39: =SUM(AR39:AS39) -> 0 | AW39: =AV39*AW$3 -> 0 | AY39: =AX39*AY$2 -> 0 | BA39: =AZ39*BA$2 -> 0 | BC39: =BB39*BC$2 -> 0 | BE39: =BD39*BE$2 -> 0 | BG39: =BF39*BG$4 -> 0 | BH39: =+AN39+AO39+AQ39+AT39+AU39+AW39+AY39+BA39+BC39+BE39+BG39 -> 0 | BI39: =AA39 -> 0 | BJ39: =SUM(BH39-BI39) -> 0 | BT39: =AA39/$AA$41 -> #DIV/0!
T40: =S40*21% -> 0 | Y40: =X40*21% -> 0 | AW40: =AV40*AW$3 -> 0 | AY40: =AX40*AY$2 -> 0 | BA40: =AZ40*BA$2 -> 0 | BC40: =BB40*BC$2 -> 0 | BE40: =BD40*BE$2 -> 0 | BG40: =BF40*BG$4 -> 0 | BH40: =+AN40+AO40+AQ40+AT40+AU40+AW40+AY40+BA40+BC40+BE40+BG40 -> 0 | BJ40: =SUM(BH40-BI40) -> 0
A41: TOTALES | B41: =MAX(B9:B40) -> 0 | C41: =SUM(C9:C40) -> 0 | D41: =MIN(D9:D40) -> 0 | E41: =MAX(E9:E40) -> 0 | F41: =SUM(F9:F40) -> 0 | G41: =SUM(G9:G40) -> 0 | H41: =SUM(H9:H40) -> 0 | I41: =SUM(I9:I40) -> 0 | K41: =SUM(K9:K40) -> 0 | L41: =MIN(L9:L40) -> 0 | M41: =MAX(M9:M40) -> 0 | N41: =SUM(N9:N40) -> 0 | O41: =SUM(O9:O40) -> 0 | P41: =SUM(P9:P40) -> 0 | Q41: =MIN(Q9:Q40) -> 0 | R41: =MAX(R9:R40) -> 0 | S41: =SUM(S9:S40) -> 0 | T41: =SUM(T9:T40) -> 0 | U41: =SUM(U9:U40) -> 0 | V41: =MIN(V9:V40) -> 0 | W41: =MAX(W9:W40) -> 0 | X41: =SUM(X9:X40) -> 0 | Y41: =SUM(Y9:Y40) -> 0 | Z41: =SUM(Z9:Z40) -> 0 | AA41: =SUM(AA9:AA40) -> 0 | AB41: =SUM(AB9:AB38) -> 0 | AC41: =SUM(AC9:AC38) -> 0 | AD41: =SUM(AD9:AD38) -> 0 | AE41: =SUM(AE9:AE38) -> 0 | AF41: =SUM(AF9:AF38) -> 0 | AG41: =SUM(AG9:AG38) -> 0 | AH41: =SUM(AH9:AH38) -> 0 | AI41: =SUM(AI9:AI38) -> 0 | ... AM41: =SUM(AM9:AM38) -> 0 | AN41: =SUM(AN9:AN40) -> 0 | AO41: =SUM(AO9:AO40) -> 0 | AP41: =SUM(AP9:AP40) -> 0 | AQ41: =SUM(AQ9:AQ40) -> 0 | AR41: =SUM(AR9:AR40) -> 0 | AS41: =SUM(AS9:AS40) -> 0 | AT41: =SUM(AT9:AT40) -> 0 | AU41: =SUM(AU9:AU40) -> 0 | ... BJ41: =SUM(BJ9:BJ40) -> 0 | BL41: =IF(AA41=0,0,(AN41+AO41)/AA41) -> 0 | BM41: =IF(AA41=0,0,(AR41)/AA41) -> 0 | BN41: =IF(AA41=0,0,(AS41)/AA41) -> 0 | BO41: =IF($AA$41=0,0,(AT41)/$AA$41) -> 0 | BP41: =IF($AA$41=0,0,(AU41)/$AA$41) -> 0 | BQ41: =IF($AA$41=0,0,(AY41+BA41+BC41)/AA41) -> 0 | BR41: =IF($AA$41=0,0,BG41/AA41) -> 0 | BS41: =SUM(BL41:BR41) -> 0
L42: 3
A43: CONTROL | L43: =L41-L42 -> -3 | Q43: =Q41-Q42 -> 0 | V43: =V41-V42 -> 0 | AB43: 0 | AC43: 0 | AD43: 0 | AE43: 0 | AF43: 0 | AG43: 0 | AH43: 0 | AI43: 0 | AJ43: 0 | AK43: 0 | AL43: 0
Z46: TOTAL | AA46: =AA41+AA45 -> 0 | AN46: $ Efectivo | AO46: $ Deposito / PIX | AP46: TARJETA DEBITO | AQ46: TARJETA CREDITO | AR46: Mercado Pago / TF | AS46: Real | AT46: Dólares | AU46: Euros
AM47: RESUMEN COBRANZA | AN47: =AN41 -> 0 | AO47: =AO41 -> 0 | AP47: =AR41 -> 0 | AQ47: =AS41 -> 0 | AR47: =AT41 -> 0 | AS47: =AW41 -> 0 | AT47: =BA41+BC41+BE41+AY41 -> 0 | AU47: =BG41 -> 0
AN48: =AN47/$AA$41 -> #DIV/0! | AO48: =AO47/$AA$41 -> #DIV/0! | AP48: =AP47/$AA$41 -> #DIV/0! | AQ48: =AQ47/$AA$41 -> #DIV/0! | AR48: =AR47/$AA$41 -> #DIV/0! | AS48: =AS47/$AA$41 -> #DIV/0! | AT48: =AT47/$AA$41 -> #DIV/0! | AU48: =AU47/$AA$41 -> #DIV/0!

Sheet LUCERO RECOLETA
AS1: Cotizaciones | AX1: De | AY1: Hasta
A2: Empresa: EL LUCERO CUERO S.A.
A3: Sucursal: LUCERO RECOLETA - Vte. Lopez 2050 Loc.214 - Shopping Recoleta Mall - CP C1128ACF
A5: INFORME DE VENTAS MENSUAL | F5: pv 00049
A7: ABRIL | B7: Detalle de FACTURAS B | L7: Detalle de TICKETS | R7: Detalle de FACTURAS A | X7: Detalle de NOTAS DE CREDITO | AD7: VENTA FINAL | AE7: INFORME SEGÚN MAIL | AP7: DIFERENCIA | AQ7: CONTROL DE CIERRE DE CAJA
A8: Fecha | B8: Informe de cierre | C8: N° Tickets | D8: Desde | E8: Hasta | F8: Anulados y/o cancelados | G8: Cant. de art. | H8: Imp. de VTA gravado | I8: IVA 21% | J8: Otros imp. | K8: Imp. de VTA total | L8: Desde | M8: Hasta | N8: Imp.de VTA gravado | O8: IVA 21% | P8: Otros imp. | Q8: Imp. de VTA total | R8: Desde | S8: Hasta | T8: Imp.de VTA gravado | U8: IVA 21% | V8: Otros imp. | W8: Imp. de VTA total | X8: Desde | Y8: Hasta | Z8: Imp.de VTA gravado | AA8: IVA 21% | AB8: Otros imp. | AC8: Imp. de VTA total | AE8: VENTA TOTAL | AF8: EFECTIVO $ | AG8: TARJETAS | AH8: MERCADO PAGO | AI8: Real | AK8: Dolar | AM8: EURO | AO8: TOTAL DE INGRESO | AQ8: $ Efectivo | AR8: $ Deposito / PIX | AS8: TARJ SEGUN PLANILLA | AT8: TOTAL TARJETAS OK | AU8: TARJETA DEBITO | AV8: TARJETA CREDITO | AW8: Mercado Pago / TF | AX8: Gastos | AY8: Real | BA8: Dólar 100 | BC8: Dólar 50 | BE8: Dólar 10. 20 | BG8: Dólar 1. 5 | BI8: EURO | BK8: Total | BL8: CIERRE | BM8: DIFERENCIA | BO8: =AQ8 -> $ Efectivo | BP8: =AU8 -> TARJETA DEBITO | BQ8: =AV8 -> TARJETA CREDITO | BR8: =AW8 -> Mercado Pago / TF | BS8: =AY8 -> Real | BT8: Dólar | BU8: Euro | BV8: Total | BW8: Venta x día
A9: 46143 | C9: 0 | D9: 1314 | E9: =IF(C9="","",C9+D9-1) -> 1313 | K9: =H9+I9+J9 -> 0 | O9: =N9*21% -> 0 | Q9: =N9+O9+P9 -> 0 | U9: =T9*21% -> 0 | W9: =T9+U9+V9 -> 0 | AA9: 0 | AC9: =Z9+AA9+AB9 -> 0 | AD9: =+K9+Q9+W9-AC9 -> 0 | AJ9: =AI9*220 -> 0 | AL9: =AK9*1200 -> 0 | AN9: =AM9*1200 -> 0 | AO9: =AF9+AG9+AH9+AJ9+AL9+AN9 -> 0 | AP9: =SUM(AO9-BK9) -> 0 | AS9: =AG9 | AT9: =SUM(AU9:AV9) -> 0 | AZ9: =AY9*AZ$2 -> 0 | BB9: =BA9*BB$2 -> 0 | BD9: =BC9*BD$2 -> 0 | BF9: =BE9*BF$2 -> 0 | BH9: =BG9*BH$2 -> 0 | BJ9: =BI9*BJ$2 -> 0 | BK9: =+AQ9+AR9+AT9+AW9+AX9+AZ9+BB9+BD9+BF9+BH8+BJ9 -> 0 | BL9: =AD9 -> 0 | BM9: =SUM(BK9-BL9) -> 0 | BO9: =IF(AQ9+AR9=0,0,(AQ9+AR9)/AD9) -> 0 | BP9: =IF(AU9=0,0,AU9/AD9) -> 0 | BQ9: =IF(AV9=0,0,AV9/AD9) -> 0 | BR9: =IF(AW9=0,0,AW9/AD9) -> 0 | BS9: =IF(AZ9=0,0,AZ9/AD9) -> 0 | BT9: =IF(BB9+BD9+BF9=0,0,(BB9+BD9+BF9)/AD9) -> 0 | BU9: =IF(BJ9=0,0,BJ9/AD9) -> 0 | BV9: =SUM(BO9:BU9) -> 0 | BW9: =AD9/$AD$41 -> 0
A10: =A9+1 -> 46144 | C10: 19 | D10: =E9+1 -> 1314 | E10: =IF(C10="","",C10+D10-1) -> 1332 | H10: 1398158.6 | I10: 293613.32 | K10: =H10+I10+J10 -> 1691771.9 | O10: =N10*21% -> 0 | Q10: =N10+O10+P10 -> 0 | U10: =T10*21% -> 0 | W10: =T10+U10+V10 -> 0 | AA10: 0 | AC10: =Z10+AA10+AB10 -> 0 | AD10: =+K10+Q10+W10-AC10 -> 1691771.9 | AJ10: =AI10*220 -> 0 | AL10: =AK10*1200 -> 0 | AN10: =AM10*1200 -> 0 | AO10: =AF10+AG10+AH10+AJ10+AL10+AN10 -> 0 | AP10: =SUM(AO10-BK10) -> -1691780 | AQ10: 100000 | AS10: =AG10 | AT10: =SUM(AU10:AV10) -> 1308780 | AU10: 415880 | AV10: 892900 | AZ10: =AY10*AZ$2 -> 0 | BA10: 200 | BB10: =BA10*1415 -> 283000 | BD10: =BC10*BD$2 -> 0 | BF10: =BE10*BF$2 -> 0 | BH10: =BG10*BH$2 -> 0 | BJ10: =BI10*BJ$2 -> 0 | BK10: =+AQ10+AR10+AT10+AW10+AX10+AZ10+BB10+BD10+BF10+BH9+BJ10 -> 1691780 | BL10: =AD10 -> 1691771.9 | BM10: =SUM(BK10-BL10) -> 8.1 | BO10: =IF(AQ10+AR10=0,0,(AQ10+AR10)/AD10) -> 0.059109623 | BP10: =IF(AU10=0,0,AU10/AD10) -> 0.2458251 | BQ10: =IF(AV10=0,0,AV10/AD10) -> 0.52778983 | BR10: =IF(AW10=0,0,AW10/AD10) -> 0 | BS10: =IF(AZ10=0,0,AZ10/AD10) -> 0 | BT10: =IF(BB10+BD10+BF10=0,0,(BB10+BD10+BF10)/AD10) -> 0.16728023 | BU10: =IF(BJ10=0,0,BJ10/AD10) -> 0 | BV10: =SUM(BO10:BU10) -> 1.0000048 | BW10: =AD10/$AD$41 -> 0.11880108
A11: =A10+1 -> 46145 | C11: 2 | D11: =E10+1 -> 1333 | E11: =IF(C11="","",C11+D11-1) -> 1334 | H11: 99148.76 | I11: 20821.24 | K11: =H11+I11+J11 -> 119970 | O11: =N11*21% -> 0 | Q11: =N11+O11+P11 -> 0 | U11: =T11*21% -> 0 | W11: =T11+U11+V11 -> 0 | AA11: 0 | AC11: =Z11+AA11+AB11 -> 0 | AD11: =+K11+Q11+W11-AC11 -> 119970 | AJ11: =AI11*220 -> 0 | AL11: =AK11*1200 -> 0 | AN11: =AM11*1200 -> 0 | AO11: =AF11+AG11+AH11+AJ11+AL11+AN11 -> 0 | AP11: =SUM(AO11-BK11) -> -119970 | AQ11: 0 | AS11: =AG11 | AT11: =SUM(AU11:AV11) -> 119970 | AU11: 79990 | AV11: 39980 | AZ11: =AY11*AZ$2 -> 0 | BB11: =BA11*1415 -> 0 | BD11: =BC11*BD$2 -> 0 | BF11: =BE11*BF$2 -> 0 | BH11: =BG11*BH$2 -> 0 | BJ11: =BI11*BJ$2 -> 0 | BK11: =+AQ11+AR11+AT11+AW11+AX11+AZ11+BB11+BD11+BF11+BH11+BJ11 -> 119970 | BL11: =AD11 -> 119970 | BM11: =SUM(BK11-BL11) -> 0 | BO11: =IF(AQ11+AR11=0,0,(AQ11+AR11)/AD11) -> 0 | BP11: =IF(AU11=0,0,AU11/AD11) -> 0.66675002 | BQ11: =IF(AV11=0,0,AV11/AD11) -> 0.33324998 | BR11: =IF(AW11=0,0,AW11/AD11) -> 0 | BS11: =IF(AZ11=0,0,AZ11/AD11) -> 0 | BT11: =IF(BB11+BD11+BF11=0,0,(BB11+BD11+BF11)/AD11) -> 0 | BU11: =IF(BJ11=0,0,BJ11/AD11) -> 0 | BV11: =SUM(BO11:BU11) -> 1 | BW11: =AD11/$AD$41 -> 0.0084246377
A12: =A11+1 -> 46146 | C12: 5 | D12: =E11+1 -> 1335 | E12: =IF(C12="","",C12+D12-1) -> 1339 | H12: 229702.48 | I12: 48237.52 | K12: =H12+I12+J12 -> 277940 | O12: =N12*21% -> 0 | Q12: =N12+O12+P12 -> 0 | U12: =T12*21% -> 0 | W12: =T12+U12+V12 -> 0 | X12: 25 | Y12: 25 | Z12: 57842.97 | AA12: 12147.03 | AC12: =Z12+AA12+AB12 -> 69990 | AD12: =+K12+Q12+W12-AC12 -> 207950 | AJ12: =AI12*220 -> 0 | AL12: =AK12*1200 -> 0 | AN12: =AM12*1200 -> 0 | AO12: =AF12+AG12+AH12+AJ12+AL12+AN12 -> 0 | AP12: =SUM(AO12-BK12) -> -231960 | AQ12: 20000 | AS12: =AG12 | AT12: =SUM(AU12:AV12) -> 211960 | AU12: 84990 | AV12: 126970 | AZ12: =AY12*AZ$2 -> 0 | BB12: =BA12*BB$2 -> 0 | BD12: =BC12*BD$2 -> 0 | BF12: =BE12*BF$2 -> 0 | BH12: =BG12*BH$2 -> 0 | BJ12: =BI12*BJ$2 -> 0 | BK12: =+AQ12+AR12+AT12+AW12+AX12+AZ12+BB12+BD12+BF12+BH12+BJ12 -> 231960 | BL12: =AD12 -> 207950 | BM12: =SUM(BK12-BL12) -> 24010 | BO12: =IF(AQ12+AR12=0,0,(AQ12+AR12)/AD12) -> 0.096176966 | BP12: =IF(AU12=0,0,AU12/AD12) -> 0.40870402 | BQ12: =IF(AV12=0,0,AV12/AD12) -> 0.61057947 | BR12: =IF(AW12=0,0,AW12/AD12) -> 0 | BS12: =IF(AZ12=0,0,AZ12/AD12) -> 0 | BT12: =IF(BB12+BD12+BF12=0,0,(BB12+BD12+BF12)/AD12) -> 0 | BU12: =IF(BJ12=0,0,BJ12/AD12) -> 0 | BV12: =SUM(BO12:BU12) -> 1.1154604 | BW12: =AD12/$AD$41 -> 0.014602846
A13: =A12+1 -> 46147 | C13: 6 | D13: =E12+1 -> 1340 | E13: =IF(C13="","",C13+D13-1) -> 1345 | H13: 376776.86 | I13: 79123.14 | K13: =H13+I13+J13 -> 455900 | O13: =N13*21% -> 0 | Q13: =N13+O13+P13 -> 0 | U13: =T13*21% -> 0 | W13: =T13+U13+V13 -> 0 | AA13: 0 | AC13: =Z13+AA13+AB13 -> 0 | AD13: =+K13+Q13+W13-AC13 -> 455900 | AJ13: =AI13*220 -> 0 | AL13: =AK13*1200 -> 0 | AN13: =AM13*1200 -> 0 | AO13: =AF13+AG13+AH13+AJ13+AL13+AN13 -> 0 | AP13: =SUM(AO13-BK13) -> -455910 | AQ13: 130000 | AS13: =AG13 | AT13: =SUM(AU13:AV13) -> 325910 | AU13: 29990 | AV13: 295920 | AZ13: =AY13*AZ$2 -> 0 | BB13: =BA13*BB$2 -> 0 | BD13: =BC13*BD$2 -> 0 | BF13: =BE13*BF$2 -> 0 | BH13: =BG13*BH$2 -> 0 | BJ13: =BI13*BJ$2 -> 0 | BK13: =+AQ13+AR13+AT13+AW13+AX13+AZ13+BB13+BD13+BF13+BH13+BJ13 -> 455910 | BL13: =AD13 -> 455900 | BM13: =SUM(BK13-BL13) -> 10 | BO13: =IF(AQ13+AR13=0,0,(AQ13+AR13)/AD13) -> 0.28515025 | BP13: =IF(AU13=0,0,AU13/AD13) -> 0.06578197 | BQ13: =IF(AV13=0,0,AV13/AD13) -> 0.64908971 | BR13: =IF(AW13=0,0,AW13/AD13) -> 0 | BS13: =IF(AZ13=0,0,AZ13/AD13) -> 0 | BT13: =IF(BB13+BD13+BF13=0,0,(BB13+BD13+BF13)/AD13) -> 0 | BU13: =IF(BJ13=0,0,BJ13/AD13) -> 0 | BV13: =SUM(BO13:BU13) -> 1.0000219 | BW13: =AD13/$AD$41 -> 0.032014606
A14: =A13+1 -> 46148 | C14: 2 | D14: =E13+1 -> 1346 | E14: =IF(C14="","",C14+D14-1) -> 1347 | H14: 181793.38 | I14: 38176.62 | K14: =H14+I14+J14 -> 219970 | O14: =N14*21% -> 0 | Q14: =N14+O14+P14 -> 0 | U14: =T14*21% -> 0 | W14: =T14+U14+V14 -> 0 | X14: 26 | Y14: 26 | Z14: 57842.97 | AA14: 12147.03 | AC14: =Z14+AA14+AB14 -> 69990 | AD14: =+K14+Q14+W14-AC14 -> 149980 | AJ14: =AI14*220 -> 0 | AL14: =AK14*1200 -> 0 | AN14: =AM14*1200 -> 0 | AO14: =AF14+AG14+AH14+AJ14+AL14+AN14 -> 0 | AP14: =SUM(AO14-BK14) -> -149980 | AQ14: 0 | AS14: =AG14 | AT14: =SUM(AU14:AV14) -> 149980 | AV14: 149980 | AZ14: =AY14*AZ$2 -> 0 | BB14: =BA14*BB$2 -> 0 | BD14: =BC14*1495 -> 0 | BF14: =BE14*BF$2 -> 0 | BH14: =BG14*BH$2 -> 0 | BJ14: =BI14*1750 -> 0 | BK14: =+AQ14+AR14+AT14+AW14+AX14+AZ14+BB14+BD14+BF14+BH14+BJ14 -> 149980 | BL14: =AD14 -> 149980 | BM14: =SUM(BK14-BL14) -> 0 | BO14: =IF(AQ14+AR14=0,0,(AQ14+AR14)/AD14) -> 0 | BP14: =IF(AU14=0,0,AU14/AD14) -> 0 | BQ14: =IF(AV14=0,0,AV14/AD14) -> 1 | BR14: =IF(AW14=0,0,AW14/AD14) -> 0 | BS14: =IF(AZ14=0,0,AZ14/AD14) -> 0 | BT14: =IF(BB14+BD14+BF14=0,0,(BB14+BD14+BF14)/AD14) -> 0 | BU14: =IF(BJ14=0,0,BJ14/AD14) -> 0 | BV14: =SUM(BO14:BU14) -> 1 | BW14: =AD14/$AD$41 -> 0.010532026
A15: =A14+1 -> 46149 | C15: 3 | D15: =E14+1 -> 1348 | E15: =IF(C15="","",C15+D15-1) -> 1350 | H15: 199975.21 | I15: 41994.79 | K15: =H15+I15+J15 -> 241970 | O15: =N15*21% -> 0 | Q15: =N15+O15+P15 -> 0 | U15: =T15*21% -> 0 | W15: =T15+U15+V15 -> 0 | AA15: 0 | AC15: =Z15+AA15+AB15 -> 0 | AD15: =+K15+Q15+W15-AC15 -> 241970 | AJ15: =AI15*220 -> 0 | AL15: =AK15*1200 -> 0 | AN15: =AM15*1200 -> 0 | AO15: =AF15+AG15+AH15+AJ15+AL15+AN15 -> 0 | AP15: =SUM(AO15-BK15) -> -246980 | AQ15: 10000 | AS15: =AG15 | AT15: =SUM(AU15:AV15) -> 236980 | AU15: 219990 | AV15: 16990 | AZ15: =AY15*AZ$2 -> 0 | BB15: =BA15*1435 -> 0 | BD15: =BC15*BD$2 -> 0 | BF15: =BE15*BF$2 -> 0 | BH15: =BG15*BH$2 -> 0 | BJ15: =BI15*BJ$2 -> 0 | BK15: =+AQ15+AR15+AT15+AW15+AX15+AZ15+BB15+BD15+BF15+BH15+BJ15 -> 246980 | BL15: =AD15 -> 241970 | BM15: =SUM(BK15-BL15) -> 5010 | BO15: =IF(AQ15+AR15=0,0,(AQ15+AR15)/AD15) -> 0.041327437 | BP15: =IF(AU15=0,0,AU15/AD15) -> 0.90916229 | BQ15: =IF(AV15=0,0,AV15/AD15) -> 0.070215316 | BR15: =IF(AW15=0,0,AW15/AD15) -> 0 | BS15: =IF(AZ15=0,0,AZ15/AD15) -> 0 | BT15: =IF(BB15+BD15+BF15=0,0,(BB15+BD15+BF15)/AD15) -> 0 | BU15: =IF(BJ15=0,0,BJ15/AD15) -> 0 | BV15: =SUM(BO15:BU15) -> 1.020705 | BW15: =AD15/$AD$41 -> 0.016991828
A16: =A15+1 -> 46150 | C16: 8 | D16: =E15+1 -> 1351 | E16: =IF(C16="","",C16+D16-1) -> 1358 | H16: 437876.02 | I16: 91953.98 | K16: =H16+I16+J16 -> 529830 | O16: =N16*21% -> 0 | Q16: =N16+O16+P16 -> 0 | R16: 12 | S16: 13 | T16: 325556.86 | U16: 68366.94 | W16: =T16+U16+V16 -> 393923.8 | AA16: 0 | AC16: =Z16+AA16+AB16 -> 0 | AD16: =+K16+Q16+W16-AC16 -> 923753.8 | AJ16: =AI16*220 -> 0 | AL16: =AK16*1200 -> 0 | AN16: =AM16*1200 -> 0 | AO16: =AF16+AG16+AH16+AJ16+AL16+AN16 -> 0 | AP16: =SUM(AO16-BK16) -> -924820 | AQ16: =120000+30000 -> 150000 | AS16: =AG16 | AT16: =SUM(AU16:AV16) -> 774820 | AU16: =180950+9990 -> 190940 | AV16: 583880 | AZ16: =AY16*AZ$2 -> 0 | BB16: =BA16*BB$2 -> 0 | BD16: =BC16*BD$2 -> 0 | BF16: =BE16*BF$2 -> 0 | BH16: =BG16*BH$2 -> 0 | BJ16: =BI16*1665 -> 0 | BK16: =+AQ16+AR16+AT16+AW16+AX16+AZ16+BB16+BD16+BF16+BH16+BJ16 -> 924820 | BL16: =AD16 -> 923753.8 | BM16: =SUM(BK16-BL16) -> 1066.2 | BO16: =IF(AQ16+AR16=0,0,(AQ16+AR16)/AD16) -> 0.16238093 | BP16: =IF(AU16=0,0,AU16/AD16) -> 0.2067001 | BQ16: =IF(AV16=0,0,AV16/AD16) -> 0.63207318 | BR16: =IF(AW16=0,0,AW16/AD16) -> 0 | BS16: =IF(AZ16=0,0,AZ16/AD16) -> 0 | BT16: =IF(BB16+BD16+BF16=0,0,(BB16+BD16+BF16)/AD16) -> 0 | BU16: =IF(BJ16=0,0,BJ16/AD16) -> 0 | BV16: =SUM(BO16:BU16) -> 1.0011542 | BW16: =AD16/$AD$41 -> 0.064868643
A17: =A16+1 -> 46151 | C17: 9 | D17: =E16+1 -> 1359 | E17: =IF(C17="","",C17+D17-1) -> 1367 | H17: 741218.01 | I17: 155655.79 | K17: =H17+I17+J17 -> 896873.8 | O17: =N17*21% -> 0 | Q17: =N17+O17+P17 -> 0 | U17: =T17*21% -> 0 | W17: =T17+U17+V17 -> 0 | AA17: 0 | AC17: =Z17+AA17+AB17 -> 0 | AD17: =+K17+Q17+W17-AC17 -> 896873.8 | AJ17: =AI17*220 -> 0 | AL17: =AK17*1200 -> 0 | AN17: =AM17*1200 -> 0 | AO17: =AF17+AG17+AH17+AJ17+AL17+AN17 -> 0 | AP17: =SUM(AO17-BK17) -> -894920 | AQ17: 30000 | AS17: =AG17 | AT17: =SUM(AU17:AV17) -> 847280 | AU17: 289950 | AV17: 557330 | AY17: 60 | AZ17: =AY17*294 -> 17640 | BB17: =BA17*BB$2 -> 0 | BD17: =BC17*BD$2 -> 0 | BF17: =BE17*BF$2 -> 0 | BH17: =BG17*BH$2 -> 0 | BJ17: =BI17*BJ$2 -> 0 | BK17: =+AQ17+AR17+AT17+AW17+AX17+AZ17+BB17+BD17+BF17+BH17+BJ17 -> 894920 | BL17: =AD17 -> 896873.8 | BM17: =SUM(BK17-BL17) -> -1953.8 | BO17: =IF(AQ17+AR17=0,0,(AQ17+AR17)/AD17) -> 0.033449522 | BP17: =IF(AU17=0,0,AU17/AD17) -> 0.32328963 | BQ17: =IF(AV17=0,0,AV17/AD17) -> 0.62141407 | BR17: =IF(AW17=0,0,AW17/AD17) -> 0 | BS17: =IF(AZ17=0,0,AZ17/AD17) -> 0.019668319 | BT17: =IF(BB17+BD17+BF17=0,0,(BB17+BD17+BF17)/AD17) -> 0 | BU17: =IF(BJ17=0,0,BJ17/AD17) -> 0 | BV17: =SUM(BO17:BU17) -> 0.99782154 | BW17: =AD17/$AD$41 -> 0.062981052
A18: =A17+1 -> 46152 | C18: 8 | D18: =E17+1 -> 1368 | E18: =IF(C18="","",C18+D18-1) -> 1375 | H18: 410661.16 | I18: 86238.84 | K18: =H18+I18+J18 -> 496900 | O18: =N18*21% -> 0 | Q18: =N18+O18+P18 -> 0 | U18: =T18*21% -> 0 | W18: =T18+U18+V18 -> 0 | AA18: 0 | AC18: =Z18+AA18+AB18 -> 0 | AD18: =+K18+Q18+W18-AC18 -> 496900 | AJ18: =AI18*220 -> 0 | AL18: =AK18*1200 -> 0 | AN18: =AM18*1200 -> 0 | AO18: =AF18+AG18+AH18+AJ18+AL18+AN18 -> 0 | AP18: =SUM(AO18-BK18) -> -496900 | AQ18: 0 | AS18: =AG18 | AT18: =SUM(AU18:AV18) -> 496900 | AU18: 84990 | AV18: 411910 | AZ18: =AY18*284 -> 0 | BB18: =BA18*1415 -> 0 | BD18: =BC18*BD$2 -> 0 | BF18: =BE18*BF$2 -> 0 | BH18: =BG18*BH$2 -> 0 | BJ18: =BI18*BJ$2 -> 0 | BK18: =+AQ18+AR18+AT18+AW18+AX18+AZ18+BB18+BD18+BF18+BH18+BJ18 -> 496900 | BL18: =AD18 -> 496900 | BM18: =SUM(BK18-BL18) -> 0 | BO18: =IF(AQ18+AR18=0,0,(AQ18+AR18)/AD18) -> 0 | BP18: =IF(AU18=0,0,AU18/AD18) -> 0.17104045 | BQ18: =IF(AV18=0,0,AV18/AD18) -> 0.82895955 | BR18: =IF(AW18=0,0,AW18/AD18) -> 0 | BS18: =IF(AZ18=0,0,AZ18/AD18) -> 0 | BT18: =IF(BB18+BD18+BF18=0,0,(BB18+BD18+BF18)/AD18) -> 0 | BU18: =IF(BJ18=0,0,BJ18/AD18) -> 0 | BV18: =SUM(BO18:BU18) -> 1 | BW18: =AD18/$AD$41 -> 0.034893744
A19: =A18+1 -> 46153 | C19: 3 | D19: =E18+1 -> 1376 | E19: =IF(C19="","",C19+D19-1) -> 1378 | H19: 239628.1 | I19: 50321.9 | K19: =H19+I19+J19 -> 289950 | O19: =N19*21% -> 0 | Q19: =N19+O19+P19 -> 0 | U19: =T19*21% -> 0 | W19: =T19+U19+V19 -> 0 | AA19: 0 | AC19: =Z19+AA19+AB19 -> 0 | AD19: =+K19+Q19+W19-AC19 -> 289950 | AJ19: =AI19*220 -> 0 | AL19: =AK19*1200 -> 0 | AN19: =AM19*1200 -> 0 | AO19: =AF19+AG19+AH19+AJ19+AL19+AN19 -> 0 | AP19: =SUM(AO19-BK19) -> -289950 | AQ19: 0 | AS19: =AG19 | AT19: =SUM(AU19:AV19) -> 289950 | AV19: 289950 | AZ19: =AY19*AZ$3 -> 0 | BB19: =BA19*BB$2 -> 0 | BD19: =BC19*BD$2 -> 0 | BF19: =BE19*BF$2 -> 0 | BH19: =BG19*BH$2 -> 0 | BJ19: =BI19*BJ$2 -> 0 | BK19: =+AQ19+AR19+AT19+AW19+AX19+AZ19+BB19+BD19+BF19+BH19+BJ19 -> 289950 | BL19: =AD19 -> 289950 | BM19: =SUM(BK19-BL19) -> 0 | BO19: =IF(AQ19+AR19=0,0,(AQ19+AR19)/AD19) -> 0 | BP19: =IF(AU19=0,0,AU19/AD19) -> 0 | BQ19: =IF(AV19=0,0,AV19/AD19) -> 1 | BR19: =IF(AW19=0,0,AW19/AD19) -> 0 | BS19: =IF(AZ19=0,0,AZ19/AD19) -> 0 | BT19: =IF(BB19+BD19+BF19=0,0,(BB19+BD19+BF19)/AD19) -> 0 | BU19: =IF(BJ19=0,0,BJ19/AD19) -> 0 | BV19: =SUM(BO19:BU19) -> 1 | BW19: =AD19/$AD$41 -> 0.020361121
A20: =A19+1 -> 46154 | C20: 1 | D20: =E19+1 -> 1379 | E20: =IF(C20="","",C20+D20-1) -> 1379 | H20: 66107.44 | I20: 13882.56 | K20: =H20+I20+J20 -> 79990 | O20: =N20*21% -> 0 | Q20: =N20+O20+P20 -> 0 | U20: =T20*21% -> 0 | W20: =T20+U20+V20 -> 0 | AA20: 0 | AC20: =Z20+AA20+AB20 -> 0 | AD20: =+K20+Q20+W20-AC20 -> 79990 | AJ20: =AI20*220 -> 0 | AL20: =AK20*1200 -> 0 | AN20: =AM20*1200 -> 0 | AO20: =AF20+AG20+AH20+AJ20+AL20+AN20 -> 0 | AP20: =SUM(AO20-BK20) -> -79990 | AQ20: 0 | AS20: =AG20 | AT20: =SUM(AU20:AV20) -> 79990 | AV20: 79990 | AZ20: =AY20*AZ$3 -> 0 | BB20: =BA20*1425 -> 0 | BD20: =BC20*BD$2 -> 0 | BF20: =BE20*BF$2 -> 0 | BH20: =BG20*BH$2 -> 0 | BJ20: =BI20*BJ$2 -> 0 | BK20: =+AQ20+AR20+AT20+AW20+AX20+AZ20+BB20+BD20+BF20+BH20+BJ20 -> 79990 | BL20: =AD20 -> 79990 | BM20: =SUM(BK20-BL20) -> 0 | BO20: =IF(AQ20+AR20=0,0,(AQ20+AR20)/AD20) -> 0 | BP20: =IF(AU20=0,0,AU20/AD20) -> 0 | BQ20: =IF(AV20=0,0,AV20/AD20) -> 1 | BR20: =IF(AW20=0,0,AW20/AD20) -> 0 | BS20: =IF(AZ20=0,0,AZ20/AD20) -> 0 | BT20: =IF(BB20+BD20+BF20=0,0,(BB20+BD20+BF20)/AD20) -> 0 | BU20: =IF(BJ20=0,0,BJ20/AD20) -> 0 | BV20: =SUM(BO20:BU20) -> 1 | BW20: =AD20/$AD$41 -> 0.0056171274
A21: =A20+1 -> 46155 | C21: 2 | D21: =E20+1 -> 1380 | E21: =IF(C21="","",C21+D21-1) -> 1381 | H21: 53702.47 | I21: 11277.53 | K21: =H21+I21+J21 -> 64980 | O21: =N21*21% -> 0 | Q21: =N21+O21+P21 -> 0 | U21: =T21*21% -> 0 | W21: =T21+U21+V21 -> 0 | AA21: 0 | AC21: =Z21+AA21+AB21 -> 0 | AD21: =+K21+Q21+W21-AC21 -> 64980 | AJ21: =AI21*220 -> 0 | AL21: =AK21*1200 -> 0 | AN21: =AM21*1200 -> 0 | AO21: =AF21+AG21+AH21+AJ21+AL21+AN21 -> 0 | AP21: =SUM(AO21-BK21) -> -64980 | AQ21: 0 | AS21: =AG21 | AT21: =SUM(AU21:AV21) -> 64980 | AV21: 64980 | AZ21: =AY21*AZ$3 -> 0 | BB21: =BA21*1425 -> 0 | BD21: =BC21*BD$2 -> 0 | BF21: =BE21*BF$2 -> 0 | BH21: =BG21*BH$2 -> 0 | BJ21: =BI21*BJ$2 -> 0 | BK21: =+AQ21+AR21+AT21+AW21+AX21+AZ21+BB21+BD21+BF21+BH21+BJ21 -> 64980 | BL21: =AD21 -> 64980 | BM21: =SUM(BK21-BL21) -> 0 | BO21: =IF(AQ21+AR21=0,0,(AQ21+AR21)/AD21) -> 0 | BP21: =IF(AU21=0,0,AU21/AD21) -> 0 | BQ21: =IF(AV21=0,0,AV21/AD21) -> 1 | BR21: =IF(AW21=0,0,AW21/AD21) -> 0 | BS21: =IF(AZ21=0,0,AZ21/AD21) -> 0 | BT21: =IF(BB21+BD21+BF21=0,0,(BB21+BD21+BF21)/AD21) -> 0 | BU21: =IF(BJ21=0,0,BJ21/AD21) -> 0 | BV21: =SUM(BO21:BU21) -> 1 | BW21: =AD21/$AD$41 -> 0.0045630821
A22: =A21+1 -> 46156 | C22: 3 | D22: =E21+1 -> 1382 | E22: =IF(C22="","",C22+D22-1) -> 1384 | H22: 261851.24 | I22: 54988.76 | K22: =H22+I22+J22 -> 316840 | O22: =N22*21% -> 0 | Q22: =N22+O22+P22 -> 0 | U22: =T22*21% -> 0 | W22: =T22+U22+V22 -> 0 | AA22: 0 | AC22: =Z22+AA22+AB22 -> 0 | AD22: =+K22+Q22+W22-AC22 -> 316840 | AJ22: =AI22*220 -> 0 | AL22: =AK22*1200 -> 0 | AN22: =AM22*1200 -> 0 | AO22: =AF22+AG22+AH22+AJ22+AL22+AN22 -> 0 | AP22: =SUM(AO22-BK22) -> -316850 | AQ22: 100000 | AS22: =AG22 | AT22: =SUM(AU22:AV22) -> 216850 | AU22: 106930 | AV22: 109920 | AZ22: =AY22*AZ$3 -> 0 | BB22: =BA22*1425 -> 0 | BD22: =BC22*BD$2 -> 0 | BF22: =BE22*BF$2 -> 0 | BH22: =BG22*BH$2 -> 0 | BJ22: =BI22*BJ$2 -> 0 | BK22: =+AQ22+AR22+AT22+AW22+AX22+AZ22+BB22+BD22+BF22+BH22+BJ22 -> 316850 | BL22: =AD22 -> 316840 | BM22: =SUM(BK22-BL22) -> 10 | BO22: =IF(AQ22+AR22=0,0,(AQ22+AR22)/AD22) -> 0.31561672 | BP22: =IF(AU22=0,0,AU22/AD22) -> 0.33748895 | BQ22: =IF(AV22=0,0,AV22/AD22) -> 0.34692589 | BR22: =IF(AW22=0,0,AW22/AD22) -> 0 | BS22: =IF(AZ22=0,0,AZ22/AD22) -> 0 | BT22: =IF(BB22+BD22+BF22=0,0,(BB22+BD22+BF22)/AD22) -> 0 | BU22: =IF(BJ22=0,0,BJ22/AD22) -> 0 | BV22: =SUM(BO22:BU22) -> 1.0000316 | BW22: =AD22/$AD$41 -> 0.022249414
A23: =A22+1 -> 46157 | C23: 6 | D23: =E22+1 -> 1385 | E23: =IF(C23="","",C23+D23-1) -> 1390 | H23: 368520.65 | I23: 77389.35 | K23: =H23+I23+J23 -> 445910 | O23: =N23*21% -> 0 | Q23: =N23+O23+P23 -> 0 | U23: =T23*21% -> 0 | W23: =T23+U23+V23 -> 0 | AA23: 0 | AC23: =Z23+AA23+AB23 -> 0 | AD23: =+K23+Q23+W23-AC23 -> 445910 | AJ23: =AI23*220 -> 0 | AL23: =AK23*1200 -> 0 | AN23: =AM23*1200 -> 0 | AO23: =AF23+AG23+AH23+AJ23+AL23+AN23 -> 0 | AP23: =SUM(AO23-BK23) -> -445920 | AQ23: 30000 | AS23: =AG23 | AT23: =SUM(AU23:AV23) -> 415920 | AU23: 49990 | AV23: 365930 | AZ23: =AY23*AZ$3 -> 0 | BB23: =BA23*1425 -> 0 | BD23: =BC23*BD$2 -> 0 | BF23: =BE23*BF$2 -> 0 | BH23: =BG23*BH$2 -> 0 | BJ23: =BI23*BJ$2 -> 0 | BK23: =+AQ23+AR23+AT23+AW23+AX23+AZ23+BB23+BD23+BF23+BH23+BJ23 -> 445920 | BL23: =AD23 -> 445910 | BM23: =SUM(BK23-BL23) -> 10 | BO23: =IF(AQ23+AR23=0,0,(AQ23+AR23)/AD23) -> 0.06727815 | BP23: =IF(AU23=0,0,AU23/AD23) -> 0.11210782 | BQ23: =IF(AV23=0,0,AV23/AD23) -> 0.82063645 | BR23: =IF(AW23=0,0,AW23/AD23) -> 0 | BS23: =IF(AZ23=0,0,AZ23/AD23) -> 0 | BT23: =IF(BB23+BD23+BF23=0,0,(BB23+BD23+BF23)/AD23) -> 0 | BU23: =IF(BJ23=0,0,BJ23/AD23) -> 0 | BV23: =SUM(BO23:BU23) -> 1.0000224 | BW23: =AD23/$AD$41 -> 0.03131308
A24: =A23+1 -> 46158 | C24: 8 | D24: =E23+1 -> 1391 | E24: =IF(C24="","",C24+D24-1) -> 1398 | H24: 641223.13 | I24: 134656.87 | K24: =H24+I24+J24 -> 775880 | O24: =N24*21% -> 0 | Q24: =N24+O24+P24 -> 0 | U24: =T24*21% -> 0 | W24: =T24+U24+V24 -> 0 | X24: 27 | Y24: 27 | Z24: 41314.05 | AA24: 8675.95 | AC24: =Z24+AA24+AB24 -> 49990 | AD24: =+K24+Q24+W24-AC24 -> 725890 | AJ24: =AI24*220 -> 0 | AL24: =AK24*1200 -> 0 | AN24: =AM24*1200 -> 0 | AO24: =AF24+AG24+AH24+AJ24+AL24+AN24 -> 0 | AP24: =SUM(AO24-BK24) -> -727960 | AQ24: =100000 -> 100000 | AS24: =AG24 | AT24: =SUM(AU24:AV24) -> 345960 | AV24: 345960 | AZ24: =AY24*AZ$3 -> 0 | BA24: 200 | BB24: =BA24*1410 -> 282000 | BD24: =BC24*BD$2 -> 0 | BF24: =BE24*BF$2 -> 0 | BH24: =BG24*BH$2 -> 0 | BJ24: =BI24*BJ$2 -> 0 | BK24: =+AQ24+AR24+AT24+AW24+AX24+AZ24+BB24+BD24+BF24+BH24+BJ24 -> 727960 | BL24: =AD24 -> 725890 | BM24: =SUM(BK24-BL24) -> 2070 | BO24: =IF(AQ24+AR24=0,0,(AQ24+AR24)/AD24) -> 0.13776192 | BP24: =IF(AU24=0,0,AU24/AD24) -> 0 | BQ24: =IF(AV24=0,0,AV24/AD24) -> 0.47660114 | BR24: =IF(AW24=0,0,AW24/AD24) -> 0 | BS24: =IF(AZ24=0,0,AZ24/AD24) -> 0 | BT24: =IF(BB24+BD24+BF24=0,0,(BB24+BD24+BF24)/AD24) -> 0.38848861 | BU24: =IF(BJ24=0,0,BJ24/AD24) -> 0 | BV24: =SUM(BO24:BU24) -> 1.0028517 | BW24: =AD24/$AD$41 -> 0.050974079
A25: =A24+1 -> 46159 | C25: 7 | D25: =E24+1 -> 1399 | E25: =IF(C25="","",C25+D25-1) -> 1405 | H25: 542867.76 | I25: 114002.24 | K25: =H25+I25+J25 -> 656870 | O25: =N25*21% -> 0 | Q25: =N25+O25+P25 -> 0 | U25: =T25*21% -> 0 | W25: =T25+U25+V25 -> 0 | X25: 28 | Y25: 28 | Z25: 165280.99 | AA25: 34709.01 | AC25: =Z25+AA25+AB25 -> 199990 | AD25: =+K25+Q25+W25-AC25 -> 456880 | AJ25: =AI25*220 -> 0 | AL25: =AK25*1200 -> 0 | AN25: =AM25*1200 -> 0 | AO25: =AF25+AG25+AH25+AJ25+AL25+AN25 -> 0 | AP25: =SUM(AO25-BK25) -> -456880 | AQ25: 0 | AS25: =AG25 | AT25: =SUM(AU25:AV25) -> 456880 | AU25: =29990+29990 -> 59980 | AV25: 396900 | AZ25: =AY25*AZ$3 -> 0 | BB25: =BA25*1415 -> 0 | BD25: =BC25*BD$2 -> 0 | BF25: =BE25*BF$2 -> 0 | BH25: =BG25*BH$2 -> 0 | BJ25: =BI25*BJ$2 -> 0 | BK25: =+AQ25+AR25+AT25+AW25+AX25+AZ25+BB25+BD25+BF25+BH25+BJ25 -> 456880 | BL25: =AD25 -> 456880 | BM25: =SUM(BK25-BL25) -> 0 | BO25: =IF(AQ25+AR25=0,0,(AQ25+AR25)/AD25) -> 0 | BP25: =IF(AU25=0,0,AU25/AD25) -> 0.13128174 | BQ25: =IF(AV25=0,0,AV25/AD25) -> 0.86871826 | BR25: =IF(AW25=0,0,AW25/AD25) -> 0 | BS25: =IF(AZ25=0,0,AZ25/AD25) -> 0 | BT25: =IF(BB25+BD25+BF25=0,0,(BB25+BD25+BF25)/AD25) -> 0 | BU25: =IF(BJ25=0,0,BJ25/AD25) -> 0 | BV25: =SUM(BO25:BU25) -> 1 | BW25: =AD25/$AD$41 -> 0.032083425
A26: =A25+1 -> 46160 | C26: 6 | D26: =E25+1 -> 1406 | E26: =IF(C26="","",C26+D26-1) -> 1411 | H26: 797446.27 | I26: 167463.73 | K26: =H26+I26+J26 -> 964910 | O26: =N26*21% -> 0 | Q26: =N26+O26+P26 -> 0 | U26: =T26*21% -> 0 | W26: =T26+U26+V26 -> 0 | AA26: 0 | AC26: =Z26+AA26+AB26 -> 0 | AD26: =+K26+Q26+W26-AC26 -> 964910 | AJ26: =AI26*220 -> 0 | AL26: =AK26*1200 -> 0 | AN26: =AM26*1200 -> 0 | AO26: =AF26+AG26+AH26+AJ26+AL26+AN26 -> 0 | AP26: =SUM(AO26-BK26) -> -977940 | AQ26: 0 | AS26: =AG26 | AT26: =SUM(AU26:AV26) -> 554940 | AV26: 554940 | AZ26: =AY26*AZ$3 -> 0 | BA26: 300 | BB26: =BA26*1410 -> 423000 | BD26: =BC26*1415 -> 0 | BF26: =BE26*BF$2 -> 0 | BH26: =BG26*BH$2 -> 0 | BJ26: =BI26*BJ$2 -> 0 | BK26: =+AQ26+AR26+AT26+AW26+AX26+AZ26+BB26+BD26+BF26+BH26+BJ26 -> 977940 | BL26: =AD26 -> 964910 | BM26: =SUM(BK26-BL26) -> 13030 | BO26: =IF(AQ26+AR26=0,0,(AQ26+AR26)/AD26) -> 0 | BP26: =IF(AU26=0,0,AU26/AD26) -> 0 | BQ26: =IF(AV26=0,0,AV26/AD26) -> 0.575121 | BR26: =IF(AW26=0,0,AW26/AD26) -> 0 | BS26: =IF(AZ26=0,0,AZ26/AD26) -> 0 | BT26: =IF(BB26+BD26+BF26=0,0,(BB26+BD26+BF26)/AD26) -> 0.43838285 | BU26: =IF(BJ26=0,0,BJ26/AD26) -> 0 | BV26: =SUM(BO26:BU26) -> 1.0135038 | BW26: =AD26/$AD$41 -> 0.067758749
A27: =A26+1 -> 46161 | C27: 4 | D27: =E26+1 -> 1412 | E27: =IF(C27="","",C27+D27-1) -> 1415 | H27: 138786.69 | I27: 29145.21 | K27: =H27+I27+J27 -> 167931.9 | O27: =N27*21% -> 0 | Q27: =N27+O27+P27 -> 0 | U27: =T27*21% -> 0 | W27: =T27+U27+V27 -> 0 | AA27: 0 | AC27: =Z27+AA27+AB27 -> 0 | AD27: =+K27+Q27+W27-AC27 -> 167931.9 | AJ27: =AI27*220 -> 0 | AL27: =AK27*1200 -> 0 | AN27: =AM27*1200 -> 0 | AO27: =AF27+AG27+AH27+AJ27+AL27+AN27 -> 0 | AP27: =SUM(AO27-BK27) -> -167930 | AQ27: 0 | AS27: =AG27 | AT27: =SUM(AU27:AV27) -> 167930 | AU27: 92950 | AV27: 74980 | AZ27: =AY27*278 -> 0 | BB27: =BA27*BB$2 -> 0 | BD27: =BC27*1480 -> 0 | BF27: =BE27*1480 -> 0 | BH27: =BG27*BH$2 -> 0 | BJ27: =BI27*BJ$2 -> 0 | BK27: =+AQ27+AR27+AT27+AW27+AX27+AZ27+BB27+BD27+BF27+BH27+BJ27 -> 167930 | BL27: =AD27 -> 167931.9 | BM27: =SUM(BK27-BL27) -> -1.9 | BO27: =IF(AQ27+AR27=0,0,(AQ27+AR27)/AD27) -> 0 | BP27: =IF(AU27=0,0,AU27/AD27) -> 0.55349817 | BQ27: =IF(AV27=0,0,AV27/AD27) -> 0.44649051 | BR27: =IF(AW27=0,0,AW27/AD27) -> 0 | BS27: =IF(AZ27=0,0,AZ27/AD27) -> 0 | BT27: =IF(BB27+BD27+BF27=0,0,(BB27+BD27+BF27)/AD27) -> 0 | BU27: =IF(BJ27=0,0,BJ27/AD27) -> 0 | BV27: =SUM(BO27:BU27) -> 0.99998869 | BW27: =AD27/$AD$41 -> 0.01179266
A28: =A27+1 -> 46162 | C28: 4 | D28: =E27+1 -> 1416 | E28: =IF(C28="","",C28+D28-1) -> 1419 | H28: 424743.81 | I28: 89196.19 | K28: =H28+I28+J28 -> 513940 | O28: =N28*21% -> 0 | Q28: =N28+O28+P28 -> 0 | R28: 14 | S28: 14 | T28: 41314.05 | U28: 8675.95 | W28: =T28+U28+V28 -> 49990 | AA28: 0 | AC28: =Z28+AA28+AB28 -> 0 | AD28: =+K28+Q28+W28-AC28 -> 563930 | AJ28: =AI28*220 -> 0 | AL28: =AK28*1200 -> 0 | AN28: =AM28*1200 -> 0 | AO28: =AF28+AG28+AH28+AJ28+AL28+AN28 -> 0 | AP28: =SUM(AO28-BK28) -> -563930 | AQ28: 0 | AS28: =AG28 | AT28: =SUM(AU28:AV28) -> 563930 | AU28: =319980+159980 -> 479960 | AV28: 83970 | AZ28: =AY28*281 -> 0 | BB28: =BA28*BB$2 -> 0 | BD28: =BC28*BD$2 -> 0 | BF28: =BE28*BF$2 -> 0 | BH28: =BG28*BH$2 -> 0 | BJ28: =BI28*BJ$2 -> 0 | BK28: =+AQ28+AR28+AT28+AW28+AX28+AZ28+BB28+BD28+BF28+BH28+BJ28 -> 563930 | BL28: =AD28 -> 563930 | BM28: =SUM(BK28-BL28) -> 0 | BO28: =IF(AQ28+AR28=0,0,(AQ28+AR28)/AD28) -> 0 | BP28: =IF(AU28=0,0,AU28/AD28) -> 0.85109854 | BQ28: =IF(AV28=0,0,AV28/AD28) -> 0.14890146 | BR28: =IF(AW28=0,0,AW28/AD28) -> 0 | BS28: =IF(AZ28=0,0,AZ28/AD28) -> 0 | BT28: =IF(BB28+BD28+BF28=0,0,(BB28+BD28+BF28)/AD28) -> 0 | BU28: =IF(BJ28=0,0,BJ28/AD28) -> 0 | BV28: =SUM(BO28:BU28) -> 1 | BW28: =AD28/$AD$41 -> 0.039600783
A29: =A28+1 -> 46163 | C29: 6 | D29: =E28+1 -> 1420 | E29: =IF(C29="","",C29+D29-1) -> 1425 | H29: 245388.43 | I29: 51531.57 | K29: =H29+I29+J29 -> 296920 | O29: =N29*21% -> 0 | Q29: =N29+O29+P29 -> 0 | U29: =T29*21% -> 0 | W29: =T29+U29+V29 -> 0 | AA29: 0 | AC29: =Z29+AA29+AB29 -> 0 | AD29: =+K29+Q29+W29-AC29 -> 296920 | AJ29: =AI29*220 -> 0 | AL29: =AK29*1200 -> 0 | AN29: =AM29*1200 -> 0 | AO29: =AF29+AG29+AH29+AJ29+AL29+AN29 -> 0 | AP29: =SUM(AO29-BK29) -> -275960 | AQ29: =80000+10000 -> 90000 | AS29: =AG29 | AT29: =SUM(AU29:AV29) -> 185960 | AU29: 163970 | AV29: 21990 | AZ29: =AY29*AZ$3 -> 0 | BB29: =BA29*BB$3 -> 0 | BD29: =BC29*BD$3 -> 0 | BF29: =BE29*BF$3 -> 0 | BH29: =BG29*BH$3 -> 0 | BJ29: =BI29*BJ$3 -> 0 | BK29: =+AQ29+AR29+AT29+AW29+AX29+AZ29+BB29+BD29+BF29+BH29+BJ29 -> 275960 | BL29: =AD29 -> 296920 | BM29: =SUM(BK29-BL29) -> -20960 | BO29: =IF(AQ29+AR29=0,0,(AQ29+AR29)/AD29) -> 0.30311195 | BP29: =IF(AU29=0,0,AU29/AD29) -> 0.55223629 | BQ29: =IF(AV29=0,0,AV29/AD29) -> 0.074060353 | BR29: =IF(AW29=0,0,AW29/AD29) -> 0 | BS29: =IF(AZ29=0,0,AZ29/AD29) -> 0 | BT29: =IF(BB29+BD29+BF29=0,0,(BB29+BD29+BF29)/AD29) -> 0 | BU29: =IF(BJ29=0,0,BJ29/AD29) -> 0 | BV29: =SUM(BO29:BU29) -> 0.92940859 | BW29: =AD29/$AD$41 -> 0.020850575
A30: =A29+1 -> 46164 | C30: 6 | D30: =E29+1 -> 1426 | E30: =IF(C30="","",C30+D30-1) -> 1431 | H30: 366066.1 | I30: 76873.9 | K30: =H30+I30+J30 -> 442940 | O30: =N30*21% -> 0 | Q30: =N30+O30+P30 -> 0 | U30: =T30*21% -> 0 | W30: =T30+U30+V30 -> 0 | AA30: 0 | AC30: =Z30+AA30+AB30 -> 0 | AD30: =+K30+Q30+W30-AC30 -> 442940 | AJ30: =AI30*220 -> 0 | AL30: =AK30*1200 -> 0 | AN30: =AM30*1200 -> 0 | AO30: =AF30+AG30+AH30+AJ30+AL30+AN30 -> 0 | AP30: =SUM(AO30-BK30) -> -447970 | AQ30: =80000+20000 -> 100000 | AS30: =AG30 | AT30: =SUM(AU30:AV30) -> 347970 | AV30: 347970 | AZ30: =AY30*AZ$3 -> 0 | BB30: =BA30*1400 -> 0 | BD30: =BC30*BD$3 -> 0 | BF30: =BE30*BF$3 -> 0 | BH30: =BG30*BH$3 -> 0 | BJ30: =BI30*BJ$3 -> 0 | BK30: =+AQ30+AR30+AT30+AW30+AX30+AZ30+BB30+BD30+BF30+BH30+BJ30 -> 447970 | BL30: =AD30 -> 442940 | BM30: =SUM(BK30-BL30) -> 5030 | BO30: =IF(AQ30+AR30=0,0,(AQ30+AR30)/AD30) -> 0.22576421 | BP30: =IF(AU30=0,0,AU30/AD30) -> 0 | BQ30: =IF(AV30=0,0,AV30/AD30) -> 0.78559173 | BR30: =IF(AW30=0,0,AW30/AD30) -> 0 | BS30: =IF(AZ30=0,0,AZ30/AD30) -> 0 | BT30: =IF(BB30+BD30+BF30=0,0,(BB30+BD30+BF30)/AD30) -> 0 | BU30: =IF(BJ30=0,0,BJ30/AD30) -> 0 | BV30: =SUM(BO30:BU30) -> 1.0113559 | BW30: =AD30/$AD$41 -> 0.031104518
A31: =A30+1 -> 46165 | C31: 6 | D31: =E30+1 -> 1432 | E31: =IF(C31="","",C31+D31-1) -> 1437 | H31: 303256.19 | I31: 63683.81 | K31: =H31+I31+J31 -> 366940 | O31: =N31*21% -> 0 | Q31: =N31+O31+P31 -> 0 | U31: =T31*21% -> 0 | W31: =T31+U31+V31 -> 0 | AA31: 0 | AC31: =Z31+AA31+AB31 -> 0 | AD31: =+K31+Q31+W31-AC31 -> 366940 | AJ31: =AI31*220 -> 0 | AL31: =AK31*1200 -> 0 | AN31: =AM31*1200 -> 0 | AO31: =AF31+AG31+AH31+AJ31+AL31+AN31 -> 0 | AP31: =SUM(AO31-BK31) -> -359960 | AQ31: =10000+20000 -> 30000 | AS31: =AG31 | AT31: =SUM(AU31:AV31) -> 329960 | AU31: 99975 | AV31: 229985 | AZ31: =AY31*AZ$3 -> 0 | BB31: =BA31*BB$3 -> 0 | BD31: =BC31*BD$3 -> 0 | BF31: =BE31*BF$3 -> 0 | BH31: =BG31*BH$3 -> 0 | BJ31: =BI31*BJ$3 -> 0 | BK31: =+AQ31+AR31+AT31+AW31+AX31+AZ31+BB31+BD31+BF31+BH31+BJ31 -> 359960 | BL31: =AD31 -> 366940 | BM31: =SUM(BK31-BL31) -> -6980 | BO31: =IF(AQ31+AR31=0,0,(AQ31+AR31)/AD31) -> 0.081757236 | BP31: =IF(AU31=0,0,AU31/AD31) -> 0.27245599 | BQ31: =IF(AV31=0,0,AV31/AD31) -> 0.62676459 | BR31: =IF(AW31=0,0,AW31/AD31) -> 0 | BS31: =IF(AZ31=0,0,AZ31/AD31) -> 0 | BT31: =IF(BB31+BD31+BF31=0,0,(BB31+BD31+BF31)/AD31) -> 0 | BU31: =IF(BJ31=0,0,BJ31/AD31) -> 0 | BV31: =SUM(BO31:BU31) -> 0.98097782 | BW31: =AD31/$AD$41 -> 0.02576758
A32: =A31+1 -> 46166 | C32: 7 | D32: =E31+1 -> 1438 | E32: =IF(C32="","",C32+D32-1) -> 1444 | H32: 637910.65 | I32: 133961.25 | K32: =H32+I32+J32 -> 771871.9 | O32: =N32*21% -> 0 | Q32: =N32+O32+P32 -> 0 | U32: =T32*21% -> 0 | W32: =T32+U32+V32 -> 0 | AA32: 0 | AC32: =Z32+AA32+AB32 -> 0 | AD32: =+K32+Q32+W32-AC32 -> 771871.9 | AJ32: =AI32*220 -> 0 | AL32: =AK32*1200 -> 0 | AN32: =AM32*1200 -> 0 | AO32: =AF32+AG32+AH32+AJ32+AL32+AN32 -> 0 | AP32: =SUM(AO32-BK32) -> -779690 | AQ32: =20000+50000 -> 70000 | AS32: =AG32 | AT32: =SUM(AU32:AV32) -> 510890 | AU32: =59990 -> 59990 | AV32: 450900 | AZ32: =AY32*AZ$3 -> 0 | BA32: 140 | BB32: =BA32*1420 -> 198800 | BD32: =BC32*1400 -> 0 | BF32: =BE32*BF$3 -> 0 | BH32: =BG32*BH$3 -> 0 | BJ32: =BI32*BJ$3 -> 0 | BK32: =+AQ32+AR32+AT32+AW32+AX32+AZ32+BB32+BD32+BF32+BH32+BJ32 -> 779690 | BL32: =AD32 -> 771871.9 | BM32: =SUM(BK32-BL32) -> 7818.1 | BO32: =IF(AQ32+AR32=0,0,(AQ32+AR32)/AD32) -> 0.090688623 | BP32: =IF(AU32=0,0,AU32/AD32) -> 0.07772015 | BQ32: =IF(AV32=0,0,AV32/AD32) -> 0.58416429 | BR32: =IF(AW32=0,0,AW32/AD32) -> 0 | BS32: =IF(AZ32=0,0,AZ32/AD32) -> 0 | BT32: =IF(BB32+BD32+BF32=0,0,(BB32+BD32+BF32)/AD32) -> 0.25755569 | BU32: =IF(BJ32=0,0,BJ32/AD32) -> 0 | BV32: =SUM(BO32:BU32) -> 1.0101288 | BW32: =AD32/$AD$41 -> 0.05420306
A33: =A32+1 -> 46167 | C33: 10 | D33: =E32+1 -> 1445 | E33: =IF(C33="","",C33+D33-1) -> 1454 | H33: 519732.88 | I33: 109143.92 | K33: =H33+I33+J33 -> 628876.8 | O33: =N33*21% -> 0 | Q33: =N33+O33+P33 -> 0 | U33: =T33*21% -> 0 | W33: =T33+U33+V33 -> 0 | AA33: 0 | AC33: =Z33+AA33+AB33 -> 0 | AD33: =+K33+Q33+W33-AC33 -> 628876.8 | AJ33: =AI33*220 -> 0 | AL33: =AK33*1200 -> 0 | AN33: =AM33*1200 -> 0 | AO33: =AF33+AG33+AH33+AJ33+AL33+AN33 -> 0 | AP33: =SUM(AO33-BK33) -> -637910 | AQ33: 0 | AS33: =AG33 | AT33: =SUM(AU33:AV33) -> 495910 | AU33: 92980 | AV33: 402930 | AZ33: =AY33*AZ$3 -> 0 | BA33: 100 | BB33: =BA33*1420 -> 142000 | BD33: =BC33*BD$3 -> 0 | BF33: =BE33*BF$3 -> 0 | BH33: =BG33*BH$3 -> 0 | BJ33: =BI33*BJ$3 -> 0 | BK33: =+AQ33+AR33+AT33+AW33+AX33+AZ33+BB33+BD33+BF33+BH33+BJ33 -> 637910 | BL33: =AD33 -> 628876.8 | BM33: =SUM(BK33-BL33) -> 9033.2 | BO33: =IF(AQ33+AR33=0,0,(AQ33+AR33)/AD33) -> 0 | BP33: =IF(AU33=0,0,AU33/AD33) -> 0.1478509 | BQ33: =IF(AV33=0,0,AV33/AD33) -> 0.64071373 | BR33: =IF(AW33=0,0,AW33/AD33) -> 0 | BS33: =IF(AZ33=0,0,AZ33/AD33) -> 0 | BT33: =IF(BB33+BD33+BF33=0,0,(BB33+BD33+BF33)/AD33) -> 0.22579939 | BU33: =IF(BJ33=0,0,BJ33/AD33) -> 0 | BV33: =SUM(BO33:BU33) -> 1.014364 | BW33: =AD33/$AD$41 -> 0.044161534
A34: =A33+1 -> 46168 | C34: 5 | D34: =E33+1 -> 1455 | E34: =IF(C34="","",C34+D34-1) -> 1459 | H34: 274330.57 | I34: 57609.43 | K34: =H34+I34+J34 -> 331940 | O34: =N34*21% -> 0 | Q34: =N34+O34+P34 -> 0 | U34: =T34*21% -> 0 | W34: =T34+U34+V34 -> 0 | AA34: 0 | AC34: =Z34+AA34+AB34 -> 0 | AD34: =+K34+Q34+W34-AC34 -> 331940 | AJ34: =AI34*220 -> 0 | AL34: =AK34*1200 -> 0 | AN34: =AM34*1200 -> 0 | AO34: =AF34+AG34+AH34+AJ34+AL34+AN34 -> 0 | AP34: =SUM(AO34-BK34) -> -331940 | AQ34: 0 | AS34: =AG34 | AT34: =SUM(AU34:AV34) -> 331940 | AU34: =232970+26990 -> 259960 | AV34: 71980 | AZ34: =AY34*AZ$3 -> 0 | BB34: =BA34*BB$3 -> 0 | BD34: =BC34*BD$3 -> 0 | BF34: =BE34*BF$3 -> 0 | BH34: =BG34*BH$3 -> 0 | BJ34: =BI34*BJ$3 -> 0 | BK34: =+AQ34+AR34+AT34+AW34+AX34+AZ34+BB34+BD34+BF34+BH34+BJ34 -> 331940 | BL34: =AD34 -> 331940 | BM34: =SUM(BK34-BL34) -> 0 | BO34: =IF(AQ34+AR34=0,0,(AQ34+AR34)/AD34) -> 0 | BP34: =IF(AU34=0,0,AU34/AD34) -> 0.78315358 | BQ34: =IF(AV34=0,0,AV34/AD34) -> 0.21684642 | BR34: =IF(AW34=0,0,AW34/AD34) -> 0 | BS34: =IF(AZ34=0,0,AZ34/AD34) -> 0 | BT34: =IF(BB34+BD34+BF34=0,0,(BB34+BD34+BF34)/AD34) -> 0 | BU34: =IF(BJ34=0,0,BJ34/AD34) -> 0 | BV34: =SUM(BO34:BU34) -> 1 | BW34: =AD34/$AD$41 -> 0.023309779
A35: =A34+1 -> 46169 | C35: 1 | D35: =E34+1 -> 1460 | E35: =IF(C35="","",C35+D35-1) -> 1460 | H35: 79305.79 | I35: 16654.21 | K35: =H35+I35+J35 -> 95960 | O35: =N35*21% -> 0 | Q35: =N35+O35+P35 -> 0 | U35: =T35*21% -> 0 | W35: =T35+U35+V35 -> 0 | AA35: 0 | AC35: =Z35+AA35+AB35 -> 0 | AD35: =+K35+Q35+W35-AC35 -> 95960 | AJ35: =AI35*220 -> 0 | AL35: =AK35*1200 -> 0 | AN35: =AM35*1200 -> 0 | AO35: =AF35+AG35+AH35+AJ35+AL35+AN35 -> 0 | AP35: =SUM(AO35-BK35) -> -95960 | AQ35: 0 | AS35: =AG35 | AT35: =SUM(AU35:AV35) -> 95960 | AV35: 95960 | AZ35: =AY35*AZ$3 -> 0 | BB35: =BA35*1420 -> 0 | BD35: =BC35*BD$3 -> 0 | BF35: =BE35*BF$3 -> 0 | BH35: =BG35*BH$3 -> 0 | BJ35: =BI35*BJ$3 -> 0 | BK35: =+AQ35+AR35+AT35+AW35+AX35+AZ35+BB35+BD35+BF35+BH35+BJ35 -> 95960 | BL35: =AD35 -> 95960 | BM35: =SUM(BK35-BL35) -> 0 | BO35: =IF(AQ35+AR35=0,0,(AQ35+AR35)/AD35) -> 0 | BP35: =IF(AU35=0,0,AU35/AD35) -> 0 | BQ35: =IF(AV35=0,0,AV35/AD35) -> 1 | BR35: =IF(AW35=0,0,AW35/AD35) -> 0 | BS35: =IF(AZ35=0,0,AZ35/AD35) -> 0 | BT35: =IF(BB35+BD35+BF35=0,0,(BB35+BD35+BF35)/AD35) -> 0 | BU35: =IF(BJ35=0,0,BJ35/AD35) -> 0 | BV35: =SUM(BO35:BU35) -> 1 | BW35: =AD35/$AD$41 -> 0.0067385866
A36: =A35+1 -> 46170 | C36: 6 | D36: =E35+1 -> 1461 | E36: =IF(C36="","",C36+D36-1) -> 1466 | H36: 410652.89 | I36: 86237.11 | K36: =H36+I36+J36 -> 496890 | O36: =N36*21% -> 0 | Q36: =N36+O36+P36 -> 0 | U36: =T36*21% -> 0 | W36: =T36+U36+V36 -> 0 | AA36: 0 | AC36: =Z36+AA36+AB36 -> 0 | AD36: =+K36+Q36+W36-AC36 -> 496890 | AJ36: =AI36*220 -> 0 | AL36: =AK36*1200 -> 0 | AN36: =AM36*1200 -> 0 | AO36: =AF36+AG36+AH36+AJ36+AL36+AN36 -> 0 | AP36: =SUM(AO36-BK36) -> -496890 | AQ36: 0 | AS36: =AG36 | AT36: =SUM(AU36:AV36) -> 496890 | AU36: 13010 | AV36: 483880 | AZ36: =AY36*AZ$3 -> 0 | BB36: =BA36*BB$3 -> 0 | BD36: =BC36*BD$3 -> 0 | BF36: =BE36*BF$3 -> 0 | BH36: =BG36*BH$3 -> 0 | BJ36: =BI36*BJ$3 -> 0 | BK36: =+AQ36+AR36+AT36+AW36+AX36+AZ36+BB36+BD36+BF36+BH36+BJ36 -> 496890 | BL36: =AD36 -> 496890 | BM36: =SUM(BK36-BL36) -> 0 | BO36: =IF(AQ36+AR36=0,0,(AQ36+AR36)/AD36) -> 0 | BP36: =IF(AU36=0,0,AU36/AD36) -> 0.026182857 | BQ36: =IF(AV36=0,0,AV36/AD36) -> 0.97381714 | BR36: =IF(AW36=0,0,AW36/AD36) -> 0 | BS36: =IF(AZ36=0,0,AZ36/AD36) -> 0 | BT36: =IF(BB36+BD36+BF36=0,0,(BB36+BD36+BF36)/AD36) -> 0 | BU36: =IF(BJ36=0,0,BJ36/AD36) -> 0 | BV36: =SUM(BO36:BU36) -> 1 | BW36: =AD36/$AD$41 -> 0.034893042
A37: =A36+1 -> 46171 | C37: 7 | D37: =E36+1 -> 1467 | E37: =IF(C37="","",C37+D37-1) -> 1473 | H37: 441225.62 | I37: 92657.38 | K37: =H37+I37+J37 -> 533883 | O37: =N37*21% -> 0 | Q37: =N37+O37+P37 -> 0 | U37: =T37*21% -> 0 | W37: =T37+U37+V37 -> 0 | AA37: 0 | AC37: =Z37+AA37+AB37 -> 0 | AD37: =+K37+Q37+W37-AC37 -> 533883 | AJ37: =AI37*220 -> 0 | AL37: =AK37*1200 -> 0 | AN37: =AM37*1200 -> 0 | AO37: =AF37+AG37+AH37+AJ37+AL37+AN37 -> 0 | AP37: =SUM(AO37-BK37) -> -520883 | AQ37: =100000+20000 -> 120000 | AS37: =AG37 | AT37: =SUM(AU37:AV37) -> 400883 | AU37: 45983 | AV37: 354900 | AZ37: =AY37*AZ$3 -> 0 | BB37: =BA37*1430 -> 0 | BD37: =BC37*1400 -> 0 | BF37: =BE37*BF$3 -> 0 | BH37: =BG37*BH$3 -> 0 | BJ37: =BI37*BJ$3 -> 0 | BK37: =+AQ37+AR37+AT37+AW37+AX37+AZ37+BB37+BD37+BF37+BH37+BJ37 -> 520883 | BL37: =AD37 -> 533883 | BM37: =SUM(BK37-BL37) -> -13000 | BO37: =IF(AQ37+AR37=0,0,(AQ37+AR37)/AD37) -> 0.22476835 | BP37: =IF(AU37=0,0,AU37/AD37) -> 0.086129358 | BQ37: =IF(AV37=0,0,AV37/AD37) -> 0.66475239 | BR37: =IF(AW37=0,0,AW37/AD37) -> 0 | BS37: =IF(AZ37=0,0,AZ37/AD37) -> 0 | BT37: =IF(BB37+BD37+BF37=0,0,(BB37+BD37+BF37)/AD37) -> 0 | BU37: =IF(BJ37=0,0,BJ37/AD37) -> 0 | BV37: =SUM(BO37:BU37) -> 0.9756501 | BW37: =AD37/$AD$41 -> 0.037490796
A38: =A37+1 -> 46172 | C38: 5 | D38: =E37+1 -> 1474 | E38: =IF(C38="","",C38+D38-1) -> 1478 | H38: 477636.36 | I38: 100303.64 | K38: =H38+I38+J38 -> 577940 | O38: =N38*21% -> 0 | Q38: =N38+O38+P38 -> 0 | U38: =T38*21% -> 0 | W38: =T38+U38+V38 -> 0 | X38: 29 | Y38: 29 | Z38: 66107.44 | AA38: 13882.56 | AC38: =Z38+AA38+AB38 -> 79990 | AD38: =+K38+Q38+W38-AC38 -> 497950 | AJ38: =AI38*220 -> 0 | AL38: =AK38*1200 -> 0 | AN38: =AM38*1200 -> 0 | AO38: =AF38+AG38+AH38+AJ38+AL38+AN38 -> 0 | AP38: =SUM(AO38-BK38) -> -497950 | AQ38: 0 | AS38: =AG38 | AT38: =SUM(AU38:AV38) -> 497950 | AU38: 49990 | AV38: 447960 | AZ38: =AY38*AZ$3 -> 0 | BB38: =BA38*1460 -> 0 | BD38: =BC38*BD$3 -> 0 | BF38: =BE38*BF$3 -> 0 | BH38: =BG38*BH$3 -> 0 | BJ38: =BI38*BJ$3 -> 0 | BK38: =+AQ38+AR38+AT38+AW38+AX38+AZ38+BB38+BD38+BF38+BH38+BJ38 -> 497950 | BL38: =AD38 -> 497950 | BM38: =SUM(BK38-BL38) -> 0 | BO38: =IF(AQ38+AR38=0,0,(AQ38+AR38)/AD38) -> 0 | BP38: =IF(AU38=0,0,AU38/AD38) -> 0.10039161 | BQ38: =IF(AV38=0,0,AV38/AD38) -> 0.89960839 | BR38: =IF(AW38=0,0,AW38/AD38) -> 0 | BS38: =IF(AZ38=0,0,AZ38/AD38) -> 0 | BT38: =IF(BB38+BD38+BF38=0,0,(BB38+BD38+BF38)/AD38) -> 0 | BU38: =IF(BJ38=0,0,BJ38/AD38) -> 0 | BV38: =SUM(BO38:BU38) -> 1 | BW38: =AD38/$AD$41 -> 0.034967478
A39: =A38+1 -> 46173 | C39: 7 | D39: =E38+1 -> 1479 | E39: =IF(C39="","",C39+D39-1) -> 1485 | H39: 424728.82 | I39: 89193.08 | K39: =H39+I39+J39 -> 513921.9 | O39: =N39*21% -> 0 | Q39: =N39+O39+P39 -> 0 | U39: =T39*21% -> 0 | W39: =T39+U39+V39 -> 0 | AA39: =Z39*21% -> 0 | AC39: =Z39+AA39+AB39 -> 0 | AD39: =+K39+Q39+W39-AC39 -> 513921.9 | AJ39: =AI39*220 -> 0 | AL39: =AK39*1200 -> 0 | AN39: =AM39*1200 -> 0 | AQ39: =10000+3000 -> 13000 | AT39: =SUM(AU39:AV39) -> 499930 | AU39: 49990 | AV39: 449940 | AZ39: =AY39*AZ$3 -> 0 | BB39: =BA39*BB$3 -> 0 | BD39: =BC39*BD$3 -> 0 | BF39: =BE39*BF$3 -> 0 | BH39: =BG39*BH$3 -> 0 | BJ39: =BI39*BJ$3 -> 0 | BK39: =+AQ39+AR39+AT39+AW39+AX39+AZ39+BB39+BD39+BF39+BH39+BJ39 -> 512930 | BL39: =AD39 -> 513921.9 | BM39: =SUM(BK39-BL39) -> -991.9 | BO39: =IF(AQ39+AR39=0,0,(AQ39+AR39)/AD39) -> 0.025295672 | BP39: =IF(AU39=0,0,AU39/AD39) -> 0.097271589 | BQ39: =IF(AV39=0,0,AV39/AD39) -> 0.87550268 | BR39: =IF(AW39=0,0,AW39/AD39) -> 0 | BS39: =IF(AZ39=0,0,AZ39/AD39) -> 0 | BT39: =IF(BB39+BD39+BF39=0,0,(BB39+BD39+BF39)/AD39) -> 0 | BU39: =IF(BJ39=0,0,BJ39/AD39) -> 0 | BV39: =SUM(BO39:BU39) -> 0.99806994 | BW39: =AD39/$AD$41 -> 0.036089071
D40: =E39+1 -> 1486 | E40: =IF(C40="","",C40+D40-1) | I40: =H40*21% -> 0 | K40: =H40+I40+J40 -> 0 | O40: =N40*21% -> 0 | U40: =T40*21% -> 0 | X40: 0 | AA40: =Z40*21% -> 0 | AZ40: =AY40*AZ$3 -> 0 | BB40: =BA40*BB$3 -> 0 | BD40: =BC40*BD$3 -> 0 | BF40: =BE40*BF$3 -> 0 | BH40: =BG40*BH$3 -> 0 | BJ40: =BI40*BJ$3 -> 0 | BK40: =+AQ40+AR40+AT40+AW40+AX40+AZ40+BB40+BD40+BF40+BH40+BJ40 -> 0 | BM40: =SUM(BK40-BL40) -> 0 | BO40: =IF(AQ40+AR40=0,0,(AQ40+AR40)/AD40) -> 0 | BP40: =IF(AU40=0,0,AU40/AD40) -> 0 | BQ40: =IF(AV40=0,0,AV40/AD40) -> 0 | BR40: =IF(AW40=0,0,AW40/AD40) -> 0 | BS40: =IF(AZ40=0,0,AZ40/AD40) -> 0 | BT40: =IF(BB40+BD40+BF40=0,0,(BB40+BD40+BF40)/AD40) -> 0 | BU40: =IF(BJ40=0,0,BJ40/AD40) -> 0 | BV40: =SUM(BO40:BU40) -> 0 | BW40: =AD40/$AD$41 -> 0
A41: TOTALES | B41: =MAX(B9:B40) -> 0 | C41: =SUM(C9:C40) -> 172 | D41: =MIN(D9:D40) -> 1314 | E41: =MAX(E9:E40) -> 1485 | F41: =SUM(F9:F40) -> 0 | G41: =SUM(G9:G40) -> 0 | H41: =SUM(H9:H40) -> 11790422 | I41: =SUM(I9:I40) -> 2475988.9 | K41: =SUM(K9:K40) -> 14266411 | L41: =MIN(L9:L40) -> 0 | M41: =MAX(M9:M40) -> 0 | N41: =SUM(N9:N40) -> 0 | O41: =SUM(O9:O40) -> 0 | Q41: =SUM(Q9:Q40) -> 0 | R41: =MIN(R9:R40) -> 12 | S41: =MAX(S9:S40) -> 14 | T41: =SUM(T9:T40) -> 366870.91 | U41: =SUM(U9:U40) -> 77042.89 | W41: =SUM(W9:W40) -> 443913.8 | X41: =MIN(X9:X40) -> 0 | Y41: =MAX(Y9:Y40) -> 29 | Z41: =SUM(Z9:Z40) -> 388388.42 | AA41: =SUM(AA9:AA40) -> 81561.58 | AC41: =SUM(AC9:AC40) -> 469950 | AD41: =SUM(AD9:AD40) -> 14240375 | AE41: =SUM(AE9:AE38) -> 0 | AF41: =SUM(AF9:AF38) -> 0 | AG41: =SUM(AG9:AG38) -> 0 | AH41: =SUM(AH9:AH38) -> 0 | AI41: =SUM(AI9:AI38) -> 0 | AJ41: =SUM(AJ9:AJ38) -> 0 | AK41: =SUM(AK9:AK38) -> 0 | AL41: =SUM(AL9:AL38) -> 0 | ... AP41: =SUM(AP9:AP38) -> -13750663 | AQ41: =SUM(AQ9:AQ40) -> 1093000 | AR41: =SUM(AR9:AR40) -> 0 | AS41: =SUM(AS9:AS40) -> 0 | AT41: =SUM(AT9:AT40) -> 11824153 | AU41: =SUM(AU9:AU40) -> 3022378 | AV41: =SUM(AV9:AV40) -> 8801775 | AW41: =SUM(AW9:AW40) -> 0 | AX41: =SUM(AX9:AX40) -> 0 | ... BM41: =SUM(BM9:BM40) -> 23218 | BO41: =IF(AQ41+AR41=0,0,(AQ41+AR41)/AD41) -> 0.076753597 | BP41: =IF(AU41=0,0,AU41/AD41) -> 0.21224006 | BQ41: =IF(AV41=0,0,AV41/AD41) -> 0.6180859 | BR41: =IF(AW41=0,0,AW41/AD41) -> 0 | BS41: =IF(AZ41=0,0,AZ41/AD41) -> 0.0012387314 | BT41: =IF(BB41+BD41+BF41=0,0,(BB41+BD41+BF41)/AD41) -> 0.093312149 | BU41: =IF(BJ41=0,0,BJ41/AD41) -> 0 | BV41: =SUM(BO41:BU41) -> 1.0016304 | BW41: =AD41/$AD$41 -> 1
D42: 789 | L42: 0 | R42: 7 | X42: 5
A43: CONTROL | B43: =B9-B42 -> 0 | D43: =D9-D42 -> 525 | L43: =M41-L42 -> 0 | R43: =S41-R42 -> 7 | AE43: 0 | AF43: 0 | AG43: 0 | AH43: 0 | AI43: 0 | AJ43: 0 | AK43: 0 | AL43: 0 | AM43: 0 | AN43: 0 | AO43: 0
AC46: TOTAL | AD46: =AD41+AD45 -> 14240375 | AQ46: $ Efectivo | AR46: $ Deposito / PIX | AS46: TARJETA DEBITO | AT46: TARJETA CREDITO | AU46: Mercado Pago / TF | AV46: Real | AW46: Dólares | AX46: Euros
AP47: RESUMEN COBRANZA | AQ47: =AQ41 -> 1093000 | AR47: =AR41 -> 0 | AS47: =AU41 -> 3022378 | AT47: =AV41 -> 8801775 | AU47: =AW41 -> 0 | AV47: =AZ41 -> 17640 | AW47: =BD41+BF41+BH41+BB41 -> 1328800 | AX47: =BJ41 -> 0
AQ48: =AQ47/$AD$41 -> 0.076753597 | AR48: =AR47/$AD$41 -> 0 | AS48: =AS47/$AD$41 -> 0.21224006 | AT48: =AT47/$AD$41 -> 0.6180859 | AU48: =AU47/$AD$41 -> 0 | AV48: =AV47/$AD$41 -> 0.0012387314 | AW48: =AW47/$AD$41 -> 0.093312149 | AX48: =AX47/$AD$41 -> 0

Sheet LUCERO FLORIDA
AS1: Cotizaciones | AX1: De | AY1: Hasta
A2: Empresa: EL LUCERO CUERO S.A. | AS2: ='LUCERO RECOLETA'!AS2 | AX2: ='LUCERO RECOLETA'!AX2 | AY2: ='LUCERO RECOLETA'!AY2 | AZ2: ='LUCERO RECOLETA'!AZ2 | BA2: ='LUCERO RECOLETA'!BA2 | BB2: ='LUCERO RECOLETA'!BB2 | BC2: ='LUCERO RECOLETA'!BC2 | BD2: ='LUCERO RECOLETA'!BD2 | BE2: ='LUCERO RECOLETA'!BE2 | ... BJ2: ='LUCERO RECOLETA'!BJ2
A3: Sucursal: LUCERO FLORIDA - Florida 823 CABA | AS3: ='LUCERO RECOLETA'!AS3 | AX3: ='LUCERO RECOLETA'!AX3 | AY3: ='LUCERO RECOLETA'!AY3 | AZ3: ='LUCERO RECOLETA'!AZ3 | BA3: ='LUCERO RECOLETA'!BA3 | BB3: ='LUCERO RECOLETA'!BB3 | BC3: ='LUCERO RECOLETA'!BC3 | BD3: ='LUCERO RECOLETA'!BD3 | BE3: ='LUCERO RECOLETA'!BE3 | ... BJ3: ='LUCERO RECOLETA'!BJ3
AS4: ='LUCERO RECOLETA'!AS4 | AX4: ='LUCERO RECOLETA'!AX4 | AY4: ='LUCERO RECOLETA'!AY4 | AZ4: ='LUCERO RECOLETA'!AZ4 | BA4: ='LUCERO RECOLETA'!BA4 | BB4: ='LUCERO RECOLETA'!BB4 | BC4: ='LUCERO RECOLETA'!BC4 | BD4: ='LUCERO RECOLETA'!BD4 | BE4: ='LUCERO RECOLETA'!BE4 | ... BJ4: ='LUCERO RECOLETA'!BJ4
A5: INFORME DE VENTAS MENSUAL | E5: pv 00043 | AS5: ='LUCERO RECOLETA'!AS5 | AX5: ='LUCERO RECOLETA'!AX5 | AY5: ='LUCERO RECOLETA'!AY5 | AZ5: ='LUCERO RECOLETA'!AZ5 | BA5: ='LUCERO RECOLETA'!BA5 | BB5: ='LUCERO RECOLETA'!BB5 | BC5: ='LUCERO RECOLETA'!BC5 | BD5: ='LUCERO RECOLETA'!BD5 | BE5: ='LUCERO RECOLETA'!BE5 | ... BJ5: ='LUCERO RECOLETA'!BJ5
A7: ='LUCERO RECOLETA'!A7 -> ABRIL | B7: Detalle de FACTURAS B | L7: Detalle de TICKETS | R7: Detalle de FACTURAS A | X7: Detalle de NOTAS DE CREDITO | AD7: VENTA FINAL | AE7: INFORME SEGÚN MAIL | AP7: DIFERENCIA | AQ7: CONTROL DE CIERRE DE CAJA
A8: Fecha | B8: Informe de cierre | C8: N° Tickets | D8: Desde | E8: Hasta | F8: Anulados y/o cancelados | G8: Cant. de art. | H8: Imp. de VTA gravado | I8: IVA 21% | J8: Otros imp. | K8: Imp. de VTA total | L8: Desde | M8: Hasta | N8: Imp.de VTA gravado | O8: IVA 21% | P8: Otros imp. | Q8: Imp. de VTA total | R8: Desde | S8: Hasta | T8: Imp.de VTA gravado | U8: IVA 21% | V8: Otros imp. | W8: Imp. de VTA total | X8: Desde | Y8: Hasta | Z8: Imp.de VTA gravado | AA8: IVA 21% | AB8: Otros imp. | AC8: Imp. de VTA total | AE8: VENTA TOTAL | AF8: EFECTIVO $ | AG8: TARJETAS | AH8: MERCADO PAGO | AI8: Real | AK8: Dolar | AM8: EURO | AO8: TOTAL DE INGRESO | AQ8: $ Efectivo | AR8: $ Deposito / PIX | AS8: TARJ SEGUN PLANILLA | AT8: TOTAL TARJETAS OK | AU8: TARJETA DEBITO | AV8: TARJETA CREDITO | AW8: Mercado Pago / TF | AX8: Gastos | AY8: Real | BA8: Dólar 100 | BC8: Dólar 50 | BE8: Dólar 10. 20 | BG8: Dólar 1. 5 | BI8: EURO | BK8: Total | BL8: CIERRE | BM8: DIFERENCIA | BO8: =AQ8 -> $ Efectivo | BP8: =AU8 -> TARJETA DEBITO | BQ8: =AV8 -> TARJETA CREDITO | BR8: =AW8 -> Mercado Pago / TF | BS8: =AY8 -> Real | BT8: Dólar | BU8: Euro | BV8: Total | BW8: Venta x día
A9: ='LUCERO RECOLETA'!A9 -> 46143 | C9: 0 | D9: 543 | E9: =IF(C9="","",C9+D9-1) -> 542 | K9: =H9+I9+J9 -> 0 | O9: =N9*21% -> 0 | Q9: =N9+O9+P9 -> 0 | U9: =T9*21% -> 0 | W9: =T9+U9+V9 -> 0 | AA9: =Z9*21% -> 0 | AC9: =Z9+AA9+AB9 -> 0 | AD9: =+K9+Q9+W9-AC9 -> 0 | AJ9: =AI9*220 -> 0 | AL9: =AK9*1200 -> 0 | AN9: =AM9*1200 -> 0 | AO9: =AF9+AG9+AH9+AJ9+AL9+AN9 -> 0 | AP9: =SUM(AO9-BK9) -> 0 | AT9: 0 | AZ9: =AY9*277 -> 0 | BB9: =BA9*1405 -> 0 | BD9: =BC9*BD$2 -> 0 | BF9: =BE9*BF$2 -> 0 | BH9: =BG9*BH$2 -> 0 | BJ9: =BI9*1640 -> 0 | BK9: =+AQ9+AR9+AT9+AW9+AX9+AZ9+BB9+BD9+BF9+BH8+BJ9 -> 0 | BL9: =AD9 -> 0 | BM9: =SUM(BK9-BL9) -> 0 | BO9: =IF(AQ9+AR9=0,0,(AQ9+AR9)/AD9) -> 0 | BP9: =IF(AU9=0,0,AU9/AD9) -> 0 | BQ9: =IF(AT9=0,0,AT9/AD9) -> 0 | BR9: =IF(AW9=0,0,AW9/AD9) -> 0 | BS9: =IF(AZ9=0,0,AZ9/AD9) -> 0 | BT9: =IF(BB9+BD9+BF9=0,0,(BB9+BD9+BF9)/AD9) -> 0 | BU9: =IF(BJ9=0,0,BJ9/AD9) -> 0 | BV9: =SUM(BO9:BU9) -> 0 | BW9: =AD9/$AD$41 -> 0
A10: ='LUCERO RECOLETA'!A10 -> 46144 | C10: 21 | D10: =E9+1 -> 543 | E10: =IF(C10="","",C10+D10-1) -> 563 | H10: 1866687.5 | I10: 392004.38 | K10: =H10+I10+J10 -> 2258691.9 | O10: =N10*21% -> 0 | Q10: =N10+O10+P10 -> 0 | U10: =T10*21% -> 0 | W10: =T10+U10+V10 -> 0 | X10: 17 | Y10: 17 | Z10: 165280.99 | AA10: 34709.01 | AC10: =Z10+AA10+AB10 -> 199990 | AD10: =+K10+Q10+W10-AC10 -> 2058701.9 | AJ10: =AI10*220 -> 0 | AL10: =AK10*1200 -> 0 | AN10: =AM10*1200 -> 0 | AO10: =AF10+AG10+AH10+AJ10+AL10+AN10 -> 0 | AP10: =SUM(AO10-BK10) -> -2037740 | AQ10: =40000+10000+40000 -> 90000 | AT10: 1947740 | AZ10: =AY10*276 -> 0 | BB10: =BA10*1465 -> 0 | BD10: =BC10*1480 -> 0 | BF10: =BE10*BF$2 -> 0 | BH10: =BG10*BH$2 -> 0 | BJ10: =BI10*BJ$2 -> 0 | BK10: =+AQ10+AR10+AT10+AW10+AX10+AZ10+BB10+BD10+BF10+BH9+BJ10 -> 2037740 | BL10: =AD10 -> 2058701.9 | BM10: =SUM(BK10-BL10) -> -20961.9 | BO10: =IF(AQ10+AR10=0,0,(AQ10+AR10)/AD10) -> 0.043716868 | BP10: =IF(AU10=0,0,AU10/AD10) -> 0 | BQ10: =IF(AT10=0,0,AT10/AD10) -> 0.94610104 | BR10: =IF(AW10=0,0,AW10/AD10) -> 0 | BS10: =IF(AZ10=0,0,AZ10/AD10) -> 0 | BT10: =IF(BB10+BD10+BF10=0,0,(BB10+BD10+BF10)/AD10) -> 0 | BU10: =IF(BJ10=0,0,BJ10/AD10) -> 0 | BV10: =SUM(BO10:BU10) -> 0.9898179 | BW10: =AD10/$AD$41 -> 0.044453399
A11: ='LUCERO RECOLETA'!A11 -> 46145 | C11: 21 | D11: =E10+1 -> 564 | E11: =IF(C11="","",C11+D11-1) -> 584 | H11: 1682719 | I11: 353371.01 | K11: =H11+I11+J11 -> 2036090 | O11: =N11*21% -> 0 | Q11: =N11+O11+P11 -> 0 | U11: =T11*21% -> 0 | W11: =T11+U11+V11 -> 0 | AA11: =Z11*21% -> 0 | AC11: =Z11+AA11+AB11 -> 0 | AD11: =+K11+Q11+W11-AC11 -> 2036090 | AJ11: =AI11*220 -> 0 | AL11: =AK11*1200 -> 0 | AN11: =AM11*1200 -> 0 | AO11: =AF11+AG11+AH11+AJ11+AL11+AN11 -> 0 | AP11: =SUM(AO11-BK11) -> -2039710 | AQ11: 15000 | AT11: 1826610 | AZ11: =AY11*283 -> 0 | BA11: 100 | BB11: =BA11*1415 -> 141500 | BC11: 40 | BD11: =BC11*1415 -> 56600 | BF11: =BE11*1470 -> 0 | BH11: =BG11*BH$2 -> 0 | BJ11: =BI11*1700 -> 0 | BK11: =+AQ11+AR11+AT11+AW11+AX11+AZ11+BB11+BD11+BF11+BH11+BJ11 -> 2039710 | BL11: =AD11 -> 2036090 | BM11: =SUM(BK11-BL11) -> 3620 | BO11: =IF(AQ11+AR11=0,0,(AQ11+AR11)/AD11) -> 0.0073670614 | BP11: =IF(AU11=0,0,AU11/AD11) -> 0 | BQ11: =IF(AT11=0,0,AT11/AD11) -> 0.89711653 | BR11: =IF(AW11=0,0,AW11/AD11) -> 0 | BS11: =IF(AZ11=0,0,AZ11/AD11) -> 0 | BT11: =IF(BB11+BD11+BF11=0,0,(BB11+BD11+BF11)/AD11) -> 0.097294324 | BU11: =IF(BJ11=0,0,BJ11/AD11) -> 0 | BV11: =SUM(BO11:BU11) -> 1.0017779 | BW11: =AD11/$AD$41 -> 0.043965142
A12: ='LUCERO RECOLETA'!A12 -> 46146 | C12: 15 | D12: =E11+1 -> 585 | E12: =IF(C12="","",C12+D12-1) -> 599 | H12: 2639396.7 | I12: 554273.3 | K12: =H12+I12+J12 -> 3193670 | O12: =N12*21% -> 0 | Q12: =N12+O12+P12 -> 0 | U12: =T12*21% -> 0 | W12: =T12+U12+V12 -> 0 | AA12: =Z12*21% -> 0 | AC12: =Z12+AA12+AB12 -> 0 | AD12: =+K12+Q12+W12-AC12 -> 3193670 | AJ12: =AI12*220 -> 0 | AL12: =AK12*1200 -> 0 | AN12: =AM12*1200 -> 0 | AO12: =AF12+AG12+AH12+AJ12+AL12+AN12 -> 0 | AP12: =SUM(AO12-BK12) -> -3191070 | AQ12: =20000+10000 -> 30000 | AT12: 2283770 | AZ12: =AY12*1495 -> 0 | BA12: 520 | BB12: =BA12*1415 -> 735800 | BC12: 100 | BD12: =BC12*1415 -> 141500 | BF12: =BE12*1495 -> 0 | BH12: =BG12*BH$2 -> 0 | BJ12: =BI12*BJ$2 -> 0 | BK12: =+AQ12+AR12+AT12+AW12+AX12+AZ12+BB12+BD12+BF12+BH12+BJ12 -> 3191070 | BL12: =AD12 -> 3193670 | BM12: =SUM(BK12-BL12) -> -2600 | BO12: =IF(AQ12+AR12=0,0,(AQ12+AR12)/AD12) -> 0.0093935817 | BP12: =IF(AU12=0,0,AU12/AD12) -> 0 | BQ12: =IF(AT12=0,0,AT12/AD12) -> 0.71509267 | BR12: =IF(AW12=0,0,AW12/AD12) -> 0 | BS12: =IF(AZ12=0,0,AZ12/AD12) -> 0 | BT12: =IF(BB12+BD12+BF12=0,0,(BB12+BD12+BF12)/AD12) -> 0.27469964 | BU12: =IF(BJ12=0,0,BJ12/AD12) -> 0 | BV12: =SUM(BO12:BU12) -> 0.99918589 | BW12: =AD12/$AD$41 -> 0.068960681
A13: ='LUCERO RECOLETA'!A13 -> 46147 | C13: 12 | D13: =E12+1 -> 600 | E13: =IF(C13="","",C13+D13-1) -> 611 | H13: 977528.92 | I13: 205281.08 | K13: =H13+I13+J13 -> 1182810 | O13: =N13*21% -> 0 | Q13: =N13+O13+P13 -> 0 | U13: =T13*21% -> 0 | W13: =T13+U13+V13 -> 0 | AA13: =Z13*21% -> 0 | AC13: =Z13+AA13+AB13 -> 0 | AD13: =+K13+Q13+W13-AC13 -> 1182810 | AJ13: =AI13*220 -> 0 | AL13: =AK13*1200 -> 0 | AN13: =AM13*1200 -> 0 | AO13: =AF13+AG13+AH13+AJ13+AL13+AN13 -> 0 | AP13: =SUM(AO13-BK13) -> -1186820 | AQ13: =80000+9000 -> 89000 | AT13: 899720 | AZ13: =AY13*AZ$2 -> 0 | BA13: 140 | BB13: =BA13*1415 -> 198100 | BD13: =BC13*BD$2 -> 0 | BF13: =BE13*BF$2 -> 0 | BH13: =BG13*BH$2 -> 0 | BJ13: =BI13*BJ$2 -> 0 | BK13: =+AQ13+AR13+AT13+AW13+AX13+AZ13+BB13+BD13+BF13+BH13+BJ13 -> 1186820 | BL13: =AD13 -> 1182810 | BM13: =SUM(BK13-BL13) -> 4010 | BO13: =IF(AQ13+AR13=0,0,(AQ13+AR13)/AD13) -> 0.075244545 | BP13: =IF(AU13=0,0,AU13/AD13) -> 0 | BQ13: =IF(AT13=0,0,AT13/AD13) -> 0.76066317 | BR13: =IF(AW13=0,0,AW13/AD13) -> 0 | BS13: =IF(AZ13=0,0,AZ13/AD13) -> 0 | BT13: =IF(BB13+BD13+BF13=0,0,(BB13+BD13+BF13)/AD13) -> 0.16748252 | BU13: =IF(BJ13=0,0,BJ13/AD13) -> 0 | BV13: =SUM(BO13:BU13) -> 1.0033902 | BW13: =AD13/$AD$41 -> 0.025540329
A14: ='LUCERO RECOLETA'!A14 -> 46148 | C14: 8 | D14: =E13+1 -> 612 | E14: =IF(C14="","",C14+D14-1) -> 619 | H14: 485839.67 | I14: 102026.33 | K14: =H14+I14+J14 -> 587866 | O14: =N14*21% -> 0 | Q14: =N14+O14+P14 -> 0 | U14: =T14*21% -> 0 | W14: =T14+U14+V14 -> 0 | AA14: =Z14*21% -> 0 | AC14: =Z14+AA14+AB14 -> 0 | AD14: =+K14+Q14+W14-AC14 -> 587866 | AJ14: =AI14*220 -> 0 | AL14: =AK14*1200 -> 0 | AN14: =AM14*1200 -> 0 | AO14: =AF14+AG14+AH14+AJ14+AL14+AN14 -> 0 | AP14: =SUM(AO14-BK14) -> -589890 | AQ14: =100000+20000+40000 -> 160000 | AT14: 429890 | AZ14: =AY14*AZ$2 -> 0 | BB14: =BA14*1415 -> 0 | BD14: =BC14*BD$2 -> 0 | BF14: =BE14*BF$2 -> 0 | BH14: =BG14*BH$2 -> 0 | BJ14: =BI14*1665 -> 0 | BK14: =+AQ14+AR14+AT14+AW14+AX14+AZ14+BB14+BD14+BF14+BH14+BJ14 -> 589890 | BL14: =AD14 -> 587866 | BM14: =SUM(BK14-BL14) -> 2024 | BO14: =IF(AQ14+AR14=0,0,(AQ14+AR14)/AD14) -> 0.27217087 | BP14: =IF(AU14=0,0,AU14/AD14) -> 0 | BQ14: =IF(AT14=0,0,AT14/AD14) -> 0.73127209 | BR14: =IF(AW14=0,0,AW14/AD14) -> 0 | BS14: =IF(AZ14=0,0,AZ14/AD14) -> 0 | BT14: =IF(BB14+BD14+BF14=0,0,(BB14+BD14+BF14)/AD14) -> 0 | BU14: =IF(BJ14=0,0,BJ14/AD14) -> 0 | BV14: =SUM(BO14:BU14) -> 1.003443 | BW14: =AD14/$AD$41 -> 0.012693747
A15: ='LUCERO RECOLETA'!A15 -> 46149 | C15: 21 | D15: =E14+1 -> 620 | E15: =IF(C15="","",C15+D15-1) -> 640 | H15: 2135231.4 | I15: 448398.6 | K15: =H15+I15+J15 -> 2583630 | O15: =N15*21% -> 0 | Q15: =N15+O15+P15 -> 0 | U15: =T15*21% -> 0 | W15: =T15+U15+V15 -> 0 | AA15: =Z15*21% -> 0 | AC15: =Z15+AA15+AB15 -> 0 | AD15: =+K15+Q15+W15-AC15 -> 2583630 | AJ15: =AI15*220 -> 0 | AL15: =AK15*1200 -> 0 | AN15: =AM15*1200 -> 0 | AO15: =AF15+AG15+AH15+AJ15+AL15+AN15 -> 0 | AP15: =SUM(AO15-BK15) -> -2581670 | AQ15: =25000+100000 -> 125000 | AT15: 2173670 | AZ15: =AY15*AZ$2 -> 0 | BA15: 200 | BB15: =BA15*1415 -> 283000 | BD15: =BC15*BD$2 -> 0 | BF15: =BE15*1465 -> 0 | BH15: =BG15*BH$2 -> 0 | BJ15: =BI15*BJ$2 -> 0 | BK15: =+AQ15+AR15+AT15+AW15+AX15+AZ15+BB15+BD15+BF15+BH15+BJ15 -> 2581670 | BL15: =AD15 -> 2583630 | BM15: =SUM(BK15-BL15) -> -1960 | BO15: =IF(AQ15+AR15=0,0,(AQ15+AR15)/AD15) -> 0.048381541 | BP15: =IF(AU15=0,0,AU15/AD15) -> 0 | BQ15: =IF(AT15=0,0,AT15/AD15) -> 0.84132403 | BR15: =IF(AW15=0,0,AW15/AD15) -> 0 | BS15: =IF(AZ15=0,0,AZ15/AD15) -> 0 | BT15: =IF(BB15+BD15+BF15=0,0,(BB15+BD15+BF15)/AD15) -> 0.10953581 | BU15: =IF(BJ15=0,0,BJ15/AD15) -> 0 | BV15: =SUM(BO15:BU15) -> 0.99924138 | BW15: =AD15/$AD$41 -> 0.055788133
A16: ='LUCERO RECOLETA'!A16 -> 46150 | C16: 10 | D16: =E15+1 -> 641 | E16: =IF(C16="","",C16+D16-1) -> 650 | H16: 566000 | I16: 118860 | K16: =H16+I16+J16 -> 684860 | O16: =N16*21% -> 0 | Q16: =N16+O16+P16 -> 0 | U16: =T16*21% -> 0 | W16: =T16+U16+V16 -> 0 | AA16: =Z16*21% -> 0 | AC16: =Z16+AA16+AB16 -> 0 | AD16: =+K16+Q16+W16-AC16 -> 684860 | AJ16: =AI16*220 -> 0 | AL16: =AK16*1200 -> 0 | AN16: =AM16*1200 -> 0 | AO16: =AF16+AG16+AH16+AJ16+AL16+AN16 -> 0 | AP16: =SUM(AO16-BK16) -> -684860 | AQ16: 0 | AT16: 684860 | AZ16: =AY16*AZ$2 -> 0 | BB16: =BA16*1465 -> 0 | BD16: =BC16*BD$2 -> 0 | BF16: =BE16*BF$2 -> 0 | BH16: =BG16*BH$2 -> 0 | BJ16: =BI16*BJ$2 -> 0 | BK16: =+AQ16+AR16+AT16+AW16+AX16+AZ16+BB16+BD16+BF16+BH16+BJ16 -> 684860 | BL16: =AD16 -> 684860 | BM16: =SUM(BK16-BL16) -> 0 | BO16: =IF(AQ16+AR16=0,0,(AQ16+AR16)/AD16) -> 0 | BP16: =IF(AU16=0,0,AU16/AD16) -> 0 | BQ16: =IF(AT16=0,0,AT16/AD16) -> 1 | BR16: =IF(AW16=0,0,AW16/AD16) -> 0 | BS16: =IF(AZ16=0,0,AZ16/AD16) -> 0 | BT16: =IF(BB16+BD16+BF16=0,0,(BB16+BD16+BF16)/AD16) -> 0 | BU16: =IF(BJ16=0,0,BJ16/AD16) -> 0 | BV16: =SUM(BO16:BU16) -> 1 | BW16: =AD16/$AD$41 -> 0.014788132
A17: ='LUCERO RECOLETA'!A17 -> 46151 | C17: 13 | D17: =E16+1 -> 651 | E17: =IF(C17="","",C17+D17-1) -> 663 | H17: 1341966.9 | I17: 281813.08 | K17: =H17+I17+J17 -> 1623780 | O17: =N17*21% -> 0 | Q17: =N17+O17+P17 -> 0 | U17: =T17*21% -> 0 | W17: =T17+U17+V17 -> 0 | AA17: =Z17*21% -> 0 | AC17: =Z17+AA17+AB17 -> 0 | AD17: =+K17+Q17+W17-AC17 -> 1623780 | AJ17: =AI17*220 -> 0 | AL17: =AK17*1200 -> 0 | AN17: =AM17*1200 -> 0 | AO17: =AF17+AG17+AH17+AJ17+AL17+AN17 -> 0 | AP17: =SUM(AO17-BK17) -> -1623600 | AQ17: =20000+20000+10000 -> 50000 | AT17: 1573600 | AZ17: =AY17*AZ$3 -> 0 | BB17: =BA17*1450 -> 0 | BD17: =BC17*BD$2 -> 0 | BF17: =BE17*1485 -> 0 | BH17: =BG17*BH$2 -> 0 | BJ17: =BI17*BJ$2 -> 0 | BK17: =+AQ17+AR17+AT17+AW17+AX17+AZ17+BB17+BD17+BF17+BH17+BJ17 -> 1623600 | BL17: =AD17 -> 1623780 | BM17: =SUM(BK17-BL17) -> -180 | BO17: =IF(AQ17+AR17=0,0,(AQ17+AR17)/AD17) -> 0.030792349 | BP17: =IF(AU17=0,0,AU17/AD17) -> 0 | BQ17: =IF(AT17=0,0,AT17/AD17) -> 0.9690968 | BR17: =IF(AW17=0,0,AW17/AD17) -> 0 | BS17: =IF(AZ17=0,0,AZ17/AD17) -> 0 | BT17: =IF(BB17+BD17+BF17=0,0,(BB17+BD17+BF17)/AD17) -> 0 | BU17: =IF(BJ17=0,0,BJ17/AD17) -> 0 | BV17: =SUM(BO17:BU17) -> 0.99988915 | BW17: =AD17/$AD$41 -> 0.035062162
A18: ='LUCERO RECOLETA'!A18 -> 46152 | C18: 14 | D18: =E17+1 -> 664 | E18: =IF(C18="","",C18+D18-1) -> 677 | H18: 918019.63 | I18: 192784.17 | K18: =H18+I18+J18 -> 1110803.8 | O18: =N18*21% -> 0 | Q18: =N18+O18+P18 -> 0 | U18: =T18*21% -> 0 | W18: =T18+U18+V18 -> 0 | AA18: =Z18*21% -> 0 | AC18: =Z18+AA18+AB18 -> 0 | AD18: =+K18+Q18+W18-AC18 -> 1110803.8 | AJ18: =AI18*220 -> 0 | AL18: =AK18*1200 -> 0 | AN18: =AM18*1200 -> 0 | AO18: =AF18+AG18+AH18+AJ18+AL18+AN18 -> 0 | AP18: =SUM(AO18-BK18) -> -1111840 | AQ18: =40000+100000+15000 -> 155000 | AT18: 956840 | AZ18: =AY18*AZ$3 -> 0 | BB18: =BA18*BB$2 -> 0 | BD18: =BC18*BD$2 -> 0 | BF18: =BE18*BF$2 -> 0 | BH18: =BG18*BH$2 -> 0 | BJ18: =BI18*1685 -> 0 | BK18: =+AQ18+AR18+AT18+AW18+AX18+AZ18+BB18+BD18+BF18+BH18+BJ18 -> 1111840 | BL18: =AD18 -> 1110803.8 | BM18: =SUM(BK18-BL18) -> 1036.2 | BO18: =IF(AQ18+AR18=0,0,(AQ18+AR18)/AD18) -> 0.13953859 | BP18: =IF(AU18=0,0,AU18/AD18) -> 0 | BQ18: =IF(AT18=0,0,AT18/AD18) -> 0.86139424 | BR18: =IF(AW18=0,0,AW18/AD18) -> 0 | BS18: =IF(AZ18=0,0,AZ18/AD18) -> 0 | BT18: =IF(BB18+BD18+BF18=0,0,(BB18+BD18+BF18)/AD18) -> 0 | BU18: =IF(BJ18=0,0,BJ18/AD18) -> 0 | BV18: =SUM(BO18:BU18) -> 1.0009328 | BW18: =AD18/$AD$41 -> 0.023985505
A19: ='LUCERO RECOLETA'!A19 -> 46153 | C19: 7 | D19: =E18+1 -> 678 | E19: =IF(C19="","",C19+D19-1) -> 684 | H19: 413157.02 | I19: 86762.98 | K19: =H19+I19+J19 -> 499920 | O19: =N19*21% -> 0 | Q19: =N19+O19+P19 -> 0 | U19: =T19*21% -> 0 | W19: =T19+U19+V19 -> 0 | AA19: =Z19*21% -> 0 | AC19: =Z19+AA19+AB19 -> 0 | AD19: =+K19+Q19+W19-AC19 -> 499920 | AJ19: =AI19*220 -> 0 | AL19: =AK19*1200 -> 0 | AN19: =AM19*1200 -> 0 | AO19: =AF19+AG19+AH19+AJ19+AL19+AN19 -> 0 | AP19: =SUM(AO19-BK19) -> -607940 | AQ19: =20000+20000 -> 40000 | AT19: 567940 | AZ19: =AY19*AZ$3 -> 0 | BB19: =BA19*BB$2 -> 0 | BD19: =BC19*BD$2 -> 0 | BF19: =BE19*BF$2 -> 0 | BH19: =BG19*BH$2 -> 0 | BJ19: =BI19*BJ$2 -> 0 | BK19: =+AQ19+AR19+AT19+AW19+AX19+AZ19+BB19+BD19+BF19+BH19+BJ19 -> 607940 | BL19: =AD19 -> 499920 | BM19: =SUM(BK19-BL19) -> 108020 | BN19: Cobrados de más $107,000 x la cajera | BO19: =IF(AQ19+AR19=0,0,(AQ19+AR19)/AD19) -> 0.080012802 | BP19: =IF(AU19=0,0,AU19/AD19) -> 0 | BQ19: =IF(AT19=0,0,AT19/AD19) -> 1.1360618 | BR19: =IF(AW19=0,0,AW19/AD19) -> 0 | BS19: =IF(AZ19=0,0,AZ19/AD19) -> 0 | BT19: =IF(BB19+BD19+BF19=0,0,(BB19+BD19+BF19)/AD19) -> 0 | BU19: =IF(BJ19=0,0,BJ19/AD19) -> 0 | BV19: =SUM(BO19:BU19) -> 1.2160746 | BW19: =AD19/$AD$41 -> 0.010794736
A20: ='LUCERO RECOLETA'!A20 -> 46154 | C20: 8 | D20: =E19+1 -> 685 | E20: =IF(C20="","",C20+D20-1) -> 692 | H20: 784170.25 | I20: 164675.75 | K20: =H20+I20+J20 -> 948846 | O20: =N20*21% -> 0 | Q20: =N20+O20+P20 -> 0 | R20: 10 | S20: 10 | T20: 247925.62 | U20: 52064.38 | W20: =T20+U20+V20 -> 299990 | AA20: =Z20*21% -> 0 | AC20: =Z20+AA20+AB20 -> 0 | AD20: =+K20+Q20+W20-AC20 -> 1248836 | AJ20: =AI20*220 -> 0 | AL20: =AK20*1200 -> 0 | AN20: =AM20*1200 -> 0 | AO20: =AF20+AG20+AH20+AJ20+AL20+AN20 -> 0 | AP20: =SUM(AO20-BK20) -> -1243860 | AQ20: =30000+130000 -> 160000 | AT20: 1083860 | AZ20: =AY20*286 -> 0 | BB20: =BA20*1425 -> 0 | BD20: =BC20*BD$2 -> 0 | BF20: =BE20*BF$2 -> 0 | BH20: =BG20*BH$2 -> 0 | BJ20: =BI20*BJ$2 -> 0 | BK20: =+AQ20+AR20+AT20+AW20+AX20+AZ20+BB20+BD20+BF20+BH20+BJ20 -> 1243860 | BL20: =AD20 -> 1248836 | BM20: =SUM(BK20-BL20) -> -4976 | BO20: =IF(AQ20+AR20=0,0,(AQ20+AR20)/AD20) -> 0.1281193 | BP20: =IF(AU20=0,0,AU20/AD20) -> 0 | BQ20: =IF(AT20=0,0,AT20/AD20) -> 0.86789618 | BR20: =IF(AW20=0,0,AW20/AD20) -> 0 | BS20: =IF(AZ20=0,0,AZ20/AD20) -> 0 | BT20: =IF(BB20+BD20+BF20=0,0,(BB20+BD20+BF20)/AD20) -> 0 | BU20: =IF(BJ20=0,0,BJ20/AD20) -> 0 | BV20: =SUM(BO20:BU20) -> 0.99601549 | BW20: =AD20/$AD$41 -> 0.026966024
A21: ='LUCERO RECOLETA'!A21 -> 46155 | C21: 9 | D21: =E20+1 -> 693 | E21: =IF(C21="","",C21+D21-1) -> 701 | H21: 665148.77 | I21: 139681.23 | K21: =H21+I21+J21 -> 804830 | O21: =N21*21% -> 0 | Q21: =N21+O21+P21 -> 0 | U21: =T21*21% -> 0 | W21: =T21+U21+V21 -> 0 | AA21: =Z21*21% -> 0 | AC21: =Z21+AA21+AB21 -> 0 | AD21: =+K21+Q21+W21-AC21 -> 804830 | AJ21: =AI21*220 -> 0 | AL21: =AK21*1200 -> 0 | AN21: =AM21*1200 -> 0 | AO21: =AF21+AG21+AH21+AJ21+AL21+AN21 -> 0 | AP21: =SUM(AO21-BK21) -> -804840 | AQ21: 30000 | AT21: 774840 | AZ21: =AY21*AZ$3 -> 0 | BB21: =BA21*1395 -> 0 | BD21: =BC21*BD$2 -> 0 | BF21: =BE21*BF$2 -> 0 | BH21: =BG21*BH$2 -> 0 | BJ21: =BI21*BJ$2 -> 0 | BK21: =+AQ21+AR21+AT21+AW21+AX21+AZ21+BB21+BD21+BF21+BH21+BJ21 -> 804840 | BL21: =AD21 -> 804830 | BM21: =SUM(BK21-BL21) -> 10 | BO21: =IF(AQ21+AR21=0,0,(AQ21+AR21)/AD21) -> 0.037274952 | BP21: =IF(AU21=0,0,AU21/AD21) -> 0 | BQ21: =IF(AT21=0,0,AT21/AD21) -> 0.96273747 | BR21: =IF(AW21=0,0,AW21/AD21) -> 0 | BS21: =IF(AZ21=0,0,AZ21/AD21) -> 0 | BT21: =IF(BB21+BD21+BF21=0,0,(BB21+BD21+BF21)/AD21) -> 0 | BU21: =IF(BJ21=0,0,BJ21/AD21) -> 0 | BV21: =SUM(BO21:BU21) -> 1.0000124 | BW21: =AD21/$AD$41 -> 0.017378635
A22: ='LUCERO RECOLETA'!A22 -> 46156 | C22: 24 | D22: =E21+1 -> 702 | E22: =IF(C22="","",C22+D22-1) -> 725 | H22: 2567413.2 | I22: 539156.79 | K22: =H22+I22+J22 -> 3106570 | O22: =N22*21% -> 0 | Q22: =N22+O22+P22 -> 0 | U22: =T22*21% -> 0 | W22: =T22+U22+V22 -> 0 | AA22: =Z22*21% -> 0 | AC22: =Z22+AA22+AB22 -> 0 | AD22: =+K22+Q22+W22-AC22 -> 3106570 | AJ22: =AI22*220 -> 0 | AL22: =AK22*1200 -> 0 | AN22: =AM22*1200 -> 0 | AO22: =AF22+AG22+AH22+AJ22+AL22+AN22 -> 0 | AP22: =SUM(AO22-BK22) -> -3111660 | AQ22: =10000+160000+160000 -> 330000 | AT22: 2781660 | AZ22: =AY22*286 -> 0 | BB22: =BA22*1395 -> 0 | BD22: =BC22*BD$2 -> 0 | BF22: =BE22*1490 -> 0 | BH22: =BG22*BH$2 -> 0 | BJ22: =BI22*BJ$2 -> 0 | BK22: =+AQ22+AR22+AT22+AW22+AX22+AZ22+BB22+BD22+BF22+BH22+BJ22 -> 3111660 | BL22: =AD22 -> 3106570 | BM22: =SUM(BK22-BL22) -> 5090 | BO22: =IF(AQ22+AR22=0,0,(AQ22+AR22)/AD22) -> 0.10622648 | BP22: =IF(AU22=0,0,AU22/AD22) -> 0 | BQ22: =IF(AT22=0,0,AT22/AD22) -> 0.89541198 | BR22: =IF(AW22=0,0,AW22/AD22) -> 0 | BS22: =IF(AZ22=0,0,AZ22/AD22) -> 0 | BT22: =IF(BB22+BD22+BF22=0,0,(BB22+BD22+BF22)/AD22) -> 0 | BU22: =IF(BJ22=0,0,BJ22/AD22) -> 0 | BV22: =SUM(BO22:BU22) -> 1.0016385 | BW22: =AD22/$AD$41 -> 0.067079938
A23: ='LUCERO RECOLETA'!A23 -> 46157 | C23: 10 | D23: =E22+1 -> 726 | E23: =IF(C23="","",C23+D23-1) -> 735 | H23: 1708909.1 | I23: 358870.92 | K23: =H23+I23+J23 -> 2067780 | O23: =N23*21% -> 0 | Q23: =N23+O23+P23 -> 0 | U23: =T23*21% -> 0 | W23: =T23+U23+V23 -> 0 | X23: 18 | Y23: 18 | Z23: 41314.05 | AA23: 8675.95 | AC23: =Z23+AA23+AB23 -> 49990 | AD23: =+K23+Q23+W23-AC23 -> 2017790 | AJ23: =AI23*220 -> 0 | AL23: =AK23*1200 -> 0 | AN23: =AM23*1200 -> 0 | AO23: =AF23+AG23+AH23+AJ23+AL23+AN23 -> 0 | AP23: =SUM(AO23-BK23) -> -2012810 | AQ23: =130000+120000 -> 250000 | AT23: 1762810 | AZ23: =AY23*AZ$3 -> 0 | BB23: =BA23*1425 -> 0 | BD23: =BC23*BD$2 -> 0 | BF23: =BE23*BF$2 -> 0 | BH23: =BG23*BH$2 -> 0 | BJ23: =BI23*BJ$2 -> 0 | BK23: =+AQ23+AR23+AT23+AW23+AX23+AZ23+BB23+BD23+BF23+BH23+BJ23 -> 2012810 | BL23: =AD23 -> 2017790 | BM23: =SUM(BK23-BL23) -> -4980 | BO23: =IF(AQ23+AR23=0,0,(AQ23+AR23)/AD23) -> 0.12389793 | BP23: =IF(AU23=0,0,AU23/AD23) -> 0 | BQ23: =IF(AT23=0,0,AT23/AD23) -> 0.87363403 | BR23: =IF(AW23=0,0,AW23/AD23) -> 0 | BS23: =IF(AZ23=0,0,AZ23/AD23) -> 0 | BT23: =IF(BB23+BD23+BF23=0,0,(BB23+BD23+BF23)/AD23) -> 0 | BU23: =IF(BJ23=0,0,BJ23/AD23) -> 0 | BV23: =SUM(BO23:BU23) -> 0.99753195 | BW23: =AD23/$AD$41 -> 0.043569991
A24: ='LUCERO RECOLETA'!A24 -> 46158 | C24: 23 | D24: =E23+1 -> 736 | E24: =IF(C24="","",C24+D24-1) -> 758 | H24: 2094738.7 | I24: 439895.13 | K24: =H24+I24+J24 -> 2534633.8 | O24: =N24*21% -> 0 | Q24: =N24+O24+P24 -> 0 | U24: =T24*21% -> 0 | W24: =T24+U24+V24 -> 0 | X24: 19 | Y24: 19 | Z24: 132223.14 | AA24: 27766.86 | AC24: =Z24+AA24+AB24 -> 159990 | AD24: =+K24+Q24+W24-AC24 -> 2374643.8 | AJ24: =AI24*220 -> 0 | AL24: =AK24*1200 -> 0 | AN24: =AM24*1200 -> 0 | AO24: =AF24+AG24+AH24+AJ24+AL24+AN24 -> 0 | AP24: =SUM(AO24-BK24) -> -2375910 | AQ24: =30000+250000+200000+200000+100000+45000 -> 825000 | AT24: 1381710 | AZ24: =AY24*AZ$3 -> 0 | BA24: 60 | BB24: =BA24*1410 -> 84600 | BC24: 60 | BD24: =BC24*1410 -> 84600 | BF24: =BE24*BF$2 -> 0 | BH24: =BG24*BH$2 -> 0 | BJ24: =BI24*BJ$2 -> 0 | BK24: =+AQ24+AR24+AT24+AW24+AX24+AZ24+BB24+BD24+BF24+BH24+BJ24 -> 2375910 | BL24: =AD24 -> 2374643.8 | BM24: =SUM(BK24-BL24) -> 1266.2 | BO24: =IF(AQ24+AR24=0,0,(AQ24+AR24)/AD24) -> 0.34742053 | BP24: =IF(AU24=0,0,AU24/AD24) -> 0 | BQ24: =IF(AT24=0,0,AT24/AD24) -> 0.5818599 | BR24: =IF(AW24=0,0,AW24/AD24) -> 0 | BS24: =IF(AZ24=0,0,AZ24/AD24) -> 0 | BT24: =IF(BB24+BD24+BF24=0,0,(BB24+BD24+BF24)/AD24) -> 0.071252792 | BU24: =IF(BJ24=0,0,BJ24/AD24) -> 0 | BV24: =SUM(BO24:BU24) -> 1.0005332 | BW24: =AD24/$AD$41 -> 0.051275509
A25: ='LUCERO RECOLETA'!A25 -> 46159 | C25: 5 | D25: =E24+1 -> 759 | E25: =IF(C25="","",C25+D25-1) -> 763 | H25: 703247.94 | I25: 147682.06 | K25: =H25+I25+J25 -> 850930 | O25: =N25*21% -> 0 | Q25: =N25+O25+P25 -> 0 | U25: =T25*21% -> 0 | W25: =T25+U25+V25 -> 0 | AA25: =Z25*21% -> 0 | AC25: =Z25+AA25+AB25 -> 0 | AD25: =+K25+Q25+W25-AC25 -> 850930 | AJ25: =AI25*220 -> 0 | AL25: =AK25*1200 -> 0 | AN25: =AM25*1200 -> 0 | AO25: =AF25+AG25+AH25+AJ25+AL25+AN25 -> 0 | AP25: =SUM(AO25-BK25) -> -853350 | AQ25: 20000 | AT25: 494950 | AZ25: =AY25*AZ$3 -> 0 | BA25: 240 | BB25: =BA25*1410 -> 338400 | BD25: =BC25*BD$2 -> 0 | BF25: =BE25*BF$2 -> 0 | BH25: =BG25*BH$2 -> 0 | BJ25: =BI25*BJ$2 -> 0 | BK25: =+AQ25+AR25+AT25+AW25+AX25+AZ25+BB25+BD25+BF25+BH25+BJ25 -> 853350 | BL25: =AD25 -> 850930 | BM25: =SUM(BK25-BL25) -> 2420 | BO25: =IF(AQ25+AR25=0,0,(AQ25+AR25)/AD25) -> 0.023503696 | BP25: =IF(AU25=0,0,AU25/AD25) -> 0 | BQ25: =IF(AT25=0,0,AT25/AD25) -> 0.58165772 | BR25: =IF(AW25=0,0,AW25/AD25) -> 0 | BS25: =IF(AZ25=0,0,AZ25/AD25) -> 0 | BT25: =IF(BB25+BD25+BF25=0,0,(BB25+BD25+BF25)/AD25) -> 0.39768254 | BU25: =IF(BJ25=0,0,BJ25/AD25) -> 0 | BV25: =SUM(BO25:BU25) -> 1.0028439 | BW25: =AD25/$AD$41 -> 0.018374069
A26: ='LUCERO RECOLETA'!A26 -> 46160 | C26: 11 | D26: =E25+1 -> 764 | E26: =IF(C26="","",C26+D26-1) -> 774 | H26: 690785.11 | I26: 145064.89 | K26: =H26+I26+J26 -> 835850 | O26: =N26*21% -> 0 | Q26: =N26+O26+P26 -> 0 | U26: =T26*21% -> 0 | W26: =T26+U26+V26 -> 0 | AA26: =Z26*21% -> 0 | AC26: =Z26+AA26+AB26 -> 0 | AD26: =+K26+Q26+W26-AC26 -> 835850 | AJ26: =AI26*220 -> 0 | AL26: =AK26*1200 -> 0 | AN26: =AM26*1200 -> 0 | AO26: =AF26+AG26+AH26+AJ26+AL26+AN26 -> 0 | AP26: =SUM(AO26-BK26) -> -832900 | AQ26: =170000+50000+200000 -> 420000 | AT26: 412900 | AZ26: =AY26*AZ$3 -> 0 | BB26: =BA26*1395 -> 0 | BD26: =BC26*1415 -> 0 | BF26: =BE26*BF$2 -> 0 | BH26: =BG26*BH$2 -> 0 | BJ26: =BI26*BJ$2 -> 0 | BK26: =+AQ26+AR26+AT26+AW26+AX26+AZ26+BB26+BD26+BF26+BH26+BJ26 -> 832900 | BL26: =AD26 -> 835850 | BM26: =SUM(BK26-BL26) -> -2950 | BO26: =IF(AQ26+AR26=0,0,(AQ26+AR26)/AD26) -> 0.5024825 | BP26: =IF(AU26=0,0,AU26/AD26) -> 0 | BQ26: =IF(AT26=0,0,AT26/AD26) -> 0.49398816 | BR26: =IF(AW26=0,0,AW26/AD26) -> 0 | BS26: =IF(AZ26=0,0,AZ26/AD26) -> 0 | BT26: =IF(BB26+BD26+BF26=0,0,(BB26+BD26+BF26)/AD26) -> 0 | BU26: =IF(BJ26=0,0,BJ26/AD26) -> 0 | BV26: =SUM(BO26:BU26) -> 0.99647066 | BW26: =AD26/$AD$41 -> 0.018048448
A27: ='LUCERO RECOLETA'!A27 -> 46161 | C27: 7 | D27: =E26+1 -> 775 | E27: =IF(C27="","",C27+D27-1) -> 781 | H27: 651900.82 | I27: 136899.18 | K27: =H27+I27+J27 -> 788800 | O27: =N27*21% -> 0 | Q27: =N27+O27+P27 -> 0 | R27: 11 | S27: 11 | T27: 201619.84 | U27: 42340.16 | W27: =T27+U27+V27 -> 243960 | AA27: =Z27*21% -> 0 | AC27: =Z27+AA27+AB27 -> 0 | AD27: =+K27+Q27+W27-AC27 -> 1032760 | AJ27: =AI27*220 -> 0 | AL27: =AK27*1200 -> 0 | AN27: =AM27*1200 -> 0 | AO27: =AF27+AG27+AH27+AJ27+AL27+AN27 -> 0 | AP27: =SUM(AO27-BK27) -> -1031760 | AQ27: =35000 -> 35000 | AT27: 996760 | AZ27: =AY27*AZ$3 -> 0 | BB27: =BA27*1420 -> 0 | BD27: =BC27*BD$2 -> 0 | BF27: =BE27*BF$2 -> 0 | BH27: =BG27*BH$2 -> 0 | BJ27: =BI27*BJ$2 -> 0 | BK27: =+AQ27+AR27+AT27+AW27+AX27+AZ27+BB27+BD27+BF27+BH27+BJ27 -> 1031760 | BL27: =AD27 -> 1032760 | BM27: =SUM(BK27-BL27) -> -1000 | BO27: =IF(AQ27+AR27=0,0,(AQ27+AR27)/AD27) -> 0.033889771 | BP27: =IF(AU27=0,0,AU27/AD27) -> 0 | BQ27: =IF(AT27=0,0,AT27/AD27) -> 0.96514195 | BR27: =IF(AW27=0,0,AW27/AD27) -> 0 | BS27: =IF(AZ27=0,0,AZ27/AD27) -> 0 | BT27: =IF(BB27+BD27+BF27=0,0,(BB27+BD27+BF27)/AD27) -> 0 | BU27: =IF(BJ27=0,0,BJ27/AD27) -> 0 | BV27: =SUM(BO27:BU27) -> 0.99903172 | BW27: =AD27/$AD$41 -> 0.022300311
A28: ='LUCERO RECOLETA'!A28 -> 46162 | C28: 8 | D28: =E27+1 -> 782 | E28: =IF(C28="","",C28+D28-1) -> 789 | H28: 473413.21 | I28: 99416.79 | K28: =H28+I28+J28 -> 572830 | O28: =N28*21% -> 0 | Q28: =N28+O28+P28 -> 0 | U28: =T28*21% -> 0 | W28: =T28+U28+V28 -> 0 | X28: 20 | Y28: 20 | Z28: 99157.03 | AA28: 20822.97 | AC28: =Z28+AA28+AB28 -> 119980 | AD28: =+K28+Q28+W28-AC28 -> 452850 | AJ28: =AI28*220 -> 0 | AL28: =AK28*1200 -> 0 | AN28: =AM28*1200 -> 0 | AO28: =AF28+AG28+AH28+AJ28+AL28+AN28 -> 0 | AP28: =SUM(AO28-BK28) -> -452870 | AQ28: 80000 | AT28: 372870 | AZ28: =AY28*AZ$3 -> 0 | BB28: =BA28*1415 -> 0 | BD28: =BC28*BD$2 -> 0 | BF28: =BE28*1480 -> 0 | BH28: =BG28*BH$2 -> 0 | BJ28: =BI28*BJ$2 -> 0 | BK28: =+AQ28+AR28+AT28+AW28+AX28+AZ28+BB28+BD28+BF28+BH28+BJ28 -> 452870 | BL28: =AD28 -> 452850 | BM28: =SUM(BK28-BL28) -> 20 | BO28: =IF(AQ28+AR28=0,0,(AQ28+AR28)/AD28) -> 0.17665894 | BP28: =IF(AU28=0,0,AU28/AD28) -> 0 | BQ28: =IF(AT28=0,0,AT28/AD28) -> 0.82338523 | BR28: =IF(AW28=0,0,AW28/AD28) -> 0 | BS28: =IF(AZ28=0,0,AZ28/AD28) -> 0 | BT28: =IF(BB28+BD28+BF28=0,0,(BB28+BD28+BF28)/AD28) -> 0 | BU28: =IF(BJ28=0,0,BJ28/AD28) -> 0 | BV28: =SUM(BO28:BU28) -> 1.0000442 | BW28: =AD28/$AD$41 -> 0.0097783567
A29: ='LUCERO RECOLETA'!A29 -> 46163 | C29: 20 | D29: =E28+1 -> 790 | E29: =IF(C29="","",C29+D29-1) -> 809 | H29: 2064192.5 | I29: 433480.46 | K29: =H29+I29+J29 -> 2497673 | O29: =N29*21% -> 0 | Q29: =N29+O29+P29 -> 0 | U29: =T29*21% -> 0 | W29: =T29+U29+V29 -> 0 | X29: 21 | Y29: 21 | Z29: 165280.99 | AA29: 34709.01 | AC29: =Z29+AA29+AB29 -> 199990 | AD29: =+K29+Q29+W29-AC29 -> 2297683 | AJ29: =AI29*220 -> 0 | AL29: =AK29*1200 -> 0 | AN29: =AM29*1200 -> 0 | AO29: =AF29+AG29+AH29+AJ29+AL29+AN29 -> 0 | AP29: =SUM(AO29-BK29) -> -2300773 | AQ29: =220000+15000+30000+40000 -> 305000 | AT29: 1825373 | AZ29: =AY29*AZ$3 -> 0 | BA29: 20 | BB29: =BA29*1420 -> 28400 | BC29: 100 | BD29: =BC29*1420 -> 142000 | BF29: =BE29*1460 -> 0 | BH29: =BG29*BH$3 -> 0 | BJ29: =BI29*BJ$3 -> 0 | BK29: =+AQ29+AR29+AT29+AW29+AX29+AZ29+BB29+BD29+BF29+BH29+BJ29 -> 2300773 | BL29: =AD29 -> 2297683 | BM29: =SUM(BK29-BL29) -> 3090 | BO29: =IF(AQ29+AR29=0,0,(AQ29+AR29)/AD29) -> 0.13274242 | BP29: =IF(AU29=0,0,AU29/AD29) -> 0 | BQ29: =IF(AT29=0,0,AT29/AD29) -> 0.79444075 | BR29: =IF(AW29=0,0,AW29/AD29) -> 0 | BS29: =IF(AZ29=0,0,AZ29/AD29) -> 0 | BT29: =IF(BB29+BD29+BF29=0,0,(BB29+BD29+BF29)/AD29) -> 0.074161666 | BU29: =IF(BJ29=0,0,BJ29/AD29) -> 0 | BV29: =SUM(BO29:BU29) -> 1.0013448 | BW29: =AD29/$AD$41 -> 0.0496137
A30: ='LUCERO RECOLETA'!A30 -> 46164 | C30: 16 | D30: =E29+1 -> 810 | E30: =IF(C30="","",C30+D30-1) -> 825 | H30: 1777021.5 | I30: 373174.54 | K30: =H30+I30+J30 -> 2150196 | O30: =N30*21% -> 0 | Q30: =N30+O30+P30 -> 0 | U30: =T30*21% -> 0 | W30: =T30+U30+V30 -> 0 | AA30: =Z30*21% -> 0 | AC30: =Z30+AA30+AB30 -> 0 | AD30: =+K30+Q30+W30-AC30 -> 2150196 | AJ30: =AI30*220 -> 0 | AL30: =AK30*1200 -> 0 | AN30: =AM30*1200 -> 0 | AO30: =AF30+AG30+AH30+AJ30+AL30+AN30 -> 0 | AP30: =SUM(AO30-BK30) -> -2148673 | AQ30: =100000+270000 -> 370000 | AT30: 1437673 | AY30: 100 | AZ30: =AY30*286 -> 28600 | BA30: 220 | BB30: =BA30*1420 -> 312400 | BD30: =BC30*BD$3 -> 0 | BF30: =BE30*1460 -> 0 | BH30: =BG30*BH$3 -> 0 | BJ30: =BI30*BJ$3 -> 0 | BK30: =+AQ30+AR30+AT30+AW30+AX30+AZ30+BB30+BD30+BF30+BH30+BJ30 -> 2148673 | BL30: =AD30 -> 2150196 | BM30: =SUM(BK30-BL30) -> -1523 | BO30: =IF(AQ30+AR30=0,0,(AQ30+AR30)/AD30) -> 0.17207734 | BP30: =IF(AU30=0,0,AU30/AD30) -> 0 | BQ30: =IF(AT30=0,0,AT30/AD30) -> 0.66862416 | BR30: =IF(AW30=0,0,AW30/AD30) -> 0 | BS30: =IF(AZ30=0,0,AZ30/AD30) -> 0.013301113 | BT30: =IF(BB30+BD30+BF30=0,0,(BB30+BD30+BF30)/AD30) -> 0.14528908 | BU30: =IF(BJ30=0,0,BJ30/AD30) -> 0 | BV30: =SUM(BO30:BU30) -> 0.99929169 | BW30: =AD30/$AD$41 -> 0.046429024
A31: ='LUCERO RECOLETA'!A31 -> 46165 | C31: 12 | D31: =E30+1 -> 826 | E31: =IF(C31="","",C31+D31-1) -> 837 | H31: 818900.8 | I31: 171969.2 | K31: =H31+I31+J31 -> 990870 | O31: =N31*21% -> 0 | Q31: =N31+O31+P31 -> 0 | U31: =T31*21% -> 0 | W31: =T31+U31+V31 -> 0 | AA31: =Z31*21% -> 0 | AC31: =Z31+AA31+AB31 -> 0 | AD31: =+K31+Q31+W31-AC31 -> 990870 | AJ31: =AI31*220 -> 0 | AL31: =AK31*1200 -> 0 | AN31: =AM31*1200 -> 0 | AO31: =AF31+AG31+AH31+AJ31+AL31+AN31 -> 0 | AP31: =SUM(AO31-BK31) -> -987890 | AQ31: =20000 -> 20000 | AT31: 880890 | AY31: 300 | AZ31: =AY31*290 -> 87000 | BB31: =BA31*1410 -> 0 | BD31: =BC31*BD$3 -> 0 | BF31: =BE31*1460 -> 0 | BH31: =BG31*BH$3 -> 0 | BJ31: =BI31*1670 -> 0 | BK31: =+AQ31+AR31+AT31+AW31+AX31+AZ31+BB31+BD31+BF31+BH31+BJ31 -> 987890 | BL31: =AD31 -> 990870 | BM31: =SUM(BK31-BL31) -> -2980 | BO31: =IF(AQ31+AR31=0,0,(AQ31+AR31)/AD31) -> 0.020184283 | BP31: =IF(AU31=0,0,AU31/AD31) -> 0 | BQ31: =IF(AT31=0,0,AT31/AD31) -> 0.88900663 | BR31: =IF(AW31=0,0,AW31/AD31) -> 0 | BS31: =IF(AZ31=0,0,AZ31/AD31) -> 0.087801629 | BT31: =IF(BB31+BD31+BF31=0,0,(BB31+BD31+BF31)/AD31) -> 0 | BU31: =IF(BJ31=0,0,BJ31/AD31) -> 0 | BV31: =SUM(BO31:BU31) -> 0.99699254 | BW31: =AD31/$AD$41 -> 0.021395783
A32: ='LUCERO RECOLETA'!A32 -> 46166 | C32: 30 | D32: =E31+1 -> 838 | E32: =IF(C32="","",C32+D32-1) -> 867 | H32: 3311254.5 | I32: 695363.44 | K32: =H32+I32+J32 -> 4006617.9 | O32: =N32*21% -> 0 | Q32: =N32+O32+P32 -> 0 | U32: =T32*21% -> 0 | W32: =T32+U32+V32 -> 0 | AA32: =Z32*21% -> 0 | AC32: =Z32+AA32+AB32 -> 0 | AD32: =+K32+Q32+W32-AC32 -> 4006617.9 | AJ32: =AI32*220 -> 0 | AL32: =AK32*1200 -> 0 | AN32: =AM32*1200 -> 0 | AO32: =AF32+AG32+AH32+AJ32+AL32+AN32 -> 0 | AP32: =SUM(AO32-BK32) -> -4016340 | AQ32: =35000 -> 35000 | AT32: 3576640 | AZ32: =AY32*AZ$3 -> 0 | BA32: 285 | BB32: =BA32*1420 -> 404700 | BD32: =BC32*1410 -> 0 | BF32: =BE32*BF$3 -> 0 | BH32: =BG32*BH$3 -> 0 | BJ32: =BI32*BJ$3 -> 0 | BK32: =+AQ32+AR32+AT32+AW32+AX32+AZ32+BB32+BD32+BF32+BH32+BJ32 -> 4016340 | BL32: =AD32 -> 4006617.9 | BM32: =SUM(BK32-BL32) -> 9722.1 | BO32: =IF(AQ32+AR32=0,0,(AQ32+AR32)/AD32) -> 0.0087355473 | BP32: =IF(AU32=0,0,AU32/AD32) -> 0 | BQ32: =IF(AT32=0,0,AT32/AD32) -> 0.89268308 | BR32: =IF(AW32=0,0,AW32/AD32) -> 0 | BS32: =IF(AZ32=0,0,AZ32/AD32) -> 0 | BT32: =IF(BB32+BD32+BF32=0,0,(BB32+BD32+BF32)/AD32) -> 0.10100789 | BU32: =IF(BJ32=0,0,BJ32/AD32) -> 0 | BV32: =SUM(BO32:BU32) -> 1.0024265 | BW32: =AD32/$AD$41 -> 0.086514606
A33: ='LUCERO RECOLETA'!A33 -> 46167 | C33: 12 | D33: =E32+1 -> 868 | E33: =IF(C33="","",C33+D33-1) -> 879 | H33: 1053565.2 | I33: 221248.69 | K33: =H33+I33+J33 -> 1274813.9 | O33: =N33*21% -> 0 | Q33: =N33+O33+P33 -> 0 | U33: =T33*21% -> 0 | W33: =T33+U33+V33 -> 0 | AA33: =Z33*21% -> 0 | AC33: =Z33+AA33+AB33 -> 0 | AD33: =+K33+Q33+W33-AC33 -> 1274813.9 | AJ33: =AI33*220 -> 0 | AL33: =AK33*1200 -> 0 | AN33: =AM33*1200 -> 0 | AO33: =AF33+AG33+AH33+AJ33+AL33+AN33 -> 0 | AP33: =SUM(AO33-BK33) -> -1274810 | AQ33: =160000 -> 160000 | AT33: 1114810 | AZ33: =AY33*276 -> 0 | BB33: =BA33*1395 -> 0 | BD33: =BC33*1395 -> 0 | BF33: =BE33*BF$3 -> 0 | BH33: =BG33*BH$3 -> 0 | BJ33: =BI33*BJ$3 -> 0 | BK33: =+AQ33+AR33+AT33+AW33+AX33+AZ33+BB33+BD33+BF33+BH33+BJ33 -> 1274810 | BL33: =AD33 -> 1274813.9 | BM33: =SUM(BK33-BL33) -> -3.9 | BO33: =IF(AQ33+AR33=0,0,(AQ33+AR33)/AD33) -> 0.12550852 | BP33: =IF(AU33=0,0,AU33/AD33) -> 0 | BQ33: =IF(AT33=0,0,AT33/AD33) -> 0.87448843 | BR33: =IF(AW33=0,0,AW33/AD33) -> 0 | BS33: =IF(AZ33=0,0,AZ33/AD33) -> 0 | BT33: =IF(BB33+BD33+BF33=0,0,(BB33+BD33+BF33)/AD33) -> 0 | BU33: =IF(BJ33=0,0,BJ33/AD33) -> 0 | BV33: =SUM(BO33:BU33) -> 0.99999694 | BW33: =AD33/$AD$41 -> 0.027526963
A34: ='LUCERO RECOLETA'!A34 -> 46168 | C34: 9 | D34: =E33+1 -> 880 | E34: =IF(C34="","",C34+D34-1) -> 888 | H34: 1493190.1 | I34: 313569.92 | K34: =H34+I34+J34 -> 1806760 | O34: =N34*21% -> 0 | Q34: =N34+O34+P34 -> 0 | U34: =T34*21% -> 0 | W34: =T34+U34+V34 -> 0 | AA34: =Z34*21% -> 0 | AC34: =Z34+AA34+AB34 -> 0 | AD34: =+K34+Q34+W34-AC34 -> 1806760 | AJ34: =AI34*220 -> 0 | AL34: =AK34*1200 -> 0 | AN34: =AM34*1200 -> 0 | AO34: =AF34+AG34+AH34+AJ34+AL34+AN34 -> 0 | AP34: =SUM(AO34-BK34) -> -1801770 | AQ34: 10000 | AT34: 1791770 | AW34: 0 | AZ34: =AY34*AZ$3 -> 0 | BB34: =BA34*1410 -> 0 | BD34: =BC34*BD$3 -> 0 | BF34: =BE34*1420 -> 0 | BH34: =BG34*BH$3 -> 0 | BJ34: =BI34*BJ$3 -> 0 | BK34: =+AQ34+AR34+AT34+AW34+AX34+AZ34+BB34+BD34+BF34+BH34+BJ34 -> 1801770 | BL34: =AD34 -> 1806760 | BM34: =SUM(BK34-BL34) -> -4990 | BO34: =IF(AQ34+AR34=0,0,(AQ34+AR34)/AD34) -> 0.0055347694 | BP34: =IF(AU34=0,0,AU34/AD34) -> 0 | BQ34: =IF(AT34=0,0,AT34/AD34) -> 0.99170338 | BR34: =IF(AW34=0,0,AW34/AD34) -> 0 | BS34: =IF(AZ34=0,0,AZ34/AD34) -> 0 | BT34: =IF(BB34+BD34+BF34=0,0,(BB34+BD34+BF34)/AD34) -> 0 | BU34: =IF(BJ34=0,0,BJ34/AD34) -> 0 | BV34: =SUM(BO34:BU34) -> 0.99723815 | BW34: =AD34/$AD$41 -> 0.039013236
A35: ='LUCERO RECOLETA'!A35 -> 46169 | C35: 3 | D35: =E34+1 -> 889 | E35: =IF(C35="","",C35+D35-1) -> 891 | H35: 295834.71 | I35: 62125.29 | K35: =H35+I35+J35 -> 357960 | O35: =N35*21% -> 0 | Q35: =N35+O35+P35 -> 0 | U35: =T35*21% -> 0 | W35: =T35+U35+V35 -> 0 | AA35: =Z35*21% -> 0 | AC35: =Z35+AA35+AB35 -> 0 | AD35: =+K35+Q35+W35-AC35 -> 357960 | AJ35: =AI35*220 -> 0 | AL35: =AK35*1200 -> 0 | AN35: =AM35*1200 -> 0 | AO35: =AF35+AG35+AH35+AJ35+AL35+AN35 -> 0 | AP35: =SUM(AO35-BK35) -> -359980 | AQ35: 30000 | AT35: 329980 | AW35: 0 | AZ35: =AY35*AZ$3 -> 0 | BB35: =BA35*1460 -> 0 | BD35: =BC35*BD$3 -> 0 | BF35: =BE35*BF$3 -> 0 | BH35: =BG35*BH$3 -> 0 | BJ35: =BI35*BJ$3 -> 0 | BK35: =+AQ35+AR35+AT35+AW35+AX35+AZ35+BB35+BD35+BF35+BH35+BJ35 -> 359980 | BL35: =AD35 -> 357960 | BM35: =SUM(BK35-BL35) -> 2020 | BO35: =IF(AQ35+AR35=0,0,(AQ35+AR35)/AD35) -> 0.083808247 | BP35: =IF(AU35=0,0,AU35/AD35) -> 0 | BQ35: =IF(AT35=0,0,AT35/AD35) -> 0.92183484 | BR35: =IF(AW35=0,0,AW35/AD35) -> 0 | BS35: =IF(AZ35=0,0,AZ35/AD35) -> 0 | BT35: =IF(BB35+BD35+BF35=0,0,(BB35+BD35+BF35)/AD35) -> 0 | BU35: =IF(BJ35=0,0,BJ35/AD35) -> 0 | BV35: =SUM(BO35:BU35) -> 1.0056431 | BW35: =AD35/$AD$41 -> 0.007729404
A36: ='LUCERO RECOLETA'!A36 -> 46170 | C36: 15 | D36: =E35+1 -> 892 | E36: =IF(C36="","",C36+D36-1) -> 906 | H36: 1541115.7 | I36: 323634.3 | K36: =H36+I36+J36 -> 1864750 | O36: =N36*21% -> 0 | Q36: =N36+O36+P36 -> 0 | U36: =T36*21% -> 0 | W36: =T36+U36+V36 -> 0 | AA36: =Z36*21% -> 0 | AC36: =Z36+AA36+AB36 -> 0 | AD36: =+K36+Q36+W36-AC36 -> 1864750 | AJ36: =AI36*220 -> 0 | AL36: =AK36*1200 -> 0 | AN36: =AM36*1200 -> 0 | AO36: =AF36+AG36+AH36+AJ36+AL36+AN36 -> 0 | AP36: =SUM(AO36-BK36) -> -1864750 | AQ36: 0 | AT36: 1494250 | AW36: 0 | AZ36: =AY36*AZ$3 -> 0 | BA36: 260 | BB36: =BA36*1425 -> 370500 | BD36: =BC36*BD$3 -> 0 | BF36: =BE36*BF$3 -> 0 | BH36: =BG36*BH$3 -> 0 | BJ36: =BI36*BJ$3 -> 0 | BK36: =+AQ36+AR36+AT36+AW36+AX36+AZ36+BB36+BD36+BF36+BH36+BJ36 -> 1864750 | BL36: =AD36 -> 1864750 | BM36: =SUM(BK36-BL36) -> 0 | BO36: =IF(AQ36+AR36=0,0,(AQ36+AR36)/AD36) -> 0 | BP36: =IF(AU36=0,0,AU36/AD36) -> 0 | BQ36: =IF(AT36=0,0,AT36/AD36) -> 0.80131385 | BR36: =IF(AW36=0,0,AW36/AD36) -> 0 | BS36: =IF(AZ36=0,0,AZ36/AD36) -> 0 | BT36: =IF(BB36+BD36+BF36=0,0,(BB36+BD36+BF36)/AD36) -> 0.19868615 | BU36: =IF(BJ36=0,0,BJ36/AD36) -> 0 | BV36: =SUM(BO36:BU36) -> 1 | BW36: =AD36/$AD$41 -> 0.04026541
A37: ='LUCERO RECOLETA'!A37 -> 46171 | C37: 13 | D37: =E36+1 -> 907 | E37: =IF(C37="","",C37+D37-1) -> 919 | H37: 1479181.8 | I37: 310628.21 | K37: =H37+I37+J37 -> 1789810 | O37: =N37*21% -> 0 | Q37: =N37+O37+P37 -> 0 | U37: =T37*21% -> 0 | W37: =T37+U37+V37 -> 0 | X37: 22 | Y37: 22 | Z37: 82636.36 | AA37: 17353.64 | AC37: =Z37+AA37+AB37 -> 99990 | AD37: =+K37+Q37+W37-AC37 -> 1689820 | AJ37: =AI37*220 -> 0 | AL37: =AK37*1200 -> 0 | AN37: =AM37*1200 -> 0 | AO37: =AF37+AG37+AH37+AJ37+AL37+AN37 -> 0 | AP37: =SUM(AO37-BK37) -> -1699840 | AQ37: =150000+40000+60000 -> 250000 | AT37: 1449840 | AW37: 0 | AZ37: =AY37*AZ$3 -> 0 | BB37: =BA37*1400 -> 0 | BD37: =BC37*1430 -> 0 | BF37: =BE37*1430 -> 0 | BH37: =BG37*BH$3 -> 0 | BJ37: =BI37*BJ$3 -> 0 | BK37: =+AQ37+AR37+AT37+AW37+AX37+AZ37+BB37+BD37+BF37+BH37+BJ37 -> 1699840 | BL37: =AD37 -> 1689820 | BM37: =SUM(BK37-BL37) -> 10020 | BO37: =IF(AQ37+AR37=0,0,(AQ37+AR37)/AD37) -> 0.14794475 | BP37: =IF(AU37=0,0,AU37/AD37) -> 0 | BQ37: =IF(AT37=0,0,AT37/AD37) -> 0.85798487 | BR37: =IF(AW37=0,0,AW37/AD37) -> 0 | BS37: =IF(AZ37=0,0,AZ37/AD37) -> 0 | BT37: =IF(BB37+BD37+BF37=0,0,(BB37+BD37+BF37)/AD37) -> 0 | BU37: =IF(BJ37=0,0,BJ37/AD37) -> 0 | BV37: =SUM(BO37:BU37) -> 1.0059296 | BW37: =AD37/$AD$41 -> 0.036488159
A38: ='LUCERO RECOLETA'!A38 -> 46172 | C38: 5 | D38: =E37+1 -> 920 | E38: =IF(C38="","",C38+D38-1) -> 924 | H38: 690834.71 | I38: 145075.29 | K38: =H38+I38+J38 -> 835910 | O38: =N38*21% -> 0 | Q38: =N38+O38+P38 -> 0 | U38: =T38*21% -> 0 | W38: =T38+U38+V38 -> 0 | AA38: =Z38*21% -> 0 | AC38: =Z38+AA38+AB38 -> 0 | AD38: =+K38+Q38+W38-AC38 -> 835910 | AJ38: =AI38*220 -> 0 | AL38: =AK38*1200 -> 0 | AN38: =AM38*1200 -> 0 | AO38: =AF38+AG38+AH38+AJ38+AL38+AN38 -> 0 | AP38: =SUM(AO38-BK38) -> -835910 | AQ38: 0 | AT38: 835910 | AZ38: =AY38*AZ$3 -> 0 | BB38: =BA38*1415 -> 0 | BD38: =BC38*1460 -> 0 | BF38: =BE38*1415 -> 0 | BH38: =BG38*BH$3 -> 0 | BJ38: =BI38*BJ$3 -> 0 | BK38: =+AQ38+AR38+AT38+AW38+AX38+AZ38+BB38+BD38+BF38+BH38+BJ38 -> 835910 | BL38: =AD38 -> 835910 | BM38: =SUM(BK38-BL38) -> 0 | BO38: =IF(AQ38+AR38=0,0,(AQ38+AR38)/AD38) -> 0 | BP38: =IF(AU38=0,0,AU38/AD38) -> 0 | BQ38: =IF(AT38=0,0,AT38/AD38) -> 1 | BR38: =IF(AW38=0,0,AW38/AD38) -> 0 | BS38: =IF(AZ38=0,0,AZ38/AD38) -> 0 | BT38: =IF(BB38+BD38+BF38=0,0,(BB38+BD38+BF38)/AD38) -> 0 | BU38: =IF(BJ38=0,0,BJ38/AD38) -> 0 | BV38: =SUM(BO38:BU38) -> 1 | BW38: =AD38/$AD$41 -> 0.018049743
A39: ='LUCERO RECOLETA'!A39 -> 46173 | C39: 7 | D39: =E38+1 -> 925 | E39: =IF(C39="","",C39+D39-1) -> 931 | H39: 618917.36 | I39: 129972.64 | K39: =H39+I39+J39 -> 748890 | O39: =N39*21% -> 0 | Q39: =N39+O39+P39 -> 0 | U39: =T39*21% -> 0 | W39: =T39+U39+V39 -> 0 | AA39: =Z39*21% -> 0 | AC39: =Z39+AA39+AB39 -> 0 | AD39: =+K39+Q39+W39-AC39 -> 748890 | AJ39: =AI39*220 -> 0 | AL39: =AK39*1200 -> 0 | AN39: =AM39*1200 -> 0 | AQ39: 0 | AT39: 748890 | AZ39: =AY39*283 -> 0 | BB39: =BA39*BB$3 -> 0 | BD39: =BC39*BD$3 -> 0 | BF39: =BE39*BF$3 -> 0 | BH39: =BG39*BH$3 -> 0 | BJ39: =BI39*BJ$3 -> 0 | BK39: =+AQ39+AR39+AT39+AW39+AX39+AZ39+BB39+BD39+BF39+BH39+BJ39 -> 748890 | BL39: =AD39 -> 748890 | BM39: =SUM(BK39-BL39) -> 0 | BO39: =IF(AQ39+AR39=0,0,(AQ39+AR39)/AD39) -> 0 | BP39: =IF(AU39=0,0,AU39/AD39) -> 0 | BQ39: =IF(AT39=0,0,AT39/AD39) -> 1 | BR39: =IF(AW39=0,0,AW39/AD39) -> 0 | BS39: =IF(AZ39=0,0,AZ39/AD39) -> 0 | BT39: =IF(BB39+BD39+BF39=0,0,(BB39+BD39+BF39)/AD39) -> 0 | BU39: =IF(BJ39=0,0,BJ39/AD39) -> 0 | BV39: =SUM(BO39:BU39) -> 1 | BW39: =AD39/$AD$41 -> 0.016170727
E40: =IF(C40="","",C40+D40-1) | I40: =H40*21% -> 0 | K40: =H40+I40+J40 -> 0 | O40: =N40*21% -> 0 | U40: =T40*21% -> 0 | AA40: =Z40*21% -> 0 | AZ40: =AY40*AZ$3 -> 0 | BB40: =BA40*BB$3 -> 0 | BD40: =BC40*BD$3 -> 0 | BF40: =BE40*BF$3 -> 0 | BH40: =BG40*BH$3 -> 0 | BJ40: =BI40*BJ$3 -> 0 | BK40: =+AQ40+AR40+AT40+AW40+AX40+AZ40+BB40+BD40+BF40+BH40+BJ40 -> 0 | BM40: =SUM(BK40-BL40) -> 0 | BO40: =IF(AQ40+AR40=0,0,(AQ40+AR40)/AD40) -> 0 | BP40: =IF(AU40=0,0,AU40/AD40) -> 0 | BQ40: =IF(AT40=0,0,AT40/AD40) -> 0 | BR40: =IF(AW40=0,0,AW40/AD40) -> 0 | BS40: =IF(AZ40=0,0,AZ40/AD40) -> 0 | BT40: =IF(BB40+BD40+BF40=0,0,(BB40+BD40+BF40)/AD40) -> 0 | BU40: =IF(BJ40=0,0,BJ40/AD40) -> 0 | BV40: =SUM(BO40:BU40) -> 0 | BW40: =AD40/$AD$41 -> 0
A41: TOTALES | B41: =MAX(B9:B40) -> 0 | C41: =SUM(C9:C40) -> 389 | D41: =MIN(D9:D40) -> 543 | E41: =MAX(E9:E40) -> 931 | F41: =SUM(F9:F40) -> 0 | G41: =SUM(G9:G40) -> 0 | H41: =SUM(H9:H40) -> 38510283 | I41: =SUM(I9:I40) -> 8087159.7 | J41: =SUM(J9:J40) -> 0 | K41: =SUM(K9:K40) -> 46597442 | L41: =MIN(L9:L40) -> 0 | M41: =MAX(M9:M40) -> 0 | N41: =SUM(N9:N40) -> 0 | O41: =SUM(O9:O40) -> 0 | Q41: =SUM(Q9:Q40) -> 0 | R41: =MIN(R9:R40) -> 10 | S41: =MAX(S9:S40) -> 11 | T41: =SUM(T9:T40) -> 449545.46 | U41: =SUM(U9:U40) -> 94404.54 | W41: =SUM(W9:W40) -> 543950 | X41: =MIN(X9:X40) -> 17 | Y41: =MAX(Y9:Y40) -> 22 | Z41: =SUM(Z9:Z40) -> 685892.56 | AA41: =SUM(AA9:AA40) -> 144037.44 | AC41: =SUM(AC9:AC40) -> 829930 | AD41: =SUM(AD9:AD40) -> 46311462 | AE41: =SUM(AE9:AE38) -> 0 | AF41: =SUM(AF9:AF38) -> 0 | AG41: =SUM(AG9:AG38) -> 0 | AH41: =SUM(AH9:AH38) -> 0 | AI41: =SUM(AI9:AI38) -> 0 | AJ41: =SUM(AJ9:AJ38) -> 0 | AK41: =SUM(AK9:AK38) -> 0 | AL41: =SUM(AL9:AL38) -> 0 | ... AP41: =SUM(AP9:AP38) -> -45665836 | AQ41: =SUM(AQ9:AQ40) -> 4084000 | AR41: =SUM(AR9:AR40) -> 0 | AS41: =SUM(AS9:AS40) -> 0 | AT41: =SUM(AT9:AT40) -> 38893026 | AU41: =SUM(AU9:AU40) -> 0 | AV41: =SUM(AV9:AV40) -> 0 | AW41: =SUM(AW9:AW40) -> 0 | AX41: =SUM(AX9:AX40) -> 0 | ... BM41: =SUM(BM9:BM40) -> 103263.7 | BO41: =IF(AQ41+AR41=0,0,(AQ41+AR41)/AD41) -> 0.088185512 | BP41: =IF(AU41=0,0,AU41/AD41) -> 0 | BQ41: =IF(AT41=0,0,AT41/AD41) -> 0.83981425 | BR41: =IF(AW41=0,0,AW41/AD41) -> 0 | BS41: =IF(AZ41=0,0,AZ41/AD41) -> 0.0024961423 | BT41: =IF(BB41+BD41+BF41=0,0,(BB41+BD41+BF41)/AD41) -> 0.071733861 | BU41: =IF(BJ41=0,0,BJ41/AD41) -> 0 | BV41: =SUM(BO41:BU41) -> 1.0022298 | BW41: =AD41/$AD$41 -> 1
D42: 1302 | R42: 2 | X42: 4
A43: CONTROL | B43: =B9-B42 -> 0 | D43: =D42-D9 -> 759 | L43: =L41-L42 -> 0 | R43: =R41-R42 -> 8 | X43: =X41-X42 -> 13 | AE43: 0 | AF43: 0 | AG43: 0 | AH43: 0 | AI43: 0 | AJ43: 0 | AK43: 0 | AL43: 0 | AM43: 0 | AN43: 0 | AO43: 0
AC46: TOTAL | AD46: =AD41+AD45 -> 46311462 | AQ46: $ Efectivo | AR46: $ Deposito / PIX | AS46: TARJETA DEBITO | AT46: TARJETA CREDITO | AU46: Mercado Pago / TF | AV46: Real | AW46: Dólares | AX46: Euros
AP47: RESUMEN COBRANZA | AQ47: =AQ41 -> 4084000 | AR47: =AR41 -> 0 | AS47: =AU41 -> 0 | AT47: =AV41 -> 0 | AU47: =AW41 -> 0 | AV47: =AZ41 -> 115600 | AW47: =BD41+BF41+BH41+BB41 -> 3322100 | AX47: =BJ41 -> 0
AQ48: =AQ47/$AD$41 -> 0.088185512 | AR48: =AR47/$AD$41 -> 0 | AS48: =AS47/$AD$41 -> 0 | AT48: =AT47/$AD$41 -> 0 | AU48: =AU47/$AD$41 -> 0 | AV48: =AV47/$AD$41 -> 0.0024961423 | AW48: =AW47/$AD$41 -> 0.071733861 | AX48: =AX47/$AD$41 -> 0

Sheet LUCERO FRENCH
AS1: Cotizaciones | AX1: De | AY1: Hasta
A2: Empresa: EL LUCERO CUERO S.A. | AS2: ='LUCERO RECOLETA'!AS2 | AX2: ='LUCERO RECOLETA'!AX2 | AY2: ='LUCERO RECOLETA'!AY2 | AZ2: ='LUCERO RECOLETA'!AZ2 | BA2: ='LUCERO RECOLETA'!BA2 | BB2: ='LUCERO RECOLETA'!BB2 | BC2: ='LUCERO RECOLETA'!BC2 | BD2: ='LUCERO RECOLETA'!BD2 | BE2: ='LUCERO RECOLETA'!BE2 | ... BJ2: ='LUCERO RECOLETA'!BJ2
A3: Sucursal: LUCERO FRENCH - Defensa 1066 (loc 27/29) | AS3: ='LUCERO RECOLETA'!AS3 | AX3: ='LUCERO RECOLETA'!AX3 | AY3: ='LUCERO RECOLETA'!AY3 | AZ3: ='LUCERO RECOLETA'!AZ3 | BA3: ='LUCERO RECOLETA'!BA3 | BB3: ='LUCERO RECOLETA'!BB3 | BC3: ='LUCERO RECOLETA'!BC3 | BD3: ='LUCERO RECOLETA'!BD3 | BE3: ='LUCERO RECOLETA'!BE3 | ... BJ3: ='LUCERO RECOLETA'!BJ3
AS4: ='LUCERO RECOLETA'!AS4 | AX4: ='LUCERO RECOLETA'!AX4 | AY4: ='LUCERO RECOLETA'!AY4 | AZ4: ='LUCERO RECOLETA'!AZ4 | BA4: ='LUCERO RECOLETA'!BA4 | BB4: ='LUCERO RECOLETA'!BB4 | BC4: ='LUCERO RECOLETA'!BC4 | BD4: ='LUCERO RECOLETA'!BD4 | BE4: ='LUCERO RECOLETA'!BE4 | ... BJ4: ='LUCERO RECOLETA'!BJ4
A5: INFORME DE VENTAS MENSUAL | E5: pv 00045 | AS5: ='LUCERO RECOLETA'!AS5 | AX5: ='LUCERO RECOLETA'!AX5 | AY5: ='LUCERO RECOLETA'!AY5 | AZ5: ='LUCERO RECOLETA'!AZ5 | BA5: ='LUCERO RECOLETA'!BA5 | BB5: ='LUCERO RECOLETA'!BB5 | BC5: ='LUCERO RECOLETA'!BC5 | BD5: ='LUCERO RECOLETA'!BD5 | BE5: ='LUCERO RECOLETA'!BE5 | ... BK5: ='LUCERO RECOLETA'!BK5
A7: ='LUCERO RECOLETA'!A7 -> ABRIL | B7: Detalle de FACTURAS B | L7: Detalle de TICKETS | R7: Detalle de FACTURAS A | X7: Detalle de NOTAS DE CREDITO | AD7: VENTA FINAL | AE7: INFORME SEGÚN MAIL | AP7: DIFERENCIA | AQ7: CONTROL DE CIERRE DE CAJA
A8: Fecha | B8: Informe de cierre | C8: N° Tickets | D8: Desde | E8: Hasta | F8: Anulados y/o cancelados | G8: Cant. de art. | H8: Imp. de VTA gravado | I8: IVA 21% | J8: Otros imp. | K8: Imp. de VTA total | L8: Desde | M8: Hasta | N8: Imp.de VTA gravado | O8: IVA 21% | P8: Otros imp. | Q8: Imp. de VTA total | R8: Desde | S8: Hasta | T8: Imp.de VTA gravado | U8: IVA 21% | V8: Otros imp. | W8: Imp. de VTA total | X8: Desde | Y8: Hasta | Z8: Imp.de VTA gravado | AA8: IVA 21% | AB8: Otros imp. | AC8: Imp. de VTA total | AE8: VENTA TOTAL | AF8: EFECTIVO $ | AG8: TARJETAS | AH8: MERCADO PAGO | AI8: Real | AK8: Dolar | AM8: EURO | AO8: TOTAL DE INGRESO | AQ8: $ Efectivo | AR8: $ Deposito / PIX | AS8: TARJ SEGUN PLANILLA | AT8: TOTAL TARJETAS OK | AU8: TARJETA DEBITO | AV8: TARJETA CREDITO | AW8: Mercado Pago / TF | AX8: Gastos | AY8: Real | BA8: Dólar 100 | BC8: Dólar 50 | BE8: Dólar 10. 20 | BG8: Dólar 1. 5 | BI8: EURO | BK8: Total | BL8: CIERRE | BM8: DIFERENCIA | BO8: =AQ8 -> $ Efectivo | BP8: =AU8 -> TARJETA DEBITO | BQ8: =AV8 -> TARJETA CREDITO | BR8: =AW8 -> Mercado Pago / TF | BS8: =AY8 -> Real | BT8: Dólar | BU8: Euro | BV8: Total | BW8: Venta x día
A9: ='LUCERO RECOLETA'!A9 -> 46143 | C9: 0 | D9: 936 | E9: =IF(C9="","",C9+D9-1) -> 935 | K9: =H9+I9+J9 -> 0 | O9: =N9*21% -> 0 | Q9: =N9+O9+P9 -> 0 | U9: =T9*21% -> 0 | W9: =T9+U9+V9 -> 0 | AA9: =Z9*21% -> 0 | AC9: =Z9+AA9+AB9 -> 0 | AD9: =+K9+Q9+W9-AC9 -> 0 | AJ9: =AI9*220 -> 0 | AL9: =AK9*1200 -> 0 | AN9: =AM9*1200 -> 0 | AO9: =AF9+AG9+AH9+AJ9+AL9+AN9 -> 0 | AP9: =SUM(AO9-BK9) -> 0 | AT9: 0 | AW9: 0 | AZ9: =AY9*AZ$2 -> 0 | BB9: =BA9*BB$2 -> 0 | BD9: =BC9*BD$2 -> 0 | BF9: =BE9*BF$2 -> 0 | BH9: =BG9*BH$2 -> 0 | BJ9: =BI9*BJ$2 -> 0 | BK9: =+AQ9+AR9+AT9+AW9+AX9+AZ9+BB9+BD9+BF9+BH8+BJ9 -> 0 | BL9: =AD9 -> 0 | BM9: =SUM(BK9-BL9) -> 0 | BO9: =IF(AQ9+AR9=0,0,(AQ9+AR9)/AD9) -> 0 | BP9: =IF(AU9=0,0,AU9/AD9) -> 0 | BQ9: =IF(AT9=0,0,AT9/AD9) -> 0 | BR9: =IF(AW9=0,0,AW9/AD9) -> 0 | BS9: =IF(AZ9=0,0,AZ9/AD9) -> 0 | BT9: =IF(BB9+BD9+BF9=0,0,(BB9+BD9+BF9)/AD9) -> 0 | BU9: =IF(BJ9=0,0,BJ9/AD9) -> 0 | BV9: =SUM(BO9:BU9) -> 0 | BW9: =AD9/$AD$41 -> 0
A10: ='LUCERO RECOLETA'!A10 -> 46144 | C10: 6 | D10: =E9+1 -> 936 | E10: =IF(C10="","",C10+D10-1) -> 941 | H10: 242910.65 | I10: 51011.25 | K10: =H10+I10+J10 -> 293921.9 | O10: =N10*21% -> 0 | Q10: =N10+O10+P10 -> 0 | U10: =T10*21% -> 0 | W10: =T10+U10+V10 -> 0 | AA10: =Z10*21% -> 0 | AC10: =Z10+AA10+AB10 -> 0 | AD10: =+K10+Q10+W10-AC10 -> 293921.9 | AJ10: =AI10*220 -> 0 | AL10: =AK10*1200 -> 0 | AN10: =AM10*1200 -> 0 | AO10: =AF10+AG10+AH10+AJ10+AL10+AN10 -> 0 | AP10: =SUM(AO10-BK10) -> -293920 | AQ10: 0 | AT10: 293920 | AW10: 0 | AZ10: =AY10*AZ$2 -> 0 | BB10: =BA10*BB$2 -> 0 | BD10: =BC10*BD$2 -> 0 | BF10: =BE10*BF$2 -> 0 | BH10: =BG10*BH$2 -> 0 | BJ10: =BI10*BJ$2 -> 0 | BK10: =+AQ10+AR10+AT10+AW10+AX10+AZ10+BB10+BD10+BF10+BH9+BJ10 -> 293920 | BL10: =AD10 -> 293921.9 | BM10: =SUM(BK10-BL10) -> -1.9 | BO10: =IF(AQ10+AR10=0,0,(AQ10+AR10)/AD10) -> 0 | BP10: =IF(AU10=0,0,AU10/AD10) -> 0 | BQ10: =IF(AT10=0,0,AT10/AD10) -> 0.99999354 | BR10: =IF(AW10=0,0,AW10/AD10) -> 0 | BS10: =IF(AZ10=0,0,AZ10/AD10) -> 0 | BT10: =IF(BB10+BD10+BF10=0,0,(BB10+BD10+BF10)/AD10) -> 0 | BU10: =IF(BJ10=0,0,BJ10/AD10) -> 0 | BV10: =SUM(BO10:BU10) -> 0.99999354 | BW10: =AD10/$AD$41 -> 0.014709303
A11: ='LUCERO RECOLETA'!A11 -> 46145 | C11: 13 | D11: =E10+1 -> 942 | E11: =IF(C11="","",C11+D11-1) -> 954 | H11: 1237876 | I11: 259953.98 | K11: =H11+I11+J11 -> 1497830 | O11: =N11*21% -> 0 | Q11: =N11+O11+P11 -> 0 | U11: =T11*21% -> 0 | W11: =T11+U11+V11 -> 0 | AA11: =Z11*21% -> 0 | AC11: =Z11+AA11+AB11 -> 0 | AD11: =+K11+Q11+W11-AC11 -> 1497830 | AJ11: =AI11*220 -> 0 | AL11: =AK11*1200 -> 0 | AN11: =AM11*1200 -> 0 | AO11: =AF11+AG11+AH11+AJ11+AL11+AN11 -> 0 | AP11: =SUM(AO11-BK11) -> -1504450 | AQ11: 0 | AT11: 1447850 | AW11: 0 | AZ11: =AY11*AZ$2 -> 0 | BA11: 40 | BB11: =BA11*1415 -> 56600 | BD11: =BC11*BD$2 -> 0 | BF11: =BE11*BF$2 -> 0 | BH11: =BG11*BH$2 -> 0 | BJ11: =BI11*BJ$2 -> 0 | BK11: =+AQ11+AR11+AT11+AW11+AX11+AZ11+BB11+BD11+BF11+BH11+BJ11 -> 1504450 | BL11: =AD11 -> 1497830 | BM11: =SUM(BK11-BL11) -> 6620 | BO11: =IF(AQ11+AR11=0,0,(AQ11+AR11)/AD11) -> 0 | BP11: =IF(AU11=0,0,AU11/AD11) -> 0 | BQ11: =IF(AT11=0,0,AT11/AD11) -> 0.96663173 | BR11: =IF(AW11=0,0,AW11/AD11) -> 0 | BS11: =IF(AZ11=0,0,AZ11/AD11) -> 0 | BT11: =IF(BB11+BD11+BF11=0,0,(BB11+BD11+BF11)/AD11) -> 0.037788 | BU11: =IF(BJ11=0,0,BJ11/AD11) -> 0 | BV11: =SUM(BO11:BU11) -> 1.0044197 | BW11: =AD11/$AD$41 -> 0.07495881
A12: ='LUCERO RECOLETA'!A12 -> 46146 | C12: 3 | D12: =E11+1 -> 955 | E12: =IF(C12="","",C12+D12-1) -> 957 | H12: 307404.96 | I12: 64555.04 | K12: =H12+I12+J12 -> 371960 | O12: =N12*21% -> 0 | Q12: =N12+O12+P12 -> 0 | U12: =T12*21% -> 0 | W12: =T12+U12+V12 -> 0 | AA12: =Z12*21% -> 0 | AC12: =Z12+AA12+AB12 -> 0 | AD12: =+K12+Q12+W12-AC12 -> 371960 | AJ12: =AI12*220 -> 0 | AL12: =AK12*1200 -> 0 | AN12: =AM12*1200 -> 0 | AO12: =AF12+AG12+AH12+AJ12+AL12+AN12 -> 0 | AP12: =SUM(AO12-BK12) -> -371960 | AQ12: 0 | AT12: 371960 | AW12: 0 | AZ12: =AY12*AZ$2 -> 0 | BB12: =BA12*BB$2 -> 0 | BD12: =BC12*1495 -> 0 | BF12: =BE12*1495 -> 0 | BH12: =BG12*BH$2 -> 0 | BJ12: =BI12*BJ$2 -> 0 | BK12: =+AQ12+AR12+AT12+AW12+AX12+AZ12+BB12+BD12+BF12+BH12+BJ12 -> 371960 | BL12: =AD12 -> 371960 | BM12: =SUM(BK12-BL12) -> 0 | BO12: =IF(AQ12+AR12=0,0,(AQ12+AR12)/AD12) -> 0 | BP12: =IF(AU12=0,0,AU12/AD12) -> 0 | BQ12: =IF(AT12=0,0,AT12/AD12) -> 1 | BR12: =IF(AW12=0,0,AW12/AD12) -> 0 | BS12: =IF(AZ12=0,0,AZ12/AD12) -> 0 | BT12: =IF(BB12+BD12+BF12=0,0,(BB12+BD12+BF12)/AD12) -> 0 | BU12: =IF(BJ12=0,0,BJ12/AD12) -> 0 | BV12: =SUM(BO12:BU12) -> 1 | BW12: =AD12/$AD$41 -> 0.018614715
A13: ='LUCERO RECOLETA'!A13 -> 46147 | C13: 3 | D13: =E12+1 -> 958 | E13: =IF(C13="","",C13+D13-1) -> 960 | H13: 181793.38 | I13: 38176.62 | K13: =H13+I13+J13 -> 219970 | O13: =N13*21% -> 0 | Q13: =N13+O13+P13 -> 0 | U13: =T13*21% -> 0 | W13: =T13+U13+V13 -> 0 | AA13: =Z13*21% -> 0 | AC13: =Z13+AA13+AB13 -> 0 | AD13: =+K13+Q13+W13-AC13 -> 219970 | AJ13: =AI13*220 -> 0 | AL13: =AK13*1200 -> 0 | AN13: =AM13*1200 -> 0 | AO13: =AF13+AG13+AH13+AJ13+AL13+AN13 -> 0 | AP13: =SUM(AO13-BK13) -> -219980 | AQ13: 100000 | AT13: 119980 | AW13: 0 | AZ13: =AY13*AZ$2 -> 0 | BB13: =BA13*1415 -> 0 | BD13: =BC13*BD$2 -> 0 | BF13: =BE13*BF$2 -> 0 | BH13: =BG13*BH$2 -> 0 | BJ13: =BI13*BJ$2 -> 0 | BK13: =+AQ13+AR13+AT13+AW13+AX13+AZ13+BB13+BD13+BF13+BH13+BJ13 -> 219980 | BL13: =AD13 -> 219970 | BM13: =SUM(BK13-BL13) -> 10 | BO13: =IF(AQ13+AR13=0,0,(AQ13+AR13)/AD13) -> 0.45460745 | BP13: =IF(AU13=0,0,AU13/AD13) -> 0 | BQ13: =IF(AT13=0,0,AT13/AD13) -> 0.54543801 | BR13: =IF(AW13=0,0,AW13/AD13) -> 0 | BS13: =IF(AZ13=0,0,AZ13/AD13) -> 0 | BT13: =IF(BB13+BD13+BF13=0,0,(BB13+BD13+BF13)/AD13) -> 0 | BU13: =IF(BJ13=0,0,BJ13/AD13) -> 0 | BV13: =SUM(BO13:BU13) -> 1.0000455 | BW13: =AD13/$AD$41 -> 0.011008385
A14: ='LUCERO RECOLETA'!A14 -> 46148 | C14: 1 | D14: =E13+1 -> 961 | E14: =IF(C14="","",C14+D14-1) -> 961 | H14: 165272.73 | I14: 34707.27 | K14: =H14+I14+J14 -> 199980 | O14: =N14*21% -> 0 | Q14: =N14+O14+P14 -> 0 | U14: =T14*21% -> 0 | W14: =T14+U14+V14 -> 0 | AA14: =Z14*21% -> 0 | AC14: =Z14+AA14+AB14 -> 0 | AD14: =+K14+Q14+W14-AC14 -> 199980 | AJ14: =AI14*220 -> 0 | AL14: =AK14*1200 -> 0 | AN14: =AM14*1200 -> 0 | AO14: =AF14+AG14+AH14+AJ14+AL14+AN14 -> 0 | AP14: =SUM(AO14-BK14) -> -199980 | AQ14: 0 | AT14: 199980 | AW14: 0 | AZ14: =AY14*AZ$2 -> 0 | BB14: =BA14*BB$2 -> 0 | BD14: =BC14*1495 -> 0 | BF14: =BE14*BF$2 -> 0 | BH14: =BG14*BH$2 -> 0 | BJ14: =BI14*BJ$2 -> 0 | BK14: =+AQ14+AR14+AT14+AW14+AX14+AZ14+BB14+BD14+BF14+BH14+BJ14 -> 199980 | BL14: =AD14 -> 199980 | BM14: =SUM(BK14-BL14) -> 0 | BO14: =IF(AQ14+AR14=0,0,(AQ14+AR14)/AD14) -> 0 | BP14: =IF(AU14=0,0,AU14/AD14) -> 0 | BQ14: =IF(AT14=0,0,AT14/AD14) -> 1 | BR14: =IF(AW14=0,0,AW14/AD14) -> 0 | BS14: =IF(AZ14=0,0,AZ14/AD14) -> 0 | BT14: =IF(BB14+BD14+BF14=0,0,(BB14+BD14+BF14)/AD14) -> 0 | BU14: =IF(BJ14=0,0,BJ14/AD14) -> 0 | BV14: =SUM(BO14:BU14) -> 1 | BW14: =AD14/$AD$41 -> 0.010007987
A15: ='LUCERO RECOLETA'!A15 -> 46149 | C15: 2 | D15: =E14+1 -> 962 | E15: =IF(C15="","",C15+D15-1) -> 963 | H15: 405743.8 | I15: 85206.2 | K15: =H15+I15+J15 -> 490950 | O15: =N15*21% -> 0 | Q15: =N15+O15+P15 -> 0 | U15: =T15*21% -> 0 | W15: =T15+U15+V15 -> 0 | AA15: =Z15*21% -> 0 | AC15: =Z15+AA15+AB15 -> 0 | AD15: =+K15+Q15+W15-AC15 -> 490950 | AJ15: =AI15*220 -> 0 | AL15: =AK15*1200 -> 0 | AN15: =AM15*1200 -> 0 | AO15: =AF15+AG15+AH15+AJ15+AL15+AN15 -> 0 | AP15: =SUM(AO15-BK15) -> -490950 | AQ15: 0 | AT15: 490950 | AW15: 0 | AZ15: =AY15*AZ$2 -> 0 | BB15: =BA15*BB$2 -> 0 | BD15: =BC15*BD$2 -> 0 | BF15: =BE15*BF$2 -> 0 | BH15: =BG15*BH$2 -> 0 | BJ15: =BI15*1665 -> 0 | BK15: =+AQ15+AR15+AT15+AW15+AX15+AZ15+BB15+BD15+BF15+BH15+BJ15 -> 490950 | BL15: =AD15 -> 490950 | BM15: =SUM(BK15-BL15) -> 0 | BO15: =IF(AQ15+AR15=0,0,(AQ15+AR15)/AD15) -> 0 | BP15: =IF(AU15=0,0,AU15/AD15) -> 0 | BQ15: =IF(AT15=0,0,AT15/AD15) -> 1 | BR15: =IF(AW15=0,0,AW15/AD15) -> 0 | BS15: =IF(AZ15=0,0,AZ15/AD15) -> 0 | BT15: =IF(BB15+BD15+BF15=0,0,(BB15+BD15+BF15)/AD15) -> 0 | BU15: =IF(BJ15=0,0,BJ15/AD15) -> 0 | BV15: =SUM(BO15:BU15) -> 1 | BW15: =AD15/$AD$41 -> 0.024569563
A16: ='LUCERO RECOLETA'!A16 -> 46150 | C16: 2 | D16: =E15+1 -> 964 | E16: =IF(C16="","",C16+D16-1) -> 965 | H16: 84280.99 | I16: 17699.01 | K16: =H16+I16+J16 -> 101980 | O16: =N16*21% -> 0 | Q16: =N16+O16+P16 -> 0 | U16: =T16*21% -> 0 | W16: =T16+U16+V16 -> 0 | AA16: =Z16*21% -> 0 | AC16: =Z16+AA16+AB16 -> 0 | AD16: =+K16+Q16+W16-AC16 -> 101980 | AJ16: =AI16*220 -> 0 | AL16: =AK16*1200 -> 0 | AN16: =AM16*1200 -> 0 | AO16: =AF16+AG16+AH16+AJ16+AL16+AN16 -> 0 | AP16: =SUM(AO16-BK16) -> -101980 | AQ16: 0 | AT16: 101980 | AW16: 0 | AZ16: =AY16*AZ$2 -> 0 | BB16: =BA16*1435 -> 0 | BD16: =BC16*BD$2 -> 0 | BF16: =BE16*BF$2 -> 0 | BH16: =BG16*BH$2 -> 0 | BJ16: =BI16*BJ$2 -> 0 | BK16: =+AQ16+AR16+AT16+AW16+AX16+AZ16+BB16+BD16+BF16+BH16+BJ16 -> 101980 | BL16: =AD16 -> 101980 | BM16: =SUM(BK16-BL16) -> 0 | BO16: =IF(AQ16+AR16=0,0,(AQ16+AR16)/AD16) -> 0 | BP16: =IF(AU16=0,0,AU16/AD16) -> 0 | BQ16: =IF(AT16=0,0,AT16/AD16) -> 1 | BR16: =IF(AW16=0,0,AW16/AD16) -> 0 | BS16: =IF(AZ16=0,0,AZ16/AD16) -> 0 | BT16: =IF(BB16+BD16+BF16=0,0,(BB16+BD16+BF16)/AD16) -> 0 | BU16: =IF(BJ16=0,0,BJ16/AD16) -> 0 | BV16: =SUM(BO16:BU16) -> 1 | BW16: =AD16/$AD$41 -> 0.0051035828
A17: ='LUCERO RECOLETA'!A17 -> 46151 | C17: 3 | D17: =E16+1 -> 966 | E17: =IF(C17="","",C17+D17-1) -> 968 | H17: 179289.26 | I17: 37650.74 | K17: =H17+I17+J17 -> 216940 | O17: =N17*21% -> 0 | Q17: =N17+O17+P17 -> 0 | U17: =T17*21% -> 0 | W17: =T17+U17+V17 -> 0 | AA17: =Z17*21% -> 0 | AC17: =Z17+AA17+AB17 -> 0 | AD17: =+K17+Q17+W17-AC17 -> 216940 | AJ17: =AI17*220 -> 0 | AL17: =AK17*1200 -> 0 | AN17: =AM17*1200 -> 0 | AO17: =AF17+AG17+AH17+AJ17+AL17+AN17 -> 0 | AP17: =SUM(AO17-BK17) -> -216940 | AQ17: 0 | AT17: 51960 | AW17: 164980 | AZ17: =AY17*AZ$2 -> 0 | BB17: =BA17*BB$2 -> 0 | BD17: =BC17*BD$2 -> 0 | BF17: =BE17*BF$2 -> 0 | BH17: =BG17*BH$2 -> 0 | BJ17: =BI17*BJ$2 -> 0 | BK17: =+AQ17+AR17+AT17+AW17+AX17+AZ17+BB17+BD17+BF17+BH17+BJ17 -> 216940 | BL17: =AD17 -> 216940 | BM17: =SUM(BK17-BL17) -> 0 | BO17: =IF(AQ17+AR17=0,0,(AQ17+AR17)/AD17) -> 0 | BP17: =IF(AU17=0,0,AU17/AD17) -> 0 | BQ17: =IF(AT17=0,0,AT17/AD17) -> 0.23951323 | BR17: =IF(AW17=0,0,AW17/AD17) -> 0.76048677 | BS17: =IF(AZ17=0,0,AZ17/AD17) -> 0 | BT17: =IF(BB17+BD17+BF17=0,0,(BB17+BD17+BF17)/AD17) -> 0 | BU17: =IF(BJ17=0,0,BJ17/AD17) -> 0 | BV17: =SUM(BO17:BU17) -> 1 | BW17: =AD17/$AD$41 -> 0.010856749
A18: ='LUCERO RECOLETA'!A18 -> 46152 | C18: 11 | D18: =E17+1 -> 969 | E18: =IF(C18="","",C18+D18-1) -> 979 | H18: 1705285.1 | I18: 358109.87 | K18: =H18+I18+J18 -> 2063395 | O18: =N18*21% -> 0 | Q18: =N18+O18+P18 -> 0 | U18: =T18*21% -> 0 | W18: =T18+U18+V18 -> 0 | AA18: =Z18*21% -> 0 | AC18: =Z18+AA18+AB18 -> 0 | AD18: =+K18+Q18+W18-AC18 -> 2063395 | AJ18: =AI18*220 -> 0 | AL18: =AK18*1200 -> 0 | AN18: =AM18*1200 -> 0 | AO18: =AF18+AG18+AH18+AJ18+AL18+AN18 -> 0 | AP18: =SUM(AO18-BK18) -> -2063435 | AQ18: =120000+440000+20000 -> 580000 | AT18: 1483435 | AW18: 0 | AZ18: =AY18*AZ$2 -> 0 | BB18: =BA18*BB$2 -> 0 | BD18: =BC18*BD$2 -> 0 | BF18: =BE18*BF$2 -> 0 | BH18: =BG18*BH$2 -> 0 | BJ18: =BI18*BJ$2 -> 0 | BK18: =+AQ18+AR18+AT18+AW18+AX18+AZ18+BB18+BD18+BF18+BH18+BJ18 -> 2063435 | BL18: =AD18 -> 2063395 | BM18: =SUM(BK18-BL18) -> 40 | BO18: =IF(AQ18+AR18=0,0,(AQ18+AR18)/AD18) -> 0.28109015 | BP18: =IF(AU18=0,0,AU18/AD18) -> 0 | BQ18: =IF(AT18=0,0,AT18/AD18) -> 0.71892924 | BR18: =IF(AW18=0,0,AW18/AD18) -> 0 | BS18: =IF(AZ18=0,0,AZ18/AD18) -> 0 | BT18: =IF(BB18+BD18+BF18=0,0,(BB18+BD18+BF18)/AD18) -> 0 | BU18: =IF(BJ18=0,0,BJ18/AD18) -> 0 | BV18: =SUM(BO18:BU18) -> 1.0000194 | BW18: =AD18/$AD$41 -> 0.10326248
A19: ='LUCERO RECOLETA'!A19 -> 46153 | C19: 0 | D19: =E18+1 -> 980 | E19: =IF(C19="","",C19+D19-1) -> 979 | K19: =H19+I19+J19 -> 0 | O19: =N19*21% -> 0 | Q19: =N19+O19+P19 -> 0 | U19: =T19*21% -> 0 | W19: =T19+U19+V19 -> 0 | AA19: =Z19*21% -> 0 | AC19: =Z19+AA19+AB19 -> 0 | AD19: =+K19+Q19+W19-AC19 -> 0 | AJ19: =AI19*220 -> 0 | AL19: =AK19*1200 -> 0 | AN19: =AM19*1200 -> 0 | AO19: =AF19+AG19+AH19+AJ19+AL19+AN19 -> 0 | AP19: =SUM(AO19-BK19) -> 0 | AQ19: 0 | AT19: 0 | AW19: 0 | AZ19: =AY19*AZ$2 -> 0 | BB19: =BA19*BB$2 -> 0 | BD19: =BC19*BD$2 -> 0 | BF19: =BE19*BF$2 -> 0 | BH19: =BG19*BH$2 -> 0 | BJ19: =BI19*BJ$2 -> 0 | BK19: =+AQ19+AR19+AT19+AW19+AX19+AZ19+BB19+BD19+BF19+BH19+BJ19 -> 0 | BL19: =AD19 -> 0 | BM19: =SUM(BK19-BL19) -> 0 | BO19: =IF(AQ19+AR19=0,0,(AQ19+AR19)/AD19) -> 0 | BP19: =IF(AU19=0,0,AU19/AD19) -> 0 | BQ19: =IF(AT19=0,0,AT19/AD19) -> 0 | BR19: =IF(AW19=0,0,AW19/AD19) -> 0 | BS19: =IF(AZ19=0,0,AZ19/AD19) -> 0 | BT19: =IF(BB19+BD19+BF19=0,0,(BB19+BD19+BF19)/AD19) -> 0 | BU19: =IF(BJ19=0,0,BJ19/AD19) -> 0 | BV19: =SUM(BO19:BU19) -> 0 | BW19: =AD19/$AD$41 -> 0
A20: ='LUCERO RECOLETA'!A20 -> 46154 | C20: 2 | D20: =E19+1 -> 980 | E20: =IF(C20="","",C20+D20-1) -> 981 | H20: 173528.92 | I20: 36441.08 | K20: =H20+I20+J20 -> 209970 | O20: =N20*21% -> 0 | Q20: =N20+O20+P20 -> 0 | U20: =T20*21% -> 0 | W20: =T20+U20+V20 -> 0 | AA20: =Z20*21% -> 0 | AC20: =Z20+AA20+AB20 -> 0 | AD20: =+K20+Q20+W20-AC20 -> 209970 | AJ20: =AI20*220 -> 0 | AL20: =AK20*1200 -> 0 | AN20: =AM20*1200 -> 0 | AO20: =AF20+AG20+AH20+AJ20+AL20+AN20 -> 0 | AP20: =SUM(AO20-BK20) -> -209980 | AQ20: 30000 | AT20: 179980 | AW20: 0 | AZ20: =AY20*AZ$2 -> 0 | BB20: =BA20*BB$2 -> 0 | BD20: =BC20*BD$2 -> 0 | BF20: =BE20*BF$2 -> 0 | BH20: =BG20*BH$2 -> 0 | BJ20: =BI20*BJ$2 -> 0 | BK20: =+AQ20+AR20+AT20+AW20+AX20+AZ20+BB20+BD20+BF20+BH20+BJ20 -> 209980 | BL20: =AD20 -> 209970 | BM20: =SUM(BK20-BL20) -> 10 | BO20: =IF(AQ20+AR20=0,0,(AQ20+AR20)/AD20) -> 0.14287755 | BP20: =IF(AU20=0,0,AU20/AD20) -> 0 | BQ20: =IF(AT20=0,0,AT20/AD20) -> 0.85717007 | BR20: =IF(AW20=0,0,AW20/AD20) -> 0 | BS20: =IF(AZ20=0,0,AZ20/AD20) -> 0 | BT20: =IF(BB20+BD20+BF20=0,0,(BB20+BD20+BF20)/AD20) -> 0 | BU20: =IF(BJ20=0,0,BJ20/AD20) -> 0 | BV20: =SUM(BO20:BU20) -> 1.0000476 | BW20: =AD20/$AD$41 -> 0.010507936
A21: ='LUCERO RECOLETA'!A21 -> 46155 | C21: 3 | D21: =E20+1 -> 982 | E21: =IF(C21="","",C21+D21-1) -> 984 | K21: =H21+I21+J21 -> 0 | O21: =N21*21% -> 0 | Q21: =N21+O21+P21 -> 0 | U21: =T21*21% -> 0 | W21: =T21+U21+V21 -> 0 | AA21: =Z21*21% -> 0 | AC21: =Z21+AA21+AB21 -> 0 | AD21: =+K21+Q21+W21-AC21 -> 0 | AJ21: =AI21*220 -> 0 | AL21: =AK21*1200 -> 0 | AN21: =AM21*1200 -> 0 | AO21: =AF21+AG21+AH21+AJ21+AL21+AN21 -> 0 | AP21: =SUM(AO21-BK21) -> 0 | AQ21: 0 | AT21: 0 | AW21: 0 | AZ21: =AY21*AZ$2 -> 0 | BB21: =BA21*1425 -> 0 | BD21: =BC21*BD$2 -> 0 | BF21: =BE21*BF$2 -> 0 | BH21: =BG21*BH$2 -> 0 | BJ21: =BI21*BJ$2 -> 0 | BK21: =+AQ21+AR21+AT21+AW21+AX21+AZ21+BB21+BD21+BF21+BH21+BJ21 -> 0 | BL21: =AD21 -> 0 | BM21: =SUM(BK21-BL21) -> 0 | BO21: =IF(AQ21+AR21=0,0,(AQ21+AR21)/AD21) -> 0 | BP21: =IF(AU21=0,0,AU21/AD21) -> 0 | BQ21: =IF(AT21=0,0,AT21/AD21) -> 0 | BR21: =IF(AW21=0,0,AW21/AD21) -> 0 | BS21: =IF(AZ21=0,0,AZ21/AD21) -> 0 | BT21: =IF(BB21+BD21+BF21=0,0,(BB21+BD21+BF21)/AD21) -> 0 | BU21: =IF(BJ21=0,0,BJ21/AD21) -> 0 | BV21: =SUM(BO21:BU21) -> 0 | BW21: =AD21/$AD$41 -> 0
A22: ='LUCERO RECOLETA'!A22 -> 46156 | C22: 0 | D22: =E21+1 -> 985 | E22: =IF(C22="","",C22+D22-1) -> 984 | H22: 104933.88 | I22: 22036.12 | K22: =H22+I22+J22 -> 126970 | O22: =N22*21% -> 0 | Q22: =N22+O22+P22 -> 0 | U22: =T22*21% -> 0 | W22: =T22+U22+V22 -> 0 | AA22: =Z22*21% -> 0 | AC22: =Z22+AA22+AB22 -> 0 | AD22: =+K22+Q22+W22-AC22 -> 126970 | AJ22: =AI22*220 -> 0 | AL22: =AK22*1200 -> 0 | AN22: =AM22*1200 -> 0 | AO22: =AF22+AG22+AH22+AJ22+AL22+AN22 -> 0 | AP22: =SUM(AO22-BK22) -> -126970 | AQ22: 0 | AT22: 126970 | AW22: 0 | AZ22: =AY22*AZ$2 -> 0 | BB22: =BA22*1395 -> 0 | BD22: =BC22*BD$2 -> 0 | BF22: =BE22*BF$2 -> 0 | BH22: =BG22*BH$2 -> 0 | BJ22: =BI22*BJ$2 -> 0 | BK22: =+AQ22+AR22+AT22+AW22+AX22+AZ22+BB22+BD22+BF22+BH22+BJ22 -> 126970 | BL22: =AD22 -> 126970 | BM22: =SUM(BK22-BL22) -> 0 | BO22: =IF(AQ22+AR22=0,0,(AQ22+AR22)/AD22) -> 0 | BP22: =IF(AU22=0,0,AU22/AD22) -> 0 | BQ22: =IF(AT22=0,0,AT22/AD22) -> 1 | BR22: =IF(AW22=0,0,AW22/AD22) -> 0 | BS22: =IF(AZ22=0,0,AZ22/AD22) -> 0 | BT22: =IF(BB22+BD22+BF22=0,0,(BB22+BD22+BF22)/AD22) -> 0 | BU22: =IF(BJ22=0,0,BJ22/AD22) -> 0 | BV22: =SUM(BO22:BU22) -> 1 | BW22: =AD22/$AD$41 -> 0.0063542059
A23: ='LUCERO RECOLETA'!A23 -> 46157 | C23: 4 | D23: =E22+1 -> 985 | E23: =IF(C23="","",C23+D23-1) -> 988 | H23: 383438.01 | I23: 80521.99 | K23: =H23+I23+J23 -> 463960 | O23: =N23*21% -> 0 | Q23: =N23+O23+P23 -> 0 | U23: =T23*21% -> 0 | W23: =T23+U23+V23 -> 0 | AA23: =Z23*21% -> 0 | AC23: =Z23+AA23+AB23 -> 0 | AD23: =+K23+Q23+W23-AC23 -> 463960 | AJ23: =AI23*220 -> 0 | AL23: =AK23*1200 -> 0 | AN23: =AM23*1200 -> 0 | AO23: =AF23+AG23+AH23+AJ23+AL23+AN23 -> 0 | AP23: =SUM(AO23-BK23) -> -463960 | AQ23: 0 | AT23: 393970 | AW23: 69990 | AZ23: =AY23*AZ$2 -> 0 | BB23: =BA23*BB$2 -> 0 | BD23: =BC23*BD$2 -> 0 | BF23: =BE23*BF$2 -> 0 | BH23: =BG23*BH$2 -> 0 | BJ23: =BI23*BJ$2 -> 0 | BK23: =+AQ23+AR23+AT23+AW23+AX23+AZ23+BB23+BD23+BF23+BH23+BJ23 -> 463960 | BL23: =AD23 -> 463960 | BM23: =SUM(BK23-BL23) -> 0 | BO23: =IF(AQ23+AR23=0,0,(AQ23+AR23)/AD23) -> 0 | BP23: =IF(AU23=0,0,AU23/AD23) -> 0 | BQ23: =IF(AT23=0,0,AT23/AD23) -> 0.84914648 | BR23: =IF(AW23=0,0,AW23/AD23) -> 0.15085352 | BS23: =IF(AZ23=0,0,AZ23/AD23) -> 0 | BT23: =IF(BB23+BD23+BF23=0,0,(BB23+BD23+BF23)/AD23) -> 0 | BU23: =IF(BJ23=0,0,BJ23/AD23) -> 0 | BV23: =SUM(BO23:BU23) -> 1 | BW23: =AD23/$AD$41 -> 0.02321885
A24: ='LUCERO RECOLETA'!A24 -> 46158 | C24: 8 | D24: =E23+1 -> 989 | E24: =IF(C24="","",C24+D24-1) -> 996 | H24: 826347.11 | I24: 173532.89 | K24: =H24+I24+J24 -> 999880 | O24: =N24*21% -> 0 | Q24: =N24+O24+P24 -> 0 | U24: =T24*21% -> 0 | W24: =T24+U24+V24 -> 0 | AA24: =Z24*21% -> 0 | AC24: =Z24+AA24+AB24 -> 0 | AD24: =+K24+Q24+W24-AC24 -> 999880 | AJ24: =AI24*220 -> 0 | AL24: =AK24*1200 -> 0 | AN24: =AM24*1200 -> 0 | AO24: =AF24+AG24+AH24+AJ24+AL24+AN24 -> 0 | AP24: =SUM(AO24-BK24) -> -999880 | AQ24: 0 | AT24: 974890 | AW24: 24990 | AZ24: =AY24*AZ$2 -> 0 | BB24: =BA24*BB$2 -> 0 | BD24: =BC24*BD$2 -> 0 | BF24: =BE24*BF$2 -> 0 | BH24: =BG24*BH$2 -> 0 | BJ24: =BI24*BJ$2 -> 0 | BK24: =+AQ24+AR24+AT24+AW24+AX24+AZ24+BB24+BD24+BF24+BH24+BJ24 -> 999880 | BL24: =AD24 -> 999880 | BM24: =SUM(BK24-BL24) -> 0 | BO24: =IF(AQ24+AR24=0,0,(AQ24+AR24)/AD24) -> 0 | BP24: =IF(AU24=0,0,AU24/AD24) -> 0 | BQ24: =IF(AT24=0,0,AT24/AD24) -> 0.975007 | BR24: =IF(AW24=0,0,AW24/AD24) -> 0.024992999 | BS24: =IF(AZ24=0,0,AZ24/AD24) -> 0 | BT24: =IF(BB24+BD24+BF24=0,0,(BB24+BD24+BF24)/AD24) -> 0 | BU24: =IF(BJ24=0,0,BJ24/AD24) -> 0 | BV24: =SUM(BO24:BU24) -> 1 | BW24: =AD24/$AD$41 -> 0.050038933
A25: ='LUCERO RECOLETA'!A25 -> 46159 | C25: 16 | D25: =E24+1 -> 997 | E25: =IF(C25="","",C25+D25-1) -> 1012 | H25: 1143619.8 | I25: 240160.17 | K25: =H25+I25+J25 -> 1383780 | O25: =N25*21% -> 0 | Q25: =N25+O25+P25 -> 0 | U25: =T25*21% -> 0 | W25: =T25+U25+V25 -> 0 | AA25: =Z25*21% -> 0 | AC25: =Z25+AA25+AB25 -> 0 | AD25: =+K25+Q25+W25-AC25 -> 1383780 | AJ25: =AI25*220 -> 0 | AL25: =AK25*1200 -> 0 | AN25: =AM25*1200 -> 0 | AO25: =AF25+AG25+AH25+AJ25+AL25+AN25 -> 0 | AP25: =SUM(AO25-BK25) -> -1378810 | AQ25: 92000 | AT25: 1286810 | AW25: 0 | AZ25: =AY25*AZ$2 -> 0 | BB25: =BA25*BB$2 -> 0 | BD25: =BC25*BD$2 -> 0 | BF25: =BE25*BF$2 -> 0 | BH25: =BG25*BH$2 -> 0 | BJ25: =BI25*BJ$2 -> 0 | BK25: =+AQ25+AR25+AT25+AW25+AX25+AZ25+BB25+BD25+BF25+BH25+BJ25 -> 1378810 | BL25: =AD25 -> 1383780 | BM25: =SUM(BK25-BL25) -> -4970 | BO25: =IF(AQ25+AR25=0,0,(AQ25+AR25)/AD25) -> 0.066484557 | BP25: =IF(AU25=0,0,AU25/AD25) -> 0 | BQ25: =IF(AT25=0,0,AT25/AD25) -> 0.92992383 | BR25: =IF(AW25=0,0,AW25/AD25) -> 0 | BS25: =IF(AZ25=0,0,AZ25/AD25) -> 0 | BT25: =IF(BB25+BD25+BF25=0,0,(BB25+BD25+BF25)/AD25) -> 0 | BU25: =IF(BJ25=0,0,BJ25/AD25) -> 0 | BV25: =SUM(BO25:BU25) -> 0.99640839 | BW25: =AD25/$AD$41 -> 0.069251185
A26: ='LUCERO RECOLETA'!A26 -> 46160 | C26: 6 | D26: =E25+1 -> 1013 | E26: =IF(C26="","",C26+D26-1) -> 1018 | H26: 895727.28 | I26: 188102.72 | K26: =H26+I26+J26 -> 1083830 | O26: =N26*21% -> 0 | Q26: =N26+O26+P26 -> 0 | U26: =T26*21% -> 0 | W26: =T26+U26+V26 -> 0 | AA26: =Z26*21% -> 0 | AC26: =Z26+AA26+AB26 -> 0 | AD26: =+K26+Q26+W26-AC26 -> 1083830 | AJ26: =AI26*220 -> 0 | AL26: =AK26*1200 -> 0 | AN26: =AM26*1200 -> 0 | AO26: =AF26+AG26+AH26+AJ26+AL26+AN26 -> 0 | AP26: =SUM(AO26-BK26) -> -1083830 | AQ26: 0 | AT26: 1083830 | AW26: 0 | AZ26: =AY26*AZ$2 -> 0 | BB26: =BA26*1415 -> 0 | BD26: =BC26*BD$2 -> 0 | BF26: =BE26*BF$2 -> 0 | BH26: =BG26*BH$2 -> 0 | BJ26: =BI26*BJ$2 -> 0 | BK26: =+AQ26+AR26+AT26+AW26+AX26+AZ26+BB26+BD26+BF26+BH26+BJ26 -> 1083830 | BL26: =AD26 -> 1083830 | BM26: =SUM(BK26-BL26) -> 0 | BO26: =IF(AQ26+AR26=0,0,(AQ26+AR26)/AD26) -> 0 | BP26: =IF(AU26=0,0,AU26/AD26) -> 0 | BQ26: =IF(AT26=0,0,AT26/AD26) -> 1 | BR26: =IF(AW26=0,0,AW26/AD26) -> 0 | BS26: =IF(AZ26=0,0,AZ26/AD26) -> 0 | BT26: =IF(BB26+BD26+BF26=0,0,(BB26+BD26+BF26)/AD26) -> 0 | BU26: =IF(BJ26=0,0,BJ26/AD26) -> 0 | BV26: =SUM(BO26:BU26) -> 1 | BW26: =AD26/$AD$41 -> 0.054240206
A27: ='LUCERO RECOLETA'!A27 -> 46161 | C27: 6 | D27: =E26+1 -> 1019 | E27: =IF(C27="","",C27+D27-1) -> 1024 | H27: 799479.33 | I27: 167890.67 | K27: =H27+I27+J27 -> 967370 | O27: =N27*21% -> 0 | Q27: =N27+O27+P27 -> 0 | U27: =T27*21% -> 0 | W27: =T27+U27+V27 -> 0 | AA27: =Z27*21% -> 0 | AC27: =Z27+AA27+AB27 -> 0 | AD27: =+K27+Q27+W27-AC27 -> 967370 | AJ27: =AI27*220 -> 0 | AL27: =AK27*1200 -> 0 | AN27: =AM27*1200 -> 0 | AO27: =AF27+AG27+AH27+AJ27+AL27+AN27 -> 0 | AP27: =SUM(AO27-BK27) -> -979180 | AQ27: 0 | AT27: 922380 | AW27: 0 | AZ27: =AY27*AZ$2 -> 0 | BA27: 40 | BB27: =BA27*1420 -> 56800 | BD27: =BC27*BD$2 -> 0 | BF27: =BE27*BF$2 -> 0 | BH27: =BG27*BH$2 -> 0 | BJ27: =BI27*BJ$2 -> 0 | BK27: =+AQ27+AR27+AT27+AW27+AX27+AZ27+BB27+BD27+BF27+BH27+BJ27 -> 979180 | BL27: =AD27 -> 967370 | BM27: =SUM(BK27-BL27) -> 11810 | BO27: =IF(AQ27+AR27=0,0,(AQ27+AR27)/AD27) -> 0 | BP27: =IF(AU27=0,0,AU27/AD27) -> 0 | BQ27: =IF(AT27=0,0,AT27/AD27) -> 0.95349246 | BR27: =IF(AW27=0,0,AW27/AD27) -> 0 | BS27: =IF(AZ27=0,0,AZ27/AD27) -> 0 | BT27: =IF(BB27+BD27+BF27=0,0,(BB27+BD27+BF27)/AD27) -> 0.0587159 | BU27: =IF(BJ27=0,0,BJ27/AD27) -> 0 | BV27: =SUM(BO27:BU27) -> 1.0122084 | BW27: =AD27/$AD$41 -> 0.048411972
A28: ='LUCERO RECOLETA'!A28 -> 46162 | C28: 2 | D28: =E27+1 -> 1025 | E28: =IF(C28="","",C28+D28-1) -> 1026 | H28: 272710.74 | I28: 57269.26 | K28: =H28+I28+J28 -> 329980 | O28: =N28*21% -> 0 | Q28: =N28+O28+P28 -> 0 | U28: =T28*21% -> 0 | W28: =T28+U28+V28 -> 0 | AA28: =Z28*21% -> 0 | AC28: =Z28+AA28+AB28 -> 0 | AD28: =+K28+Q28+W28-AC28 -> 329980 | AJ28: =AI28*220 -> 0 | AL28: =AK28*1200 -> 0 | AN28: =AM28*1200 -> 0 | AO28: =AF28+AG28+AH28+AJ28+AL28+AN28 -> 0 | AP28: =SUM(AO28-BK28) -> -329980 | AQ28: 0 | AT28: 329980 | AW28: 0 | AZ28: =AY28*AZ$2 -> 0 | BB28: =BA28*BB$2 -> 0 | BD28: =BC28*BD$2 -> 0 | BF28: =BE28*BF$2 -> 0 | BH28: =BG28*BH$2 -> 0 | BJ28: =BI28*BJ$2 -> 0 | BK28: =+AQ28+AR28+AT28+AW28+AX28+AZ28+BB28+BD28+BF28+BH28+BJ28 -> 329980 | BL28: =AD28 -> 329980 | BM28: =SUM(BK28-BL28) -> 0 | BO28: =IF(AQ28+AR28=0,0,(AQ28+AR28)/AD28) -> 0 | BP28: =IF(AU28=0,0,AU28/AD28) -> 0 | BQ28: =IF(AT28=0,0,AT28/AD28) -> 1 | BR28: =IF(AW28=0,0,AW28/AD28) -> 0 | BS28: =IF(AZ28=0,0,AZ28/AD28) -> 0 | BT28: =IF(BB28+BD28+BF28=0,0,(BB28+BD28+BF28)/AD28) -> 0 | BU28: =IF(BJ28=0,0,BJ28/AD28) -> 0 | BV28: =SUM(BO28:BU28) -> 1 | BW28: =AD28/$AD$41 -> 0.016513829
A29: ='LUCERO RECOLETA'!A29 -> 46163 | C29: 3 | D29: =E28+1 -> 1027 | E29: =IF(C29="","",C29+D29-1) -> 1029 | H29: 736272.73 | I29: 154617.27 | K29: =H29+I29+J29 -> 890890 | O29: =N29*21% -> 0 | Q29: =N29+O29+P29 -> 0 | U29: =T29*21% -> 0 | W29: =T29+U29+V29 -> 0 | AA29: =Z29*21% -> 0 | AC29: =Z29+AA29+AB29 -> 0 | AD29: =+K29+Q29+W29-AC29 -> 890890 | AJ29: =AI29*220 -> 0 | AL29: =AK29*1200 -> 0 | AN29: =AM29*1200 -> 0 | AO29: =AF29+AG29+AH29+AJ29+AL29+AN29 -> 0 | AP29: =SUM(AO29-BK29) -> -880900 | AQ29: =160000+20000 -> 180000 | AT29: 685910 | AW29: 14990 | AZ29: =AY29*AZ$2 -> 0 | BB29: =BA29*BB$2 -> 0 | BD29: =BC29*BD$2 -> 0 | BF29: =BE29*BF$2 -> 0 | BH29: =BG29*BH$2 -> 0 | BJ29: =BI29*BJ$2 -> 0 | BK29: =+AQ29+AR29+AT29+AW29+AX29+AZ29+BB29+BD29+BF29+BH29+BJ29 -> 880900 | BL29: =AD29 -> 890890 | BM29: =SUM(BK29-BL29) -> -9990 | BO29: =IF(AQ29+AR29=0,0,(AQ29+AR29)/AD29) -> 0.20204515 | BP29: =IF(AU29=0,0,AU29/AD29) -> 0 | BQ29: =IF(AT29=0,0,AT29/AD29) -> 0.76991548 | BR29: =IF(AW29=0,0,AW29/AD29) -> 0.016825871 | BS29: =IF(AZ29=0,0,AZ29/AD29) -> 0 | BT29: =IF(BB29+BD29+BF29=0,0,(BB29+BD29+BF29)/AD29) -> 0 | BU29: =IF(BJ29=0,0,BJ29/AD29) -> 0 | BV29: =SUM(BO29:BU29) -> 0.98878649 | BW29: =AD29/$AD$41 -> 0.044584535
A30: ='LUCERO RECOLETA'!A30 -> 46164 | C30: 0 | D30: =E29+1 -> 1030 | E30: =IF(C30="","",C30+D30-1) -> 1029 | K30: =H30+I30+J30 -> 0 | O30: =N30*21% -> 0 | Q30: =N30+O30+P30 -> 0 | U30: =T30*21% -> 0 | W30: =T30+U30+V30 -> 0 | AA30: =Z30*21% -> 0 | AC30: =Z30+AA30+AB30 -> 0 | AD30: =+K30+Q30+W30-AC30 -> 0 | AJ30: =AI30*220 -> 0 | AL30: =AK30*1200 -> 0 | AN30: =AM30*1200 -> 0 | AO30: =AF30+AG30+AH30+AJ30+AL30+AN30 -> 0 | AP30: =SUM(AO30-BK30) -> 0 | AQ30: 0 | AT30: 0 | AW30: 0 | AZ30: =AY30*AZ$2 -> 0 | BB30: =BA30*1415 -> 0 | BD30: =BC30*BD$2 -> 0 | BF30: =BE30*BF$2 -> 0 | BH30: =BG30*BH$2 -> 0 | BJ30: =BI30*BJ$2 -> 0 | BK30: =+AQ30+AR30+AT30+AW30+AX30+AZ30+BB30+BD30+BF30+BH30+BJ30 -> 0 | BL30: =AD30 -> 0 | BM30: =SUM(BK30-BL30) -> 0 | BO30: =IF(AQ30+AR30=0,0,(AQ30+AR30)/AD30) -> 0 | BP30: =IF(AU30=0,0,AU30/AD30) -> 0 | BQ30: =IF(AT30=0,0,AT30/AD30) -> 0 | BR30: =IF(AW30=0,0,AW30/AD30) -> 0 | BS30: =IF(AZ30=0,0,AZ30/AD30) -> 0 | BT30: =IF(BB30+BD30+BF30=0,0,(BB30+BD30+BF30)/AD30) -> 0 | BU30: =IF(BJ30=0,0,BJ30/AD30) -> 0 | BV30: =SUM(BO30:BU30) -> 0 | BW30: =AD30/$AD$41 -> 0
A31: ='LUCERO RECOLETA'!A31 -> 46165 | C31: 10 | D31: =E30+1 -> 1030 | E31: =IF(C31="","",C31+D31-1) -> 1039 | H31: 1106497.4 | I31: 232364.47 | K31: =H31+I31+J31 -> 1338861.9 | O31: =N31*21% -> 0 | Q31: =N31+O31+P31 -> 0 | U31: =T31*21% -> 0 | W31: =T31+U31+V31 -> 0 | AA31: =Z31*21% -> 0 | AC31: =Z31+AA31+AB31 -> 0 | AD31: =+K31+Q31+W31-AC31 -> 1338861.9 | AJ31: =AI31*220 -> 0 | AL31: =AK31*1200 -> 0 | AN31: =AM31*1200 -> 0 | AO31: =AF31+AG31+AH31+AJ31+AL31+AN31 -> 0 | AP31: =SUM(AO31-BK31) -> -1338270 | AQ31: 0 | AT31: 1238870 | AW31: 0 | AZ31: =AY31*AZ$2 -> 0 | BA31: 70 | BB31: =BA31*1420 -> 99400 | BD31: =BC31*BD$2 -> 0 | BF31: =BE31*BF$2 -> 0 | BH31: =BG31*BH$2 -> 0 | BJ31: =BI31*BJ$2 -> 0 | BK31: =+AQ31+AR31+AT31+AW31+AX31+AZ31+BB31+BD31+BF31+BH31+BJ31 -> 1338270 | BL31: =AD31 -> 1338861.9 | BM31: =SUM(BK31-BL31) -> -591.9 | BO31: =IF(AQ31+AR31=0,0,(AQ31+AR31)/AD31) -> 0 | BP31: =IF(AU31=0,0,AU31/AD31) -> 0 | BQ31: =IF(AT31=0,0,AT31/AD31) -> 0.92531575 | BR31: =IF(AW31=0,0,AW31/AD31) -> 0 | BS31: =IF(AZ31=0,0,AZ31/AD31) -> 0 | BT31: =IF(BB31+BD31+BF31=0,0,(BB31+BD31+BF31)/AD31) -> 0.07424216 | BU31: =IF(BJ31=0,0,BJ31/AD31) -> 0 | BV31: =SUM(BO31:BU31) -> 0.99955791 | BW31: =AD31/$AD$41 -> 0.067003262
A32: ='LUCERO RECOLETA'!A32 -> 46166 | C32: 21 | D32: =E31+1 -> 1040 | E32: =IF(C32="","",C32+D32-1) -> 1060 | H32: 1338198.3 | I32: 281021.66 | K32: =H32+I32+J32 -> 1619220 | O32: =N32*21% -> 0 | Q32: =N32+O32+P32 -> 0 | U32: =T32*21% -> 0 | W32: =T32+U32+V32 -> 0 | AA32: =Z32*21% -> 0 | AC32: =Z32+AA32+AB32 -> 0 | AD32: =+K32+Q32+W32-AC32 -> 1619220 | AJ32: =AI32*220 -> 0 | AL32: =AK32*1200 -> 0 | AN32: =AM32*1200 -> 0 | AO32: =AF32+AG32+AH32+AJ32+AL32+AN32 -> 0 | AP32: =SUM(AO32-BK32) -> -1616000 | AQ32: =100000+20000 -> 120000 | AT32: 1251810 | AW32: 16990 | AZ32: =AY32*AZ$2 -> 0 | BA32: 160 | BB32: =BA32*1420 -> 227200 | BD32: =BC32*BD$2 -> 0 | BF32: =BE32*1400 -> 0 | BH32: =BG32*BH$2 -> 0 | BJ32: =BI32*BJ$2 -> 0 | BK32: =+AQ32+AR32+AT32+AW32+AX32+AZ32+BB32+BD32+BF32+BH32+BJ32 -> 1616000 | BL32: =AD32 -> 1619220 | BM32: =SUM(BK32-BL32) -> -3220 | BO32: =IF(AQ32+AR32=0,0,(AQ32+AR32)/AD32) -> 0.074109757 | BP32: =IF(AU32=0,0,AU32/AD32) -> 0 | BQ32: =IF(AT32=0,0,AT32/AD32) -> 0.77309445 | BR32: =IF(AW32=0,0,AW32/AD32) -> 0.010492706 | BS32: =IF(AZ32=0,0,AZ32/AD32) -> 0 | BT32: =IF(BB32+BD32+BF32=0,0,(BB32+BD32+BF32)/AD32) -> 0.14031447 | BU32: =IF(BJ32=0,0,BJ32/AD32) -> 0 | BV32: =SUM(BO32:BU32) -> 0.99801139 | BW32: =AD32/$AD$41 -> 0.081033765
A33: ='LUCERO RECOLETA'!A33 -> 46167 | C33: 12 | D33: =E32+1 -> 1061 | E33: =IF(C33="","",C33+D33-1) -> 1072 | H33: 921390 | I33: 193491.9 | K33: =H33+I33+J33 -> 1114881.9 | O33: =N33*21% -> 0 | Q33: =N33+O33+P33 -> 0 | U33: =T33*21% -> 0 | W33: =T33+U33+V33 -> 0 | AA33: =Z33*21% -> 0 | AC33: =Z33+AA33+AB33 -> 0 | AD33: =+K33+Q33+W33-AC33 -> 1114881.9 | AJ33: =AI33*220 -> 0 | AL33: =AK33*1200 -> 0 | AN33: =AM33*1200 -> 0 | AO33: =AF33+AG33+AH33+AJ33+AL33+AN33 -> 0 | AP33: =SUM(AO33-BK33) -> -1121900 | AQ33: 40000 | AT33: 1066910 | AW33: 14990 | AZ33: =AY33*AZ$2 -> 0 | BB33: =BA33*1410 -> 0 | BD33: =BC33*BD$2 -> 0 | BF33: =BE33*1420 -> 0 | BH33: =BG33*BH$2 -> 0 | BJ33: =BI33*BJ$2 -> 0 | BK33: =+AQ33+AR33+AT33+AW33+AX33+AZ33+BB33+BD33+BF33+BH33+BJ33 -> 1121900 | BL33: =AD33 -> 1114881.9 | BM33: =SUM(BK33-BL33) -> 7018.1 | BO33: =IF(AQ33+AR33=0,0,(AQ33+AR33)/AD33) -> 0.03587824 | BP33: =IF(AU33=0,0,AU33/AD33) -> 0 | BQ33: =IF(AT33=0,0,AT33/AD33) -> 0.95697132 | BR33: =IF(AW33=0,0,AW33/AD33) -> 0.01344537 | BS33: =IF(AZ33=0,0,AZ33/AD33) -> 0 | BT33: =IF(BB33+BD33+BF33=0,0,(BB33+BD33+BF33)/AD33) -> 0 | BU33: =IF(BJ33=0,0,BJ33/AD33) -> 0 | BV33: =SUM(BO33:BU33) -> 1.0062949 | BW33: =AD33/$AD$41 -> 0.055794196
A34: ='LUCERO RECOLETA'!A34 -> 46168 | C34: 5 | D34: =E33+1 -> 1073 | E34: =IF(C34="","",C34+D34-1) -> 1077 | H34: 542900.82 | I34: 114009.18 | K34: =H34+I34+J34 -> 656910 | O34: =N34*21% -> 0 | Q34: =N34+O34+P34 -> 0 | U34: =T34*21% -> 0 | W34: =T34+U34+V34 -> 0 | AA34: =Z34*21% -> 0 | AC34: =Z34+AA34+AB34 -> 0 | AD34: =+K34+Q34+W34-AC34 -> 656910 | AJ34: =AI34*220 -> 0 | AL34: =AK34*1200 -> 0 | AN34: =AM34*1200 -> 0 | AO34: =AF34+AG34+AH34+AJ34+AL34+AN34 -> 0 | AP34: =SUM(AO34-BK34) -> -668490 | AQ34: 0 | AT34: 69990 | AW34: 0 | AZ34: =AY34*AZ$3 -> 0 | BA34: 420 | BB34: =BA34*1425 -> 598500 | BD34: =BC34*BD$3 -> 0 | BF34: =BE34*BF$3 -> 0 | BH34: =BG34*BH$3 -> 0 | BJ34: =BI34*BJ$3 -> 0 | BK34: =+AQ34+AR34+AT34+AW34+AX34+AZ34+BB34+BD34+BF34+BH34+BJ34 -> 668490 | BL34: =AD34 -> 656910 | BM34: =SUM(BK34-BL34) -> 11580 | BO34: =IF(AQ34+AR34=0,0,(AQ34+AR34)/AD34) -> 0 | BP34: =IF(AU34=0,0,AU34/AD34) -> 0 | BQ34: =IF(AT34=0,0,AT34/AD34) -> 0.10654428 | BR34: =IF(AW34=0,0,AW34/AD34) -> 0 | BS34: =IF(AZ34=0,0,AZ34/AD34) -> 0 | BT34: =IF(BB34+BD34+BF34=0,0,(BB34+BD34+BF34)/AD34) -> 0.91108371 | BU34: =IF(BJ34=0,0,BJ34/AD34) -> 0 | BV34: =SUM(BO34:BU34) -> 1.017628 | BW34: =AD34/$AD$41 -> 0.032875021
A35: ='LUCERO RECOLETA'!A35 -> 46169 | C35: 5 | D35: =E34+1 -> 1078 | E35: =IF(C35="","",C35+D35-1) -> 1082 | H35: 356958.68 | I35: 74961.32 | K35: =H35+I35+J35 -> 431920 | O35: =N35*21% -> 0 | Q35: =N35+O35+P35 -> 0 | U35: =T35*21% -> 0 | W35: =T35+U35+V35 -> 0 | AA35: =Z35*21% -> 0 | AC35: =Z35+AA35+AB35 -> 0 | AD35: =+K35+Q35+W35-AC35 -> 431920 | AJ35: =AI35*220 -> 0 | AL35: =AK35*1200 -> 0 | AN35: =AM35*1200 -> 0 | AO35: =AF35+AG35+AH35+AJ35+AL35+AN35 -> 0 | AP35: =SUM(AO35-BK35) -> -431920 | AQ35: 0 | AT35: 431920 | AW35: 0 | AZ35: =AY35*AZ$3 -> 0 | BB35: =BA35*1460 -> 0 | BD35: =BC35*BD$3 -> 0 | BF35: =BE35*BF$3 -> 0 | BH35: =BG35*BH$3 -> 0 | BJ35: =BI35*BJ$3 -> 0 | BK35: =+AQ35+AR35+AT35+AW35+AX35+AZ35+BB35+BD35+BF35+BH35+BJ35 -> 431920 | BL35: =AD35 -> 431920 | BM35: =SUM(BK35-BL35) -> 0 | BO35: =IF(AQ35+AR35=0,0,(AQ35+AR35)/AD35) -> 0 | BP35: =IF(AU35=0,0,AU35/AD35) -> 0 | BQ35: =IF(AT35=0,0,AT35/AD35) -> 1 | BR35: =IF(AW35=0,0,AW35/AD35) -> 0 | BS35: =IF(AZ35=0,0,AZ35/AD35) -> 0 | BT35: =IF(BB35+BD35+BF35=0,0,(BB35+BD35+BF35)/AD35) -> 0 | BU35: =IF(BJ35=0,0,BJ35/AD35) -> 0 | BV35: =SUM(BO35:BU35) -> 1 | BW35: =AD35/$AD$41 -> 0.02161541
A36: ='LUCERO RECOLETA'!A36 -> 46170 | C36: 1 | D36: =E35+1 -> 1083 | E36: =IF(C36="","",C36+D36-1) -> 1083 | H36: 22305.78 | I36: 4684.22 | K36: =H36+I36+J36 -> 26990 | O36: =N36*21% -> 0 | Q36: =N36+O36+P36 -> 0 | U36: =T36*21% -> 0 | W36: =T36+U36+V36 -> 0 | AA36: =Z36*21% -> 0 | AC36: =Z36+AA36+AB36 -> 0 | AD36: =+K36+Q36+W36-AC36 -> 26990 | AJ36: =AI36*220 -> 0 | AL36: =AK36*1200 -> 0 | AN36: =AM36*1200 -> 0 | AO36: =AF36+AG36+AH36+AJ36+AL36+AN36 -> 0 | AP36: =SUM(AO36-BK36) -> -26990 | AQ36: 0 | AT36: 26990 | AW36: 0 | AZ36: =AY36*AZ$3 -> 0 | BB36: =BA36*BB$3 -> 0 | BD36: =BC36*BD$3 -> 0 | BF36: =BE36*BF$3 -> 0 | BH36: =BG36*BH$3 -> 0 | BJ36: =BI36*BJ$3 -> 0 | BK36: =+AQ36+AR36+AT36+AW36+AX36+AZ36+BB36+BD36+BF36+BH36+BJ36 -> 26990 | BL36: =AD36 -> 26990 | BM36: =SUM(BK36-BL36) -> 0 | BO36: =IF(AQ36+AR36=0,0,(AQ36+AR36)/AD36) -> 0 | BP36: =IF(AU36=0,0,AU36/AD36) -> 0 | BQ36: =IF(AT36=0,0,AT36/AD36) -> 1 | BR36: =IF(AW36=0,0,AW36/AD36) -> 0 | BS36: =IF(AZ36=0,0,AZ36/AD36) -> 0 | BT36: =IF(BB36+BD36+BF36=0,0,(BB36+BD36+BF36)/AD36) -> 0 | BU36: =IF(BJ36=0,0,BJ36/AD36) -> 0 | BV36: =SUM(BO36:BU36) -> 1 | BW36: =AD36/$AD$41 -> 0.0013507129
A37: ='LUCERO RECOLETA'!A37 -> 46171 | C37: 2 | D37: =E36+1 -> 1084 | E37: =IF(C37="","",C37+D37-1) -> 1085 | H37: 404925.62 | I37: 85034.38 | K37: =H37+I37+J37 -> 489960 | O37: =N37*21% -> 0 | Q37: =N37+O37+P37 -> 0 | U37: =T37*21% -> 0 | W37: =T37+U37+V37 -> 0 | AA37: =Z37*21% -> 0 | AC37: =Z37+AA37+AB37 -> 0 | AD37: =+K37+Q37+W37-AC37 -> 489960 | AJ37: =AI37*220 -> 0 | AL37: =AK37*1200 -> 0 | AN37: =AM37*1200 -> 0 | AO37: =AF37+AG37+AH37+AJ37+AL37+AN37 -> 0 | AP37: =SUM(AO37-BK37) -> -489720 | AQ37: 0 | AT37: 389970 | AW37: 0 | AZ37: =AY37*AZ$3 -> 0 | BA37: 70 | BB37: =BA37*1425 -> 99750 | BD37: =BC37*BD$3 -> 0 | BF37: =BE37*BF$3 -> 0 | BH37: =BG37*BH$3 -> 0 | BJ37: =BI37*BJ$3 -> 0 | BK37: =+AQ37+AR37+AT37+AW37+AX37+AZ37+BB37+BD37+BF37+BH37+BJ37 -> 489720 | BL37: =AD37 -> 489960 | BM37: =SUM(BK37-BL37) -> -240 | BO37: =IF(AQ37+AR37=0,0,(AQ37+AR37)/AD37) -> 0 | BP37: =IF(AU37=0,0,AU37/AD37) -> 0 | BQ37: =IF(AT37=0,0,AT37/AD37) -> 0.79592212 | BR37: =IF(AW37=0,0,AW37/AD37) -> 0 | BS37: =IF(AZ37=0,0,AZ37/AD37) -> 0 | BT37: =IF(BB37+BD37+BF37=0,0,(BB37+BD37+BF37)/AD37) -> 0.20358805 | BU37: =IF(BJ37=0,0,BJ37/AD37) -> 0 | BV37: =SUM(BO37:BU37) -> 0.99951016 | BW37: =AD37/$AD$41 -> 0.024520018
A38: ='LUCERO RECOLETA'!A38 -> 46172 | C38: 8 | D38: =E37+1 -> 1086 | E38: =IF(C38="","",C38+D38-1) -> 1093 | H38: 559438 | I38: 117482 | K38: =H38+I38+J38 -> 676920 | O38: =N38*21% -> 0 | Q38: =N38+O38+P38 -> 0 | U38: =T38*21% -> 0 | W38: =T38+U38+V38 -> 0 | AA38: =Z38*21% -> 0 | AC38: =Z38+AA38+AB38 -> 0 | AD38: =+K38+Q38+W38-AC38 -> 676920 | AJ38: =AI38*220 -> 0 | AL38: =AK38*1200 -> 0 | AN38: =AM38*1200 -> 0 | AO38: =AF38+AG38+AH38+AJ38+AL38+AN38 -> 0 | AP38: =SUM(AO38-BK38) -> -676920 | AQ38: 0 | AS38: =AG38 | AT38: 676920 | AW38: 0 | AZ38: =AY38*AZ$3 -> 0 | BB38: =BA38*1400 -> 0 | BD38: =BC38*BD$3 -> 0 | BF38: =BE38*BF$3 -> 0 | BH38: =BG38*BH$3 -> 0 | BJ38: =BI38*BJ$3 -> 0 | BK38: =+AQ38+AR38+AT38+AW38+AX38+AZ38+BB38+BD38+BF38+BH38+BJ38 -> 676920 | BL38: =AD38 -> 676920 | BM38: =SUM(BK38-BL38) -> 0 | BO38: =IF(AQ38+AR38=0,0,(AQ38+AR38)/AD38) -> 0 | BP38: =IF(AU38=0,0,AU38/AD38) -> 0 | BQ38: =IF(AT38=0,0,AT38/AD38) -> 1 | BR38: =IF(AW38=0,0,AW38/AD38) -> 0 | BS38: =IF(AZ38=0,0,AZ38/AD38) -> 0 | BT38: =IF(BB38+BD38+BF38=0,0,(BB38+BD38+BF38)/AD38) -> 0 | BU38: =IF(BJ38=0,0,BJ38/AD38) -> 0 | BV38: =SUM(BO38:BU38) -> 1 | BW38: =AD38/$AD$41 -> 0.03387642
A39: ='LUCERO RECOLETA'!A39 -> 46173 | C39: 14 | D39: =E38+1 -> 1094 | E39: =IF(C39="","",C39+D39-1) -> 1107 | H39: 1415553.7 | I39: 297266.28 | K39: =H39+I39+J39 -> 1712820 | O39: =N39*21% -> 0 | Q39: =N39+O39+P39 -> 0 | U39: =T39*21% -> 0 | W39: =T39+U39+V39 -> 0 | AA39: =Z39*21% -> 0 | AC39: =Z39+AA39+AB39 -> 0 | AD39: =+K39+Q39+W39-AC39 -> 1712820 | AJ39: =AI39*220 -> 0 | AL39: =AK39*1200 -> 0 | AN39: =AM39*1200 -> 0 | AQ39: 228000 | AT39: 1271840 | AW39: 0 | AZ39: =AY39*AZ$3 -> 0 | BA39: 140 | BB39: =BA39*1425 -> 199500 | BD39: =BC39*BD$3 -> 0 | BF39: =BE39*BF$3 -> 0 | BH39: =BG39*BH$3 -> 0 | BJ39: =BI39*BJ$3 -> 0 | BK39: =+AQ39+AR39+AT39+AW39+AX39+AZ39+BB39+BD39+BF39+BH39+BJ39 -> 1699340 | BL39: =AD39 -> 1712820 | BM39: =SUM(BK39-BL39) -> -13480 | BO39: =IF(AQ39+AR39=0,0,(AQ39+AR39)/AD39) -> 0.13311381 | BP39: =IF(AU39=0,0,AU39/AD39) -> 0 | BQ39: =IF(AT39=0,0,AT39/AD39) -> 0.74254154 | BR39: =IF(AW39=0,0,AW39/AD39) -> 0 | BS39: =IF(AZ39=0,0,AZ39/AD39) -> 0 | BT39: =IF(BB39+BD39+BF39=0,0,(BB39+BD39+BF39)/AD39) -> 0.11647459 | BU39: =IF(BJ39=0,0,BJ39/AD39) -> 0 | BV39: =SUM(BO39:BU39) -> 0.99212994 | BW39: =AD39/$AD$41 -> 0.085717972
D40: =E39+1 -> 1108 | E40: =IF(C40="","",C40+D40-1) | I40: =H40*21% -> 0 | K40: =H40+I40+J40 -> 0 | O40: =N40*21% -> 0 | U40: =T40*21% -> 0 | X40: 0 | AA40: =Z40*21% -> 0 | AZ40: =AY40*AZ$3 -> 0 | BB40: =BA40*BB$3 -> 0 | BD40: =BC40*BD$3 -> 0 | BF40: =BE40*BF$3 -> 0 | BH40: =BG40*BH$3 -> 0 | BJ40: =BI40*BJ$3 -> 0 | BK40: =+AQ40+AR40+AT40+AW40+AX40+AZ40+BB40+BD40+BF40+BH40+BJ40 -> 0 | BM40: =SUM(BK40-BL40) -> 0 | BO40: =IF(AQ40+AR40=0,0,(AQ40+AR40)/AD40) -> 0 | BP40: =IF(AU40=0,0,AU40/AD40) -> 0 | BQ40: =IF(AT40=0,0,AT40/AD40) -> 0 | BR40: =IF(AW40=0,0,AW40/AD40) -> 0 | BS40: =IF(AZ40=0,0,AZ40/AD40) -> 0 | BT40: =IF(BB40+BD40+BF40=0,0,(BB40+BD40+BF40)/AD40) -> 0 | BU40: =IF(BJ40=0,0,BJ40/AD40) -> 0 | BV40: =SUM(BO40:BU40) -> 0 | BW40: =AD40/$AD$41 -> 0
A41: TOTALES | B41: =MAX(B9:B40) -> 0 | C41: =SUM(C9:C40) -> 172 | D41: =MIN(D9:D40) -> 936 | E41: =MAX(E9:E40) -> 1107 | F41: =SUM(F9:F40) -> 0 | G41: =SUM(G9:G40) -> 0 | H41: =SUM(H9:H40) -> 16514083 | I41: =SUM(I9:I40) -> 3467957.6 | K41: =SUM(K9:K40) -> 19982041 | L41: =MIN(L9:L40) -> 0 | M41: =MAX(M9:M40) -> 0 | N41: =SUM(N9:N40) -> 0 | O41: =SUM(O9:O40) -> 0 | Q41: =SUM(Q9:Q40) -> 0 | R41: =MIN(R9:R40) -> 0 | S41: =MAX(S9:S40) -> 0 | T41: =SUM(T9:T40) -> 0 | U41: =SUM(U9:U40) -> 0 | W41: =SUM(W9:W40) -> 0 | X41: =MIN(X9:X40) -> 0 | Y41: =MAX(Y9:Y40) -> 0 | Z41: =SUM(Z9:Z40) -> 0 | AA41: =SUM(AA9:AA40) -> 0 | AC41: =SUM(AC9:AC40) -> 0 | AD41: =SUM(AD9:AD40) -> 19982041 | AE41: =SUM(AE9:AE38) -> 0 | AF41: =SUM(AF9:AF38) -> 0 | AG41: =SUM(AG9:AG38) -> 0 | AH41: =SUM(AH9:AH38) -> 0 | AI41: =SUM(AI9:AI38) -> 0 | AJ41: =SUM(AJ9:AJ38) -> 0 | AK41: =SUM(AK9:AK38) -> 0 | AL41: =SUM(AL9:AL38) -> 0 | ... AP41: =SUM(AP9:AP38) -> -18287295 | AQ41: =SUM(AQ9:AQ40) -> 1370000 | AR41: =SUM(AR9:AR40) -> 0 | AS41: =SUM(AS9:AS40) -> 0 | AT41: =SUM(AT9:AT40) -> 16971955 | AU41: =SUM(AU9:AU40) -> 0 | AV41: =SUM(AV9:AV40) -> 0 | AW41: =SUM(AW9:AW40) -> 306930 | AX41: =SUM(AX9:AX40) -> 0 | ... BM41: =SUM(BM9:BM40) -> 4594.3 | BO41: =IF(AD41=0,0,(AQ41+AR41)/AD41) -> 0.068561566 | BP41: =IF(AD41=0,0,(AU41)/AD41) -> 0 | BQ41: =IF(AT41=0,0,AT41/AD41) -> 0.84936045 | BR41: =IF($AD$41=0,0,(AW41)/$AD$41) -> 0.015360293 | BS41: =IF($AD$41=0,0,(AX41)/$AD$41) -> 0 | BT41: =IF($AD$41=0,0,(BB41+BD41+BF41)/AD41) -> 0.066947617 | BU41: =IF($AD$41=0,0,BJ41/AD41) -> 0 | BV41: =SUM(BO41:BU41) -> 1.0002299 | BW41: =AD41/$AD$41 -> 1
D42: 564 | R42: 1 | X42: 2
A43: CONTROL | B43: =B9-B42 -> 0 | D43: =D41-D42 -> 372 | L43: =L41-L42 -> 0 | R43: =R41-R42 -> -1 | X43: =X41-X42 -> -2 | AE43: 0 | AF43: 0 | AG43: 0 | AH43: 0 | AI43: 0 | AJ43: 0 | AK43: 0 | AL43: 0 | AM43: 0 | AN43: 0 | AO43: 0
AC46: TOTAL | AD46: =AD41+AD45 -> 19982041 | AQ46: $ Efectivo | AR46: $ Deposito / PIX | AS46: TARJETA DEBITO | AT46: TARJETA CREDITO | AU46: Mercado Pago / TF | AV46: Real | AW46: Dólares | AX46: Euros
AP47: RESUMEN COBRANZA | AQ47: =AQ41 -> 1370000 | AR47: =AR41 -> 0 | AS47: =AU41 -> 0 | AT47: =AV41 -> 0 | AU47: =AW41 -> 306930 | AV47: =AZ41 -> 0 | AW47: =BD41+BF41+BH41+BB41 -> 1337750 | AX47: =BJ41 -> 0
AQ48: =AQ47/$AD$41 -> 0.068561566 | AR48: =AR47/$AD$41 -> 0 | AS48: =AS47/$AD$41 -> 0 | AT48: =AT47/$AD$41 -> 0 | AU48: =AU47/$AD$41 -> 0.015360293 | AV48: =AV47/$AD$41 -> 0 | AW48: =AW47/$AD$41 -> 0.066947617 | AX48: =AX47/$AD$41 -> 0

Sheet AS SAN TELMO
AS1: Cotizaciones | AX1: De | AY1: Hasta
A2: Empresa: EL LUCERO CUERO S.A. | AS2: ='LUCERO RECOLETA'!AS2 | AX2: ='LUCERO RECOLETA'!AX2 | AY2: ='LUCERO RECOLETA'!AY2 | AZ2: ='LUCERO RECOLETA'!AZ2 | BA2: ='LUCERO RECOLETA'!BA2 | BB2: ='LUCERO RECOLETA'!BB2 | BC2: ='LUCERO RECOLETA'!BC2 | BD2: ='LUCERO RECOLETA'!BD2 | BE2: ='LUCERO RECOLETA'!BE2 | ... BJ2: ='LUCERO RECOLETA'!BJ2
A3: Sucursal: ACCESORIES STORE SAN TELMO - Bolivar 970 (loc 120/121) - CP C1066AAT | AS3: ='LUCERO RECOLETA'!AS3 | AX3: ='LUCERO RECOLETA'!AX3 | AY3: ='LUCERO RECOLETA'!AY3 | AZ3: ='LUCERO RECOLETA'!AZ3 | BA3: ='LUCERO RECOLETA'!BA3 | BB3: ='LUCERO RECOLETA'!BB3 | BC3: ='LUCERO RECOLETA'!BC3 | BD3: ='LUCERO RECOLETA'!BD3 | BE3: ='LUCERO RECOLETA'!BE3 | ... BJ3: ='LUCERO RECOLETA'!BJ3
