Workbook

Sheet Agosto-real
C1: =1335 -> 1335 | J1: Evolución del porcentaje de los gastos en relación con las ventas desde enero 2025
B2: Tienda_Zona | C2: Venta | D2: Sueldos | E2: Alquileres | F2: Expensas | G2: Total alquileres + expensas | H2: Otros gastos | J2: Tienda_Zona | K2: Venta | L2: Sueldos | M2: Alquileres + expensas | N2: Otros gastos
B3: Florida | C3: 45735238 | D3: 5359007 | E3: 6550000 | F3: 407740.5 | G3: =E3+F3 -> 6957740.5 | H3: 1845033.1 | J3: Florida
B4: Recoleta | C4: 21770316 | D4: 3174723 | E4: 1299988.6 | F4: 1901854.1 | G4: =E4+F4 -> 3201842.7 | H4: 509583.35 | J4: Recoleta
B5: Güemes | C5: 4168817.5 | D5: 1914315.8 | E5: 599275.1 | F5: 328003.06 | G5: =E5+F5 -> 927278.16 | H5: 315055 | J5: Güemes
B6: Lucero_Zona Centro | C6: =SUM(C3:C5) -> 71674372 | D6: =SUM(D3:D5) -> 10448046 | E6: =SUM(E3:E5) -> 8449263.7 | F6: =SUM(F3:F5) -> 2637597.7 | G6: =SUM(G3:G5) -> 11086861 | H6: =SUM(H3:H5) -> 2669671.4 | J6: Lucero_Zona Centro
B7: San Telmo | C7: 34037280 | D7: 3084694.7 | E7: 1741513.4 | F7: 573285.05 | G7: =E7+F7 -> 2314798.5 | H7: 276404.91 | J7: San Telmo
B8: French | C8: 16141623 | D8: 2609720.2 | E8: 667200 | F8: 242602.21 | G8: =E8+F8 -> 909802.21 | H8: 462502.76 | J8: French
B9: San Telmo 2 | C9: 10898600 | D9: 2415229.8 | E9: 887700 | F9: 573285.05 | G9: =E9+F9 -> 1460985.1 | H9: 444315.8 | J9: San Telmo 2
B10: Lucero_Zona San Telmo | C10: =SUM(C7:C9) -> 61077503 | D10: =SUM(D7:D9) -> 8109644.7 | E10: =SUM(E7:E9) -> 3296413.4 | F10: =SUM(F7:F9) -> 1389172.3 | G10: =SUM(G7:G9) -> 4685585.8 | H10: =SUM(H7:H9) -> 1183223.5 | J10: Lucero_Zona San Telmo
B11: AS San Telmo | C11: 14676490 | D11: 3434064.9 | E11: 1569765 | F11: 1146570 | G11: =E11+F11 -> 2716335 | H11: 2896000 | J11: AS San Telmo
B13: Tienda_Zona | C13: Sueldos | D13: Alquileres | E13: Expensas | F13: Total alquileres + expensas | G13: Otros gastos | K13: Proyectado | L13: Real | M13: Desvío
B14: Florida | C14: =D3/$C3 -> 0.11717457 | D14: =E3/$C3 -> 0.14321561 | E14: =F3/$C3 -> 0.0089152372 | F14: =G3/$C3 -> 0.15213085 | G14: =H3/$C3 -> 0.040341608 | J14: Sueldos | K14: =SUM(K15:K17) -> 21671969 | L14: =SUM(L15:L17) -> 21991755 | M14: =L14/K14-1 -> 0.014755743
B15: Recoleta | C15: =D4/$C4 -> 0.14582806 | D15: =E4/$C4 -> 0.059713815 | E15: =F4/$C4 -> 0.08735997 | F15: =G4/$C4 -> 0.14707378 | G15: =H4/$C4 -> 0.023407256 | J15: Lucero_Zona Centro | K15: 10350791 | L15: 10448046 | M15: =L15/K15-1 -> 0.0093958476
B16: Güemes | C16: =D5/$C5 -> 0.45919875 | D16: =E5/$C5 -> 0.14375182 | E16: =F5/$C5 -> 0.07868012 | F16: =G5/$C5 -> 0.22243194 | G16: =H5/$C5 -> 0.075574189 | J16: Lucero_Zona San Telmo | K16: 8010447 | L16: 8109644.7 | M16: =L16/K16-1 -> 0.01238354
B17: Lucero_Zona Centro | C17: =D6/$C6 -> 0.14577101 | D17: =E6/$C6 -> 0.11788403 | E17: =F6/$C6 -> 0.036799732 | F17: =G6/$C6 -> 0.15468376 | G17: =H6/$C6 -> 0.037247225 | J17: AS San Telmo | K17: 3310731.1 | L17: 3434064.9 | M17: =L17/K17-1 -> 0.037252758
B18: San Telmo | C18: =D7/$C7 -> 0.090626945 | D18: =E7/$C7 -> 0.051164883 | E18: =F7/$C7 -> 0.016842857 | F18: =G7/$C7 -> 0.06800774 | G18: =H7/$C7 -> 0.0081206521
B19: French | C19: =D8/$C8 -> 0.16167645 | D19: =E8/$C8 -> 0.041334134 | E19: =F8/$C8 -> 0.015029605 | F19: =G8/$C8 -> 0.056363738 | G19: =H8/$C8 -> 0.028652804
B20: San Telmo 2 | C20: =D9/$C9 -> 0.22160918 | D20: =E9/$C9 -> 0.081450828 | E20: =F9/$C9 -> 0.052601715 | F20: =G9/$C9 -> 0.13405254 | G20: =H9/$C9 -> 0.040768154
B21: Lucero_Zona San Telmo | C21: =D10/$C10 -> 0.1327763 | D21: =E10/$C10 -> 0.053970992 | E21: =F10/$C10 -> 0.022744419 | F21: =G10/$C10 -> 0.076715411 | G21: =H10/$C10 -> 0.019372493
B22: AS San Telmo | C22: =D11/$C11 -> 0.23398407 | D22: =E11/$C11 -> 0.10695779 | E22: =F11/$C11 -> 0.078122903 | F22: =G11/$C11 -> 0.1850807 | G22: =H11/$C11 -> 0.19732238

Sheet Septiembre_proy
C1: =1335 -> 1335
B2: Tienda_Zona | C2: Venta proyectada | D2: Sueldos | E2: Incentivos por venta | F2: Total gasto de personal | G2: Alquileres | H2: Expensas | I2: Total alquileres + expensas
B3: Florida | C3: 49500000 | D3: 4973400 | E3: =C3*0.014293 -> 707503.5 | F3: =D3+E3 -> 5680903.5 | G3: 6875000 | H3: 515040.5 | I3: =G3+H3 -> 7390040.5
B4: Recoleta | C4: 23500000 | D4: 3039300 | E4: =C4*0.014293 -> 335885.5 | F4: =D4+E4 -> 3375185.5 | G4: 1495384.8 | H4: 1912694.2 | I4: =G4+H4 -> 3408079.1
B5: Lucero_Zona Centro | C5: =SUM(C3:C4) -> 73000000 | D5: =SUM(D3:D4) -> 8012700 | E5: =SUM(E3:E4) -> 1043389 | F5: =SUM(F3:F4) -> 9056089 | G5: =SUM(G3:G4) -> 8370384.8 | H5: =SUM(H3:H4) -> 2427734.7 | I5: =SUM(I3:I4) -> 10798120
B6: San Telmo | C6: 36000000 | D6: 2947200 | E6: =C6*0.014293 -> 514548 | F6: =D6+E6 -> 3461748 | G6: 2268093.2 | H6: 573285.05 | I6: =G6+H6 -> 2841378.3
B7: French | C7: 17000000 | D7: 2394600 | E7: =C7*0.014293 -> 242981 | F7: =D7+E7 -> 2637581 | G7: 718564 | H7: 242602.21 | I7: =G7+H7 -> 961166.21
B8: Lucero_Zona San Telmo | C8: =SUM(C6:C7) -> 53000000 | D8: =SUM(D6:D7) -> 5341800 | E8: =SUM(E6:E7) -> 757529 | F8: =SUM(F6:F7) -> 6099329 | G8: =SUM(G6:G7) -> 2986657.2 | H8: =SUM(H6:H7) -> 815887.26 | I8: =SUM(I6:I7) -> 3802544.5
B9: Güemes | C9: 4700000 | D9: 1823580 | E9: =C9*0.014293 -> 67177.1 | F9: =D9+E9 -> 1890757.1 | G9: 599544 | H9: 328003.06 | I9: =G9+H9 -> 927547.06
B10: San Telmo 2 | C10: 11500000 | D10: 2210400 | E10: =C10*0.014293 -> 164369.5 | F10: =D10+E10 -> 2374769.5 | G10: 897405.79 | H10: 573285.05 | I10: =G10+H10 -> 1470690.8
B11: Lucero_Güemes+San Telmo 2 | C11: =SUM(C9:C10) -> 16200000 | D11: =SUM(D9:D10) -> 4033980 | E11: =SUM(E9:E10) -> 231546.6 | F11: =SUM(F9:F10) -> 4265526.6 | G11: =SUM(G9:G10) -> 1496949.8 | H11: =SUM(H9:H10) -> 901288.11 | I11: =SUM(I9:I10) -> 2398237.9
B12: AS San Telmo | C12: 16000000 | D12: 2947200 | E12: =C12*0.014293 -> 228688 | F12: =D12+E12 -> 3175888 | G12: 1085858.2 | H12: 1146570 | I12: =G12+H12 -> 2232428.2
B13: Total general | C13: =+C5+C8+C11+C12 -> 158200000 | D13: =+D5+D8+D11+D12 -> 20335680 | E13: =+E5+E8+E11+E12 -> 2261152.6 | F13: =+F5+F8+F11+F12 -> 22596833 | G13: =+G5+G8+G11+G12 -> 13939850 | H13: =+H5+H8+H11+H12 -> 5291480.1 | I13: =+I5+I8+I11+I12 -> 19231330
B15: Tienda_Zona | C15: Sueldos | D15: Incentivos por venta | E15: Total gasto de personal | F15: Alquileres | G15: Expensas | H15: Total alquileres + expensas
B16: Florida | C16: =D3/$C3 -> 0.10047273 | D16: =E3/$C3 -> 0.014293 | E16: =F3/$C3 -> 0.11476573 | F16: =G3/$C3 -> 0.13888889 | G16: =H3/$C3 -> 0.010404859 | H16: =I3/$C3 -> 0.14929375
B17: Recoleta | C17: =D4/$C4 -> 0.12933191 | D17: =E4/$C4 -> 0.014293 | E17: =F4/$C4 -> 0.14362491 | F17: =G4/$C4 -> 0.063633397 | G17: =H4/$C4 -> 0.081391243 | H17: =I4/$C4 -> 0.14502464
B18: Lucero_Zona Centro | C18: =D5/$C5 -> 0.10976301 | D18: =E5/$C5 -> 0.014293 | E18: =F5/$C5 -> 0.12405601 | F18: =G5/$C5 -> 0.11466281 | G18: =H5/$C5 -> 0.03325664 | H18: =I5/$C5 -> 0.14791945
B19: San Telmo | C19: =D6/$C6 -> 0.081866667 | D19: =E6/$C6 -> 0.014293 | E19: =F6/$C6 -> 0.096159667 | F19: =G6/$C6 -> 0.06300259 | G19: =H6/$C6 -> 0.015924585 | H19: =I6/$C6 -> 0.078927174
B20: French | C20: =D7/$C7 -> 0.14085882 | D20: =E7/$C7 -> 0.014293 | E20: =F7/$C7 -> 0.15515182 | F20: =G7/$C7 -> 0.042268471 | G20: =H7/$C7 -> 0.014270718 | H20: =I7/$C7 -> 0.056539189
B21: Lucero_Zona San Telmo | C21: =D8/$C8 -> 0.10078868 | D21: =E8/$C8 -> 0.014293 | E21: =F8/$C8 -> 0.11508168 | F21: =G8/$C8 -> 0.056352023 | G21: =H8/$C8 -> 0.015394099 | H21: =I8/$C8 -> 0.071746122
B22: Güemes | C22: =D9/$C9 -> 0.38799574 | D22: =E9/$C9 -> 0.014293 | E22: =F9/$C9 -> 0.40228874 | F22: =G9/$C9 -> 0.12756255 | G22: =H9/$C9 -> 0.069787885 | H22: =I9/$C9 -> 0.19735044
B23: San Telmo 2 | C23: =D10/$C10 -> 0.1922087 | D23: =E10/$C10 -> 0.014293 | E23: =F10/$C10 -> 0.2065017 | F23: =G10/$C10 -> 0.078035286 | G23: =H10/$C10 -> 0.049850874 | H23: =I10/$C10 -> 0.12788616
B24: Lucero_Güemes+San Telmo 2 | C24: =D11/$C11 -> 0.24901111 | D24: =E11/$C11 -> 0.014293 | E24: =F11/$C11 -> 0.26330411 | F24: =G11/$C11 -> 0.092404308 | G24: =H11/$C11 -> 0.055635069 | H24: =I11/$C11 -> 0.14803938
B25: AS San Telmo | C25: =D12/$C12 -> 0.1842 | D25: =E12/$C12 -> 0.014293 | E25: =F12/$C12 -> 0.198493 | F25: =G12/$C12 -> 0.067866136 | G25: =H12/$C12 -> 0.071660626 | H25: =I12/$C12 -> 0.13952676
B26: Total general | C26: =D13/$C13 -> 0.12854412 | D26: =E13/$C13 -> 0.014293 | E26: =F13/$C13 -> 0.14283712 | F26: =G13/$C13 -> 0.08811536 | G26: =H13/$C13 -> 0.033448041 | H26: =I13/$C13 -> 0.1215634

Sheet Septiembre_real
C1: =1335 -> 1335
B2: Tienda_Zona | C2: Venta real | D2: Sueldos | E2: Alquileres | F2: Expensas | G2: Total alquileres + expensas | H2: Otros gastos
B3: Florida | C3: 62713661 | D3: 5345060 | E3: 7000000 | F3: 300440.5 | G3: =E3+F3 -> 7300440.5 | H3: 1773489.2
B4: Recoleta | C4: 22885150 | D4: 3082266 | E4: 1448355.7 | F4: 1948016.5 | G4: =E4+F4 -> 3396372.2 | H4: 209674.47
B5: Lucero_Zona Centro | C5: =SUM(C3:C4) -> 85598811 | D5: =SUM(D3:D4) -> 8427326 | E5: =SUM(E3:E4) -> 8448355.7 | F5: =SUM(F3:F4) -> 2248457 | G5: =SUM(G3:G4) -> 10696813 | H5: =SUM(H3:H4) -> 1983163.6
B6: San Telmo | C6: 33133540 | D6: 2263663 | E6: 2250334.6 | F6: 531320.8 | G6: =E6+F6 -> 2781655.4 | H6: 200815.63
B7: French | C7: 19997040 | D7: 2444318 | E7: 703000 | F7: 220840 | G7: =E7+F7 -> 923840 | H7: 419343.85
B8: Lucero_Zona San Telmo | C8: =SUM(C6:C7) -> 53130580 | D8: =SUM(D6:D7) -> 4707981 | E8: =SUM(E6:E7) -> 2953334.6 | F8: =SUM(F6:F7) -> 752160.8 | G8: =SUM(G6:G7) -> 3705495.4 | H8: =SUM(H6:H7) -> 620159.48
B9: Güemes | C9: 4814090 | D9: 1976546 | E9: 599275.1 | F9: 338831.14 | G9: =E9+F9 -> 938106.24 | H9: 159124
B10: San Telmo 2 | C10: 12808500 | D10: 2087438 | E10: 900710.7 | F10: 531320.8 | G10: =E10+F10 -> 1432031.5 | H10: 189129.62
B11: Lucero_Güemes+San Telmo 2 | C11: =SUM(C9:C10) -> 17622590 | D11: =SUM(D9:D10) -> 4063984 | E11: =SUM(E9:E10) -> 1499985.8 | F11: =SUM(F9:F10) -> 870151.94 | G11: =SUM(G9:G10) -> 2370137.7 | H11: =SUM(H9:H10) -> 348253.62
B12: AS San Telmo | C12: 12870480 | D12: 2855608 | E12: 1091639.7 | F12: 1062641.6 | G12: =E12+F12 -> 2154281.3 | H12: 2038403.4
B13: Total general | C13: =+C5+C8+C11+C12 -> 1.6922246e+08 | D13: =+D5+D8+D11+D12 -> 20054899 | E13: =+E5+E8+E11+E12 -> 13993316 | F13: =+F5+F8+F11+F12 -> 4933411.3 | G13: =+G5+G8+G11+G12 -> 18926727 | H13: =+H5+H8+H11+H12 -> 4989980.2
B15: Tienda_Zona | C15: Sueldos | D15: Alquileres | E15: Expensas | F15: Total alquileres + expensas | G15: Otros gastos
B16: Florida | C16: =D3/$C3 -> 0.085229596 | D16: =E3/$C3 -> 0.11161842 | E16: =F3/$C3 -> 0.0047906707 | F16: =G3/$C3 -> 0.11640909 | G16: =H3/$C3 -> 0.028279152
B17: Recoleta | C17: =D4/$C4 -> 0.13468411 | D17: =E4/$C4 -> 0.063288015 | E17: =F4/$C4 -> 0.085121422 | F17: =G4/$C4 -> 0.14840944 | G17: =H4/$C4 -> 0.0091620317
B18: Lucero_Zona Centro | C18: =D5/$C5 -> 0.098451438 | D18: =E5/$C5 -> 0.098697115 | E18: =F5/$C5 -> 0.026267386 | F18: =G5/$C5 -> 0.1249645 | G18: =H5/$C5 -> 0.023168121
B19: San Telmo | C19: =D6/$C6 -> 0.068319383 | D19: =E6/$C6 -> 0.067917121 | E19: =F6/$C6 -> 0.016035739 | F19: =G6/$C6 -> 0.08395286 | G19: =H6/$C6 -> 0.0060607961
B20: French | C20: =D7/$C7 -> 0.12223399 | D20: =E7/$C7 -> 0.035155203 | E20: =F7/$C7 -> 0.011043634 | F20: =G7/$C7 -> 0.046198837 | G20: =H7/$C7 -> 0.020970296
B21: Lucero_Zona San Telmo | C21: =D8/$C8 -> 0.088611511 | D21: =E8/$C8 -> 0.055586343 | E21: =F8/$C8 -> 0.014156834 | F21: =G8/$C8 -> 0.069743177 | G21: =H8/$C8 -> 0.011672364
B22: Güemes | C22: =D9/$C9 -> 0.41057521 | D22: =E9/$C9 -> 0.12448357 | E22: =F9/$C9 -> 0.070383217 | F22: =G9/$C9 -> 0.19486678 | G22: =H9/$C9 -> 0.033053807
B23: San Telmo 2 | C23: =D10/$C10 -> 0.16297287 | D23: =E10/$C10 -> 0.070321326 | E23: =F10/$C10 -> 0.041481891 | F23: =G10/$C10 -> 0.11180322 | G23: =H10/$C10 -> 0.014765946
B24: Lucero_Güemes+San Telmo 2 | C24: =D11/$C11 -> 0.23061219 | D24: =E11/$C11 -> 0.085117216 | E24: =F11/$C11 -> 0.049377075 | F24: =G11/$C11 -> 0.13449429 | G24: =H11/$C11 -> 0.019761773
B25: AS San Telmo | C25: =D12/$C12 -> 0.22187269 | D25: =E12/$C12 -> 0.084817326 | E25: =F12/$C12 -> 0.082564255 | F25: =G12/$C12 -> 0.16738158 | G25: =H12/$C12 -> 0.1583782
B26: Total general | C26: =D13/$C13 -> 0.11851204 | D26: =E13/$C13 -> 0.082691835 | E26: =F13/$C13 -> 0.029153407 | F26: =G13/$C13 -> 0.11184524 | G26: =H13/$C13 -> 0.029487694

Sheet Octubre_proy
C1: =1335 -> 1335
B2: Tienda_Zona | C2: Venta proyectada | D2: Sueldos | E2: Incentivos por venta | F2: Total gasto de personal | G2: Alquileres | H2: Expensas | I2: Total alquileres + expensas
B3: Florida | C3: 68551715 | D3: 5328900 | E3: =C3*0.014293 -> 979809.66 | F3: =D3+E3 -> 6308709.7 | G3: 7000000 | H3: 515040.5 | I3: =G3+H3 -> 7515040.5
B4: Recoleta | C4: 28417188 | D4: 3256550 | E4: =C4*0.014293 -> 406166.87 | F4: =D4+E4 -> 3662716.9 | G4: 1575471 | H4: 2045417 | I4: =G4+H4 -> 3620888
B5: Lucero_Zona Centro | C5: =SUM(C3:C4) -> 96968903 | D5: =SUM(D3:D4) -> 8585450 | E5: =SUM(E3:E4) -> 1385976.5 | F5: =SUM(F3:F4) -> 9971426.5 | G5: =SUM(G3:G4) -> 8575471 | H5: =SUM(H3:H4) -> 2560457.5 | I5: =SUM(I3:I4) -> 11135928
B6: San Telmo | C6: 53365632 | D6: 2979600 | E6: =C6*0.014293 -> 762754.98 | F6: =D6+E6 -> 3742355 | G6: 2205191 | H6: 557887 | I6: =G6+H6 -> 2763078
B7: French | C7: 24216000 | D7: 2540300 | E7: =C7*0.014293 -> 346119.29 | F7: =D7+E7 -> 2886419.3 | G7: 703000 | H7: 231882 | I7: =G7+H7 -> 934882
B8: Lucero_Zona San Telmo | C8: =SUM(C6:C7) -> 77581632 | D8: =SUM(D6:D7) -> 5519900 | E8: =SUM(E6:E7) -> 1108874.3 | F8: =SUM(F6:F7) -> 6628774.3 | G8: =SUM(G6:G7) -> 2908191 | H8: =SUM(H6:H7) -> 789769 | I8: =SUM(I6:I7) -> 3697960
B9: Güemes | C9: 5776908 | D9: 1976850 | E9: =C9*0.014293 -> 82569.346 | F9: =D9+E9 -> 2059419.3 | G9: 644652 | H9: 355773 | I9: =G9+H9 -> 1000425
B10: San Telmo 2 | C10: 15461400 | D10: 2368400 | E10: =C10*0.014293 -> 220989.79 | F10: =D10+E10 -> 2589389.8 | G10: 1064835 | H10: 557887 | I10: =G10+H10 -> 1622722
B11: Lucero_Güemes+San Telmo 2 | C11: =SUM(C9:C10) -> 21238308 | D11: =SUM(D9:D10) -> 4345250 | E11: =SUM(E9:E10) -> 303559.14 | F11: =SUM(F9:F10) -> 4648809.1 | G11: =SUM(G9:G10) -> 1709487 | H11: =SUM(H9:H10) -> 913660 | I11: =SUM(I9:I10) -> 2623147
B12: AS San Telmo | C12: 18012064 | D12: 2674000 | E12: =C12*0.014293 -> 257446.43 | F12: =D12+E12 -> 2931446.4 | G12: 955537 | H12: 1115774 | I12: =G12+H12 -> 2071311
B13: Total general | C13: =+C5+C8+C11+C12 -> 2.1380091e+08 | D13: =+D5+D8+D11+D12 -> 21124600 | E13: =+E5+E8+E11+E12 -> 3055856.4 | F13: =+F5+F8+F11+F12 -> 24180456 | G13: =+G5+G8+G11+G12 -> 14148686 | H13: =+H5+H8+H11+H12 -> 5379660.5 | I13: =+I5+I8+I11+I12 -> 19528346
B15: Tienda_Zona | C15: Sueldos | D15: Incentivos por venta | E15: Total gasto de personal | F15: Alquileres | G15: Expensas | H15: Total alquileres + expensas
B16: Florida | C16: =D3/$C3 -> 0.077735473 | D16: =E3/$C3 -> 0.014293 | E16: =F3/$C3 -> 0.092028473 | F16: =G3/$C3 -> 0.10211269 | G16: =H3/$C3 -> 0.0075131672 | H16: =I3/$C3 -> 0.10962586
B17: Recoleta | C17: =D4/$C4 -> 0.1145979 | D17: =E4/$C4 -> 0.014293 | E17: =F4/$C4 -> 0.1288909 | F17: =G4/$C4 -> 0.055440778 | G17: =H4/$C4 -> 0.071978163 | H17: =I4/$C4 -> 0.12741894
B18: Lucero_Zona Centro | C18: =D5/$C5 -> 0.088538178 | D18: =E5/$C5 -> 0.014293 | E18: =F5/$C5 -> 0.10283118 | F18: =G5/$C5 -> 0.088435269 | G18: =H5/$C5 -> 0.026404934 | H18: =I5/$C5 -> 0.1148402
B19: San Telmo | C19: =D6/$C6 -> 0.055833687 | D19: =E6/$C6 -> 0.014293 | E19: =F6/$C6 -> 0.070126687 | F19: =G6/$C6 -> 0.041322306 | G19: =H6/$C6 -> 0.01045405 | H19: =I6/$C6 -> 0.051776357
B20: French | C20: =D7/$C7 -> 0.10490172 | D20: =E7/$C7 -> 0.014293 | E20: =F7/$C7 -> 0.11919472 | F20: =G7/$C7 -> 0.029030393 | G20: =H7/$C7 -> 0.0095755699 | H20: =I7/$C7 -> 0.038605963
B21: Lucero_Zona San Telmo | C21: =D8/$C8 -> 0.071149573 | D21: =E8/$C8 -> 0.014293 | E21: =F8/$C8 -> 0.085442573 | F21: =G8/$C8 -> 0.037485561 | G21: =H8/$C8 -> 0.010179845 | H21: =I8/$C8 -> 0.047665406
B22: Güemes | C22: =D9/$C9 -> 0.34219863 | D22: =E9/$C9 -> 0.014293 | E22: =F9/$C9 -> 0.35649163 | F22: =G9/$C9 -> 0.11159118 | G22: =H9/$C9 -> 0.061585367 | H22: =I9/$C9 -> 0.17317655
B23: San Telmo 2 | C23: =D10/$C10 -> 0.15318147 | D23: =E10/$C10 -> 0.014293 | E23: =F10/$C10 -> 0.16747447 | F23: =G10/$C10 -> 0.068870542 | G23: =H10/$C10 -> 0.036082567 | H23: =I10/$C10 -> 0.10495311
B24: Lucero_Güemes+San Telmo 2 | C24: =D11/$C11 -> 0.20459492 | D24: =E11/$C11 -> 0.014293 | E24: =F11/$C11 -> 0.21888792 | F24: =G11/$C11 -> 0.080490734 | G24: =H11/$C11 -> 0.043019435 | H24: =I11/$C11 -> 0.12351017
B25: AS San Telmo | C25: =D12/$C12 -> 0.14845606 | D25: =E12/$C12 -> 0.014293 | E25: =F12/$C12 -> 0.16274906 | F25: =G12/$C12 -> 0.053049834 | G25: =H12/$C12 -> 0.061945927 | H25: =I12/$C12 -> 0.11499576
B26: Total general | C26: =D13/$C13 -> 0.098805006 | D26: =E13/$C13 -> 0.014293 | E26: =F13/$C13 -> 0.11309801 | F26: =G13/$C13 -> 0.066176922 | G26: =H13/$C13 -> 0.02516201 | H26: =I13/$C13 -> 0.091338932

Sheet Octubre_real
C1: =1335 -> 1335 | J1: Evolución del porcentaje de los gastos en relación con las ventas desde enero 2025
B2: Tienda_Zona | C2: Venta | D2: Sueldos | E2: Alquileres | F2: Expensas | G2: Total alquileres + expensas | H2: Otros gastos | J2: Tienda_Zona | K2: Venta | L2: % Sueldos | M2: % Alquileres + expensas | N2: % Otros gastos
B3: Florida | C3: 58604767 | D3: 5231714 | E3: 7275000 | F3: 461390.5 | G3: =E3+F3 -> 7736390.5 | H3: 1966770.3 | J3: Florida
B4: Recoleta | C4: 31723946 | D4: 3488427 | E4: 1572090 | F4: 2030009.8 | G4: =E4+F4 -> 3602099.8 | H4: 560026.23 | J4: Recoleta
B5: Lucero_Zona Centro | C5: =SUM(C3:C4) -> 90328713 | D5: =SUM(D3:D4) -> 8720141 | E5: =SUM(E3:E4) -> 8847090 | F5: =SUM(F3:F4) -> 2491400.3 | G5: =SUM(G3:G4) -> 11338490 | H5: =SUM(H3:H4) -> 2526796.5 | J5: Lucero_Zona Centro
B6: San Telmo | C6: 32348520 | D6: 3210558 | E6: 2190647 | F6: 538620.31 | G6: =E6+F6 -> 2729267.3 | H6: 251999.59 | J6: San Telmo
B7: French | C7: 19749649 | D7: 2611013 | E7: 703000 | F7: 249237.97 | G7: =E7+F7 -> 952237.97 | H7: 523330.01 | J7: French
B8: Lucero_Zona San Telmo | C8: =SUM(C6:C7) -> 52098169 | D8: =SUM(D6:D7) -> 5821571 | E8: =SUM(E6:E7) -> 2893647 | F8: =SUM(F6:F7) -> 787858.28 | G8: =SUM(G6:G7) -> 3681505.3 | H8: =SUM(H6:H7) -> 775329.6 | J8: Lucero_Zona San Telmo
B9: Güemes | C9: 5985346 | D9: 2111208 | E9: =599275+46204 -> 645479 | F9: 355414 | G9: =E9+F9 -> 1000893 | H9: 409319 | J9: Güemes
B10: San Telmo 2 | C10: 14527110 | D10: 2640837 | E10: 1058553 | F10: 538620.31 | G10: =E10+F10 -> 1597173.3 | H10: 146799.82 | J10: San Telmo 2
B11: Lucero_Güemes+San Telmo 2 | C11: =SUM(C9:C10) -> 20512456 | D11: =SUM(D9:D10) -> 4752045 | E11: =SUM(E9:E10) -> 1704032 | F11: =SUM(F9:F10) -> 894034.31 | G11: =SUM(G9:G10) -> 2598066.3 | H11: =SUM(H9:H10) -> 556118.82 | J11: Lucero_Güemes+San Telmo 2
B12: AS San Telmo | C12: 19169518 | D12: 3435615 | E12: 957292.11 | F12: 1077240.6 | G12: =E12+F12 -> 2034532.7 | H12: 470452.8 | J12: AS San Telmo
B13: El Solar | C13: 6544524 | D13: 4586090.1 | E13: =1350000*1.1 -> 1485000 | F13: 150000 | G13: =E13+F13 -> 1635000 | H13: 0 | J13: El Solar
B14: Total general | C14: =+C5+C8+C11+C12+C13 -> 1.8865338e+08 | D14: =+D5+D8+D11+D12+D13 -> 27315462 | E14: =+E5+E8+E11+E12+E13 -> 15887061 | F14: =+F5+F8+F11+F12+F13 -> 5400533.5 | G14: =+G5+G8+G11+G12+G13 -> 21287595 | H14: =+H5+H8+H11+H12+H13 -> 4328697.8 | J14: Total general
B16: Tienda_Zona | C16: Sueldos | D16: Alquileres | E16: Expensas | F16: Total alquileres + expensas | G16: Otros gastos
B17: Florida | C17: =D3/$C3 -> 0.089271134 | D17: =E3/$C3 -> 0.12413666 | E17: =F3/$C3 -> 0.0078729176 | F17: =G3/$C3 -> 0.13200958 | G17: =H3/$C3 -> 0.033559903
B18: Recoleta | C18: =D4/$C4 -> 0.10996195 | D18: =E4/$C4 -> 0.049555311 | E18: =F4/$C4 -> 0.063989827 | F18: =G4/$C4 -> 0.11354514 | G18: =H4/$C4 -> 0.017653108 | K18: Proyectado | L18: Real | M18: Desvío
B19: Lucero_Zona Centro | C19: =D5/$C5 -> 0.096537864 | D19: =E5/$C5 -> 0.097943275 | E19: =F5/$C5 -> 0.027581488 | F19: =G5/$C5 -> 0.12552476 | G19: =H5/$C5 -> 0.027973348 | J19: Sueldos | K19: =Octubre_proy!F13 -> 24180456 | L19: =D14-D13 -> 22729372 | M19: =L19/K19-1 -> -0.060010628
B20: San Telmo | C20: =D6/$C6 -> 0.099248993 | D20: =E6/$C6 -> 0.067720162 | E20: =F6/$C6 -> 0.01665054 | F20: =G6/$C6 -> 0.084370702 | G20: =H6/$C6 -> 0.0077901428 | J20: Lucero_Zona Centro | K20: =Octubre_proy!F5 -> 9971426.5 | L20: =D5 -> 8720141 | M20: =L20/K20-1 -> -0.12548711
B21: French | C21: =D7/$C7 -> 0.13220554 | D21: =E7/$C7 -> 0.035595569 | E21: =F7/$C7 -> 0.012619868 | F21: =G7/$C7 -> 0.048215438 | G21: =H7/$C7 -> 0.026498193 | J21: Lucero_Zona San Telmo | K21: =Octubre_proy!F8 -> 6628774.3 | L21: =D8 -> 5821571 | M21: =L21/K21-1 -> -0.12177263
B22: Lucero_Zona San Telmo | C22: =D8/$C8 -> 0.11174233 | D22: =E8/$C8 -> 0.055542202 | E22: =F8/$C8 -> 0.015122571 | F22: =G8/$C8 -> 0.070664773 | G22: =H8/$C8 -> 0.014882089 | J22: Lucero_Güemes+San Telmo 2 | K22: =Octubre_proy!F11 -> 4648809.1 | L22: =D11 -> 4752045 | M22: =L22/K22-1 -> 0.022206948
B23: Güemes | C23: =D9/$C9 -> 0.35272948 | D23: =E9/$C9 -> 0.10784322 | E23: =F9/$C9 -> 0.059380694 | F23: =G9/$C9 -> 0.16722392 | G23: =H9/$C9 -> 0.068386857 | J23: AS San Telmo | K23: =Octubre_proy!F12 -> 2931446.4 | L23: =D12 -> 3435615 | M23: =L23/K23-1 -> 0.17198628
B24: San Telmo 2 | C24: =D10/$C10 -> 0.18178681 | D24: =E10/$C10 -> 0.072867418 | E24: =F10/$C10 -> 0.037076907 | F24: =G10/$C10 -> 0.10994433 | G24: =H10/$C10 -> 0.010105232
B25: Lucero_Güemes+San Telmo 2 | C25: =D11/$C11 -> 0.23166631 | D25: =E11/$C11 -> 0.083073036 | E25: =F11/$C11 -> 0.043584947 | F25: =G11/$C11 -> 0.12665798 | G25: =H11/$C11 -> 0.027111274
B26: AS San Telmo | C26: =D12/$C12 -> 0.17922282 | D26: =E12/$C12 -> 0.049938246 | E26: =F12/$C12 -> 0.056195498 | F26: =G12/$C12 -> 0.10613374 | G26: =H12/$C12 -> 0.024541713
B27: El Solar | C27: =D13/$C13 -> 0.70075227 | D27: =E13/$C13 -> 0.22690726 | E27: =F13/$C13 -> 0.022919925 | F27: =G13/$C13 -> 0.24982718 | G27: =H13/$C13 -> 0
B28: Total general | C28: =D14/$C14 -> 0.1447918 | D28: =E14/$C14 -> 0.084212968 | E28: =F14/$C14 -> 0.028626752 | F28: =G14/$C14 -> 0.11283972 | G28: =H14/$C14 -> 0.022945244

Sheet Noviembre_proy
C1: =1335 -> 1335
B2: Tienda_Zona | C2: Venta proyectada | D2: Sueldos | E2: Incentivos por venta | F2: Total gasto de personal | G2: Alquileres | H2: Expensas | I2: Total alquileres + expensas
B3: Florida | E3: =C3*0.014293 -> 0 | F3: =D3+E3 -> 0 | G3: 7300000 | H3: 484460.03 | I3: =G3+H3 -> 7784460
B4: Recoleta | E4: =C4*0.014293 -> 0 | F4: =D4+E4 -> 0 | G4: 2120000 | H4: 2131510.3 | I4: =G4+H4 -> 4251510.3
B5: Lucero_Zona Centro | C5: =SUM(C3:C4) -> 0 | D5: =SUM(D3:D4) -> 0 | E5: =SUM(E3:E4) -> 0 | F5: =SUM(F3:F4) -> 0 | G5: =SUM(G3:G4) -> 9420000 | H5: =SUM(H3:H4) -> 2615970.3 | I5: =SUM(I3:I4) -> 12035970
B6: San Telmo | E6: =C6*0.014293 -> 0 | F6: =D6+E6 -> 0 | G6: 2135537.2 | H6: 565551.33 | I6: =G6+H6 -> 2701088.5
B7: French | E7: =C7*0.014293 -> 0 | F7: =D7+E7 -> 0 | G7: 703000 | H7: 261699.87 | I7: =G7+H7 -> 964699.87
B8: Lucero_Zona San Telmo | C8: =SUM(C6:C7) -> 0 | D8: =SUM(D6:D7) -> 0 | E8: =SUM(E6:E7) -> 0 | F8: =SUM(F6:F7) -> 0 | G8: =SUM(G6:G7) -> 2838537.2 | H8: =SUM(H6:H7) -> 827251.19 | I8: =SUM(I6:I7) -> 3665788.4
B9: Güemes | E9: =C9*0.014293 -> 0 | F9: =D9+E9 -> 0 | G9: 645612 | H9: 373184.7 | I9: =G9+H9 -> 1018796.7
B10: San Telmo 2 | E10: =C10*0.014293 -> 0 | F10: =D10+E10 -> 0 | G10: 1157000 | H10: 565551.33 | I10: =G10+H10 -> 1722551.3
B11: Lucero_Güemes+San Telmo 2 | C11: =SUM(C9:C10) -> 0 | D11: =SUM(D9:D10) -> 0 | E11: =SUM(E9:E10) -> 0 | F11: =SUM(F9:F10) -> 0 | G11: =SUM(G9:G10) -> 1802612 | H11: =SUM(H9:H10) -> 938736.03 | I11: =SUM(I9:I10) -> 2741348
B12: AS San Telmo | E12: =C12*0.014293 -> 0 | F12: =D12+E12 -> 0 | G12: 1361157 | H12: 1131102.7 | I12: =G12+H12 -> 2492259.7
B13: El Solar | E13: =C13*0.014293 -> 0 | F13: =D13+E13 -> 0 | G13: =1400000+140000 -> 1540000 | H13: 156000 | I13: =G13+H13 -> 1696000
B14: Total general | C14: =+C5+C8+C11+C12+C13 -> 0 | D14: =+D5+D8+D11+D12+D13 -> 0 | E14: =+E5+E8+E11+E12+E13 -> 0 | F14: =+F5+F8+F11+F12+F13 -> 0 | G14: =+G5+G8+G11+G12+G13 -> 16962306 | H14: =+H5+H8+H11+H12+H13 -> 5669060.2 | I14: =+I5+I8+I11+I12+I13 -> 22631366
B16: Tienda_Zona | C16: Sueldos | D16: Incentivos por venta | E16: Total gasto de personal | F16: Alquileres | G16: Expensas | H16: Total alquileres + expensas
B17: Florida | C17: =D3/$C3 -> #DIV/0! | D17: =E3/$C3 -> #DIV/0! | E17: =F3/$C3 -> #DIV/0! | F17: =G3/$C3 -> #DIV/0! | G17: =H3/$C3 -> #DIV/0! | H17: =I3/$C3 -> #DIV/0!
B18: Recoleta | C18: =D4/$C4 -> #DIV/0! | D18: =E4/$C4 -> #DIV/0! | E18: =F4/$C4 -> #DIV/0! | F18: =G4/$C4 -> #DIV/0! | G18: =H4/$C4 -> #DIV/0! | H18: =I4/$C4 -> #DIV/0!
B19: Lucero_Zona Centro | C19: =D5/$C5 -> #DIV/0! | D19: =E5/$C5 -> #DIV/0! | E19: =F5/$C5 -> #DIV/0! | F19: =G5/$C5 -> #DIV/0! | G19: =H5/$C5 -> #DIV/0! | H19: =I5/$C5 -> #DIV/0!
B20: San Telmo | C20: =D6/$C6 -> #DIV/0! | D20: =E6/$C6 -> #DIV/0! | E20: =F6/$C6 -> #DIV/0! | F20: =G6/$C6 -> #DIV/0! | G20: =H6/$C6 -> #DIV/0! | H20: =I6/$C6 -> #DIV/0!
B21: French | C21: =D7/$C7 -> #DIV/0! | D21: =E7/$C7 -> #DIV/0! | E21: =F7/$C7 -> #DIV/0! | F21: =G7/$C7 -> #DIV/0! | G21: =H7/$C7 -> #DIV/0! | H21: =I7/$C7 -> #DIV/0!
B22: Lucero_Zona San Telmo | C22: =D8/$C8 -> #DIV/0! | D22: =E8/$C8 -> #DIV/0! | E22: =F8/$C8 -> #DIV/0! | F22: =G8/$C8 -> #DIV/0! | G22: =H8/$C8 -> #DIV/0! | H22: =I8/$C8 -> #DIV/0!
B23: Güemes | C23: =D9/$C9 -> #DIV/0! | D23: =E9/$C9 -> #DIV/0! | E23: =F9/$C9 -> #DIV/0! | F23: =G9/$C9 -> #DIV/0! | G23: =H9/$C9 -> #DIV/0! | H23: =I9/$C9 -> #DIV/0!
B24: San Telmo 2 | C24: =D10/$C10 -> #DIV/0! | D24: =E10/$C10 -> #DIV/0! | E24: =F10/$C10 -> #DIV/0! | F24: =G10/$C10 -> #DIV/0! | G24: =H10/$C10 -> #DIV/0! | H24: =I10/$C10 -> #DIV/0!
B25: Lucero_Güemes+San Telmo 2 | C25: =D11/$C11 -> #DIV/0! | D25: =E11/$C11 -> #DIV/0! | E25: =F11/$C11 -> #DIV/0! | F25: =G11/$C11 -> #DIV/0! | G25: =H11/$C11 -> #DIV/0! | H25: =I11/$C11 -> #DIV/0!
B26: AS San Telmo | C26: =D12/$C12 -> #DIV/0! | D26: =E12/$C12 -> #DIV/0! | E26: =F12/$C12 -> #DIV/0! | F26: =G12/$C12 -> #DIV/0! | G26: =H12/$C12 -> #DIV/0! | H26: =I12/$C12 -> #DIV/0!
B27: El Solar | C27: =D13/$C13 -> #DIV/0! | D27: =E13/$C13 -> #DIV/0! | E27: =F13/$C13 -> #DIV/0! | F27: =G13/$C13 -> #DIV/0! | G27: =H13/$C13 -> #DIV/0! | H27: =I13/$C13 -> #DIV/0!
B28: Total general | C28: =D14/$C14 -> #DIV/0! | D28: =E14/$C14 -> #DIV/0! | E28: =F14/$C14 -> #DIV/0! | F28: =G14/$C14 -> #DIV/0! | G28: =H14/$C14 -> #DIV/0! | H28: =I14/$C14 -> #DIV/0!

Sheet Noviembre_real
C1: =1335 -> 1335 | J1: Evolución del porcentaje de los gastos en relación con las ventas desde enero 2025
B2: Tienda_Zona | C2: Venta | D2: Sueldos | E2: Alquileres | F2: Expensas | G2: Total alquileres + expensas | H2: Otros gastos | J2: Tienda_Zona | K2: Venta | L2: % Sueldos | M2: % Alquileres + expensas | N2: % Otros gastos
B3: Florida | C3: 84288372 | D3: 6586095 | E3: 7050000 | F3: 482850.5 | G3: =E3+F3 -> 7532850.5 | H3: 1732487.7 | J3: Florida
B4: Recoleta | C4: 35080566 | D4: 3710746 | E4: =IFERROR(__xludf.DUMMYFUNCTION("""COMPUTED_VALUE"""),2248205.26) -> 2248205.3 | F4: =IFERROR(__xludf.DUMMYFUNCTION("""COMPUTED_VALUE"""),2081805.58) -> 2081805.6 | G4: =E4+F4 -> 4330010.8 | H4: 801724.66 | J4: Recoleta
B5: Lucero_Zona Centro | C5: =SUM(C3:C4) -> 119368938 | D5: =SUM(D3:D4) -> 10296841 | E5: =SUM(E3:E4) -> 9298205.3 | F5: =SUM(F3:F4) -> 2564656.1 | G5: =SUM(G3:G4) -> 11862861 | H5: =SUM(H3:H4) -> 2534212.4 | J5: Lucero_Zona Centro
B6: San Telmo | C6: 62909140 | D6: 3830165 | E6: 2138745 | F6: 650090.67 | G6: =E6+F6 -> 2788835.7 | H6: 325565.29 | J6: San Telmo
B7: French | C7: 31448390 | D7: 2874528 | E7: 703000 | F7: 246306 | G7: =E7+F7 -> 949306 | H7: 433695.18 | J7: French
B8: Lucero_Zona San Telmo | C8: =SUM(C6:C7) -> 94357530 | D8: =SUM(D6:D7) -> 6704693 | E8: =SUM(E6:E7) -> 2841745 | F8: =SUM(F6:F7) -> 896396.67 | G8: =SUM(G6:G7) -> 3738141.7 | H8: =SUM(H6:H7) -> 759260.47 | J8: Lucero_Zona San Telmo
B9: Güemes | C9: 5000090 | D9: 1669932 | E9: 645479.21 | F9: 352047.74 | G9: =E9+F9 -> 997526.95 | H9: 150044 | J9: Güemes
B10: San Telmo 2 | C10: 24191146 | D10: 2658266 | E10: 1200587.6 | F10: 650090.67 | G10: =E10+F10 -> 1850678.3 | H10: 1291237.8 | J10: San Telmo 2
B11: Lucero_Güemes+San Telmo 2 | C11: =SUM(C9:C10) -> 29191236 | D11: =SUM(D9:D10) -> 4328198 | E11: =SUM(E9:E10) -> 1846066.8 | F11: =SUM(F9:F10) -> 1002138.4 | G11: =SUM(G9:G10) -> 2848205.2 | H11: =SUM(H9:H10) -> 1441281.8 | J11: Lucero_Güemes+San Telmo 2
B12: AS San Telmo | C12: 20563510 | D12: 3468754 | E12: 1425831.8 | F12: 1300181.3 | G12: =E12+F12 -> 2726013.2 | H12: 189763.77 | J12: AS San Telmo
B13: El Solar | C13: 6889990 | D13: 5328412.8 | E13: =IFERROR(__xludf.DUMMYFUNCTION("""COMPUTED_VALUE"""),1544265.55) -> 1544265.6 | F13: 236898.87 | G13: =E13+F13 -> 1781164.4 | H13: 125207.61 | J13: El Solar
B14: AS Güemes | C14: 898200 | D14: 1201341.5 | E14: 267700 | F14: 19514.84 | G14: =E14+F14 -> 287214.84 | H14: 191900 | J14: AS Güemes
B15: Güemes 2 | C15: 1268801 | D15: 994591.3 | E15: 461056.58 | F15: 53860.96 | G15: =E15+F15 -> 514917.54 | H15: 2224.68 | J15: Güemes 2
B16: Total general | C16: =+C5+C8+C11+C12+C13+C14+C15 -> 272538205 | D16: =+D5+D8+D11+D12+D13+D14+D15 -> 32322832 | E16: =+E5+E8+E11+E12+E13+E14+E15 -> 17684871 | F16: =+F5+F8+F11+F12+F13+F14+F15 -> 6073647.2 | G16: =+G5+G8+G11+G12+G13+G14+G15 -> 23758518 | H16: =+H5+H8+H11+H12+H13+H14+H15 -> 5243850.7 | J16: Total general
B18: Tienda_Zona | C18: Sueldos | D18: Alquileres | E18: Expensas | F18: Total alquileres + expensas | G18: Otros gastos
B19: Florida | C19: =D3/$C3 -> 0.078137646 | D19: =E3/$C3 -> 0.08364143 | E19: =F3/$C3 -> 0.0057285541 | F19: =G3/$C3 -> 0.089369985 | G19: =H3/$C3 -> 0.020554291
B20: Recoleta | C20: =D4/$C4 -> 0.10577783 | D20: =E4/$C4 -> 0.064086915 | E20: =F4/$C4 -> 0.059343557 | F20: =G4/$C4 -> 0.12343047 | G20: =H4/$C4 -> 0.022853812 | K20: Proyectado | L20: Real | M20: Desvío
B21: Lucero_Zona Centro | C21: =D5/$C5 -> 0.08626064 | D21: =E5/$C5 -> 0.07789468 | E21: =F5/$C5 -> 0.021485121 | F21: =G5/$C5 -> 0.099379801 | G21: =H5/$C5 -> 0.021230082 | J21: Sueldos | M21: =L21/K21-1 -> #DIV/0!
B22: San Telmo | C22: =D6/$C6 -> 0.060884078 | D22: =E6/$C6 -> 0.033997366 | E22: =F6/$C6 -> 0.010333803 | F22: =G6/$C6 -> 0.044331169 | G22: =H6/$C6 -> 0.0051751668 | J22: Lucero_Zona Centro | M22: =L22/K22-1 -> #DIV/0!
B23: French | C23: =D7/$C7 -> 0.091404616 | D23: =E7/$C7 -> 0.022354086 | E23: =F7/$C7 -> 0.0078320703 | F23: =G7/$C7 -> 0.030186156 | G23: =H7/$C7 -> 0.013790696 | J23: Lucero_Zona San Telmo | M23: =L23/K23-1 -> #DIV/0!
B24: Lucero_Zona San Telmo | C24: =D8/$C8 -> 0.071056258 | D24: =E8/$C8 -> 0.030116781 | E24: =F8/$C8 -> 0.0095000014 | F24: =G8/$C8 -> 0.039616782 | G24: =H8/$C8 -> 0.0080466336 | J24: Lucero_Güemes+San Telmo 2 | M24: =L24/K24-1 -> #DIV/0!
B25: Güemes | C25: =D9/$C9 -> 0.33398039 | D25: =E9/$C9 -> 0.12909352 | E25: =F9/$C9 -> 0.070408281 | F25: =G9/$C9 -> 0.1995018 | G25: =H9/$C9 -> 0.03000826 | J25: AS San Telmo | M25: =L25/K25-1 -> #DIV/0!
B26: San Telmo 2 | C26: =D10/$C10 -> 0.10988591 | D26: =E10/$C10 -> 0.049629216 | E26: =F10/$C10 -> 0.026873083 | F26: =G10/$C10 -> 0.076502298 | G26: =H10/$C10 -> 0.053376463 | J26: El Solar | M26: =L26/K26-1 -> #DIV/0!
B27: Lucero_Güemes+San Telmo 2 | C27: =D11/$C11 -> 0.14827046 | D27: =E11/$C11 -> 0.063240447 | E27: =F11/$C11 -> 0.034330112 | F27: =G11/$C11 -> 0.097570559 | G27: =H11/$C11 -> 0.049373785 | J27: AS Güemes | M27: =L27/K27-1 -> #DIV/0!
B28: AS San Telmo | C28: =D12/$C12 -> 0.16868492 | D28: =E12/$C12 -> 0.06933796 | E28: =F12/$C12 -> 0.063227598 | F28: =G12/$C12 -> 0.13256556 | G28: =H12/$C12 -> 0.0092281799 | J28: Güemes 2 | M28: =L28/K28-1 -> #DIV/0!
B29: El Solar | C29: =D13/$C13 -> 0.77335567 | D29: =E13/$C13 -> 0.22413175 | E29: =F13/$C13 -> 0.03438305 | F29: =G13/$C13 -> 0.2585148 | G29: =H13/$C13 -> 0.018172394
B30: AS Güemes | C30: =D14/$C14 -> 1.3374989 | D30: =E14/$C14 -> 0.29804053 | E30: =F14/$C14 -> 0.021726609 | F30: =G14/$C14 -> 0.31976713 | G30: =H14/$C14 -> 0.21364952
B31: Güemes 2 | C31: =D15/$C15 -> 0.78388282 | D31: =E15/$C15 -> 0.36337974 | E31: =F15/$C15 -> 0.042450282 | F31: =G15/$C15 -> 0.40583002 | G31: =H15/$C15 -> 0.0017533719
B32: Total general | C32: =D16/$C16 -> 0.11859927 | D32: =E16/$C16 -> 0.064889512 | E32: =F16/$C16 -> 0.022285489 | F32: =G16/$C16 -> 0.087175001 | G32: =H16/$C16 -> 0.019240791

Sheet Diciembre_real
C1: =1335 -> 1335 | J1: Evolución del porcentaje de los gastos en relación con las ventas desde enero 2025
B2: Tienda_Zona | C2: Venta | D2: Sueldos | E2: Alquileres | F2: Expensas | G2: Total alquileres + expensas | H2: Otros gastos | J2: Tienda_Zona | K2: Venta | L2: % Sueldos | M2: % Alquileres + expensas | N2: % Otros gastos
B3: Florida | G3: =E3+F3 -> 0 | J3: Florida
B4: Recoleta | G4: =E4+F4 -> 0 | J4: Recoleta
B5: Lucero_Zona Centro | C5: =SUM(C3:C4) -> 0 | D5: =SUM(D3:D4) -> 0 | E5: =SUM(E3:E4) -> 0 | F5: =SUM(F3:F4) -> 0 | G5: =SUM(G3:G4) -> 0 | H5: =SUM(H3:H4) -> 0 | J5: Lucero_Zona Centro
B6: San Telmo | G6: =E6+F6 -> 0 | J6: San Telmo
B7: French | G7: =E7+F7 -> 0 | J7: French
B8: Lucero_Zona San Telmo | C8: =SUM(C6:C7) -> 0 | D8: =SUM(D6:D7) -> 0 | E8: =SUM(E6:E7) -> 0 | F8: =SUM(F6:F7) -> 0 | G8: =SUM(G6:G7) -> 0 | H8: =SUM(H6:H7) -> 0 | J8: Lucero_Zona San Telmo
B9: Güemes | G9: =E9+F9 -> 0 | J9: Güemes
B10: San Telmo 2 | G10: =E10+F10 -> 0 | J10: San Telmo 2
B11: Lucero_Güemes+San Telmo 2 | C11: =SUM(C9:C10) -> 0 | D11: =SUM(D9:D10) -> 0 | E11: =SUM(E9:E10) -> 0 | F11: =SUM(F9:F10) -> 0 | G11: =SUM(G9:G10) -> 0 | H11: =SUM(H9:H10) -> 0 | J11: Lucero_Güemes+San Telmo 2
B12: AS San Telmo | G12: =E12+F12 -> 0 | J12: AS San Telmo
B13: El Solar | G13: =E13+F13 -> 0 | J13: El Solar
B14: Total general | C14: =+C5+C8+C11+C12+C13 -> 0 | D14: =+D5+D8+D11+D12+D13 -> 0 | E14: =+E5+E8+E11+E12+E13 -> 0 | F14: =+F5+F8+F11+F12+F13 -> 0 | G14: =+G5+G8+G11+G12+G13 -> 0 | H14: =+H5+H8+H11+H12+H13 -> 0 | J14: Total general
B16: Tienda_Zona | C16: Sueldos | D16: Alquileres | E16: Expensas | F16: Total alquileres + expensas | G16: Otros gastos
B17: Florida | C17: =D3/$C3 -> #DIV/0! | D17: =E3/$C3 -> #DIV/0! | E17: =F3/$C3 -> #DIV/0! | F17: =G3/$C3 -> #DIV/0! | G17: =H3/$C3 -> #DIV/0!
B18: Recoleta | C18: =D4/$C4 -> #DIV/0! | D18: =E4/$C4 -> #DIV/0! | E18: =F4/$C4 -> #DIV/0! | F18: =G4/$C4 -> #DIV/0! | G18: =H4/$C4 -> #DIV/0! | K18: Proyectado | L18: Real | M18: Desvío
B19: Lucero_Zona Centro | C19: =D5/$C5 -> #DIV/0! | D19: =E5/$C5 -> #DIV/0! | E19: =F5/$C5 -> #DIV/0! | F19: =G5/$C5 -> #DIV/0! | G19: =H5/$C5 -> #DIV/0! | J19: Sueldos | M19: =L19/K19-1 -> #DIV/0!
B20: San Telmo | C20: =D6/$C6 -> #DIV/0! | D20: =E6/$C6 -> #DIV/0! | E20: =F6/$C6 -> #DIV/0! | F20: =G6/$C6 -> #DIV/0! | G20: =H6/$C6 -> #DIV/0! | J20: Lucero_Zona Centro | M20: =L20/K20-1 -> #DIV/0!
B21: French | C21: =D7/$C7 -> #DIV/0! | D21: =E7/$C7 -> #DIV/0! | E21: =F7/$C7 -> #DIV/0! | F21: =G7/$C7 -> #DIV/0! | G21: =H7/$C7 -> #DIV/0! | J21: Lucero_Zona San Telmo | M21: =L21/K21-1 -> #DIV/0!
B22: Lucero_Zona San Telmo | C22: =D8/$C8 -> #DIV/0! | D22: =E8/$C8 -> #DIV/0! | E22: =F8/$C8 -> #DIV/0! | F22: =G8/$C8 -> #DIV/0! | G22: =H8/$C8 -> #DIV/0! | J22: Lucero_Güemes+San Telmo 2 | M22: =L22/K22-1 -> #DIV/0!
B23: Güemes | C23: =D9/$C9 -> #DIV/0! | D23: =E9/$C9 -> #DIV/0! | E23: =F9/$C9 -> #DIV/0! | F23: =G9/$C9 -> #DIV/0! | G23: =H9/$C9 -> #DIV/0! | J23: AS San Telmo | M23: =L23/K23-1 -> #DIV/0!
B24: San Telmo 2 | C24: =D10/$C10 -> #DIV/0! | D24: =E10/$C10 -> #DIV/0! | E24: =F10/$C10 -> #DIV/0! | F24: =G10/$C10 -> #DIV/0! | G24: =H10/$C10 -> #DIV/0! | J24: El Solar | M24: =L24/K24-1 -> #DIV/0!
B25: Lucero_Güemes+San Telmo 2 | C25: =D11/$C11 -> #DIV/0! | D25: =E11/$C11 -> #DIV/0! | E25: =F11/$C11 -> #DIV/0! | F25: =G11/$C11 -> #DIV/0! | G25: =H11/$C11 -> #DIV/0!
B26: AS San Telmo | C26: =D12/$C12 -> #DIV/0! | D26: =E12/$C12 -> #DIV/0! | E26: =F12/$C12 -> #DIV/0! | F26: =G12/$C12 -> #DIV/0! | G26: =H12/$C12 -> #DIV/0!
B27: El Solar | C27: =D13/$C13 -> #DIV/0! | D27: =E13/$C13 -> #DIV/0! | E27: =F13/$C13 -> #DIV/0! | F27: =G13/$C13 -> #DIV/0! | G27: =H13/$C13 -> #DIV/0!
B28: Total general | C28: =D14/$C14 -> #DIV/0! | D28: =E14/$C14 -> #DIV/0! | E28: =F14/$C14 -> #DIV/0! | F28: =G14/$C14 -> #DIV/0! | G28: =H14/$C14 -> #DIV/0!

Sheet Tablas
A1: FLORIDA
A2: Concepto | B2: 1-ene | C2: 1-feb | D2: 1-mar | E2: 1-abr | F2: 1-may | G2: 1-jun | H2: 1-jul | I2: 1-ago | J2: 45901 | K2: 45931 | L2: 45962 | M2: 45992
A3: Venta | B3: 40118678 | C3: 23978279 | D3: 44687119 | E3: 33033180 | F3: 35772422 | G3: 29767639 | H3: 35622735 | I3: ='Agosto-real'!C3 -> 45735238 | J3: =Septiembre_real!C3 -> 62713661 | K3: =Octubre_real!C3 -> 58604767 | L3: =Noviembre_real!C3 -> 84288372 | M3: =Diciembre_real!C3 -> 0
A4: Sueldos | B4: 4472073.3 | C4: 4562990.2 | D4: 6276593.3 | E4: 7019683.5 | F4: 5916115.2 | G4: 6458324.6 | H4: 5522865.2 | I4: ='Agosto-real'!D3 -> 5359007 | J4: =Septiembre_real!D3 -> 5345060 | K4: =Octubre_real!D3 -> 5231714 | L4: =Noviembre_real!D3 -> 6586095 | M4: =Diciembre_real!D3 -> 0
A5: Alquiler y expensas | B5: 3772412.1 | C5: 3114681 | D5: 1963560.4 | E5: 3332116.6 | F5: 2654438.3 | G5: 2853389.1 | H5: 6890040.5 | I5: ='Agosto-real'!G3 -> 6957740.5 | J5: =Septiembre_real!G3 -> 7300440.5 | K5: =Octubre_real!G3 -> 7736390.5 | L5: =Noviembre_real!G3 -> 7532850.5 | M5: =Diciembre_real!G3 -> 0
A6: Otros gastos | B6: 1727784.4 | C6: 1353670.4 | D6: 1730685.7 | E6: 1635733.9 | F6: 1831466.3 | G6: 1208216.3 | H6: 1988927.1 | I6: ='Agosto-real'!H3 -> 1845033.1 | J6: =Septiembre_real!H3 -> 1773489.2 | K6: =Octubre_real!H3 -> 1966770.3 | L6: =Noviembre_real!H3 -> 1732487.7 | M6: =Diciembre_real!H3 -> 0
A7: Sueldos | B7: =B4/B$3 -> 0.1114711 | C7: =C4/C$3 -> 0.19029682 | D7: =D4/D$3 -> 0.14045643 | E7: =E4/E$3 -> 0.21250402 | F7: =F4/F$3 -> 0.16538202 | G7: =G4/G$3 -> 0.2169579 | H7: =H4/H$3 -> 0.15503765 | I7: =I4/I$3 -> 0.11717457 | ... M7: =M4/M$3 -> #DIV/0!
A8: Alquiler y expensas | B8: =B5/B$3 -> 0.094031316 | C8: =C5/C$3 -> 0.12989594 | D8: =D5/D$3 -> 0.043940188 | E8: =E5/E$3 -> 0.10087181 | F8: =F5/F$3 -> 0.074203482 | G8: =G5/G$3 -> 0.095855404 | H8: =H5/H$3 -> 0.19341694 | I8: =I5/I$3 -> 0.15213085 | ... M8: =M5/M$3 -> #DIV/0!
A9: Otros gastos | B9: =B6/B$3 -> 0.043066834 | C9: =C6/C$3 -> 0.056454028 | D9: =D6/D$3 -> 0.038728961 | E9: =E6/E$3 -> 0.049517907 | F9: =F6/F$3 -> 0.051197716 | G9: =G6/G$3 -> 0.040588248 | H9: =H6/H$3 -> 0.055833083 | I9: =I6/I$3 -> 0.040341608 | ... M9: =M6/M$3 -> #DIV/0!
A12: RECOLETA
A13: Concepto | B13: 1-ene | C13: 1-feb | D13: 1-mar | E13: 1-abr | F13: 1-may | G13: 1-jun | H13: 1-jul | I13: 1-ago | J13: 45901 | K13: 45931 | L13: 45962 | M13: 45992
A14: Venta | B14: 20476370 | C14: 15336680 | D14: 25739876 | E14: 17076570 | F14: 15486300 | G14: 17483909 | H14: 18589226 | I14: ='Agosto-real'!C4 -> 21770316 | J14: =Septiembre_real!C4 -> 22885150 | K14: =Octubre_real!C4 -> 31723946 | L14: =Noviembre_real!C4 -> 35080566 | M14: =Diciembre_real!C4 -> 0
A15: Sueldos | B15: 2404008.8 | C15: 2469244.1 | D15: 2988002.4 | E15: 3434635 | F15: 3457993.3 | G15: 3446985.9 | H15: 3716181.3 | I15: ='Agosto-real'!D4 -> 3174723 | J15: =Septiembre_real!D4 -> 3082266 | K15: =Octubre_real!D4 -> 3488427 | L15: =Noviembre_real!D4 -> 3710746 | M15: =Diciembre_real!D4 -> 0
A16: Alquiler y expensas | B16: 3865858.9 | C16: 3070147 | D16: 2976335.4 | E16: 3631434.9 | F16: 3199043.5 | G16: 3114002.6 | H16: 3146052.8 | I16: ='Agosto-real'!G4 -> 3201842.7 | J16: =Septiembre_real!G4 -> 3396372.2 | K16: =Octubre_real!G4 -> 3602099.8 | L16: =Noviembre_real!G4 -> 4330010.8 | M16: =Diciembre_real!G4 -> 0
A17: Otros gastos | B17: 185581.34 | C17: 211084.93 | D17: 231848.83 | E17: 201527.02 | F17: 343699.47 | G17: 204799.53 | H17: 226376.6 | I17: ='Agosto-real'!H4 -> 509583.35 | J17: =Septiembre_real!H4 -> 209674.47 | K17: =Octubre_real!H4 -> 560026.23 | L17: =Noviembre_real!H4 -> 801724.66 | M17: =Diciembre_real!H4 -> 0
A18: Sueldos | B18: =B15/B$14 -> 0.11740405 | C18: =C15/C$14 -> 0.16100252 | D18: =D15/D$14 -> 0.11608457 | E18: =E15/E$14 -> 0.20113143 | F18: =F15/F$14 -> 0.2232937 | G18: =G15/G$14 -> 0.1971519 | H18: =H15/H$14 -> 0.19991049 | I18: =I15/I$14 -> 0.14582806 | ... M18: =M15/M$14 -> #DIV/0!
A19: Alquiler y expensas | B19: =B16/B$14 -> 0.1887961 | C19: =C16/C$14 -> 0.20018329 | D19: =D16/D$14 -> 0.1156313 | E19: =E16/E$14 -> 0.21265599 | F19: =F16/F$14 -> 0.20657249 | G19: =G16/G$14 -> 0.17810677 | H19: =H16/H$14 -> 0.16924066 | I19: =I16/I$14 -> 0.14707378 | ... M19: =M16/M$14 -> #DIV/0!
A20: Otros gastos | B20: =B17/B$14 -> 0.0090631953 | C20: =C17/C$14 -> 0.013763404 | D20: =D17/D$14 -> 0.0090073794 | E20: =E17/E$14 -> 0.011801376 | F20: =F17/F$14 -> 0.022193776 | G20: =G17/G$14 -> 0.011713601 | H20: =H17/H$14 -> 0.012177839 | I20: =I17/I$14 -> 0.023407256 | ... M20: =M17/M$14 -> #DIV/0!
A23: ZONA CENTRO
A24: Concepto | B24: 1-ene | C24: 1-feb | D24: 1-mar | E24: 1-abr | F24: 1-may | G24: 1-jun | H24: 1-jul | I24: 1-ago | J24: 45901 | K24: 45931 | L24: 45962 | M24: 45992
A25: Venta | B25: =B3+B14 -> 60595048 | C25: =C3+C14 -> 39314959 | D25: =D3+D14 -> 70426995 | E25: =E3+E14 -> 50109750 | F25: =F3+F14 -> 51258722 | G25: =G3+G14 -> 47251548 | H25: =H3+H14 -> 54211961 | I25: =I3+I14 -> 67505554 | ... M25: =M3+M14 -> 0
A26: Sueldos | B26: =B4+B15 -> 6876082.1 | C26: =C4+C15 -> 7032234.3 | D26: =D4+D15 -> 9264595.8 | E26: =E4+E15 -> 10454318 | F26: =F4+F15 -> 9374108.5 | G26: =G4+G15 -> 9905310.5 | H26: =H4+H15 -> 9239046.5 | I26: =I4+I15 -> 8533730 | ... M26: =M4+M15 -> 0
A27: Alquiler y expensas | B27: =B5+B16 -> 7638270.9 | C27: =C5+C16 -> 6184828 | D27: =D5+D16 -> 4939895.8 | E27: =E5+E16 -> 6963551.5 | F27: =F5+F16 -> 5853481.8 | G27: =G5+G16 -> 5967391.7 | H27: =H5+H16 -> 10036093 | I27: =I5+I16 -> 10159583 | ... M27: =M5+M16 -> 0
A28: Otros gastos | B28: =B6+B17 -> 1913365.8 | C28: =C6+C17 -> 1564755.4 | D28: =D6+D17 -> 1962534.5 | E28: =E6+E17 -> 1837260.9 | F28: =F6+F17 -> 2175165.8 | G28: =G6+G17 -> 1413015.8 | H28: =H6+H17 -> 2215303.7 | I28: =I6+I17 -> 2354616.4 | ... M28: =M6+M17 -> 0
A29: Sueldos | B29: =B26/B$25 -> 0.11347597 | C29: =C26/C$25 -> 0.17886918 | D29: =D26/D$25 -> 0.13154893 | E29: =E26/E$25 -> 0.20862843 | F29: =F26/F$25 -> 0.18287831 | G29: =G26/G$25 -> 0.20962933 | H29: =H26/H$25 -> 0.1704245 | I29: =I26/I$25 -> 0.12641523 | ... M29: =M26/M$25 -> #DIV/0!
A30: Alquiler y expensas | B30: =B27/B$25 -> 0.12605438 | C30: =C27/C$25 -> 0.15731488 | D30: =D27/D$25 -> 0.070142079 | E30: =E27/E$25 -> 0.138966 | F30: =F27/F$25 -> 0.11419484 | G30: =G27/G$25 -> 0.12628987 | H30: =H27/H$25 -> 0.18512692 | I30: =I27/I$25 -> 0.15049996 | ... M30: =M27/M$25 -> #DIV/0!
A31: Otros gastos | B31: =B28/B$25 -> 0.031576273 | C31: =C28/C$25 -> 0.039800509 | D31: =D28/D$25 -> 0.027866225 | E31: =E28/E$25 -> 0.03666474 | F31: =F28/F$25 -> 0.042435037 | G31: =G28/G$25 -> 0.029904117 | H31: =H28/H$25 -> 0.040863745 | I31: =I28/I$25 -> 0.034880336 | ... M31: =M28/M$25 -> #DIV/0!
A34: SAN TELMO
A35: Concepto | B35: 1-ene | C35: 1-feb | D35: 1-mar | E35: 1-abr | F35: 1-may | G35: 1-jun | H35: 1-jul | I35: 1-ago | J35: 45901 | K35: 45931 | L35: 45962 | M35: 45992
A36: Venta | B36: 40058419 | C36: 32509360 | D36: 35443210 | E36: 24391050 | F36: 23316110 | G36: 24499270 | H36: 26482450 | I36: ='Agosto-real'!C7 -> 34037280 | J36: =Septiembre_real!C6 -> 33133540 | K36: =Octubre_real!C6 -> 32348520 | L36: =Noviembre_real!C6 -> 62909140 | M36: =Diciembre_real!C6 -> 0
A37: Sueldos | B37: 2433243.5 | C37: 2525034.6 | D37: 4606184.9 | E37: 4232893 | F37: 4663105.6 | G37: 4735048.2 | H37: 4609368.3 | I37: ='Agosto-real'!D7 -> 3084694.7 | J37: =Septiembre_real!D6 -> 2263663 | K37: =Octubre_real!D6 -> 3210558 | L37: =Noviembre_real!D6 -> 3830165 | M37: =Diciembre_real!D6 -> 0
A38: Alquiler y expensas | B38: 3533075.2 | C38: 3056573.4 | D38: 2482630.1 | E38: 2676375.7 | F38: 2101384.2 | G38: 2063766.2 | H38: 2076405.1 | I38: ='Agosto-real'!G7 -> 2314798.5 | J38: =Septiembre_real!G6 -> 2781655.4 | K38: =Octubre_real!G6 -> 2729267.3 | L38: =Noviembre_real!G6 -> 2788835.7 | M38: =Diciembre_real!G6 -> 0
A39: Otros gastos | B39: 166504.56 | C39: 237510 | D39: 128425.78 | E39: 146897.99 | F39: 108542.57 | G39: 120334.86 | H39: 141039.3 | I39: ='Agosto-real'!H7 -> 276404.91 | J39: =Septiembre_real!H6 -> 200815.63 | K39: =Octubre_real!H6 -> 251999.59 | L39: =Noviembre_real!H6 -> 325565.29 | M39: =Diciembre_real!H6 -> 0
A40: Sueldos | B40: =B37/B$36 -> 0.060742374 | C40: =C37/C$36 -> 0.077671002 | D40: =D37/D$36 -> 0.12995959 | E40: =E37/E$36 -> 0.17354288 | F40: =F37/F$36 -> 0.19999501 | G40: =G37/G$36 -> 0.19327303 | H40: =H37/H$36 -> 0.1740537 | I40: =I37/I$36 -> 0.090626945 | ... M40: =M37/M$36 -> #DIV/0!
A41: Alquiler y expensas | B41: =B38/B$36 -> 0.088198069 | C41: =C38/C$36 -> 0.094021333 | D41: =D38/D$36 -> 0.070045296 | E41: =E38/E$36 -> 0.10972778 | F41: =F38/F$36 -> 0.090125848 | G41: =G38/G$36 -> 0.084237865 | H41: =H38/H$36 -> 0.078406836 | I41: =I38/I$36 -> 0.06800774 | ... M41: =M38/M$36 -> #DIV/0!
A42: Otros gastos | B42: =B39/B$36 -> 0.0041565434 | C42: =C39/C$36 -> 0.0073058959 | D42: =D39/D$36 -> 0.0036234241 | E42: =E39/E$36 -> 0.0060226185 | F42: =F39/F$36 -> 0.0046552607 | G42: =G39/G$36 -> 0.0049117733 | H42: =H39/H$36 -> 0.0053257648 | I42: =I39/I$36 -> 0.0081206521 | ... M42: =M39/M$36 -> #DIV/0!
A45: FRENCH
A46: Concepto | B46: 1-ene | C46: 1-feb | D46: 1-mar | E46: 1-abr | F46: 1-may | G46: 1-jun | H46: 1-jul | I46: 1-ago | J46: 45901 | K46: 45931 | L46: 45962 | M46: 45992
A47: Venta | B47: 15489470 | C47: 10874150 | D47: 20184000 | E47: 13943860 | F47: 16508620 | G47: 16960280 | H47: 15519341 | I47: ='Agosto-real'!C8 -> 16141623 | J47: =Septiembre_real!C7 -> 19997040 | K47: =Octubre_real!C7 -> 19749649 | L47: =Noviembre_real!C7 -> 31448390 | M47: =Diciembre_real!C7 -> 0
A48: Sueldos | B48: 2954248.5 | C48: 3743565.4 | D48: 3179852.3 | E48: 3429207.4 | F48: 3409856.4 | G48: 3488406.3 | H48: 3398151.3 | I48: ='Agosto-real'!D8 -> 2609720.2 | J48: =Septiembre_real!D7 -> 2444318 | K48: =Octubre_real!D7 -> 2611013 | L48: =Noviembre_real!D7 -> 2874528 | M48: =Diciembre_real!D7 -> 0
A49: Alquiler y expensas | B49: 868340 | C49: 784600 | D49: 828230 | E49: 825046.93 | F49: 873351.79 | G49: 907729.21 | H49: 884335.92 | I49: ='Agosto-real'!G8 -> 909802.21 | J49: =Septiembre_real!G7 -> 923840 | K49: =Octubre_real!G7 -> 952237.97 | L49: =Noviembre_real!G7 -> 949306 | M49: =Diciembre_real!G7 -> 0
A50: Otros gastos | B50: 285289.01 | C50: 336254.14 | D50: 287638.92 | E50: 325369.83 | F50: 347427.62 | G50: 271715 | H50: 299902.2 | I50: ='Agosto-real'!H8 -> 462502.76 | J50: =Septiembre_real!H7 -> 419343.85 | K50: =Octubre_real!H7 -> 523330.01 | L50: =Noviembre_real!H7 -> 433695.18 | M50: =Diciembre_real!H7 -> 0
A51: Sueldos | B51: =B48/B$47 -> 0.19072625 | C51: =C48/C$47 -> 0.34426281 | D51: =D48/D$47 -> 0.15754322 | E51: =E48/E$47 -> 0.24592956 | F51: =F48/F$47 -> 0.20655006 | G51: =G48/G$47 -> 0.20568094 | H51: =H48/H$47 -> 0.21896234 | I51: =I48/I$47 -> 0.16167645 | ... M51: =M48/M$47 -> #DIV/0!
A52: Alquiler y expensas | B52: =B49/B$47 -> 0.05606002 | C52: =C49/C$47 -> 0.072152766 | D52: =D49/D$47 -> 0.041033987 | E52: =E49/E$47 -> 0.059169192 | F52: =F49/F$47 -> 0.052902774 | G52: =G49/G$47 -> 0.053520886 | H52: =H49/H$47 -> 0.056982827 | I52: =I49/I$47 -> 0.056363738 | ... M52: =M49/M$47 -> #DIV/0!
A53: Otros gastos | B53: =B50/B$47 -> 0.018418255 | C53: =C50/C$47 -> 0.030922338 | D53: =D50/D$47 -> 0.014250838 | E53: =E50/E$47 -> 0.023334273 | F53: =F50/F$47 -> 0.021045225 | G53: =G50/G$47 -> 0.016020667 | H53: =H50/H$47 -> 0.019324416 | I53: =I50/I$47 -> 0.028652804 | ... M53: =M50/M$47 -> #DIV/0!
A56: ZONA SAN TELMO
A57: Concepto | B57: 1-ene | C57: 1-feb | D57: 1-mar | E57: 1-abr | F57: 1-may | G57: 1-jun | H57: 1-jul | I57: 1-ago | J57: 45901 | K57: 45931 | L57: 45962 | M57: 45992
A58: Venta | B58: =B36+B47 -> 55547889 | C58: =C36+C47 -> 43383510 | D58: =D36+D47 -> 55627210 | E58: =E36+E47 -> 38334910 | F58: =F36+F47 -> 39824730 | G58: =G36+G47 -> 41459550 | H58: =H36+H47 -> 42001791 | I58: =I36+I47 -> 50178903 | ... M58: =M36+M47 -> 0
A59: Sueldos | B59: =B37+B48 -> 5387491.9 | C59: =C37+C48 -> 6268600 | D59: =D37+D48 -> 7786037.2 | E59: =E37+E48 -> 7662100.3 | F59: =F37+F48 -> 8072962 | G59: =G37+G48 -> 8223454.5 | H59: =H37+H48 -> 8007519.6 | I59: =I37+I48 -> 5694414.9 | ... M59: =M37+M48 -> 0
A60: Alquiler y expensas | B60: =B38+B49 -> 4401415.2 | C60: =C38+C49 -> 3841173.4 | D60: =D38+D49 -> 3310860.1 | E60: =E38+E49 -> 3501422.6 | F60: =F38+F49 -> 2974736 | G60: =G38+G49 -> 2971495.4 | H60: =H38+H49 -> 2960741 | I60: =I38+I49 -> 3224600.7 | ... M60: =M38+M49 -> 0
A61: Otros gastos | B61: =B39+B50 -> 451793.57 | C61: =C39+C50 -> 573764.14 | D61: =D39+D50 -> 416064.7 | E61: =E39+E50 -> 472267.82 | F61: =F39+F50 -> 455970.19 | G61: =G39+G50 -> 392049.86 | H61: =H39+H50 -> 440941.5 | I61: =I39+I50 -> 738907.67 | ... M61: =M39+M50 -> 0
A62: Sueldos | B62: =B59/B$58 -> 0.096988239 | C62: =C59/C$58 -> 0.14449269 | D62: =D59/D$58 -> 0.13996814 | E62: =E59/E$58 -> 0.19987266 | F62: =F59/F$58 -> 0.20271229 | G62: =G59/G$58 -> 0.19834886 | H62: =H59/H$58 -> 0.1906471 | I62: =I59/I$58 -> 0.11348225 | ... M62: =M59/M$58 -> #DIV/0!
A63: Alquiler y expensas | B63: =B60/B$58 -> 0.079236408 | C63: =C60/C$58 -> 0.08853994 | D63: =D60/D$58 -> 0.059518716 | E63: =E60/E$58 -> 0.091337703 | F63: =F60/F$58 -> 0.074695697 | G63: =G60/G$58 -> 0.071672158 | H63: =H60/H$58 -> 0.070490828 | I63: =I60/I$58 -> 0.06426208 | ... M63: =M60/M$58 -> #DIV/0!
A64: Otros gastos | B64: =B61/B$58 -> 0.0081334066 | C64: =C61/C$58 -> 0.013225397 | D64: =D61/D$58 -> 0.0074795177 | E64: =E61/E$58 -> 0.012319523 | F64: =F61/F$58 -> 0.011449423 | G64: =G61/G$58 -> 0.0094562015 | H64: =H61/H$58 -> 0.010498159 | I64: =I61/I$58 -> 0.014725465 | ... M64: =M61/M$58 -> #DIV/0!
A67: SAN TELMO 2
A68: Concepto | B68: 1-ene | C68: 1-feb | D68: 1-mar | E68: 1-abr | F68: 1-may | G68: 1-jun | H68: 1-jul | I68: 1-ago | J68: 45901 | K68: 45931 | L68: 45962 | M68: 45992
A69: Venta | B69: 2472710 | C69: 4561520 | D69: 9767149 | E69: 7597050 | F69: 7007130 | G69: 10595670 | H69: 9569768 | I69: ='Agosto-real'!C9 -> 10898600 | J69: =Septiembre_real!C10 -> 12808500 | K69: =Octubre_real!C10 -> 14527110 | L69: =Noviembre_real!C10 -> 24191146 | M69: =Diciembre_real!C10 -> 0
A70: Sueldos | B70: 1809449.8 | C70: 1924583 | D70: 2035425.9 | E70: 2341500.5 | F70: 2921356.6 | G70: 2451863.4 | H70: 2342497.3 | I70: ='Agosto-real'!D9 -> 2415229.8 | J70: =Septiembre_real!D10 -> 2087438 | K70: =Octubre_real!D10 -> 2640837 | L70: =Noviembre_real!D10 -> 2658266 | M70: =Diciembre_real!D10 -> 0
A71: Alquiler y expensas | B71: 1337846.8 | C71: 1242335 | D71: 1164596.8 | E71: 1168004.5 | F71: 1302751 | G71: 1417632.2 | H71: 1385521.1 | I71: ='Agosto-real'!G9 -> 1460985.1 | J71: =Septiembre_real!G10 -> 1432031.5 | K71: =Octubre_real!G10 -> 1597173.3 | L71: =Noviembre_real!G10 -> 1850678.3 | M71: =Diciembre_real!G10 -> 0
A72: Otros gastos | B72: 83461.05 | C72: 118196.65 | D72: 119133.85 | E72: 137554.67 | F72: 178268.44 | G72: 113029.67 | H72: 81728.47 | I72: ='Agosto-real'!H9 -> 444315.8 | J72: =Septiembre_real!H10 -> 189129.62 | K72: =Octubre_real!H10 -> 146799.82 | L72: =Noviembre_real!H10 -> 1291237.8 | M72: =Diciembre_real!H10 -> 0
A73: Sueldos | B73: =B70/B$69 -> 0.7317679 | C73: =C70/C$69 -> 0.42191704 | D73: =D70/D$69 -> 0.20839509 | E73: =E70/E$69 -> 0.30821181 | F73: =F70/F$69 -> 0.416912 | G73: =G70/G$69 -> 0.23140239 | H73: =H70/H$69 -> 0.24478099 | I73: =I70/I$69 -> 0.22160918 | ... M73: =M70/M$69 -> #DIV/0!
A74: Alquiler y expensas | B74: =B71/B$69 -> 0.54104475 | C74: =C71/C$69 -> 0.27235109 | D74: =D71/D$69 -> 0.1192361 | E74: =E71/E$69 -> 0.15374448 | F74: =F71/F$69 -> 0.18591791 | G74: =G71/G$69 -> 0.13379354 | H74: =H71/H$69 -> 0.14478106 | I74: =I71/I$69 -> 0.13405254 | ... M74: =M71/M$69 -> #DIV/0!
A75: Otros gastos | B75: =B72/B$69 -> 0.033752866 | C75: =C72/C$69 -> 0.025911681 | D75: =D72/D$69 -> 0.012197403 | E75: =E72/E$69 -> 0.018106327 | F75: =F72/F$69 -> 0.025441007 | G75: =G72/G$69 -> 0.010667534 | H75: =H72/H$69 -> 0.008540277 | I75: =I72/I$69 -> 0.040768154 | ... M75: =M72/M$69 -> #DIV/0!
A78: GÜEMES
A79: Concepto | B79: 1-ene | C79: 1-feb | D79: 1-mar | E79: 1-abr | F79: 1-may | G79: 1-jun | H79: 1-jul | I79: 1-ago | J79: 45901 | K79: 45931 | L79: 45962 | M79: 45992
A80: Venta | B80: 2607560 | C80: 3150490 | D80: 3287540 | E80: 2853620 | F80: 4034430 | G80: 4016350 | H80: 4523190 | I80: ='Agosto-real'!C5 -> 4168817.5 | J80: =Septiembre_real!C9 -> 4814090 | K80: =Octubre_real!C9 -> 5985346 | L80: =Noviembre_real!C9 -> 5000090 | M80: =Diciembre_real!C9 -> 0
A81: Sueldos | B81: 1796986.9 | C81: 797689.43 | D81: 1447369.1 | E81: 2296399.7 | F81: 2303093.9 | G81: 2059091.1 | H81: 2159026.7 | I81: ='Agosto-real'!D5 -> 1914315.8 | J81: =Septiembre_real!D9 -> 1976546 | K81: =Octubre_real!D9 -> 2111208 | L81: =Noviembre_real!D9 -> 1669932 | M81: =Diciembre_real!D9 -> 0
A82: Alquiler y expensas | B82: 1122708.8 | C82: 806259 | D82: 798589 | E82: 821068.89 | F82: 815338.14 | G82: 881448.16 | H82: 906090.96 | I82: ='Agosto-real'!G5 -> 927278.16 | J82: =Septiembre_real!G9 -> 938106.24 | K82: =Octubre_real!G9 -> 1000893 | L82: =Noviembre_real!G9 -> 997526.95 | M82: =Diciembre_real!G9 -> 0
A83: Otros gastos | B83: 101378.79 | C83: 39614.16 | D83: 2000443 | E83: 58830 | F83: 59755 | G83: 139251 | H83: 104555 | I83: ='Agosto-real'!H5 -> 315055 | J83: =Septiembre_real!H9 -> 159124 | K83: =Octubre_real!H9 -> 409319 | L83: =Noviembre_real!H9 -> 150044 | M83: =Diciembre_real!H9 -> 0
A84: Sueldos | B84: =B81/B$80 -> 0.689145 | C84: =C81/C$80 -> 0.25319535 | D84: =D81/D$80 -> 0.44025901 | E84: =E81/E$80 -> 0.80473213 | F84: =F81/F$80 -> 0.5708598 | G84: =G81/G$80 -> 0.51267721 | H84: =H81/H$80 -> 0.4773239 | I84: =I81/I$80 -> 0.45919875 | ... M84: =M81/M$80 -> #DIV/0!
A85: Alquiler y expensas | B85: =B82/B$80 -> 0.43055914 | C85: =C82/C$80 -> 0.25591543 | D85: =D82/D$80 -> 0.24291385 | E85: =E82/E$80 -> 0.28772888 | F85: =F82/F$80 -> 0.202095 | G85: =G82/G$80 -> 0.21946498 | H85: =H82/H$80 -> 0.20032122 | I85: =I82/I$80 -> 0.22243194 | ... M85: =M82/M$80 -> #DIV/0!
A86: Otros gastos | B86: =B83/B$80 -> 0.038878795 | C86: =C83/C$80 -> 0.012573968 | D86: =D83/D$80 -> 0.60849237 | E86: =E83/E$80 -> 0.020615919 | F86: =F83/F$80 -> 0.014811262 | G86: =G83/G$80 -> 0.034671032 | H86: =H83/H$80 -> 0.023115323 | I86: =I83/I$80 -> 0.075574189 | ... M86: =M83/M$80 -> #DIV/0!
A89: GÜEMES+SAN TELMO 2
A90: Concepto | B90: 1-ene | C90: 1-feb | D90: 1-mar | E90: 1-abr | F90: 1-may | G90: 1-jun | H90: 1-jul | I90: 1-ago | J90: 45901 | K90: 45931 | L90: 45962 | M90: 45992
A91: Venta | B91: =B69+B80 -> 5080270 | C91: =C69+C80 -> 7712010 | D91: =D69+D80 -> 13054689 | E91: =E69+E80 -> 10450670 | F91: =F69+F80 -> 11041560 | G91: =G69+G80 -> 14612020 | H91: =H69+H80 -> 14092958 | I91: =I69+I80 -> 15067418 | ... M91: =M69+M80 -> 0
A92: Sueldos | B92: =B70+B81 -> 3606436.7 | C92: =C70+C81 -> 2722272.5 | D92: =D70+D81 -> 3482795.1 | E92: =E70+E81 -> 4637900.2 | F92: =F70+F81 -> 5224450.5 | G92: =G70+G81 -> 4510954.5 | H92: =H70+H81 -> 4501524 | I92: =I70+I81 -> 4329545.6 | ... M92: =M70+M81 -> 0
A93: Alquiler y expensas | B93: =B71+B82 -> 2460555.5 | C93: =C71+C82 -> 2048594 | D93: =D71+D82 -> 1963185.8 | E93: =E71+E82 -> 1989073.4 | F93: =F71+F82 -> 2118089.1 | G93: =G71+G82 -> 2299080.4 | H93: =H71+H82 -> 2291612.1 | I93: =I71+I82 -> 2388263.2 | ... M93: =M71+M82 -> 0
A94: Otros gastos | B94: =B72+B83 -> 184839.84 | C94: =C72+C83 -> 157810.81 | D94: =D72+D83 -> 2119576.9 | E94: =E72+E83 -> 196384.67 | F94: =F72+F83 -> 238023.44 | G94: =G72+G83 -> 252280.67 | H94: =H72+H83 -> 186283.47 | I94: =I72+I83 -> 759370.8 | ... M94: =M72+M83 -> 0
A95: Sueldos | B95: =B92/B$91 -> 0.70989076 | C95: =C92/C$91 -> 0.3529913 | D95: =D92/D$91 -> 0.26678499 | E95: =E92/E$91 -> 0.44378975 | F95: =F92/F$91 -> 0.47316235 | G95: =G92/G$91 -> 0.30871532 | H95: =H92/H$91 -> 0.31941655 | I95: =I92/I$91 -> 0.2873449 | ... M95: =M92/M$91 -> #DIV/0!
A96: Alquiler y expensas | B96: =B93/B$91 -> 0.48433559 | C96: =C93/C$91 -> 0.26563684 | D96: =D93/D$91 -> 0.15038166 | E96: =E93/E$91 -> 0.19032975 | F96: =F93/F$91 -> 0.19182879 | G96: =G93/G$91 -> 0.15734172 | H96: =H93/H$91 -> 0.16260689 | I96: =I93/I$91 -> 0.15850515 | ... M96: =M93/M$91 -> #DIV/0!
A97: Otros gastos | B97: =B94/B$91 -> 0.036383861 | C97: =C94/C$91 -> 0.020462993 | D97: =D94/D$91 -> 0.16236134 | E97: =E94/E$91 -> 0.018791587 | F97: =F94/F$91 -> 0.021557048 | G97: =G94/G$91 -> 0.017265284 | H97: =H94/H$91 -> 0.013218195 | I97: =I94/I$91 -> 0.050398205 | ... M97: =M94/M$91 -> #DIV/0!
A100: AS SAN TELMO
A101: Concepto | B101: 1-ene | C101: 1-feb | D101: 1-mar | E101: 1-abr | F101: 1-may | G101: 1-jun | H101: 1-jul | I101: 1-ago | J101: 45901 | K101: 45931 | L101: 45962 | M101: 45992
A102: Venta | B102: 14424775 | C102: 14999900 | D102: 21851620 | E102: 16091300 | F102: 14015923 | G102: 17355500 | H102: 20997170 | I102: ='Agosto-real'!C11 -> 14676490 | J102: =Septiembre_real!C12 -> 12870480 | K102: =Octubre_real!C12 -> 19169518 | L102: =Noviembre_real!C12 -> 20563510 | M102: =Diciembre_real!C12 -> 0
A103: Sueldos | B103: 3500002.3 | C103: 3213838.2 | D103: 4921852.2 | E103: 4520864.5 | F103: 4711699.5 | G103: 4634585 | H103: 4755910.5 | I103: ='Agosto-real'!D11 -> 3434064.9 | J103: =Septiembre_real!D12 -> 2855608 | K103: =Octubre_real!D12 -> 3435615 | L103: =Noviembre_real!D12 -> 3468754 | M103: =Diciembre_real!D12 -> 0
A104: Alquiler y expensas | B104: 2821199.3 | C104: 2604922.6 | D104: 1762890.1 | E104: 2382737.4 | F104: 2156055 | G104: 2105437.4 | H104: 2258662.2 | I104: ='Agosto-real'!G11 -> 2716335 | J104: =Septiembre_real!G12 -> 2154281.3 | K104: =Octubre_real!G12 -> 2034532.7 | L104: =Noviembre_real!G12 -> 2726013.2 | M104: =Diciembre_real!G12 -> 0
A105: Otros gastos | B105: 193861.84 | C105: 271100.95 | D105: 215696.71 | E105: 324659.96 | F105: 289620.19 | G105: 191124.74 | H105: 200142.29 | I105: ='Agosto-real'!H11 -> 2896000 | J105: =Septiembre_real!H12 -> 2038403.4 | K105: =Octubre_real!H12 -> 470452.8 | L105: =Noviembre_real!H12 -> 189763.77 | M105: =Diciembre_real!H12 -> 0
A106: Sueldos | B106: =B103/B$102 -> 0.24263826 | C106: =C103/C$102 -> 0.21425731 | D106: =D103/D$102 -> 0.22523969 | E106: =E103/E$102 -> 0.28095085 | F106: =F103/F$102 -> 0.33616762 | G106: =G103/G$102 -> 0.2670384 | H106: =H103/H$102 -> 0.22650245 | I106: =I103/I$102 -> 0.23398407 | ... M106: =M103/M$102 -> #DIV/0!
A107: Alquiler y expensas | B107: =B104/B$102 -> 0.19558012 | C107: =C104/C$102 -> 0.17366267 | D107: =D104/D$102 -> 0.080675487 | E107: =E104/E$102 -> 0.14807613 | F107: =F104/F$102 -> 0.15382897 | G107: =G104/G$102 -> 0.1213124 | H107: =H104/H$102 -> 0.10756984 | I107: =I104/I$102 -> 0.1850807 | ... M107: =M104/M$102 -> #DIV/0!
A108: Otros gastos | B108: =B105/B$102 -> 0.013439505 | C108: =C105/C$102 -> 0.018073517 | D108: =D105/D$102 -> 0.0098709711 | E108: =E105/E$102 -> 0.020176118 | F108: =F105/F$102 -> 0.020663654 | G108: =G105/G$102 -> 0.011012344 | H108: =H105/H$102 -> 0.0095318698 | I108: =I105/I$102 -> 0.19732238 | ... M108: =M105/M$102 -> #DIV/0!
A111: EL SOLAR
A112: Concepto | B112: 1-ene | C112: 1-feb | D112: 1-mar | E112: 1-abr | F112: 1-may | G112: 1-jun | H112: 1-jul | I112: 1-ago | J112: 45901 | K112: 45931 | L112: 45962 | M112: 45992
A113: Venta | K113: 6544524 | L113: 6889990 | M113: =Diciembre_real!C13 -> 0
A114: Sueldos | K114: =Octubre_real!D13 -> 4586090.1 | L114: =Noviembre_real!D13 -> 5328412.8 | M114: =Diciembre_real!D13 -> 0
A115: Alquiler y expensas | K115: =Octubre_real!G13 -> 1635000 | L115: =Noviembre_real!G13 -> 1781164.4 | M115: =Diciembre_real!G13 -> 0
A116: Otros gastos | K116: =Octubre_real!H13 -> 0 | L116: =Noviembre_real!H13 -> 125207.61 | M116: =Diciembre_real!H13 -> 0
A117: Sueldos | B117: =B114/B$102 -> 0 | C117: =C114/C$102 -> 0 | D117: =D114/D$102 -> 0 | E117: =E114/E$102 -> 0 | F117: =F114/F$102 -> 0 | G117: =G114/G$102 -> 0 | H117: =H114/H$102 -> 0 | I117: =I114/I$102 -> 0 | ... M117: =M114/M$102 -> #DIV/0!
A118: Alquiler y expensas | B118: =B115/B$102 -> 0 | C118: =C115/C$102 -> 0 | D118: =D115/D$102 -> 0 | E118: =E115/E$102 -> 0 | F118: =F115/F$102 -> 0 | G118: =G115/G$102 -> 0 | H118: =H115/H$102 -> 0 | I118: =I115/I$102 -> 0 | ... M118: =M115/M$102 -> #DIV/0!
A119: Otros gastos | B119: =B116/B$102 -> 0 | C119: =C116/C$102 -> 0 | D119: =D116/D$102 -> 0 | E119: =E116/E$102 -> 0 | F119: =F116/F$102 -> 0 | G119: =G116/G$102 -> 0 | H119: =H116/H$102 -> 0 | I119: =I116/I$102 -> 0 | ... M119: =M116/M$102 -> #DIV/0!
A122: AS Güemes
...
