Workbook

Sheet Tabla resumen
A1: GASTOS PROYECTADOS
A3: OCTUBRE 2025
A5: Tiendas | B5: Alquiler | C5: Expensas | D5: Personal | E5: Otros gastos | F5: Total
A6: Florida | B6: ='Alquileres+expensas'!G16 -> 7000000 | C6: ='Alquileres+expensas'!H16 -> 315462.53 | D6: =Personal!O28 -> 5492982.3 | E6: ='Otros gastos'!L17 -> 1940453.3 | F6: =SUM(B6:E6) -> 14748898
A7: Güemes | B7: ='Alquileres+expensas'!G17 -> 644652 | C7: ='Alquileres+expensas'!H17 -> 355772.7 | D7: =Personal!P28 -> 1962173.7 | E7: ='Otros gastos'!L18 -> 109000 | F7: =SUM(B7:E7) -> 3071598.4
A8: Recoleta | B8: ='Alquileres+expensas'!G18 -> 1503831.8 | C8: ='Alquileres+expensas'!H18 -> 2045417.3 | D8: =Personal!Q28 -> 3254091.1 | E8: ='Otros gastos'!L19 -> 222000 | F8: =SUM(B8:E8) -> 7025340.2
A9: French | B9: ='Alquileres+expensas'!G19 -> 703000 | C9: ='Alquileres+expensas'!H19 -> 231882 | D9: =Personal!T28 -> 2674963.2 | E9: ='Otros gastos'!L20 -> 343000 | F9: =SUM(B9:E9) -> 3952845.2
A10: San Telmo 1 (92) | B10: ='Alquileres+expensas'!G20 -> 2190713.4 | C10: ='Alquileres+expensas'!H20 -> 557886.84 | D10: =Personal!R28 -> 3161812.1 | E10: ='Otros gastos'!L21 -> 153000 | F10: =SUM(B10:E10) -> 6063412.3
A11: San Telmo 2 (122) | B11: ='Alquileres+expensas'!G21 -> 1058553.7 | C11: ='Alquileres+expensas'!H21 -> 557886.84 | D11: =Personal!S28 -> 2475610.5 | E11: ='Otros gastos'!L22 -> 248000 | F11: =SUM(B11:E11) -> 4340051.1
A12: AS San Telmo (120/121) | B12: ='Alquileres+expensas'!G22 -> 961918.51 | C12: ='Alquileres+expensas'!H22 -> 1115773.7 | D12: =Personal!U28 -> 3519916.5 | E12: ='Otros gastos'!L23 -> 210000 | F12: =SUM(B12:E12) -> 5807608.7
A15: NOVIEMBRE
A17: Tiendas | B17: Alquiler | C17: Expensas
A18: Florida | B18: =1450*5000 -> 7250000
A19: Güemes
A20: Recoleta
A21: French | B21: ='Alquileres+expensas'!G31 -> 1448355.7
A22: San Telmo 1 (92)
A23: San Telmo 2 (122)
A24: AS San Telmo (120/121)
A25: El Solar

Sheet Alquileres+expensas
A2: PROYECCIÓN A NOVIEMBRE 2025 | C2: Dólar proyectado: | D2: 1460
A3: Tiendas | B3: Venta de octubre x Alegra (sin terminar el 31/10) | D3: % Alquiler variable | E3: Alquiler fijo | F3: Alquiler variable | G3: Total alquiler | H3: Expensas proyectadas a pagar en noviembre (son de octubre)
B4: Con IVA | C4: Sin IVA
A5: Florida | B5: 58172539 | C5: =B5/1.21 -> 48076479 | E5: =5000*D2 -> 7300000 | F5: =C5*D5 -> 0 | G5: =E5 -> 7300000 | H5: =J16*$N$16+J16 -> 484460.03 | M5: aumento estimado de expensas: | N5: 0.05
A6: Güemes | B6: 6304810 | C6: =B6/1.21 -> 5210586.8 | D6: 0.09 | E6: 645612 | F6: =C6*D6 -> 468952.81 | G6: =IF(F6>E6,F6,E6) -> 645612 | H6: =J17*$N$16+J17 -> 373184.7
A7: Recoleta | B7: 32000000 | C7: =B7/1.21 -> 26446281 | D7: 0.07 | E7: 1157930 | F7: =C7*D7 -> 1851239.7 | G7: =IF(E7>F7,E7*1.15,F7*1.15) -> 2128925.6 | H7: =J18*$N$16+J18 -> 2131510.3
A8: French | B8: 19965750 | C8: =B8/1.21 -> 16500620 | E8: 703000 | F8: =C8*D8 -> 0 | G8: =E8 -> 703000 | H8: =J19*$N$16+J19 -> 261699.87
A9: San Telmo 1 (92) | B9: 32300000 | C9: =B9/1.21 -> 26694215 | D9: 0.08 | F9: =C9*D9 -> 2135537.2 | G9: =IF(E9>F9,E9,F9) -> 2135537.2 | H9: =J20*$N$16+J20 -> 565551.33
A10: San Telmo 2 (122) | B10: 14000000 | C10: =B10/1.21 -> 11570248 | D10: 0.1 | F10: =C10*D10 -> 1157024.8 | G10: =IF(E10>F10,E10,F10) -> 1157024.8 | H10: =J21*$N$16+J21 -> 565551.33
A11: AS San Telmo (120/121) | B11: 18300000 | C11: =B11/1.21 -> 15123967 | D11: 0.09 | F11: =C11*D11 -> 1361157 | G11: =IF(E11>F11,E11,F11) -> 1361157 | H11: =J22*$N$16+J22 -> 1131102.7
A13: CÁLCULOS OCTUBRE 2025 | C13: Dólar proyectado: | D13: 1400
A14: Tiendas | B14: Venta de septiembre (reales) | D14: % Alquiler variable | E14: Alquiler fijo | F14: Alquiler variable | G14: Total alquiler proyectado | H14: Expensas proyectadas a pagar en octubre (son de septiembre) | I14: Alquiler pagado | J14: Expensas pagadas
B15: Con IVA | C15: Sin IVA
A16: Florida | B16: 61574791 | C16: =B16/1.21 -> 50888257 | E16: =5000*D13 -> 7000000 | F16: =C16*D16 -> 0 | G16: =E16 -> 7000000 | H16: =H29*$N$16+H29 -> 315462.53 | I16: 7275000 | J16: 461390.5 | M16: aumento estimado de expensas: | N16: 0.05
A17: Güemes | B17: 4814090 | C17: =B17/1.21 -> 3978586.8 | D17: 0.09 | E17: 644652 | F17: =C17*D17 -> 358072.81 | G17: =IF(F17>E17,F17,E17) -> 644652 | H17: =H30*$N$16+H30 -> 355772.7 | I17: 599275 | J17: 355414
A18: Recoleta | B18: 22604180 | C18: =B18/1.21 -> 18681140 | D18: 0.07 | E18: 1155707 | F18: =C18*D18 -> 1307679.8 | G18: =IF(E18>F18,E18*1.15,F18*1.15) -> 1503831.8 | H18: =H31*$N$16+H31 -> 2045417.3 | I18: 1572090 | J18: 2030009.8
A19: French | B19: 17753290 | C19: =B19/1.21 -> 14672140 | E19: 703000 | F19: =C19*D19 -> 0 | G19: =E19 -> 703000 | H19: =H32*$N$16+H32 -> 231882 | I19: 703000 | J19: 249237.97
A20: San Telmo 1 (92) | B20: 33134540 | C20: =B20/1.21 -> 27383917 | D20: 0.08 | E20: 928265 | F20: =C20*D20 -> 2190713.4 | G20: =IF(E20>F20,E20,F20) -> 2190713.4 | H20: =H33*$N$16+H33 -> 557886.84 | I20: 2190647 | J20: 538620.31
A21: San Telmo 2 (122) | B21: 12808500 | C21: =B21/1.21 -> 10585537 | D21: 0.1 | E21: 955000 | F21: =C21*D21 -> 1058553.7 | G21: =IF(E21>F21,E21,F21) -> 1058553.7 | H21: =H34*$N$16+H34 -> 557886.84 | I21: 1058553 | J21: 538620.31
A22: AS San Telmo (120/121) | B22: 12932460 | C22: =B22/1.21 -> 10687983 | D22: 0.09 | E22: 836100 | F22: =C22*D22 -> 961918.51 | G22: =IF(E22>F22,E22,F22) -> 961918.51 | H22: =H35*$N$16+H35 -> 1115773.7 | I22: 957292.11 | J22: 1077240.6
A26: PROYECCIÓN A SEPTIEMBRE 2025 | C26: Dólar: | D26: 1400
A27: Tiendas | B27: Venta agosto | D27: % Alquiler variable | E27: Alquiler fijo | F27: Alquiler variable | G27: Total alquiler | H27: Expensas pagadas en septiembre (son de agosto)
B28: con IVA | C28: sin IVA
A29: Florida | B29: 45735238 | C29: =B29/1.21 -> 37797718 | E29: =5000*D26 -> 7000000 | F29: =C29*D29 -> 0 | G29: =E29 -> 7000000 | H29: 300440.5
A30: Güemes | B30: 4168817.5 | C30: =B30/1.21 -> 3445303.7 | D30: 0.09 | E30: 599275.1 | F30: =C30*D30 -> 310077.33 | G30: =IF(F30>E30,F30,E30) -> 599275.1 | H30: 338831.14
A31: Recoleta | B31: 21770316 | C31: =B31/1.21 -> 17991996 | D31: 0.07 | E31: 1092714 | F31: =C31*D31 -> 1259439.8 | G31: =IF(E31>F31,E31*1.15,F31*1.15) -> 1448355.7 | H31: 1948016.5
A32: French | B32: 16141623 | C32: =B32/1.21 -> 13340184 | E32: 703000 | F32: =C32*D32 -> 0 | G32: =E32 -> 703000 | H32: 220840
A33: San Telmo 1 (92) | B33: 34037280 | C33: =B33/1.21 -> 28129983 | D33: 0.08 | E33: 928265 | F33: =C33*D33 -> 2250398.7 | G33: =IF(E33>F33,E33,F33) -> 2250398.7 | H33: 531320.8
A34: San Telmo 2 (122) | B34: 10898600 | C34: =B34/1.21 -> 9007107.4 | D34: 0.1 | E34: 887700 | F34: =C34*D34 -> 900710.74 | G34: =IF(E34>F34,E34,F34) -> 900710.74 | H34: 531320.8
A35: AS San Telmo (120/121) | B35: 14676490 | C35: =B35/1.21 -> 12129331 | D35: 0.09 | E35: 836100 | F35: =C35*D35 -> 1091639.8 | G35: =IF(E35>F35,E35,F35) -> 1091639.8 | H35: 1062641.6
A38: Cálculos AGOSTO 2025
A39: Tiendas | B39: Venta | D39: % Alquiler variable | E39: Alquiler fijo AGOSTO | G39: Alquiler variable AGOSTO | I39: Total alquiler | K39: Expensas pagadas en agosto (son de julio)
B40: con IVA | C40: sin IVA | E40: x contrato | F40: pagado | G40: x contrato | H40: pagado | I40: x contrato | J40: pagado
A41: Florida | B41: 35622735 | C41: =B41/1.21 -> 29440277 | F41: 6550000 | G41: =C41*D41 -> 0 | I41: =E41 -> 0 | J41: =H41+F41 -> 6550000 | K41: 407740.5
A42: Güemes | B42: 4523190 | C42: =B42/1.21 -> 3738173.6 | D42: 0.09 | E42: 599544 | F42: 599275.1 | G42: =C42*D42 -> 336435.62 | I42: =IF(G42>E42,G42,E42) -> 599544 | J42: =H42+F42 -> 599275.1 | K42: 328003.06
A43: Recoleta | B43: 18589226 | C43: =B43/1.21 -> 15362997 | D43: 0.07 | E43: 1092714 | F43: 1299988.6 | G43: =C43*D43 -> 1075409.8 | I43: =IF(G43>E43,G43,E43) -> 1092714 | J43: =H43+F43 -> 1299988.6 | K43: 1901854.1
A44: French | B44: 15519341 | C44: =B44/1.21 -> 12825902 | E44: 663059 | F44: 667200 | G44: =C44*D44 -> 0 | I44: =E44 -> 663059 | J44: =H44+F44 -> 667200 | K44: 242602
A45: San Telmo 1 (92) | B45: 26482450 | C45: =B45/1.21 -> 21886322 | D45: 0.08 | F45: 928265 | G45: =C45*D45 -> 1750905.8 | H45: 813248.44 | I45: =E45+G45 -> 1750905.8 | J45: =H45+F45 -> 1741513.4 | K45: 573285.05
A46: San Telmo 2 (122) | B46: 9569768 | C46: =B46/1.21 -> 7908899.2 | D46: 0.1 | F46: 887700 | G46: =C46*D46 -> 790889.92 | I46: =E46+G46 -> 790889.92 | J46: =H46+F46 -> 887700 | K46: =K45 -> 573285.05
A47: AS San Telmo (120/121) | B47: 20997170 | C47: =B47/1.21 -> 17353033 | D47: 0.09 | F47: 836100 | G47: =C47*D47 -> 1561773 | H47: 733664.97 | I47: =E47+G47 -> 1561773 | J47: =H47+F47 -> 1569765 | K47: 1146570.1

Sheet Personal
A1: HORAS | D1: 0.025
A2: Legajo | B2: Apellido y Nombre | C2: Valor hora AGOSTO | D2: Valor hora proyectada a OCTUBRE | E2: Florida | F2: Güemes | G2: Recoleta | H2: San Telmo 1 | I2: San Telmo 2 | J2: French | K2: AS San Telmo | L2: Total horas | O2: Florida | P2: Güemes | Q2: Recoleta | R2: San Telmo 1 | S2: San Telmo 2 | T2: French | U2: AS San Telmo
A3: 1 | B3: Viña Sofia | C3: =VLOOKUP(A3,[1]Listado!$A$2:$Q$28,17,FALSE) -> 10040.929 | D3: =C3*$D$1+C3 -> 10291.952 | E3: 117 | L3: =SUM(E3:K3) -> 117 | O3: =E3*$D3 -> 1204158.4 | P3: =F3*$D3 -> 0 | Q3: =G3*$D3 -> 0 | R3: =H3*$D3 -> 0 | S3: =I3*$D3 -> 0 | T3: =J3*$D3 -> 0 | U3: =K3*$D3 -> 0
A4: 3 | B4: Ruiz de la Torre Maitena | C4: =VLOOKUP(A4,[1]Listado!$A$2:$Q$28,17,FALSE) -> 9702.5268 | D4: =C4*$D$1+C4 -> 9945.09 | E4: 122 | L4: =SUM(E4:K4) -> 122 | O4: =E4*$D4 -> 1213301 | P4: =F4*$D4 -> 0 | Q4: =G4*$D4 -> 0 | R4: =H4*$D4 -> 0 | S4: =I4*$D4 -> 0 | T4: =J4*$D4 -> 0 | U4: =K4*$D4 -> 0
A5: 4 | B5: Imperiale Candela | C5: =VLOOKUP(A5,[1]Listado!$A$2:$Q$28,17,FALSE) -> 9963.7222 | D5: =C5*$D$1+C5 -> 10212.815 | E5: 130 | L5: =SUM(E5:K5) -> 130 | O5: =E5*$D5 -> 1327666 | P5: =F5*$D5 -> 0 | Q5: =G5*$D5 -> 0 | R5: =H5*$D5 -> 0 | S5: =I5*$D5 -> 0 | T5: =J5*$D5 -> 0 | U5: =K5*$D5 -> 0
A6: 5 | B6: Balmaceda Luciana | C6: =VLOOKUP(A6,[1]Listado!$A$2:$Q$28,17,FALSE) -> 9042.4032 | D6: =C6*$D$1+C6 -> 9268.4633 | L6: =SUM(E6:K6) -> 0 | O6: =E6*$D6 -> 0 | P6: =F6*$D6 -> 0 | Q6: =G6*$D6 -> 0 | R6: =H6*$D6 -> 0 | S6: =I6*$D6 -> 0 | T6: =J6*$D6 -> 0 | U6: =K6*$D6 -> 0
A7: 6 | B7: Martina Migueles | C7: =VLOOKUP(A7,[1]Listado!$A$2:$Q$28,17,FALSE) -> 9272.548 | D7: =C7*$D$1+C7 -> 9504.3617 | E7: 102 | L7: =SUM(E7:K7) -> 102 | O7: =E7*$D7 -> 969444.9 | P7: =F7*$D7 -> 0 | Q7: =G7*$D7 -> 0 | R7: =H7*$D7 -> 0 | S7: =I7*$D7 -> 0 | T7: =J7*$D7 -> 0 | U7: =K7*$D7 -> 0
A8: 10 | B8: Carrizo Camila | C8: =VLOOKUP(A8,[1]Listado!$A$2:$Q$28,17,FALSE) -> 9953.6936 | D8: =C8*$D$1+C8 -> 10202.536 | K8: 108 | L8: =SUM(E8:K8) -> 108 | O8: =E8*$D8 -> 0 | P8: =F8*$D8 -> 0 | Q8: =G8*$D8 -> 0 | R8: =H8*$D8 -> 0 | S8: =I8*$D8 -> 0 | T8: =J8*$D8 -> 0 | U8: =K8*$D8 -> 1101873.9
A9: 11 | B9: Esposito Candela | C9: =VLOOKUP(A9,[1]Listado!$A$2:$Q$28,17,FALSE) -> 10318.755 | D9: =C9*$D$1+C9 -> 10576.724 | H9: 127 | L9: =SUM(E9:K9) -> 127 | O9: =E9*$D9 -> 0 | P9: =F9*$D9 -> 0 | Q9: =G9*$D9 -> 0 | R9: =H9*$D9 -> 1343244 | S9: =I9*$D9 -> 0 | T9: =J9*$D9 -> 0 | U9: =K9*$D9 -> 0
A10: 12 | B10: Barajas Barbara | C10: =VLOOKUP(A10,[1]Listado!$A$2:$Q$28,17,FALSE) -> 9889.5837 | D10: =C10*$D$1+C10 -> 10136.823 | G10: 132 | L10: =SUM(E10:K10) -> 132 | O10: =E10*$D10 -> 0 | P10: =F10*$D10 -> 0 | Q10: =G10*$D10 -> 1338060.7 | R10: =H10*$D10 -> 0 | S10: =I10*$D10 -> 0 | T10: =J10*$D10 -> 0 | U10: =K10*$D10 -> 0
A11: 13 | B11: De Brito Rocio | C11: =VLOOKUP(A11,[1]Listado!$A$2:$Q$28,17,FALSE) -> 9380.7631 | D11: =C11*$D$1+C11 -> 9615.2822 | F11: 102 | G11: 8 | L11: =SUM(E11:K11) -> 110 | O11: =E11*$D11 -> 0 | P11: =F11*$D11 -> 980758.78 | Q11: =G11*$D11 -> 76922.257 | R11: =H11*$D11 -> 0 | S11: =I11*$D11 -> 0 | T11: =J11*$D11 -> 0 | U11: =K11*$D11 -> 0
A12: 14 | B12: Lara Robbio | C12: =VLOOKUP(A12,[1]Listado!$A$2:$Q$28,17,FALSE) -> 10200.577 | D12: =C12*$D$1+C12 -> 10455.591 | H12: 69 | I12: 40 | L12: =SUM(E12:K12) -> 109 | O12: =E12*$D12 -> 0 | P12: =F12*$D12 -> 0 | Q12: =G12*$D12 -> 0 | R12: =H12*$D12 -> 721435.79 | S12: =I12*$D12 -> 418223.65 | T12: =J12*$D12 -> 0 | U12: =K12*$D12 -> 0
A13: 15 | B13: Molina Agustina | C13: =VLOOKUP(A13,[1]Listado!$A$2:$Q$28,17,FALSE) -> 9668.3033 | D13: =C13*$D$1+C13 -> 9910.0109 | K13: 108 | L13: =SUM(E13:K13) -> 108 | O13: =E13*$D13 -> 0 | P13: =F13*$D13 -> 0 | Q13: =G13*$D13 -> 0 | R13: =H13*$D13 -> 0 | S13: =I13*$D13 -> 0 | T13: =J13*$D13 -> 0 | U13: =K13*$D13 -> 1070281.2
A14: 16 | B14: Kiara Corbalan | C14: =VLOOKUP(A14,[1]Listado!$A$2:$Q$28,17,FALSE) -> 9668.3033 | D14: =C14*$D$1+C14 -> 9910.0109 | K14: 108 | L14: =SUM(E14:K14) -> 108 | O14: =E14*$D14 -> 0 | P14: =F14*$D14 -> 0 | Q14: =G14*$D14 -> 0 | R14: =H14*$D14 -> 0 | S14: =I14*$D14 -> 0 | T14: =J14*$D14 -> 0 | U14: =K14*$D14 -> 1070281.2
A15: 17 | B15: Martínez Brisa | C15: =VLOOKUP(A15,[1]Listado!$A$2:$Q$28,17,FALSE) -> 9668.3033 | D15: =C15*$D$1+C15 -> 9910.0109 | K15: 28 | L15: =SUM(E15:K15) -> 28 | O15: =E15*$D15 -> 0 | P15: =F15*$D15 -> 0 | Q15: =G15*$D15 -> 0 | R15: =H15*$D15 -> 0 | S15: =I15*$D15 -> 0 | T15: =J15*$D15 -> 0 | U15: =K15*$D15 -> 277480.31
A16: 18 | B16: CORONEL Mailen | C16: =VLOOKUP(A16,[1]Listado!$A$2:$Q$28,17,FALSE) -> 9295.9026 | D16: =C16*$D$1+C16 -> 9528.3002 | E16: 8 | F16: 103 | L16: =SUM(E16:K16) -> 111 | O16: =E16*$D16 -> 76226.401 | P16: =F16*$D16 -> 981414.92 | Q16: =G16*$D16 -> 0 | R16: =H16*$D16 -> 0 | S16: =I16*$D16 -> 0 | T16: =J16*$D16 -> 0 | U16: =K16*$D16 -> 0
A17: 19 | B17: Gimenez Candela | C17: =VLOOKUP(A17,[1]Listado!$A$2:$Q$28,17,FALSE) -> 9928.3935 | D17: =C17*$D$1+C17 -> 10176.603 | E17: 69 | G17: 57 | L17: =SUM(E17:K17) -> 126 | O17: =E17*$D17 -> 702185.63 | P17: =F17*$D17 -> 0 | Q17: =G17*$D17 -> 580066.39 | R17: =H17*$D17 -> 0 | S17: =I17*$D17 -> 0 | T17: =J17*$D17 -> 0 | U17: =K17*$D17 -> 0
A18: 20 | B18: Oliva Micaela | C18: =VLOOKUP(A18,[1]Listado!$A$2:$Q$28,17,FALSE) -> 9448.7187 | D18: =C18*$D$1+C18 -> 9684.9367 | G18: 130 | L18: =SUM(E18:K18) -> 130 | O18: =E18*$D18 -> 0 | P18: =F18*$D18 -> 0 | Q18: =G18*$D18 -> 1259041.8 | R18: =H18*$D18 -> 0 | S18: =I18*$D18 -> 0 | T18: =J18*$D18 -> 0 | U18: =K18*$D18 -> 0
A19: 21 | B19: Mohamad Daila | C19: =VLOOKUP(A19,[1]Listado!$A$2:$Q$28,17,FALSE) -> 9537.1213 | D19: =C19*$D$1+C19 -> 9775.5494 | I19: 112 | L19: =SUM(E19:K19) -> 112 | O19: =E19*$D19 -> 0 | P19: =F19*$D19 -> 0 | Q19: =G19*$D19 -> 0 | R19: =H19*$D19 -> 0 | S19: =I19*$D19 -> 1094861.5 | T19: =J19*$D19 -> 0 | U19: =K19*$D19 -> 0
A20: 22 | B20: Morena Martinez | C20: =VLOOKUP(A20,[1]Listado!$A$2:$Q$28,17,FALSE) -> 9836.9755 | D20: =C20*$D$1+C20 -> 10082.9 | H20: 71 | I20: 44 | L20: =SUM(E20:K20) -> 115 | O20: =E20*$D20 -> 0 | P20: =F20*$D20 -> 0 | Q20: =G20*$D20 -> 0 | R20: =H20*$D20 -> 715885.89 | S20: =I20*$D20 -> 443647.59 | T20: =J20*$D20 -> 0 | U20: =K20*$D20 -> 0
A21: 23 | B21: Sarapura Rebecca | C21: =VLOOKUP(A21,[1]Listado!$A$2:$Q$28,17,FALSE) -> 9537.1213 | D21: =C21*$D$1+C21 -> 9775.5494 | H21: 39 | L21: =SUM(E21:K21) -> 39 | O21: =E21*$D21 -> 0 | P21: =F21*$D21 -> 0 | Q21: =G21*$D21 -> 0 | R21: =H21*$D21 -> 381246.43 | S21: =I21*$D21 -> 0 | T21: =J21*$D21 -> 0 | U21: =K21*$D21 -> 0
A22: 120 | B22: Bertolo Milagros | C22: =VLOOKUP(A22,[1]Listado!$A$2:$Q$28,17,FALSE) -> 9912.1277 | D22: =C22*$D$1+C22 -> 10159.931 | J22: 109 | L22: =SUM(E22:K22) -> 109 | O22: =E22*$D22 -> 0 | P22: =F22*$D22 -> 0 | Q22: =G22*$D22 -> 0 | R22: =H22*$D22 -> 0 | S22: =I22*$D22 -> 0 | T22: =J22*$D22 -> 1107432.5 | U22: =K22*$D22 -> 0
A23: 174 | B23: Machuca Araceli | C23: =VLOOKUP(A23,[1]Listado!$A$2:$Q$28,17,FALSE) -> 9785.664 | D23: =C23*$D$1+C23 -> 10030.306 | I23: 24 | J23: 82 | L23: =SUM(E23:K23) -> 106 | O23: =E23*$D23 -> 0 | P23: =F23*$D23 -> 0 | Q23: =G23*$D23 -> 0 | R23: =H23*$D23 -> 0 | S23: =I23*$D23 -> 240727.33 | T23: =J23*$D23 -> 822485.06 | U23: =K23*$D23 -> 0
A24: 194 | B24: Scholler Chavez Ruth | C24: =VLOOKUP(A24,[1]Listado!$A$2:$Q$28,17,FALSE) -> 9691.6515 | D24: =C24*$D$1+C24 -> 9933.9427 | I24: 28 | J24: 75 | L24: =SUM(E24:K24) -> 103 | O24: =E24*$D24 -> 0 | P24: =F24*$D24 -> 0 | Q24: =G24*$D24 -> 0 | R24: =H24*$D24 -> 0 | S24: =I24*$D24 -> 278150.4 | T24: =J24*$D24 -> 745045.71 | U24: =K24*$D24 -> 0
A25: 184 | B25: Villarruel Candela | C25: =VLOOKUP(A25,[1]Listado!$A$2:$Q$28,17,FALSE) -> 0 | D25: =C25*$D$1+C25 -> 0 | L25: =SUM(E25:K25) -> 0 | O25: =E25*$D25 -> 0 | P25: =F25*$D25 -> 0 | Q25: =G25*$D25 -> 0 | R25: =H25*$D25 -> 0 | S25: =I25*$D25 -> 0 | T25: =J25*$D25 -> 0 | U25: =K25*$D25 -> 0
A26: 2 | B26: Urbieta Barbara Giselle | C26: =VLOOKUP(A26,[1]Listado!$A$2:$Q$28,17,FALSE) -> 0 | D26: =C26*$D$1+C26 -> 0 | L26: =SUM(E26:K26) -> 0 | O26: =E26*$D26 -> 0 | P26: =F26*$D26 -> 0 | Q26: =G26*$D26 -> 0 | R26: =H26*$D26 -> 0 | S26: =I26*$D26 -> 0 | T26: =J26*$D26 -> 0 | U26: =K26*$D26 -> 0
A27: 9 | B27: Cabovianco Natalia | C27: =VLOOKUP(A27,[1]Listado!$A$2:$Q$28,17,FALSE) -> 0 | D27: =C27*$D$1+C27 -> 0 | L27: =SUM(E27:K27) -> 0 | O27: =E27*$D27 -> 0 | P27: =F27*$D27 -> 0 | Q27: =G27*$D27 -> 0 | R27: =H27*$D27 -> 0 | S27: =I27*$D27 -> 0 | T27: =J27*$D27 -> 0 | U27: =K27*$D27 -> 0
A28: Total | E28: =SUM(E3:E27) -> 548 | F28: =SUM(F3:F27) -> 205 | G28: =SUM(G3:G27) -> 327 | H28: =SUM(H3:H27) -> 306 | I28: =SUM(I3:I27) -> 248 | J28: =SUM(J3:J27) -> 266 | K28: =SUM(K3:K27) -> 352 | L28: =SUM(E28:K28) -> 2252 | O28: =SUM(O3:O27) -> 5492982.3 | P28: =SUM(P3:P27) -> 1962173.7 | Q28: =SUM(Q3:Q27) -> 3254091.1 | R28: =SUM(R3:R27) -> 3161812.1 | S28: =SUM(S3:S27) -> 2475610.5 | T28: =SUM(T3:T27) -> 2674963.2 | U28: =SUM(U3:U27) -> 3519916.5

Sheet Otros gastos
A2: PERIODICIDAD
A3: Tiendas | B3: ABL | C3: ALARMA | D3: AYSA | E3: EDESUR | F3: FUMIGACION | G3: INTERNET | H3: MATAFUEGO | L3: MANTENIMIENTO | M3: OTROS | N3: OBSERVACIONES
H4: CONTROL | I4: PRÓX CONTROL | J4: RECARGA | K4: PRÓX RECARGA
A5: Florida | B5: mensual | C5: mensual | D5: mensual | E5: mensual | F5: mensual | G5: mensual | H5: trimestral | I5: 45962 | J5: anual | K5: 45931 | L5: eventual | N5: Tiene 3 facturas de edesur x mes
A6: Güemes | B6: - | C6: mensual | D6: - | E6: - | F6: mensual | G6: mensual | H6: trimestral | I6: 45992 | J6: anual | K6: 45992 | L6: eventual
A7: Recoleta | B7: - | C7: mensual | D7: - | E7: mensual | F7: mensual | G7: mensual | H7: trimestral | I7: 45962 | J7: anual | K7: 46054 | L7: eventual
A8: French | B8: - | C8: mensual | D8: - | E8: mensual | F8: mensual | G8: mensual | H8: trimestral | I8: 45962 | J8: anual | K8: 46023 | L8: eventual | N8: Tiene 2 facturas de edesur x mes
A9: San Telmo 1 (92) | B9: - | C9: mensual | D9: - | E9: mensual | F9: mensual | G9: - | H9: trimestral | I9: 45962 | J9: anual | K9: 46113 | L9: eventual | N9: Comparte internet de AS San Telmo
A10: San Telmo 2 (122) | B10: - | C10: mensual | D10: - | E10: mensual | F10: mensual | G10: - | H10: trimestral | I10: 45992 | J10: anual | K10: 45931 | L10: eventual | N10: Comparte internet de AS San Telmo
A11: AS San Telmo (120/121) | B11: - | C11: mensual | D11: - | E11: mensual | F11: mensual | G11: mensual | H11: trimestral | I11: 45992 | J11: anual | K11: 46113 | L11: eventual
A14: PROYECTADO A OCTUBRE
A15: Tiendas | B15: ABL | C15: ALARMA | D15: AYSA | E15: EDESUR | F15: FUMIGACION | G15: INTERNET | H15: MATAFUEGO | J15: MANTENIMIENTO | K15: OTROS | L15: TOTAL
H16: CONTROL | I16: RECARGA
A17: Florida | B17: 550953.27 | C17: 40000 | D17: 410000 | E17: 650000 | F17: 41500 | G17: 148000 | H17: - | I17: 100000 | L17: =SUM(B17:J17) -> 1940453.3 | M17: VER SI POR EL NUEVO SISTEMA VAMOS A TENER MÁS GASTOS EN OCTUBRE Y SI HAY OTRO TIPO DE GASTO PROYECTADO
A18: Güemes | B18: - | C18: 40000 | D18: - | E18: - | F18: 33000 | G18: 36000 | H18: - | I18: - | L18: =SUM(B18:J18) -> 109000
A19: Recoleta | B19: - | C19: 40000 | D19: - | E19: 90000 | F19: 33000 | G19: 59000 | H19: - | I19: - | L19: =SUM(B19:J19) -> 222000
A20: French | B20: - | C20: 40000 | D20: - | E20: 160000 | F20: 33000 | G20: 110000 | H20: - | I20: - | L20: =SUM(B20:J20) -> 343000
A21: San Telmo 1 (92) | B21: - | C21: 40000 | D21: - | E21: 80000 | F21: 33000 | G21: - | H21: - | I21: - | L21: =SUM(B21:J21) -> 153000
A22: San Telmo 2 (122) | B22: - | C22: 40000 | D22: - | E22: 115000 | F22: 33000 | G22: - | H22: - | I22: 60000 | L22: =SUM(B22:J22) -> 248000
A23: AS San Telmo (120/121) | B23: - | C23: 40000 | D23: - | E23: 42000 | F23: 33000 | G23: 95000 | H23: - | I23: - | L23: =SUM(B23:J23) -> 210000
